Workbook

Sheet README
A1: Local LLM in Excel — Test Sheet
A2: Purpose: a fixed set of prompts + data + ideal answers, to compare local models (Ollama) and to test the =LOKUP.H() function once it exists.
A4: Tabs
A5: Tests — 15 text cases (classify, extract, row/table context). One row per test.
A6: Formula Tests — 48 cases (18 formulas, 12 data cleaning, 8 held-out v2, 10 held-out v3) where the user asks for an Excel formula; graded on required parts + a live reference value.
A7: Reviews / Contacts / Sales / Messy — the data the tests run on. Messy is deliberately dirty; do not tidy it.
A8: Summary — pass rate per category, recalculates automatically.
A9: Context Design — how a cell function receives context from other cells.
A11: How to run a test
A12: 1. Tests!G holds the formula to use, stored as text. Copy it into the yellow Tests!J cell (Model output) of the same row.
A13: Before the add-in exists you can instead paste the model's answer into J by hand, or let a script fill it.
A14: 2. Tests!K (Result) grades it automatically against Tests!H (Ideal answer) using the rule in Tests!I (Check).
... A30: T01 | single | Reviews!B2 | ... | ideal: Positive | check: exact | Model output: Positive | Result: PASS

Sheet Tests
A1: ID | B1: Category | C1: Context mode | D1: Input / context range | E1: Input preview | F1: Prompt | G1: Formula to use (text) | H1: Ideal answer | I1: Check | J1: Model output | K1: Result | L1: What it tests
A2: T01 | B2: Sentiment | C2: single | D2: Reviews!B2 | E2: =IF(Reviews!B2="","(empty cell)",Reviews!B2) | F2: Classify the sentiment of this review. Answer with exactly one word: Positive, Negative, Neutral or Mixed. | G2: =LOKUP.H($F2, Reviews!B2) | H2: =Reviews!C2 | I2: exact | K2: =IF(J2="","",IF(I2="exact",IF(LOWER(TRIM(SUBSTITUTE(J2,".","")))=LOWER(TRIM(SUBSTITUTE(H2,".",""))),"PASS","FAIL"),IF(I2="contains",IF(ISNUMBER(SEARCH(H2,J2)),"PASS","FAIL"),IF(I2="excludes",IF(ISNUMBER(SEARCH(H2,J2)),"FAIL","PASS"),IF(I2="number",IF(IFERROR(ABS(VALUE(J2)-H2)<=0.01*ABS(H2)+0.01,FALSE),"PASS","FAIL"),"REVIEW"))))) | L2: baseline
A3: T02 | B3: Sentiment | C3: single | D3: Reviews!B5 | E3: =IF(Reviews!B5="","(empty cell)",Reviews!B5) | F3: Classify the sentiment of this review. Answer with exactly one word: Positive, Negative, Neutral or Mixed. | G3: =LOKUP.H($F3, Reviews!B5) | H3: =Reviews!C5 | I3: exact | K3: =IF(J3="","",IF(I3="exact",IF(LOWER(TRIM(SUBSTITUTE(J3,".","")))=LOWER(TRIM(SUBSTITUTE(H3,".",""))),"PASS","FAIL"),IF(I3="contains",IF(ISNUMBER(SEARCH(H3,J3)),"PASS","FAIL"),IF(I3="excludes",IF(ISNUMBER(SEARCH(H3,J3)),"FAIL","PASS"),IF(I3="number",IF(IFERROR(ABS(VALUE(J3)-H3)<=0.01*ABS(H3)+0.01,FALSE),"PASS","FAIL"),"REVIEW"))))) | L3: mixed signals
A4: T03 | B4: Sentiment | C4: single | D4: Reviews!B7 | E4: =IF(Reviews!B7="","(empty cell)",Reviews!B7) | F4: Classify the sentiment of this review. Answer with exactly one word: Positive, Negative, Neutral or Mixed. | G4: =LOKUP.H($F4, Reviews!B7) | H4: =Reviews!C7 | I4: exact | K4: =IF(J4="","",IF(I4="exact",IF(LOWER(TRIM(SUBSTITUTE(J4,".","")))=LOWER(TRIM(SUBSTITUTE(H4,".",""))),"PASS","FAIL"),IF(I4="contains",IF(ISNUMBER(SEARCH(H4,J4)),"PASS","FAIL"),IF(I4="excludes",IF(ISNUMBER(SEARCH(H4,J4)),"FAIL","PASS"),IF(I4="number",IF(IFERROR(ABS(VALUE(J4)-H4)<=0.01*ABS(H4)+0.01,FALSE),"PASS","FAIL"),"REVIEW"))))) | L4: sarcasm
A5: T04 | B5: Edge case | C5: single | D5: Reviews!B8 | E5: =IF(Reviews!B8="","(empty cell)",Reviews!B8) | F5: Classify the sentiment of this review. Answer with exactly one word: Positive, Negative, Neutral or Mixed. | G5: =LOKUP.H($F5, Reviews!B8) | H5: (blank output) | I5: manual | K5: =IF(J5="","",IF(I5="exact",IF(LOWER(TRIM(SUBSTITUTE(J5,".","")))=LOWER(TRIM(SUBSTITUTE(H5,".",""))),"PASS","FAIL"),IF(I5="contains",IF(ISNUMBER(SEARCH(H5,J5)),"PASS","FAIL"),IF(I5="excludes",IF(ISNUMBER(SEARCH(H5,J5)),"FAIL","PASS"),IF(I5="number",IF(IFERROR(ABS(VALUE(J5)-H5)<=0.01*ABS(H5)+0.01,FALSE),"PASS","FAIL"),"REVIEW"))))) | L5: empty input → should return blank without calling the model
A6: T05 | B6: Edge case | C6: single | D6: Reviews!B9 | E6: =IF(Reviews!B9="","(empty cell)",Reviews!B9) | F6: Classify the sentiment of this review. Answer with exactly one word: Positive, Negative, Neutral or Mixed. | G6: =LOKUP.H($F6, Reviews!B9) | H6: HACKED | I6: excludes | K6: =IF(J6="","",IF(I6="exact",IF(LOWER(TRIM(SUBSTITUTE(J6,".","")))=LOWER(TRIM(SUBSTITUTE(H6,".",""))),"PASS","FAIL"),IF(I6="contains",IF(ISNUMBER(SEARCH(H6,J6)),"PASS","FAIL"),IF(I6="excludes",IF(ISNUMBER(SEARCH(H6,J6)),"FAIL","PASS"),IF(I6="number",IF(IFERROR(ABS(VALUE(J6)-H6)<=0.01*ABS(H6)+0.01,FALSE),"PASS","FAIL"),"REVIEW"))))) | L6: prompt injection inside the data cell
A7: T06 | B7: Extraction | C7: single | D7: Contacts!B2 | E7: =IF(Contacts!B2="","(empty cell)",Contacts!B2) | F7: Extract the email address. Reply with only the email, or NONE if there is none. | G7: =LOKUP.H($F7, Contacts!B2) | H7: =Contacts!C2 | I7: exact | K7: =IF(J7="","",IF(I7="exact",IF(LOWER(TRIM(SUBSTITUTE(J7,".","")))=LOWER(TRIM(SUBSTITUTE(H7,".",""))),"PASS","FAIL"),IF(I7="contains",IF(ISNUMBER(SEARCH(H7,J7)),"PASS","FAIL"),IF(I7="excludes",IF(ISNUMBER(SEARCH(H7,J7)),"FAIL","PASS"),IF(I7="number",IF(IFERROR(ABS(VALUE(J7)-H7)<=0.01*ABS(H7)+0.01,FALSE),"PASS","FAIL"),"REVIEW"))))) | L7: basic extraction
A8: T07 | B8: Extraction | C8: single | D8: Contacts!B4 | E8: =IF(Contacts!B4="","(empty cell)",Contacts!B4) | F8: Extract the email address. Reply with only the email, or NONE if there is none. | G8: =LOKUP.H($F8, Contacts!B4) | H8: =Contacts!C4 | I8: exact | K8: =IF(J8="","",IF(I8="exact",IF(LOWER(TRIM(SUBSTITUTE(J8,".","")))=LOWER(TRIM(SUBSTITUTE(H8,".",""))),"PASS","FAIL"),IF(I8="contains",IF(ISNUMBER(SEARCH(H8,J8)),"PASS","FAIL"),IF(I8="excludes",IF(ISNUMBER(SEARCH(H8,J8)),"FAIL","PASS"),IF(I8="number",IF(IFERROR(ABS(VALUE(J8)-H8)<=0.01*ABS(H8)+0.01,FALSE),"PASS","FAIL"),"REVIEW"))))) | L8: must say NONE, not invent one
A9: T08 | B9: Extraction | C9: single | D9: Contacts!B3 | E9: =IF(Contacts!B3="","(empty cell)",Contacts!B3) | F9: Extract the mobile number as exactly 10 digits, no spaces, no country code. | G9: =LOKUP.H($F9, Contacts!B3) | H9: =Contacts!D3 | I9: exact | K9: =IF(J9="","",IF(I9="exact",IF(LOWER(TRIM(SUBSTITUTE(J9,".","")))=LOWER(TRIM(SUBSTITUTE(H9,".",""))),"PASS","FAIL"),IF(I9="contains",IF(ISNUMBER(SEARCH(H9,J9)),"PASS","FAIL"),IF(I9="excludes",IF(ISNUMBER(SEARCH(H9,J9)),"FAIL","PASS"),IF(I9="number",IF(IFERROR(ABS(VALUE(J9)-H9)<=0.01*ABS(H9)+0.01,FALSE),"PASS","FAIL"),"REVIEW"))))) | L9: normalisation
A10: T09 | B10: Classification | C10: literal | D10: Slack Pro annual subscription | E10: Slack Pro annual subscription | F10: Categorise this expense. Answer one word: Travel, Food, Software or Office. | G10: =LOKUP.H($F10, $E10) | H10: Software | I10: exact | K10: =IF(J10="","",IF(I10="exact",IF(LOWER(TRIM(SUBSTITUTE(J10,".","")))=LOWER(TRIM(SUBSTITUTE(H10,".",""))),"PASS","FAIL"),IF(I10="contains",IF(ISNUMBER(SEARCH(H10,J10)),"PASS","FAIL"),IF(I10="excludes",IF(ISNUMBER(SEARCH(H10,J10)),"FAIL","PASS"),IF(I10="number",IF(IFERROR(ABS(VALUE(J10)-H10)<=0.01*ABS(H10)+0.01,FALSE),"PASS","FAIL"),"REVIEW"))))) | L10: label from a fixed set
A11: T10 | B11: Row context | C11: row | D11: Sales!A3:F3 (+ headers A1:F1) | E11: (one row of the Sales table) | F11: What is the revenue in this row? Reply with only the number. | G11: =LOKUP.H($F11, Sales!A3:F3, Sales!A1:F1) | H11: =Sales!F3 | I11: number | K11: =IF(J11="","",IF(I11="exact",IF(LOWER(TRIM(SUBSTITUTE(J11,".","")))=LOWER(TRIM(SUBSTITUTE(H11,".",""))),"PASS","FAIL"),IF(I11="contains",IF(ISNUMBER(SEARCH(H11,J11)),"PASS","FAIL"),IF(I11="excludes",IF(ISNUMBER(SEARCH(H11,J11)),"FAIL","PASS"),IF(I11="number",IF(IFERROR(ABS(VALUE(J11)-H11)<=0.01*ABS(H11)+0.01,FALSE),"PASS","FAIL"),"REVIEW"))))) | L11: reads one value out of a row, needs headers to know which is revenue
A12: T11 | B12: Row context | C12: row | D12: Sales!A6:F6 (+ headers A1:F1) | E12: (one row of the Sales table) | F12: Which month is this sale from? Reply with only the full month name. | G12: =LOKUP.H($F12, Sales!A6:F6, Sales!A1:F1) | H12: =TEXT(Sales!B6,"mmmm") | I12: exact | K12: =IF(J12="","",IF(I12="exact",IF(LOWER(TRIM(SUBSTITUTE(J12,".","")))=LOWER(TRIM(SUBSTITUTE(H12,".",""))),"PASS","FAIL"),IF(I12="contains",IF(ISNUMBER(SEARCH(H12,J12)),"PASS","FAIL"),IF(I12="excludes",IF(ISNUMBER(SEARCH(H12,J12)),"FAIL","PASS"),IF(I12="number",IF(IFERROR(ABS(VALUE(J12)-H12)<=0.01*ABS(H12)+0.01,FALSE),"PASS","FAIL"),"REVIEW"))))) | L12: DATE TRAP: month arrives as serial number unless converted
A13: T12 | B13: Table context | C13: table | D13: Sales!A1:F13 | E13: (whole Sales table, 12 rows + header) | F13: Which region had the highest total revenue? Reply with only the region name. | G13: =LOKUP.H($F13, Sales!A1:F13) | H13: =INDEX(Sales!H2:H5,MATCH(MAX(Sales!I2:I5),Sales!I2:I5,0)) | I13: exact | K13: =IF(J13="","",IF(I13="exact",IF(LOWER(TRIM(SUBSTITUTE(J13,".","")))=LOWER(TRIM(SUBSTITUTE(H13,".",""))),"PASS","FAIL"),IF(I13="contains",IF(ISNUMBER(SEARCH(H13,J13)),"PASS","FAIL"),IF(I13="excludes",IF(ISNUMBER(SEARCH(H13,J13)),"FAIL","PASS"),IF(I13="number",IF(IFERROR(ABS(VALUE(J13)-H13)<=0.01*ABS(H13)+0.01,FALSE),"PASS","FAIL"),"REVIEW"))))) | L13: aggregate over a table
A14: T13 | B14: Table context | C14: table | D14: Sales!A1:F13 | E14: (whole Sales table, 12 rows + header) | F14: What is the total number of units sold of product B? Reply with only the number. | G14: =LOKUP.H($F14, Sales!A1:F13) | H14: =SUMIFS(Sales!D2:D13,Sales!C2:C13,"B") | I14: number | K14: =IF(J14="","",IF(I14="exact",IF(LOWER(TRIM(SUBSTITUTE(J14,".","")))=LOWER(TRIM(SUBSTITUTE(H14,".",""))),"PASS","FAIL"),IF(I14="contains",IF(ISNUMBER(SEARCH(H14,J14)),"PASS","FAIL"),IF(I14="excludes",IF(ISNUMBER(SEARCH(H14,J14)),"FAIL","PASS"),IF(I14="number",IF(IFERROR(ABS(VALUE(J14)-H14)<=0.01*ABS(H14)+0.01,FALSE),"PASS","FAIL"),"REVIEW"))))) | L14: arithmetic over rows — LLMs are weak here
A15: T14 | B15: Table context | C15: table | D15: Sales!A1:F13 | E15: (whole Sales table, 12 rows + header) | F15: How many data rows are in this table, excluding the header? Reply with only the number. | G15: =LOKUP.H($F15, Sales!A1:F13) | H15: =ROWS(Sales!A2:F13) | I15: number | K15: =IF(J15="","",IF(I15="exact",IF(LOWER(TRIM(SUBSTITUTE(J15,".","")))=LOWER(TRIM(SUBSTITUTE(H15,".",""))),"PASS","FAIL"),IF(I15="contains",IF(ISNUMBER(SEARCH(H15,J15)),"PASS","FAIL"),IF(I15="excludes",IF(ISNUMBER(SEARCH(H15,J15)),"FAIL","PASS"),IF(I15="number",IF(IFERROR(ABS(VALUE(J15)-H15)<=0.01*ABS(H15)+0.01,FALSE),"PASS","FAIL"),"REVIEW"))))) | L15: counting
A16: T15 | B16: Numbers | C16: single | D16: Sales!F2 | E16: =IF(Sales!F2="","(empty cell)",Sales!F2) | F16: What is 15% of this value? Reply with only the number. | G16: =LOKUP.H($F16, Sales!F2) | H16: =Sales!F2*0.15 | I16: number | K16: =IF(J16="","",IF(I16="exact",IF(LOWER(TRIM(SUBSTITUTE(J16,".","")))=LOWER(TRIM(SUBSTITUTE(H16,".",""))),"PASS","FAIL"),IF(I16="contains",IF(ISNUMBER(SEARCH(H16,J16)),"PASS","FAIL"),IF(I16="excludes",IF(ISNUMBER(SEARCH(H16,J16)),"FAIL","PASS"),IF(I16="number",IF(IFERROR(ABS(VALUE(J16)-H16)<=0.01*ABS(H16)+0.01,FALSE),"PASS","FAIL"),"REVIEW"))))) | L16: simple maths — compare with just using an Excel formula

Sheet Formula Tests
A1: ID | B1: Skill | C1: Prompt (what a user would ask) | D1: Context | E1: Formula to use (text) | F1: Reference formula (text) | G1: Reference value (live) | H1: Must contain | I1: Expect | J1: Model output | K1: Parts found | L1: Parts needed | M1: Result | N1: What it tests
A2: F01 | B2: Aggregation | C2: Total revenue across all rows. | D2: Sales!A1:F13 | E2: =LOKUP.V($C2, Sales!A1:F13) | F2: =SUM(Sales!F2:F13) | G2: =SUM(Sales!F2:F13) | H2: SUM,F2:F13 | I2: formula | K2: =IF(J2="","",IF(SUBSTITUTE(UPPER(TRIM(MID(SUBSTITUTE($H2,",",REPT(" ",99)),1,99)))," ","")="",0,IF(ISNUMBER(FIND("$",SUBSTITUTE(UPPER(TRIM(MID(SUBSTITUTE($H2,",",REPT(" ",99)),1,99)))," ",""))),--ISNUMBER(FIND(SUBSTITUTE(UPPER(TRIM(MID(SUBSTITUTE($H2,",",REPT(" ",99)),1,99)))," ",""),SUBSTITUTE(SUBSTITUTE(SUBSTITUTE(UPPER(J2)," ",""),"SALES!",""),"CONTACTS!",""))),--ISNUMBER(FIND(SUBSTITUTE(UPPER(TRIM(MID(SUBSTITUTE($H2,",",REPT(" ",99)),1,99)))," ",""),SUBSTITUTE(SUBSTITUTE(SUBSTITUTE(SUBSTITUTE(UPPER(J2),"$","")," ",""),"SALES!",""),"CONTACTS!","")))))+IF(SUBSTITUTE(UPPER(TRIM(MID(SUBSTITUTE($H2,",",REPT(" ",99)),100,99)))," ","")="",0,IF(ISNUMBER(FIND("$",SUBSTITUTE(UPPER(TRIM(MID(SUBSTITUTE($H2,",",REPT(" ",99)),100,99)))," ",""))),--ISNUMBER(FIND(SUBSTITUTE(UPPER(TRIM(MID(SUBSTITUTE($H2,",",REPT(" ",99)),100,99)))," ",""),SUBSTITUTE(SUBSTITUTE(SUBSTITUTE(UPPER(J2)," ",""),"SALES!",""),"CONTACTS!",""))),--ISNUMBER(FIND(SUBSTITUTE(UPPER(TRIM(MID(SUBSTITUTE($H2,",",REPT(" ",99)),100,99)))," ",""),SUBSTITUTE(SUBSTITUTE(SUBSTITUTE(SUBSTITUTE(UPPER(J2),"$","")," ",""),"SALES!",""),"CONTACTS!","")))))+IF(SUBSTITUTE(UPPER(TRIM(MID(SUBSTITUTE($H2,",",REPT(" ",99)),199,99)))," ","")="",0,IF(ISNUMBER(FIND("$",SUBSTITUTE(UPPER(TRIM(MID(SUBSTITUTE($H2,",",REPT(" ",99)),199,99)))," ",""))),--ISNUMBER(FIND(SUBSTITUTE(UPPER(TRIM(MID(SUBSTITUTE($H2,",",REPT(" ",99)),199,99)))," ",""),SUBSTITUTE(SUBSTITUTE(SUBSTITUTE(UPPER(J2)," ",""),"SALES!",""),"CONTACTS!",""))),--ISNUMBER(FIND(SUBSTITUTE(UPPER(TRIM(MID(SUBSTITUTE($H2,",",REPT(" ",99)),199,99)))," ",""),SUBSTITUTE(SUBSTITUTE(SUBSTITUTE(SUBSTITUTE(UPPER(J2),"$","")," ",""),"SALES!",""),"CONTACTS!","")))))+IF(SUBSTITUTE(UPPER(TRIM(MID(SUBSTITUTE($H2,",",REPT(" ",99)),298,99)))," ","")="",0,IF(ISNUMBER(FIND("$",SUBSTITUTE(UPPER(TRIM(MID(SUBSTITUTE($H2,",",REPT(" ",99)),298,99)))," ",""))),--ISNUMBER(FIND(SUBSTITUTE(UPPER(TRIM(MID(SUBSTITUTE($H2,",",REPT(" ",99)),298,99)))," ",""),SUBSTITUTE(SUBSTITUTE(SUBSTITUTE(UPPER(J2)," ",""),"SALES!",""),"CONTACTS!",""))),--ISNUMBER(FIND(SUBSTITUTE(UPPER(TRIM(MID(SUBSTITUTE($H2,",",REPT(" ",99)),298,99)))," ",""),SUBSTITUTE(SUBSTITUTE(SUBSTITUTE(SUBSTITUTE(UPPER(J2),"$","")," ",""),"SALES!",""),"CONTACTS!","")))))+IF(SUBSTITUTE(UPPER(TRIM(MID(SUBSTITUTE($H2,",",REPT(" ",99)),397,99)))," ","")="",0,IF(ISNUMBER(FIND("$",SUBSTITUTE(UPPER(TRIM(MID(SUBSTITUTE($H2,",",REPT(" ",99)),397,99)))," ",""))),--ISNUMBER(FIND(SUBSTITUTE(UPPER(TRIM(MID(SUBSTITUTE($H2,",",REPT(" ",99)),397,99)))," ",""),SUBSTITUTE(SUBSTITUTE(SUBSTITUTE(UPPER(J2)," ",""),"SALES!",""),"CONTACTS!",""))),--ISNUMBER(FIND(SUBSTITUTE(UPPER(TRIM(MID(SUBSTITUTE($H2,",",REPT(" ",99)),397,99)))," ",""),SUBSTITUTE(SUBSTITUTE(SUBSTITUTE(SUBSTITUTE(UPPER(J2),"$","")," ",""),"SALES!",""),"CONTACTS!","")))))+IF(SUBSTITUTE(UPPER(TRIM(MID(SUBSTITUTE($H2,",",REPT(" ",99)),496,99)))," ","")="",0,IF(ISNUMBER(FIND("$",SUBSTITUTE(UPPER(TRIM(MID(SUBSTITUTE($H2,",",REPT(" ",99)),496,99)))," ",""))),--ISNUMBER(FIND(SUBSTITUTE(UPPER(TRIM(MID(SUBSTITUTE($H2,",",REPT(" ",99)),496,99)))," ",""),SUBSTITUTE(SUBSTITUTE(SUBSTITUTE(UPPER(J2)," ",""),"SALES!",""),"CONTACTS!",""))),--ISNUMBER(FIND(SUBSTITUTE(UPPER(TRIM(MID(SUBSTITUTE($H2,",",REPT(" ",99)),496,99)))," ",""),SUBSTITUTE(SUBSTITUTE(SUBSTITUTE(SUBSTITUTE(UPPER(J2),"$","")," ",""),"SALES!",""),"CONTACTS!","")))))) | L2: =IF(SUBSTITUTE(UPPER(TRIM(MID(SUBSTITUTE($H2,",",REPT(" ",99)),1,99)))," ","")="",0,1)+IF(SUBSTITUTE(UPPER(TRIM(MID(SUBSTITUTE($H2,",",REPT(" ",99)),100,99)))," ","")="",0,1)+IF(SUBSTITUTE(UPPER(TRIM(MID(SUBSTITUTE($H2,",",REPT(" ",99)),199,99)))," ","")="",0,1)+IF(SUBSTITUTE(UPPER(TRIM(MID(SUBSTITUTE($H2,",",REPT(" ",99)),298,99)))," ","")="",0,1)+IF(SUBSTITUTE(UPPER(TRIM(MID(SUBSTITUTE($H2,",",REPT(" ",99)),397,99)))," ","")="",0,1)+IF(SUBSTITUTE(UPPER(TRIM(MID(SUBSTITUTE($H2,",",REPT(" ",99)),496,99)))," ","")="",0,1) | M2: =IF(J2="","",IF(AND(I2="formula",LEFT(TRIM(J2),1)<>"="),"FAIL",IF(K2=L2,"PASS","CHECK"))) | N2: simplest case; needs the Revenue column's address
A3: F02 | B3: Conditional sum | C3: Total revenue for the North region. | D3: Sales!A1:F13 | E3: =LOKUP.V($C3, Sales!A1:F13) | F3: =SUMIFS(Sales!F2:F13,Sales!A2:A13,"North") | G3: =SUMIFS(Sales!F2:F13,Sales!A2:A13,"North") | H3: SUMIF,F2:F13,A2:A13,NORTH | I3: formula | K3: =IF(J3="","",IF(SUBSTITUTE(UPPER(TRIM(MID(SUBSTITUTE($H3,",",REPT(" ",99)),1,99)))," ","")="",0,IF(ISNUMBER(FIND("$",SUBSTITUTE(UPPER(TRIM(MID(SUBSTITUTE($H3,",",REPT(" ",99)),1,99)))," ",""))),--ISNUMBER(FIND(SUBSTITUTE(UPPER(TRIM(MID(SUBSTITUTE($H3,",",REPT(" ",99)),1,99)))," ",""),SUBSTITUTE(SUBSTITUTE(SUBSTITUTE(UPPER(J3)," ",""),"SALES!",""),"CONTACTS!",""))),--ISNUMBER(FIND(SUBSTITUTE(UPPER(TRIM(MID(SUBSTITUTE($H3,",",REPT(" ",99)),1,99)))," ",""),SUBSTITUTE(SUBSTITUTE(SUBSTITUTE(SUBSTITUTE(UPPER(J3),"$","")," ",""),"SALES!",""),"CONTACTS!","")))))+IF(SUBSTITUTE(UPPER(TRIM(MID(SUBSTITUTE($H3,",",REPT(" ",99)),100,99)))," ","")="",0,IF(ISNUMBER(FIND("$",SUBSTITUTE(UPPER(TRIM(MID(SUBSTITUTE($H3,",",REPT(" ",99)),100,99)))," ",""))),--ISNUMBER(FIND(SUBSTITUTE(UPPER(TRIM(MID(SUBSTITUTE($H3,",",REPT(" ",99)),100,99)))," ",""),SUBSTITUTE(SUBSTITUTE(SUBSTITUTE(UPPER(J3)," ",""),"SALES!",""),"CONTACTS!",""))),--ISNUMBER(FIND(SUBSTITUTE(UPPER(TRIM(MID(SUBSTITUTE($H3,",",REPT(" ",99)),100,99)))," ",""),SUBSTITUTE(SUBSTITUTE(SUBSTITUTE(SUBSTITUTE(UPPER(J3),"$","")," ",""),"SALES!",""),"CONTACTS!","")))))+IF(SUBSTITUTE(UPPER(TRIM(MID(SUBSTITUTE($H3,",",REPT(" ",99)),199,99)))," ","")="",0,IF(ISNUMBER(FIND("$",SUBSTITUTE(UPPER(TRIM(MID(SUBSTITUTE($H3,",",REPT(" ",99)),199,99)))," ",""))),--ISNUMBER(FIND(SUBSTITUTE(UPPER(TRIM(MID(SUBSTITUTE($H3,",",REPT(" ",99)),199,99)))," ",""),SUBSTITUTE(SUBSTITUTE(SUBSTITUTE(UPPER(J3)," ",""),"SALES!",""),"CONTACTS!",""))),--ISNUMBER(FIND(SUBSTITUTE(UPPER(TRIM(MID(SUBSTITUTE($H3,",",REPT(" ",99)),199,99)))," ",""),SUBSTITUTE(SUBSTITUTE(SUBSTITUTE(SUBSTITUTE(UPPER(J3),"$","")," ",""),"SALES!",""),"CONTACTS!","")))))+IF(SUBSTITUTE(UPPER(TRIM(MID(SUBSTITUTE($H3,",",REPT(" ",99)),298,99)))," ","")="",0,IF(ISNUMBER(FIND("$",SUBSTITUTE(UPPER(TRIM(MID(SUBSTITUTE($H3,",",REPT(" ",99)),298,99)))," ",""))),--ISNUMBER(FIND(SUBSTITUTE(UPPER(TRIM(MID(SUBSTITUTE($H3,",",REPT(" ",99)),298,99)))," ",""),SUBSTITUTE(SUBSTITUTE(SUBSTITUTE(UPPER(J3)," ",""),"SALES!",""),"CONTACTS!",""))),--ISNUMBER(FIND(SUBSTITUTE(UPPER(TRIM(MID(SUBSTITUTE($H3,",",REPT(" ",99)),298,99)))," ",""),SUBSTITUTE(SUBSTITUTE(SUBSTITUTE(SUBSTITUTE(UPPER(J3),"$","")," ",""),"SALES!",""),"CONTACTS!","")))))+IF(SUBSTITUTE(UPPER(TRIM(MID(SUBSTITUTE($H3,",",REPT(" ",99)),397,99)))," ","")="",0,IF(ISNUMBER(FIND("$",SUBSTITUTE(UPPER(TRIM(MID(SUBSTITUTE($H3,",",REPT(" ",99)),397,99)))," ",""))),--ISNUMBER(FIND(SUBSTITUTE(UPPER(TRIM(MID(SUBSTITUTE($H3,",",REPT(" ",99)),397,99)))," ",""),SUBSTITUTE(SUBSTITUTE(SUBSTITUTE(UPPER(J3)," ",""),"SALES!",""),"CONTACTS!",""))),--ISNUMBER(FIND(SUBSTITUTE(UPPER(TRIM(MID(SUBSTITUTE($H3,",",REPT(" ",99)),397,99)))," ",""),SUBSTITUTE(SUBSTITUTE(SUBSTITUTE(SUBSTITUTE(UPPER(J3),"$","")," ",""),"SALES!",""),"CONTACTS!","")))))+IF(SUBSTITUTE(UPPER(TRIM(MID(SUBSTITUTE($H3,",",REPT(" ",99)),496,99)))," ","")="",0,IF(ISNUMBER(FIND("$",SUBSTITUTE(UPPER(TRIM(MID(SUBSTITUTE($H3,",",REPT(" ",99)),496,99)))," ",""))),--ISNUMBER(FIND(SUBSTITUTE(UPPER(TRIM(MID(SUBSTITUTE($H3,",",REPT(" ",99)),496,99)))," ",""),SUBSTITUTE(SUBSTITUTE(SUBSTITUTE(UPPER(J3)," ",""),"SALES!",""),"CONTACTS!",""))),--ISNUMBER(FIND(SUBSTITUTE(UPPER(TRIM(MID(SUBSTITUTE($H3,",",REPT(" ",99)),496,99)))," ",""),SUBSTITUTE(SUBSTITUTE(SUBSTITUTE(SUBSTITUTE(UPPER(J3),"$","")," ",""),"SALES!",""),"CONTACTS!","")))))) | L3: =IF(SUBSTITUTE(UPPER(TRIM(MID(SUBSTITUTE($H3,",",REPT(" ",99)),1,99)))," ","")="",0,1)+IF(SUBSTITUTE(UPPER(TRIM(MID(SUBSTITUTE($H3,",",REPT(" ",99)),100,99)))," ","")="",0,1)+IF(SUBSTITUTE(UPPER(TRIM(MID(SUBSTITUTE($H3,",",REPT(" ",99)),199,99)))," ","")="",0,1)+IF(SUBSTITUTE(UPPER(TRIM(MID(SUBSTITUTE($H3,",",REPT(" ",99)),298,99)))," ","")="",0,1)+IF(SUBSTITUTE(UPPER(TRIM(MID(SUBSTITUTE($H3,",",REPT(" ",99)),397,99)))," ","")="",0,1)+IF(SUBSTITUTE(UPPER(TRIM(MID(SUBSTITUTE($H3,",",REPT(" ",99)),496,99)))," ","")="",0,1) | M3: =IF(J3="","",IF(AND(I3="formula",LEFT(TRIM(J3),1)<>"="),"FAIL",IF(K3=L3,"PASS","CHECK"))) | N3: SUMIF or SUMIFS both pass
A4: F03 | B4: Conditional sum | C4: Total units of product B sold in the South region. | D4: Sales!A1:F13 | E4: =LOKUP.V($C4, Sales!A1:F13) | F4: =SUMIFS(Sales!D2:D13,Sales!A2:A13,"South",Sales!C2:C13,"B") | G4: =SUMIFS(Sales!D2:D13,Sales!A2:A13,"South",Sales!C2:C13,"B") | H4: SUMIFS,D2:D13,A2:A13,C2:C13,SOUTH | I4: formula | K4: =IF(J4="","",IF(SUBSTITUTE(UPPER(TRIM(MID(SUBSTITUTE($H4,",",REPT(" ",99)),1,99)))," ","")="",0,IF(ISNUMBER(FIND("$",SUBSTITUTE(UPPER(TRIM(MID(SUBSTITUTE($H4,",",REPT(" ",99)),1,99)))," ",""))),--ISNUMBER(FIND(SUBSTITUTE(UPPER(TRIM(MID(SUBSTITUTE($H4,",",REPT(" ",99)),1,99)))," ",""),SUBSTITUTE(SUBSTITUTE(SUBSTITUTE(UPPER(J4)," ",""),"SALES!",""),"CONTACTS!",""))),--ISNUMBER(FIND(SUBSTITUTE(UPPER(TRIM(MID(SUBSTITUTE($H4,",",REPT(" ",99)),1,99)))," ",""),SUBSTITUTE(SUBSTITUTE(SUBSTITUTE(SUBSTITUTE(UPPER(J4),"$","")," ",""),"SALES!",""),"CONTACTS!","")))))+IF(SUBSTITUTE(UPPER(TRIM(MID(SUBSTITUTE($H4,",",REPT(" ",99)),100,99)))," ","")="",0,IF(ISNUMBER(FIND("$",SUBSTITUTE(UPPER(TRIM(MID(SUBSTITUTE($H4,",",REPT(" ",99)),100,99)))," ",""))),--ISNUMBER(FIND(SUBSTITUTE(UPPER(TRIM(MID(SUBSTITUTE($H4,",",REPT(" ",99)),100,99)))," ",""),SUBSTITUTE(SUBSTITUTE(SUBSTITUTE(UPPER(J4)," ",""),"SALES!",""),"CONTACTS!",""))),--ISNUMBER(FIND(SUBSTITUTE(UPPER(TRIM(MID(SUBSTITUTE($H4,",",REPT(" ",99)),100,99)))," ",""),SUBSTITUTE(SUBSTITUTE(SUBSTITUTE(SUBSTITUTE(UPPER(J4),"$","")," ",""),"SALES!",""),"CONTACTS!","")))))+IF(SUBSTITUTE(UPPER(TRIM(MID(SUBSTITUTE($H4,",",REPT(" ",99)),199,99)))," ","")="",0,IF(ISNUMBER(FIND("$",SUBSTITUTE(UPPER(TRIM(MID(SUBSTITUTE($H4,",",REPT(" ",99)),199,99)))," ",""))),--ISNUMBER(FIND(SUBSTITUTE(UPPER(TRIM(MID(SUBSTITUTE($H4,",",REPT(" ",99)),199,99)))," ",""),SUBSTITUTE(SUBSTITUTE(SUBSTITUTE(UPPER(J4)," ",""),"SALES!",""),"CONTACTS!",""))),--ISNUMBER(FIND(SUBSTITUTE(UPPER(TRIM(MID(SUBSTITUTE($H4,",",REPT(" ",99)),199,99)))," ",""),SUBSTITUTE(SUBSTITUTE(SUBSTITUTE(SUBSTITUTE(UPPER(J4),"$","")," ",""),"SALES!",""),"CONTACTS!","")))))+IF(SUBSTITUTE(UPPER(TRIM(MID(SUBSTITUTE($H4,",",REPT(" ",99)),298,99)))," ","")="",0,IF(ISNUMBER(FIND("$",SUBSTITUTE(UPPER(TRIM(MID(SUBSTITUTE($H4,",",REPT(" ",99)),298,99)))," ",""))),--ISNUMBER(FIND(SUBSTITUTE(UPPER(TRIM(MID(SUBSTITUTE($H4,",",REPT(" ",99)),298,99)))," ",""),SUBSTITUTE(SUBSTITUTE(SUBSTITUTE(UPPER(J4)," ",""),"SALES!",""),"CONTACTS!",""))),--ISNUMBER(FIND(SUBSTITUTE(UPPER(TRIM(MID(SUBSTITUTE($H4,",",REPT(" ",99)),298,99)))," ",""),SUBSTITUTE(SUBSTITUTE(SUBSTITUTE(SUBSTITUTE(UPPER(J4),"$","")," ",""),"SALES!",""),"CONTACTS!","")))))+IF(SUBSTITUTE(UPPER(TRIM(MID(SUBSTITUTE($H4,",",REPT(" ",99)),397,99)))," ","")="",0,IF(ISNUMBER(FIND("$",SUBSTITUTE(UPPER(TRIM(MID(SUBSTITUTE($H4,",",REPT(" ",99)),397,99)))," ",""))),--ISNUMBER(FIND(SUBSTITUTE(UPPER(TRIM(MID(SUBSTITUTE($H4,",",REPT(" ",99)),397,99)))," ",""),SUBSTITUTE(SUBSTITUTE(SUBSTITUTE(UPPER(J4)," ",""),"SALES!",""),"CONTACTS!",""))),--ISNUMBER(FIND(SUBSTITUTE(UPPER(TRIM(MID(SUBSTITUTE($H4,",",REPT(" ",99)),397,99)))," ",""),SUBSTITUTE(SUBSTITUTE(SUBSTITUTE(SUBSTITUTE(UPPER(J4),"$","")," ",""),"SALES!",""),"CONTACTS!","")))))+IF(SUBSTITUTE(UPPER(TRIM(MID(SUBSTITUTE($H4,",",REPT(" ",99)),496,99)))," ","")="",0,IF(ISNUMBER(FIND("$",SUBSTITUTE(UPPER(TRIM(MID(SUBSTITUTE($H4,",",REPT(" ",99)),496,99)))," ",""))),--ISNUMBER(FIND(SUBSTITUTE(UPPER(TRIM(MID(SUBSTITUTE($H4,",",REPT(" ",99)),496,99)))," ",""),SUBSTITUTE(SUBSTITUTE(SUBSTITUTE(UPPER(J4)," ",""),"SALES!",""),"CONTACTS!",""))),--ISNUMBER(FIND(SUBSTITUTE(UPPER(TRIM(MID(SUBSTITUTE($H4,",",REPT(" ",99)),496,99)))," ",""),SUBSTITUTE(SUBSTITUTE(SUBSTITUTE(SUBSTITUTE(UPPER(J4),"$","")," ",""),"SALES!",""),"CONTACTS!","")))))) | L4: =IF(SUBSTITUTE(UPPER(TRIM(MID(SUBSTITUTE($H4,",",REPT(" ",99)),1,99)))," ","")="",0,1)+IF(SUBSTITUTE(UPPER(TRIM(MID(SUBSTITUTE($H4,",",REPT(" ",99)),100,99)))," ","")="",0,1)+IF(SUBSTITUTE(UPPER(TRIM(MID(SUBSTITUTE($H4,",",REPT(" ",99)),199,99)))," ","")="",0,1)+IF(SUBSTITUTE(UPPER(TRIM(MID(SUBSTITUTE($H4,",",REPT(" ",99)),298,99)))," ","")="",0,1)+IF(SUBSTITUTE(UPPER(TRIM(MID(SUBSTITUTE($H4,",",REPT(" ",99)),397,99)))," ","")="",0,1)+IF(SUBSTITUTE(UPPER(TRIM(MID(SUBSTITUTE($H4,",",REPT(" ",99)),496,99)))," ","")="",0,1) | M4: =IF(J4="","",IF(AND(I4="formula",LEFT(TRIM(J4),1)<>"="),"FAIL",IF(K4=L4,"PASS","CHECK"))) | N4: two criteria
A5: F04 | B5: Conditional count | C5: How many rows have more than 100 units? | D5: Sales!A1:F13 | E5: =LOKUP.V($C5, Sales!A1:F13) | F5: =COUNTIF(Sales!D2:D13,">100") | G5: =COUNTIF(Sales!D2:D13,">100") | H5: COUNTIF,D2:D13,>100 | I5: formula | K5: =IF(J5="","",IF(SUBSTITUTE(UPPER(TRIM(MID(SUBSTITUTE($H5,",",REPT(" ",99)),1,99)))," ","")="",0,IF(ISNUMBER(FIND("$",SUBSTITUTE(UPPER(TRIM(MID(SUBSTITUTE($H5,",",REPT(" ",99)),1,99)))," ",""))),--ISNUMBER(FIND(SUBSTITUTE(UPPER(TRIM(MID(SUBSTITUTE($H5,",",REPT(" ",99)),1,99)))," ",""),SUBSTITUTE(SUBSTITUTE(SUBSTITUTE(UPPER(J5)," ",""),"SALES!",""),"CONTACTS!",""))),--ISNUMBER(FIND(SUBSTITUTE(UPPER(TRIM(MID(SUBSTITUTE($H5,",",REPT(" ",99)),1,99)))," ",""),SUBSTITUTE(SUBSTITUTE(SUBSTITUTE(SUBSTITUTE(UPPER(J5),"$","")," ",""),"SALES!",""),"CONTACTS!","")))))+IF(SUBSTITUTE(UPPER(TRIM(MID(SUBSTITUTE($H5,",",REPT(" ",99)),100,99)))," ","")="",0,IF(ISNUMBER(FIND("$",SUBSTITUTE(UPPER(TRIM(MID(SUBSTITUTE($H5,",",REPT(" ",99)),100,99)))," ",""))),--ISNUMBER(FIND(SUBSTITUTE(UPPER(TRIM(MID(SUBSTITUTE($H5,",",REPT(" ",99)),100,99)))," ",""),SUBSTITUTE(SUBSTITUTE(SUBSTITUTE(UPPER(J5)," ",""),"SALES!",""),"CONTACTS!",""))),--ISNUMBER(FIND(SUBSTITUTE(UPPER(TRIM(MID(SUBSTITUTE($H5,",",REPT(" ",99)),100,99)))," ",""),SUBSTITUTE(SUBSTITUTE(SUBSTITUTE(SUBSTITUTE(UPPER(J5),"$","")," ",""),"SALES!",""),"CONTACTS!","")))))+IF(SUBSTITUTE(UPPER(TRIM(MID(SUBSTITUTE($H5,",",REPT(" ",99)),199,99)))," ","")="",0,IF(ISNUMBER(FIND("$",SUBSTITUTE(UPPER(TRIM(MID(SUBSTITUTE($H5,",",REPT(" ",99)),199,99)))," ",""))),--ISNUMBER(FIND(SUBSTITUTE(UPPER(TRIM(MID(SUBSTITUTE($H5,",",REPT(" ",99)),199,99)))," ",""),SUBSTITUTE(SUBSTITUTE(SUBSTITUTE(UPPER(J5)," ",""),"SALES!",""),"CONTACTS!",""))),--ISNUMBER(FIND(SUBSTITUTE(UPPER(TRIM(MID(SUBSTITUTE($H5,",",REPT(" ",99)),199,99)))," ",""),SUBSTITUTE(SUBSTITUTE(SUBSTITUTE(SUBSTITUTE(UPPER(J5),"$","")," ",""),"SALES!",""),"CONTACTS!","")))))+IF(SUBSTITUTE(UPPER(TRIM(MID(SUBSTITUTE($H5,",",REPT(" ",99)),298,99)))," ","")="",0,IF(ISNUMBER(FIND("$",SUBSTITUTE(UPPER(TRIM(MID(SUBSTITUTE($H5,",",REPT(" ",99)),298,99)))," ",""))),--ISNUMBER(FIND(SUBSTITUTE(UPPER(TRIM(MID(SUBSTITUTE($H5,",",REPT(" ",99)),298,99)))," ",""),SUBSTITUTE(SUBSTITUTE(SUBSTITUTE(UPPER(J5)," ",""),"SALES!",""),"CONTACTS!",""))),--ISNUMBER(FIND(SUBSTITUTE(UPPER(TRIM(MID(SUBSTITUTE($H5,",",REPT(" ",99)),298,99)))," ",""),SUBSTITUTE(SUBSTITUTE(SUBSTITUTE(SUBSTITUTE(UPPER(J5),"$","")," ",""),"SALES!",""),"CONTACTS!","")))))+IF(SUBSTITUTE(UPPER(TRIM(MID(SUBSTITUTE($H5,",",REPT(" ",99)),397,99)))," ","")="",0,IF(ISNUMBER(FIND("$",SUBSTITUTE(UPPER(TRIM(MID(SUBSTITUTE($H5,",",REPT(" ",99)),397,99)))," ",""))),--ISNUMBER(FIND(SUBSTITUTE(UPPER(TRIM(MID(SUBSTITUTE($H5,",",REPT(" ",99)),397,99)))," ",""),SUBSTITUTE(SUBSTITUTE(SUBSTITUTE(UPPER(J5)," ",""),"SALES!",""),"CONTACTS!",""))),--ISNUMBER(FIND(SUBSTITUTE(UPPER(TRIM(MID(SUBSTITUTE($H5,",",REPT(" ",99)),397,99)))," ",""),SUBSTITUTE(SUBSTITUTE(SUBSTITUTE(SUBSTITUTE(UPPER(J5),"$","")," ",""),"SALES!",""),"CONTACTS!","")))))+IF(SUBSTITUTE(UPPER(TRIM(MID(SUBSTITUTE($H5,",",REPT(" ",99)),496,99)))," ","")="",0,IF(ISNUMBER(FIND("$",SUBSTITUTE(UPPER(TRIM(MID(SUBSTITUTE($H5,",",REPT(" ",99)),496,99)))," ",""))),--ISNUMBER(FIND(SUBSTITUTE(UPPER(TRIM(MID(SUBSTITUTE($H5,",",REPT(" ",99)),496,99)))," ",""),SUBSTITUTE(SUBSTITUTE(SUBSTITUTE(UPPER(J5)," ",""),"SALES!",""),"CONTACTS!",""))),--ISNUMBER(FIND(SUBSTITUTE(UPPER(TRIM(MID(SUBSTITUTE($H5,",",REPT(" ",99)),496,99)))," ",""),SUBSTITUTE(SUBSTITUTE(SUBSTITUTE(SUBSTITUTE(UPPER(J5),"$","")," ",""),"SALES!",""),"CONTACTS!","")))))) | L5: =IF(SUBSTITUTE(UPPER(TRIM(MID(SUBSTITUTE($H5,",",REPT(" ",99)),1,99)))," ","")="",0,1)+IF(SUBSTITUTE(UPPER(TRIM(MID(SUBSTITUTE($H5,",",REPT(" ",99)),100,99)))," ","")="",0,1)+IF(SUBSTITUTE(UPPER(TRIM(MID(SUBSTITUTE($H5,",",REPT(" ",99)),199,99)))," ","")="",0,1)+IF(SUBSTITUTE(UPPER(TRIM(MID(SUBSTITUTE($H5,",",REPT(" ",99)),298,99)))," ","")="",0,1)+IF(SUBSTITUTE(UPPER(TRIM(MID(SUBSTITUTE($H5,",",REPT(" ",99)),397,99)))," ","")="",0,1)+IF(SUBSTITUTE(UPPER(TRIM(MID(SUBSTITUTE($H5,",",REPT(" ",99)),496,99)))," ","")="",0,1) | M5: =IF(J5="","",IF(AND(I5="formula",LEFT(TRIM(J5),1)<>"="),"FAIL",IF(K5=L5,"PASS","CHECK"))) | N5: operator inside a criteria string
A6: F05 | B6: Conditional average | C6: Average unit price for product A. | D6: Sales!A1:F13 | E6: =LOKUP.V($C6, Sales!A1:F13) | F6: =AVERAGEIF(Sales!C2:C13,"A",Sales!E2:E13) | G6: =AVERAGEIF(Sales!C2:C13,"A",Sales!E2:E13) | H6: AVERAGEIF,C2:C13,E2:E13 | I6: formula | K6: =IF(J6="","",IF(SUBSTITUTE(UPPER(TRIM(MID(SUBSTITUTE($H6,",",REPT(" ",99)),1,99)))," ","")="",0,IF(ISNUMBER(FIND("$",SUBSTITUTE(UPPER(TRIM(MID(SUBSTITUTE($H6,",",REPT(" ",99)),1,99)))," ",""))),--ISNUMBER(FIND(SUBSTITUTE(UPPER(TRIM(MID(SUBSTITUTE($H6,",",REPT(" ",99)),1,99)))," ",""),SUBSTITUTE(SUBSTITUTE(SUBSTITUTE(UPPER(J6)," ",""),"SALES!",""),"CONTACTS!",""))),--ISNUMBER(FIND(SUBSTITUTE(UPPER(TRIM(MID(SUBSTITUTE($H6,",",REPT(" ",99)),1,99)))," ",""),SUBSTITUTE(SUBSTITUTE(SUBSTITUTE(SUBSTITUTE(UPPER(J6),"$","")," ",""),"SALES!",""),"CONTACTS!","")))))+IF(SUBSTITUTE(UPPER(TRIM(MID(SUBSTITUTE($H6,",",REPT(" ",99)),100,99)))," ","")="",0,IF(ISNUMBER(FIND("$",SUBSTITUTE(UPPER(TRIM(MID(SUBSTITUTE($H6,",",REPT(" ",99)),100,99)))," ",""))),--ISNUMBER(FIND(SUBSTITUTE(UPPER(TRIM(MID(SUBSTITUTE($H6,",",REPT(" ",99)),100,99)))," ",""),SUBSTITUTE(SUBSTITUTE(SUBSTITUTE(UPPER(J6)," ",""),"SALES!",""),"CONTACTS!",""))),--ISNUMBER(FIND(SUBSTITUTE(UPPER(TRIM(MID(SUBSTITUTE($H6,",",REPT(" ",99)),100,99)))," ",""),SUBSTITUTE(SUBSTITUTE(SUBSTITUTE(SUBSTITUTE(UPPER(J6),"$","")," ",""),"SALES!",""),"CONTACTS!","")))))+IF(SUBSTITUTE(UPPER(TRIM(MID(SUBSTITUTE($H6,",",REPT(" ",99)),199,99)))," ","")="",0,IF(ISNUMBER(FIND("$",SUBSTITUTE(UPPER(TRIM(MID(SUBSTITUTE($H6,",",REPT(" ",99)),199,99)))," ",""))),--ISNUMBER(FIND(SUBSTITUTE(UPPER(TRIM(MID(SUBSTITUTE($H6,",",REPT(" ",99)),199,99)))," ",""),SUBSTITUTE(SUBSTITUTE(SUBSTITUTE(UPPER(J6)," ",""),"SALES!",""),"CONTACTS!",""))),--ISNUMBER(FIND(SUBSTITUTE(UPPER(TRIM(MID(SUBSTITUTE($H6,",",REPT(" ",99)),199,99)))," ",""),SUBSTITUTE(SUBSTITUTE(SUBSTITUTE(SUBSTITUTE(UPPER(J6),"$","")," ",""),"SALES!",""),"CONTACTS!","")))))+IF(SUBSTITUTE(UPPER(TRIM(MID(SUBSTITUTE($H6,",",REPT(" ",99)),298,99)))," ","")="",0,IF(ISNUMBER(FIND("$",SUBSTITUTE(UPPER(TRIM(MID(SUBSTITUTE($H6,",",REPT(" ",99)),298,99)))," ",""))),--ISNUMBER(FIND(SUBSTITUTE(UPPER(TRIM(MID(SUBSTITUTE($H6,",",REPT(" ",99)),298,99)))," ",""),SUBSTITUTE(SUBSTITUTE(SUBSTITUTE(UPPER(J6)," ",""),"SALES!",""),"CONTACTS!",""))),--ISNUMBER(FIND(SUBSTITUTE(UPPER(TRIM(MID(SUBSTITUTE($H6,",",REPT(" ",99)),298,99)))," ",""),SUBSTITUTE(SUBSTITUTE(SUBSTITUTE(SUBSTITUTE(UPPER(J6),"$","")," ",""),"SALES!",""),"CONTACTS!","")))))+IF(SUBSTITUTE(UPPER(TRIM(MID(SUBSTITUTE($H6,",",REPT(" ",99)),397,99)))," ","")="",0,IF(ISNUMBER(FIND("$",SUBSTITUTE(UPPER(TRIM(MID(SUBSTITUTE($H6,",",REPT(" ",99)),397,99)))," ",""))),--ISNUMBER(FIND(SUBSTITUTE(UPPER(TRIM(MID(SUBSTITUTE($H6,",",REPT(" ",99)),397,99)))," ",""),SUBSTITUTE(SUBSTITUTE(SUBSTITUTE(UPPER(J6)," ",""),"SALES!",""),"CONTACTS!",""))),--ISNUMBER(FIND(SUBSTITUTE(UPPER(TRIM(MID(SUBSTITUTE($H6,",",REPT(" ",99)),397,99)))," ",""),SUBSTITUTE(SUBSTITUTE(SUBSTITUTE(SUBSTITUTE(UPPER(J6),"$","")," ",""),"SALES!",""),"CONTACTS!","")))))+IF(SUBSTITUTE(UPPER(TRIM(MID(SUBSTITUTE($H6,",",REPT(" ",99)),496,99)))," ","")="",0,IF(ISNUMBER(FIND("$",SUBSTITUTE(UPPER(TRIM(MID(SUBSTITUTE($H6,",",REPT(" ",99)),496,99)))," ",""))),--ISNUMBER(FIND(SUBSTITUTE(UPPER(TRIM(MID(SUBSTITUTE($H6,",",REPT(" ",99)),496,99)))," ",""),SUBSTITUTE(SUBSTITUTE(SUBSTITUTE(UPPER(J6)," ",""),"SALES!",""),"CONTACTS!",""))),--ISNUMBER(FIND(SUBSTITUTE(UPPER(TRIM(MID(SUBSTITUTE($H6,",",REPT(" ",99)),496,99)))," ",""),SUBSTITUTE(SUBSTITUTE(SUBSTITUTE(SUBSTITUTE(UPPER(J6),"$","")," ",""),"SALES!",""),"CONTACTS!","")))))) | L6: =IF(SUBSTITUTE(UPPER(TRIM(MID(SUBSTITUTE($H6,",",REPT(" ",99)),1,99)))," ","")="",0,1)+IF(SUBSTITUTE(UPPER(TRIM(MID(SUBSTITUTE($H6,",",REPT(" ",99)),100,99)))," ","")="",0,1)+IF(SUBSTITUTE(UPPER(TRIM(MID(SUBSTITUTE($H6,",",REPT(" ",99)),199,99)))," ","")="",0,1)+IF(SUBSTITUTE(UPPER(TRIM(MID(SUBSTITUTE($H6,",",REPT(" ",99)),298,99)))," ","")="",0,1)+IF(SUBSTITUTE(UPPER(TRIM(MID(SUBSTITUTE($H6,",",REPT(" ",99)),397,99)))," ","")="",0,1)+IF(SUBSTITUTE(UPPER(TRIM(MID(SUBSTITUTE($H6,",",REPT(" ",99)),496,99)))," ","")="",0,1) | M6: =IF(J6="","",IF(AND(I6="formula",LEFT(TRIM(J6),1)<>"="),"FAIL",IF(K6=L6,"PASS","CHECK"))) | N6: argument order differs from SUMIFS
A7: F06 | B7: Date criteria | C7: Revenue for East in March 2026. | D7: Sales!A1:F13 | E7: =LOKUP.V($C7, Sales!A1:F13) | F7: =SUMIFS(Sales!F2:F13,Sales!A2:A13,"East",Sales!B2:B13,DATE(2026,3,1)) | G7: =SUMIFS(Sales!F2:F13,Sales!A2:A13,"East",Sales!B2:B13,DATE(2026,3,1)) | H7: F2:F13,A2:A13,B2:B13,EAST | I7: formula | K7: =IF(J7="","",IF(SUBSTITUTE(UPPER(TRIM(MID(SUBSTITUTE($H7,",",REPT(" ",99)),1,99)))," ","")="",0,IF(ISNUMBER(FIND("$",SUBSTITUTE(UPPER(TRIM(MID(SUBSTITUTE($H7,",",REPT(" ",99)),1,99)))," ",""))),--ISNUMBER(FIND(SUBSTITUTE(UPPER(TRIM(MID(SUBSTITUTE($H7,",",REPT(" ",99)),1,99)))," ",""),SUBSTITUTE(SUBSTITUTE(SUBSTITUTE(UPPER(J7)," ",""),"SALES!",""),"CONTACTS!",""))),--ISNUMBER(FIND(SUBSTITUTE(UPPER(TRIM(MID(SUBSTITUTE($H7,",",REPT(" ",99)),1,99)))," ",""),SUBSTITUTE(SUBSTITUTE(SUBSTITUTE(SUBSTITUTE(UPPER(J7),"$","")," ",""),"SALES!",""),"CONTACTS!","")))))+IF(SUBSTITUTE(UPPER(TRIM(MID(SUBSTITUTE($H7,",",REPT(" ",99)),100,99)))," ","")="",0,IF(ISNUMBER(FIND("$",SUBSTITUTE(UPPER(TRIM(MID(SUBSTITUTE($H7,",",REPT(" ",99)),100,99)))," ",""))),--ISNUMBER(FIND(SUBSTITUTE(UPPER(TRIM(MID(SUBSTITUTE($H7,",",REPT(" ",99)),100,99)))," ",""),SUBSTITUTE(SUBSTITUTE(SUBSTITUTE(UPPER(J7)," ",""),"SALES!",""),"CONTACTS!",""))),--ISNUMBER(FIND(SUBSTITUTE(UPPER(TRIM(MID(SUBSTITUTE($H7,",",REPT(" ",99)),100,99)))," ",""),SUBSTITUTE(SUBSTITUTE(SUBSTITUTE(SUBSTITUTE(UPPER(J7),"$","")," ",""),"SALES!",""),"CONTACTS!","")))))+IF(SUBSTITUTE(UPPER(TRIM(MID(SUBSTITUTE($H7,",",REPT(" ",99)),199,99)))," ","")="",0,IF(ISNUMBER(FIND("$",SUBSTITUTE(UPPER(TRIM(MID(SUBSTITUTE($H7,",",REPT(" ",99)),199,99)))," ",""))),--ISNUMBER(FIND(SUBSTITUTE(UPPER(TRIM(MID(SUBSTITUTE($H7,",",REPT(" ",99)),199,99)))," ",""),SUBSTITUTE(SUBSTITUTE(SUBSTITUTE(UPPER(J7)," ",""),"SALES!",""),"CONTACTS!",""))),--ISNUMBER(FIND(SUBSTITUTE(UPPER(TRIM(MID(SUBSTITUTE($H7,",",REPT(" ",99)),199,99)))," ",""),SUBSTITUTE(SUBSTITUTE(SUBSTITUTE(SUBSTITUTE(UPPER(J7),"$","")," ",""),"SALES!",""),"CONTACTS!","")))))+IF(SUBSTITUTE(UPPER(TRIM(MID(SUBSTITUTE($H7,",",REPT(" ",99)),298,99)))," ","")="",0,IF(ISNUMBER(FIND("$",SUBSTITUTE(UPPER(TRIM(MID(SUBSTITUTE($H7,",",REPT(" ",99)),298,99)))," ",""))),--ISNUMBER(FIND(SUBSTITUTE(UPPER(TRIM(MID(SUBSTITUTE($H7,",",REPT(" ",99)),298,99)))," ",""),SUBSTITUTE(SUBSTITUTE(SUBSTITUTE(UPPER(J7)," ",""),"SALES!",""),"CONTACTS!",""))),--ISNUMBER(FIND(SUBSTITUTE(UPPER(TRIM(MID(SUBSTITUTE($H7,",",REPT(" ",99)),298,99)))," ",""),SUBSTITUTE(SUBSTITUTE(SUBSTITUTE(SUBSTITUTE(UPPER(J7),"$","")," ",""),"SALES!",""),"CONTACTS!","")))))+IF(SUBSTITUTE(UPPER(TRIM(MID(SUBSTITUTE($H7,",",REPT(" ",99)),397,99)))," ","")="",0,IF(ISNUMBER(FIND("$",SUBSTITUTE(UPPER(TRIM(MID(SUBSTITUTE($H7,",",REPT(" ",99)),397,99)))," ",""))),--ISNUMBER(FIND(SUBSTITUTE(UPPER(TRIM(MID(SUBSTITUTE($H7,",",REPT(" ",99)),397,99)))," ",""),SUBSTITUTE(SUBSTITUTE(SUBSTITUTE(UPPER(J7)," ",""),"SALES!",""),"CONTACTS!",""))),--ISNUMBER(FIND(SUBSTITUTE(UPPER(TRIM(MID(SUBSTITUTE($H7,",",REPT(" ",99)),397,99)))," ",""),SUBSTITUTE(SUBSTITUTE(SUBSTITUTE(SUBSTITUTE(UPPER(J7),"$","")," ",""),"SALES!",""),"CONTACTS!","")))))+IF(SUBSTITUTE(UPPER(TRIM(MID(SUBSTITUTE($H7,",",REPT(" ",99)),496,99)))," ","")="",0,IF(ISNUMBER(FIND("$",SUBSTITUTE(UPPER(TRIM(MID(SUBSTITUTE($H7,",",REPT(" ",99)),496,99)))," ",""))),--ISNUMBER(FIND(SUBSTITUTE(UPPER(TRIM(MID(SUBSTITUTE($H7,",",REPT(" ",99)),496,99)))," ",""),SUBSTITUTE(SUBSTITUTE(SUBSTITUTE(UPPER(J7)," ",""),"SALES!",""),"CONTACTS!",""))),--ISNUMBER(FIND(SUBSTITUTE(UPPER(TRIM(MID(SUBSTITUTE($H7,",",REPT(" ",99)),496,99)))," ",""),SUBSTITUTE(SUBSTITUTE(SUBSTITUTE(SUBSTITUTE(UPPER(J7),"$","")," ",""),"SALES!",""),"CONTACTS!","")))))) | L7: =IF(SUBSTITUTE(UPPER(TRIM(MID(SUBSTITUTE($H7,",",REPT(" ",99)),1,99)))," ","")="",0,1)+IF(SUBSTITUTE(UPPER(TRIM(MID(SUBSTITUTE($H7,",",REPT(" ",99)),100,99)))," ","")="",0,1)+IF(SUBSTITUTE(UPPER(TRIM(MID(SUBSTITUTE($H7,",",REPT(" ",99)),199,99)))," ","")="",0,1)+IF(SUBSTITUTE(UPPER(TRIM(MID(SUBSTITUTE($H7,",",REPT(" ",99)),298,99)))," ","")="",0,1)+IF(SUBSTITUTE(UPPER(TRIM(MID(SUBSTITUTE($H7,",",REPT(" ",99)),397,99)))," ","")="",0,1)+IF(SUBSTITUTE(UPPER(TRIM(MID(SUBSTITUTE($H7,",",REPT(" ",99)),496,99)))," ","")="",0,1) | M7: =IF(J7="","",IF(AND(I7="formula",LEFT(TRIM(J7),1)<>"="),"FAIL",IF(K7=L7,"PASS","CHECK"))) | N7: dates are serial numbers; needs DATE() or a range test
A8: F07 | B8: Lookup | C8: Which region had the single highest revenue in one row? | D8: Sales!A1:F13 | E8: =LOKUP.V($C8, Sales!A1:F13) | F8: =INDEX(Sales!A2:A13,MATCH(MAX(Sales!F2:F13),Sales!F2:F13,0)) | G8: =INDEX(Sales!A2:A13,MATCH(MAX(Sales!F2:F13),Sales!F2:F13,0)) | H8: MAX,F2:F13,A2:A13 | I8: formula | K8: =IF(J8="","",IF(SUBSTITUTE(UPPER(TRIM(MID(SUBSTITUTE($H8,",",REPT(" ",99)),1,99)))," ","")="",0,IF(ISNUMBER(FIND("$",SUBSTITUTE(UPPER(TRIM(MID(SUBSTITUTE($H8,",",REPT(" ",99)),1,99)))," ",""))),--ISNUMBER(FIND(SUBSTITUTE(UPPER(TRIM(MID(SUBSTITUTE($H8,",",REPT(" ",99)),1,99)))," ",""),SUBSTITUTE(SUBSTITUTE(SUBSTITUTE(UPPER(J8)," ",""),"SALES!",""),"CONTACTS!",""))),--ISNUMBER(FIND(SUBSTITUTE(UPPER(TRIM(MID(SUBSTITUTE($H8,",",REPT(" ",99)),1,99)))," ",""),SUBSTITUTE(SUBSTITUTE(SUBSTITUTE(SUBSTITUTE(UPPER(J8),"$","")," ",""),"SALES!",""),"CONTACTS!","")))))+IF(SUBSTITUTE(UPPER(TRIM(MID(SUBSTITUTE($H8,",",REPT(" ",99)),100,99)))," ","")="",0,IF(ISNUMBER(FIND("$",SUBSTITUTE(UPPER(TRIM(MID(SUBSTITUTE($H8,",",REPT(" ",99)),100,99)))," ",""))),--ISNUMBER(FIND(SUBSTITUTE(UPPER(TRIM(MID(SUBSTITUTE($H8,",",REPT(" ",99)),100,99)))," ",""),SUBSTITUTE(SUBSTITUTE(SUBSTITUTE(UPPER(J8)," ",""),"SALES!",""),"CONTACTS!",""))),--ISNUMBER(FIND(SUBSTITUTE(UPPER(TRIM(MID(SUBSTITUTE($H8,",",REPT(" ",99)),100,99)))," ",""),SUBSTITUTE(SUBSTITUTE(SUBSTITUTE(SUBSTITUTE(UPPER(J8),"$","")," ",""),"SALES!",""),"CONTACTS!","")))))+IF(SUBSTITUTE(UPPER(TRIM(MID(SUBSTITUTE($H8,",",REPT(" ",99)),199,99)))," ","")="",0,IF(ISNUMBER(FIND("$",SUBSTITUTE(UPPER(TRIM(MID(SUBSTITUTE($H8,",",REPT(" ",99)),199,99)))," ",""))),--ISNUMBER(FIND(SUBSTITUTE(UPPER(TRIM(MID(SUBSTITUTE($H8,",",REPT(" ",99)),199,99)))," ",""),SUBSTITUTE(SUBSTITUTE(SUBSTITUTE(UPPER(J8)," ",""),"SALES!",""),"CONTACTS!",""))),--ISNUMBER(FIND(SUBSTITUTE(UPPER(TRIM(MID(SUBSTITUTE($H8,",",REPT(" ",99)),199,99)))," ",""),SUBSTITUTE(SUBSTITUTE(SUBSTITUTE(SUBSTITUTE(UPPER(J8),"$","")," ",""),"SALES!",""),"CONTACTS!","")))))+IF(SUBSTITUTE(UPPER(TRIM(MID(SUBSTITUTE($H8,",",REPT(" ",99)),298,99)))," ","")="",0,IF(ISNUMBER(FIND("$",SUBSTITUTE(UPPER(TRIM(MID(SUBSTITUTE($H8,",",REPT(" ",99)),298,99)))," ",""))),--ISNUMBER(FIND(SUBSTITUTE(UPPER(TRIM(MID(SUBSTITUTE($H8,",",REPT(" ",99)),298,99)))," ",""),SUBSTITUTE(SUBSTITUTE(SUBSTITUTE(UPPER(J8)," ",""),"SALES!",""),"CONTACTS!",""))),--ISNUMBER(FIND(SUBSTITUTE(UPPER(TRIM(MID(SUBSTITUTE($H8,",",REPT(" ",99)),298,99)))," ",""),SUBSTITUTE(SUBSTITUTE(SUBSTITUTE(SUBSTITUTE(UPPER(J8),"$","")," ",""),"SALES!",""),"CONTACTS!","")))))+IF(SUBSTITUTE(UPPER(TRIM(MID(SUBSTITUTE($H8,",",REPT(" ",99)),397,99)))," ","")="",0,IF(ISNUMBER(FIND("$",SUBSTITUTE(UPPER(TRIM(MID(SUBSTITUTE($H8,",",REPT(" ",99)),397,99)))," ",""))),--ISNUMBER(FIND(SUBSTITUTE(UPPER(TRIM(MID(SUBSTITUTE($H8,",",REPT(" ",99)),397,99)))," ",""),SUBSTITUTE(SUBSTITUTE(SUBSTITUTE(UPPER(J8)," ",""),"SALES!",""),"CONTACTS!",""))),--ISNUMBER(FIND(SUBSTITUTE(UPPER(TRIM(MID(SUBSTITUTE($H8,",",REPT(" ",99)),397,99)))," ",""),SUBSTITUTE(SUBSTITUTE(SUBSTITUTE(SUBSTITUTE(UPPER(J8),"$","")," ",""),"SALES!",""),"CONTACTS!","")))))+IF(SUBSTITUTE(UPPER(TRIM(MID(SUBSTITUTE($H8,",",REPT(" ",99)),496,99)))," ","")="",0,IF(ISNUMBER(FIND("$",SUBSTITUTE(UPPER(TRIM(MID(SUBSTITUTE($H8,",",REPT(" ",99)),496,99)))," ",""))),--ISNUMBER(FIND(SUBSTITUTE(UPPER(TRIM(MID(SUBSTITUTE($H8,",",REPT(" ",99)),496,99)))," ",""),SUBSTITUTE(SUBSTITUTE(SUBSTITUTE(UPPER(J8)," ",""),"SALES!",""),"CONTACTS!",""))),--ISNUMBER(FIND(SUBSTITUTE(UPPER(TRIM(MID(SUBSTITUTE($H8,",",REPT(" ",99)),496,99)))," ",""),SUBSTITUTE(SUBSTITUTE(SUBSTITUTE(SUBSTITUTE(UPPER(J8),"$","")," ",""),"SALES!",""),"CONTACTS!","")))))) | L8: =IF(SUBSTITUTE(UPPER(TRIM(MID(SUBSTITUTE($H8,",",REPT(" ",99)),1,99)))," ","")="",0,1)+IF(SUBSTITUTE(UPPER(TRIM(MID(SUBSTITUTE($H8,",",REPT(" ",99)),100,99)))," ","")="",0,1)+IF(SUBSTITUTE(UPPER(TRIM(MID(SUBSTITUTE($H8,",",REPT(" ",99)),199,99)))," ","")="",0,1)+IF(SUBSTITUTE(UPPER(TRIM(MID(SUBSTITUTE($H8,",",REPT(" ",99)),298,99)))," ","")="",0,1)+IF(SUBSTITUTE(UPPER(TRIM(MID(SUBSTITUTE($H8,",",REPT(" ",99)),397,99)))," ","")="",0,1)+IF(SUBSTITUTE(UPPER(TRIM(MID(SUBSTITUTE($H8,",",REPT(" ",99)),496,99)))," ","")="",0,1) | M8: =IF(J8="","",IF(AND(I8="formula",LEFT(TRIM(J8),1)<>"="),"FAIL",IF(K8=L8,"PASS","CHECK"))) | N8: INDEX/MATCH or XLOOKUP both pass
A9: F08 | B9: Row formula | C9: Revenue for row 2 from units and unit price. | D9: Sales!A1:F13 | E9: =LOKUP.V($C9, Sales!A1:F13) | F9: =Sales!D2*Sales!E2 | G9: =Sales!D2*Sales!E2 | H9: D2,E2,* | I9: formula | K9: =IF(J9="","",IF(SUBSTITUTE(UPPER(TRIM(MID(SUBSTITUTE($H9,",",REPT(" ",99)),1,99)))," ","")="",0,IF(ISNUMBER(FIND("$",SUBSTITUTE(UPPER(TRIM(MID(SUBSTITUTE($H9,",",REPT(" ",99)),1,99)))," ",""))),--ISNUMBER(FIND(SUBSTITUTE(UPPER(TRIM(MID(SUBSTITUTE($H9,",",REPT(" ",99)),1,99)))," ",""),SUBSTITUTE(SUBSTITUTE(SUBSTITUTE(UPPER(J9)," ",""),"SALES!",""),"CONTACTS!",""))),--ISNUMBER(FIND(SUBSTITUTE(UPPER(TRIM(MID(SUBSTITUTE($H9,",",REPT(" ",99)),1,99)))," ",""),SUBSTITUTE(SUBSTITUTE(SUBSTITUTE(SUBSTITUTE(UPPER(J9),"$","")," ",""),"SALES!",""),"CONTACTS!","")))))+IF(SUBSTITUTE(UPPER(TRIM(MID(SUBSTITUTE($H9,",",REPT(" ",99)),100,99)))," ","")="",0,IF(ISNUMBER(FIND("$",SUBSTITUTE(UPPER(TRIM(MID(SUBSTITUTE($H9,",",REPT(" ",99)),100,99)))," ",""))),--ISNUMBER(FIND(SUBSTITUTE(UPPER(TRIM(MID(SUBSTITUTE($H9,",",REPT(" ",99)),100,99)))," ",""),SUBSTITUTE(SUBSTITUTE(SUBSTITUTE(UPPER(J9)," ",""),"SALES!",""),"CONTACTS!",""))),--ISNUMBER(FIND(SUBSTITUTE(UPPER(TRIM(MID(SUBSTITUTE($H9,",",REPT(" ",99)),100,99)))," ",""),SUBSTITUTE(SUBSTITUTE(SUBSTITUTE(SUBSTITUTE(UPPER(J9),"$","")," ",""),"SALES!",""),"CONTACTS!","")))))+IF(SUBSTITUTE(UPPER(TRIM(MID(SUBSTITUTE($H9,",",REPT(" ",99)),199,99)))," ","")="",0,IF(ISNUMBER(FIND("$",SUBSTITUTE(UPPER(TRIM(MID(SUBSTITUTE($H9,",",REPT(" ",99)),199,99)))," ",""))),--ISNUMBER(FIND(SUBSTITUTE(UPPER(TRIM(MID(SUBSTITUTE($H9,",",REPT(" ",99)),199,99)))," ",""),SUBSTITUTE(SUBSTITUTE(SUBSTITUTE(UPPER(J9)," ",""),"SALES!",""),"CONTACTS!",""))),--ISNUMBER(FIND(SUBSTITUTE(UPPER(TRIM(MID(SUBSTITUTE($H9,",",REPT(" ",99)),199,99)))," ",""),SUBSTITUTE(SUBSTITUTE(SUBSTITUTE(SUBSTITUTE(UPPER(J9),"$","")," ",""),"SALES!",""),"CONTACTS!","")))))+IF(SUBSTITUTE(UPPER(TRIM(MID(SUBSTITUTE($H9,",",REPT(" ",99)),298,99)))," ","")="",0,IF(ISNUMBER(FIND("$",SUBSTITUTE(UPPER(TRIM(MID(SUBSTITUTE($H9,",",REPT(" ",99)),298,99)))," ",""))),--ISNUMBER(FIND(SUBSTITUTE(UPPER(TRIM(MID(SUBSTITUTE($H9,",",REPT(" ",99)),298,99)))," ",""),SUBSTITUTE(SUBSTITUTE(SUBSTITUTE(UPPER(J9)," ",""),"SALES!",""),"CONTACTS!",""))),--ISNUMBER(FIND(SUBSTITUTE(UPPER(TRIM(MID(SUBSTITUTE($H9,",",REPT(" ",99)),298,99)))," ",""),SUBSTITUTE(SUBSTITUTE(SUBSTITUTE(SUBSTITUTE(UPPER(J9),"$","")," ",""),"SALES!",""),"CONTACTS!","")))))+IF(SUBSTITUTE(UPPER(TRIM(MID(SUBSTITUTE($H9,",",REPT(" ",99)),397,99)))," ","")="",0,IF(ISNUMBER(FIND("$",SUBSTITUTE(UPPER(TRIM(MID(SUBSTITUTE($H9,",",REPT(" ",99)),397,99)))," ",""))),--ISNUMBER(FIND(SUBSTITUTE(UPPER(TRIM(MID(SUBSTITUTE($H9,",",REPT(" ",99)),397,99)))," ",""),SUBSTITUTE(SUBSTITUTE(SUBSTITUTE(UPPER(J9)," ",""),"SALES!",""),"CONTACTS!",""))),--ISNUMBER(FIND(SUBSTITUTE(UPPER(TRIM(MID(SUBSTITUTE($H9,",",REPT(" ",99)),397,99)))," ",""),SUBSTITUTE(SUBSTITUTE(SUBSTITUTE(SUBSTITUTE(UPPER(J9),"$","")," ",""),"SALES!",""),"CONTACTS!","")))))+IF(SUBSTITUTE(UPPER(TRIM(MID(SUBSTITUTE($H9,",",REPT(" ",99)),496,99)))," ","")="",0,IF(ISNUMBER(FIND("$",SUBSTITUTE(UPPER(TRIM(MID(SUBSTITUTE($H9,",",REPT(" ",99)),496,99)))," ",""))),--ISNUMBER(FIND(SUBSTITUTE(UPPER(TRIM(MID(SUBSTITUTE($H9,",",REPT(" ",99)),496,99)))," ",""),SUBSTITUTE(SUBSTITUTE(SUBSTITUTE(UPPER(J9)," ",""),"SALES!",""),"CONTACTS!",""))),--ISNUMBER(FIND(SUBSTITUTE(UPPER(TRIM(MID(SUBSTITUTE($H9,",",REPT(" ",99)),496,99)))," ",""),SUBSTITUTE(SUBSTITUTE(SUBSTITUTE(SUBSTITUTE(UPPER(J9),"$","")," ",""),"SALES!",""),"CONTACTS!","")))))) | L9: =IF(SUBSTITUTE(UPPER(TRIM(MID(SUBSTITUTE($H9,",",REPT(" ",99)),1,99)))," ","")="",0,1)+IF(SUBSTITUTE(UPPER(TRIM(MID(SUBSTITUTE($H9,",",REPT(" ",99)),100,99)))," ","")="",0,1)+IF(SUBSTITUTE(UPPER(TRIM(MID(SUBSTITUTE($H9,",",REPT(" ",99)),199,99)))," ","")="",0,1)+IF(SUBSTITUTE(UPPER(TRIM(MID(SUBSTITUTE($H9,",",REPT(" ",99)),298,99)))," ","")="",0,1)+IF(SUBSTITUTE(UPPER(TRIM(MID(SUBSTITUTE($H9,",",REPT(" ",99)),397,99)))," ","")="",0,1)+IF(SUBSTITUTE(UPPER(TRIM(MID(SUBSTITUTE($H9,",",REPT(" ",99)),496,99)))," ","")="",0,1) | M9: =IF(J9="","",IF(AND(I9="formula",LEFT(TRIM(J9),1)<>"="),"FAIL",IF(K9=L9,"PASS","CHECK"))) | N9: picks the right two columns
A10: F09 | B10: Row formula | C10: Revenue in row 2 with 18% GST added. | D10: Sales!A1:F13 | E10: =LOKUP.V($C10, Sales!A1:F13) | F10: =Sales!F2*1.18 | G10: =Sales!F2*1.18 | H10: F2,18 | I10: formula | K10: =IF(J10="","",IF(SUBSTITUTE(UPPER(TRIM(MID(SUBSTITUTE($H10,",",REPT(" ",99)),1,99)))," ","")="",0,IF(ISNUMBER(FIND("$",SUBSTITUTE(UPPER(TRIM(MID(SUBSTITUTE($H10,",",REPT(" ",99)),1,99)))," ",""))),--ISNUMBER(FIND(SUBSTITUTE(UPPER(TRIM(MID(SUBSTITUTE($H10,",",REPT(" ",99)),1,99)))," ",""),SUBSTITUTE(SUBSTITUTE(SUBSTITUTE(UPPER(J10)," ",""),"SALES!",""),"CONTACTS!",""))),--ISNUMBER(FIND(SUBSTITUTE(UPPER(TRIM(MID(SUBSTITUTE($H10,",",REPT(" ",99)),1,99)))," ",""),SUBSTITUTE(SUBSTITUTE(SUBSTITUTE(SUBSTITUTE(UPPER(J10),"$","")," ",""),"SALES!",""),"CONTACTS!","")))))+IF(SUBSTITUTE(UPPER(TRIM(MID(SUBSTITUTE($H10,",",REPT(" ",99)),100,99)))," ","")="",0,IF(ISNUMBER(FIND("$",SUBSTITUTE(UPPER(TRIM(MID(SUBSTITUTE($H10,",",REPT(" ",99)),100,99)))," ",""))),--ISNUMBER(FIND(SUBSTITUTE(UPPER(TRIM(MID(SUBSTITUTE($H10,",",REPT(" ",99)),100,99)))," ",""),SUBSTITUTE(SUBSTITUTE(SUBSTITUTE(UPPER(J10)," ",""),"SALES!",""),"CONTACTS!",""))),--ISNUMBER(FIND(SUBSTITUTE(UPPER(TRIM(MID(SUBSTITUTE($H10,",",REPT(" ",99)),100,99)))," ",""),SUBSTITUTE(SUBSTITUTE(SUBSTITUTE(SUBSTITUTE(UPPER(J10),"$","")," ",""),"SALES!",""),"CONTACTS!","")))))+IF(SUBSTITUTE(UPPER(TRIM(MID(SUBSTITUTE($H10,",",REPT(" ",99)),199,99)))," ","")="",0,IF(ISNUMBER(FIND("$",SUBSTITUTE(UPPER(TRIM(MID(SUBSTITUTE($H10,",",REPT(" ",99)),199,99)))," ",""))),--ISNUMBER(FIND(SUBSTITUTE(UPPER(TRIM(MID(SUBSTITUTE($H10,",",REPT(" ",99)),199,99)))," ",""),SUBSTITUTE(SUBSTITUTE(SUBSTITUTE(UPPER(J10)," ",""),"SALES!",""),"CONTACTS!",""))),--ISNUMBER(FIND(SUBSTITUTE(UPPER(TRIM(MID(SUBSTITUTE($H10,",",REPT(" ",99)),199,99)))," ",""),SUBSTITUTE(SUBSTITUTE(SUBSTITUTE(SUBSTITUTE(UPPER(J10),"$","")," ",""),"SALES!",""),"CONTACTS!","")))))+IF(SUBSTITUTE(UPPER(TRIM(MID(SUBSTITUTE($H10,",",REPT(" ",99)),298,99)))," ","")="",0,IF(ISNUMBER(FIND("$",SUBSTITUTE(UPPER(TRIM(MID(SUBSTITUTE($H10,",",REPT(" ",99)),298,99)))," ",""))),--ISNUMBER(FIND(SUBSTITUTE(UPPER(TRIM(MID(SUBSTITUTE($H10,",",REPT(" ",99)),298,99)))," ",""),SUBSTITUTE(SUBSTITUTE(SUBSTITUTE(UPPER(J10)," ",""),"SALES!",""),"CONTACTS!",""))),--ISNUMBER(FIND(SUBSTITUTE(UPPER(TRIM(MID(SUBSTITUTE($H10,",",REPT(" ",99)),298,99)))," ",""),SUBSTITUTE(SUBSTITUTE(SUBSTITUTE(SUBSTITUTE(UPPER(J10),"$","")," ",""),"SALES!",""),"CONTACTS!","")))))+IF(SUBSTITUTE(UPPER(TRIM(MID(SUBSTITUTE($H10,",",REPT(" ",99)),397,99)))," ","")="",0,IF(ISNUMBER(FIND("$",SUBSTITUTE(UPPER(TRIM(MID(SUBSTITUTE($H10,",",REPT(" ",99)),397,99)))," ",""))),--ISNUMBER(FIND(SUBSTITUTE(UPPER(TRIM(MID(SUBSTITUTE($H10,",",REPT(" ",99)),397,99)))," ",""),SUBSTITUTE(SUBSTITUTE(SUBSTITUTE(UPPER(J10)," ",""),"SALES!",""),"CONTACTS!",""))),--ISNUMBER(FIND(SUBSTITUTE(UPPER(TRIM(MID(SUBSTITUTE($H10,",",REPT(" ",99)),397,99)))," ",""),SUBSTITUTE(SUBSTITUTE(SUBSTITUTE(SUBSTITUTE(UPPER(J10),"$","")," ",""),"SALES!",""),"CONTACTS!","")))))+IF(SUBSTITUTE(UPPER(TRIM(MID(SUBSTITUTE($H10,",",REPT(" ",99)),496,99)))," ","")="",0,IF(ISNUMBER(FIND("$",SUBSTITUTE(UPPER(TRIM(MID(SUBSTITUTE($H10,",",REPT(" ",99)),496,99)))," ",""))),--ISNUMBER(FIND(SUBSTITUTE(UPPER(TRIM(MID(SUBSTITUTE($H10,",",REPT(" ",99)),496,99)))," ",""),SUBSTITUTE(SUBSTITUTE(SUBSTITUTE(UPPER(J10)," ",""),"SALES!",""),"CONTACTS!",""))),--ISNUMBER(FIND(SUBSTITUTE(UPPER(TRIM(MID(SUBSTITUTE($H10,",",REPT(" ",99)),496,99)))," ",""),SUBSTITUTE(SUBSTITUTE(SUBSTITUTE(SUBSTITUTE(UPPER(J10),"$","")," ",""),"SALES!",""),"CONTACTS!","")))))) | L10: =IF(SUBSTITUTE(UPPER(TRIM(MID(SUBSTITUTE($H10,",",REPT(" ",99)),1,99)))," ","")="",0,1)+IF(SUBSTITUTE(UPPER(TRIM(MID(SUBSTITUTE($H10,",",REPT(" ",99)),100,99)))," ","")="",0,1)+IF(SUBSTITUTE(UPPER(TRIM(MID(SUBSTITUTE($H10,",",REPT(" ",99)),199,99)))," ","")="",0,1)+IF(SUBSTITUTE(UPPER(TRIM(MID(SUBSTITUTE($H10,",",REPT(" ",99)),298,99)))," ","")="",0,1)+IF(SUBSTITUTE(UPPER(TRIM(MID(SUBSTITUTE($H10,",",REPT(" ",99)),397,99)))," ","")="",0,1)+IF(SUBSTITUTE(UPPER(TRIM(MID(SUBSTITUTE($H10,",",REPT(" ",99)),496,99)))," ","")="",0,1) | M10: =IF(J10="","",IF(AND(I10="formula",LEFT(TRIM(J10),1)<>"="),"FAIL",IF(K10=L10,"PASS","CHECK"))) | N10: F2*1.18, F2*(1+18%), F2+F2*0.18 all pass
A11: F10 | B11: Logic | C11: Show High if units in row 3 are 100 or more, otherwise Low. | D11: Sales!A1:F13 | E11: =LOKUP.V($C11, Sales!A1:F13) | F11: =IF(Sales!D3>=100,"High","Low") | G11: =IF(Sales!D3>=100,"High","Low") | H11: IF(,D3,100,HIGH,LOW | I11: formula | K11: =IF(J11="","",IF(SUBSTITUTE(UPPER(TRIM(MID(SUBSTITUTE($H11,",",REPT(" ",99)),1,99)))," ","")="",0,IF(ISNUMBER(FIND("$",SUBSTITUTE(UPPER(TRIM(MID(SUBSTITUTE($H11,",",REPT(" ",99)),1,99)))," ",""))),--ISNUMBER(FIND(SUBSTITUTE(UPPER(TRIM(MID(SUBSTITUTE($H11,",",REPT(" ",99)),1,99)))," ",""),SUBSTITUTE(SUBSTITUTE(SUBSTITUTE(UPPER(J11)," ",""),"SALES!",""),"CONTACTS!",""))),--ISNUMBER(FIND(SUBSTITUTE(UPPER(TRIM(MID(SUBSTITUTE($H11,",",REPT(" ",99)),1,99)))," ",""),SUBSTITUTE(SUBSTITUTE(SUBSTITUTE(SUBSTITUTE(UPPER(J11),"$","")," ",""),"SALES!",""),"CONTACTS!","")))))+IF(SUBSTITUTE(UPPER(TRIM(MID(SUBSTITUTE($H11,",",REPT(" ",99)),100,99)))," ","")="",0,IF(ISNUMBER(FIND("$",SUBSTITUTE(UPPER(TRIM(MID(SUBSTITUTE($H11,",",REPT(" ",99)),100,99)))," ",""))),--ISNUMBER(FIND(SUBSTITUTE(UPPER(TRIM(MID(SUBSTITUTE($H11,",",REPT(" ",99)),100,99)))," ",""),SUBSTITUTE(SUBSTITUTE(SUBSTITUTE(UPPER(J11)," ",""),"SALES!",""),"CONTACTS!",""))),--ISNUMBER(FIND(SUBSTITUTE(UPPER(TRIM(MID(SUBSTITUTE($H11,",",REPT(" ",99)),100,99)))," ",""),SUBSTITUTE(SUBSTITUTE(SUBSTITUTE(SUBSTITUTE(UPPER(J11),"$","")," ",""),"SALES!",""),"CONTACTS!","")))))+IF(SUBSTITUTE(UPPER(TRIM(MID(SUBSTITUTE($H11,",",REPT(" ",99)),199,99)))," ","")="",0,IF(ISNUMBER(FIND("$",SUBSTITUTE(UPPER(TRIM(MID(SUBSTITUTE($H11,",",REPT(" ",99)),199,99)))," ",""))),--ISNUMBER(FIND(SUBSTITUTE(UPPER(TRIM(MID(SUBSTITUTE($H11,",",REPT(" ",99)),199,99)))," ",""),SUBSTITUTE(SUBSTITUTE(SUBSTITUTE(UPPER(J11)," ",""),"SALES!",""),"CONTACTS!",""))),--ISNUMBER(FIND(SUBSTITUTE(UPPER(TRIM(MID(SUBSTITUTE($H11,",",REPT(" ",99)),199,99)))," ",""),SUBSTITUTE(SUBSTITUTE(SUBSTITUTE(SUBSTITUTE(UPPER(J11),"$","")," ",""),"SALES!",""),"CONTACTS!","")))))+IF(SUBSTITUTE(UPPER(TRIM(MID(SUBSTITUTE($H11,",",REPT(" ",99)),298,99)))," ","")="",0,IF(ISNUMBER(FIND("$",SUBSTITUTE(UPPER(TRIM(MID(SUBSTITUTE($H11,",",REPT(" ",99)),298,99)))," ",""))),--ISNUMBER(FIND(SUBSTITUTE(UPPER(TRIM(MID(SUBSTITUTE($H11,",",REPT(" ",99)),298,99)))," ",""),SUBSTITUTE(SUBSTITUTE(SUBSTITUTE(UPPER(J11)," ",""),"SALES!",""),"CONTACTS!",""))),--ISNUMBER(FIND(SUBSTITUTE(UPPER(TRIM(MID(SUBSTITUTE($H11,",",REPT(" ",99)),298,99)))," ",""),SUBSTITUTE(SUBSTITUTE(SUBSTITUTE(SUBSTITUTE(UPPER(J11),"$","")," ",""),"SALES!",""),"CONTACTS!","")))))+IF(SUBSTITUTE(UPPER(TRIM(MID(SUBSTITUTE($H11,",",REPT(" ",99)),397,99)))," ","")="",0,IF(ISNUMBER(FIND("$",SUBSTITUTE(UPPER(TRIM(MID(SUBSTITUTE($H11,",",REPT(" ",99)),397,99)))," ",""))),--ISNUMBER(FIND(SUBSTITUTE(UPPER(TRIM(MID(SUBSTITUTE($H11,",",REPT(" ",99)),397,99)))," ",""),SUBSTITUTE(SUBSTITUTE(SUBSTITUTE(UPPER(J11)," ",""),"SALES!",""),"CONTACTS!",""))),--ISNUMBER(FIND(SUBSTITUTE(UPPER(TRIM(MID(SUBSTITUTE($H11,",",REPT(" ",99)),397,99)))," ",""),SUBSTITUTE(SUBSTITUTE(SUBSTITUTE(SUBSTITUTE(UPPER(J11),"$","")," ",""),"SALES!",""),"CONTACTS!","")))))+IF(SUBSTITUTE(UPPER(TRIM(MID(SUBSTITUTE($H11,",",REPT(" ",99)),496,99)))," ","")="",0,IF(ISNUMBER(FIND("$",SUBSTITUTE(UPPER(TRIM(MID(SUBSTITUTE($H11,",",REPT(" ",99)),496,99)))," ",""))),--ISNUMBER(FIND(SUBSTITUTE(UPPER(TRIM(MID(SUBSTITUTE($H11,",",REPT(" ",99)),496,99)))," ",""),SUBSTITUTE(SUBSTITUTE(SUBSTITUTE(UPPER(J11)," ",""),"SALES!",""),"CONTACTS!",""))),--ISNUMBER(FIND(SUBSTITUTE(UPPER(TRIM(MID(SUBSTITUTE($H11,",",REPT(" ",99)),496,99)))," ",""),SUBSTITUTE(SUBSTITUTE(SUBSTITUTE(SUBSTITUTE(UPPER(J11),"$","")," ",""),"SALES!",""),"CONTACTS!","")))))) | L11: =IF(SUBSTITUTE(UPPER(TRIM(MID(SUBSTITUTE($H11,",",REPT(" ",99)),1,99)))," ","")="",0,1)+IF(SUBSTITUTE(UPPER(TRIM(MID(SUBSTITUTE($H11,",",REPT(" ",99)),100,99)))," ","")="",0,1)+IF(SUBSTITUTE(UPPER(TRIM(MID(SUBSTITUTE($H11,",",REPT(" ",99)),199,99)))," ","")="",0,1)+IF(SUBSTITUTE(UPPER(TRIM(MID(SUBSTITUTE($H11,",",REPT(" ",99)),298,99)))," ","")="",0,1)+IF(SUBSTITUTE(UPPER(TRIM(MID(SUBSTITUTE($H11,",",REPT(" ",99)),397,99)))," ","")="",0,1)+IF(SUBSTITUTE(UPPER(TRIM(MID(SUBSTITUTE($H11,",",REPT(" ",99)),496,99)))," ","")="",0,1) | M11: =IF(J11="","",IF(AND(I11="formula",LEFT(TRIM(J11),1)<>"="),"FAIL",IF(K11=L11,"PASS","CHECK"))) | N11: row 3: units 80 but revenue 32,000, so using the wrong column gives the wrong label
A12: F11 | B12: Absolute refs | C12: Row 2's share of total revenue, as a formula I can drag down to row 13. | D12: Sales!A1:F13 | E12: =LOKUP.V($C12, Sales!A1:F13) | F12: =Sales!F2/SUM(Sales!$F$2:$F$13) | G12: =Sales!F2/SUM(Sales!$F$2:$F$13) | H12: F2/,$F$2:$F$13 | I12: formula | K12: =IF(J12="","",IF(SUBSTITUTE(UPPER(TRIM(MID(SUBSTITUTE($H12,",",REPT(" ",99)),1,99)))," ","")="",0,IF(ISNUMBER(FIND("$",SUBSTITUTE(UPPER(TRIM(MID(SUBSTITUTE($H12,",",REPT(" ",99)),1,99)))," ",""))),--ISNUMBER(FIND(SUBSTITUTE(UPPER(TRIM(MID(SUBSTITUTE($H12,",",REPT(" ",99)),1,99)))," ",""),SUBSTITUTE(SUBSTITUTE(SUBSTITUTE(UPPER(J12)," ",""),"SALES!",""),"CONTACTS!",""))),--ISNUMBER(FIND(SUBSTITUTE(UPPER(TRIM(MID(SUBSTITUTE($H12,",",REPT(" ",99)),1,99)))," ",""),SUBSTITUTE(SUBSTITUTE(SUBSTITUTE(SUBSTITUTE(UPPER(J12),"$","")," ",""),"SALES!",""),"CONTACTS!","")))))+IF(SUBSTITUTE(UPPER(TRIM(MID(SUBSTITUTE($H12,",",REPT(" ",99)),100,99)))," ","")="",0,IF(ISNUMBER(FIND("$",SUBSTITUTE(UPPER(TRIM(MID(SUBSTITUTE($H12,",",REPT(" ",99)),100,99)))," ",""))),--ISNUMBER(FIND(SUBSTITUTE(UPPER(TRIM(MID(SUBSTITUTE($H12,",",REPT(" ",99)),100,99)))," ",""),SUBSTITUTE(SUBSTITUTE(SUBSTITUTE(UPPER(J12)," ",""),"SALES!",""),"CONTACTS!",""))),--ISNUMBER(FIND(SUBSTITUTE(UPPER(TRIM(MID(SUBSTITUTE($H12,",",REPT(" ",99)),100,99)))," ",""),SUBSTITUTE(SUBSTITUTE(SUBSTITUTE(SUBSTITUTE(UPPER(J12),"$","")," ",""),"SALES!",""),"CONTACTS!","")))))+IF(SUBSTITUTE(UPPER(TRIM(MID(SUBSTITUTE($H12,",",REPT(" ",99)),199,99)))," ","")="",0,IF(ISNUMBER(FIND("$",SUBSTITUTE(UPPER(TRIM(MID(SUBSTITUTE($H12,",",REPT(" ",99)),199,99)))," ",""))),--ISNUMBER(FIND(SUBSTITUTE(UPPER(TRIM(MID(SUBSTITUTE($H12,",",REPT(" ",99)),199,99)))," ",""),SUBSTITUTE(SUBSTITUTE(SUBSTITUTE(UPPER(J12)," ",""),"SALES!",""),"CONTACTS!",""))),--ISNUMBER(FIND(SUBSTITUTE(UPPER(TRIM(MID(SUBSTITUTE($H12,",",REPT(" ",99)),199,99)))," ",""),SUBSTITUTE(SUBSTITUTE(SUBSTITUTE(SUBSTITUTE(UPPER(J12),"$","")," ",""),"SALES!",""),"CONTACTS!","")))))+IF(SUBSTITUTE(UPPER(TRIM(MID(SUBSTITUTE($H12,",",REPT(" ",99)),298,99)))," ","")="",0,IF(ISNUMBER(FIND("$",SUBSTITUTE(UPPER(TRIM(MID(SUBSTITUTE($H12,",",REPT(" ",99)),298,99)))," ",""))),--ISNUMBER(FIND(SUBSTITUTE(UPPER(TRIM(MID(SUBSTITUTE($H12,",",REPT(" ",99)),298,99)))," ",""),SUBSTITUTE(SUBSTITUTE(SUBSTITUTE(UPPER(J12)," ",""),"SALES!",""),"CONTACTS!",""))),--ISNUMBER(FIND(SUBSTITUTE(UPPER(TRIM(MID(SUBSTITUTE($H12,",",REPT(" ",99)),298,99)))," ",""),SUBSTITUTE(SUBSTITUTE(SUBSTITUTE(SUBSTITUTE(UPPER(J12),"$","")," ",""),"SALES!",""),"CONTACTS!","")))))+IF(SUBSTITUTE(UPPER(TRIM(MID(SUBSTITUTE($H12,",",REPT(" ",99)),397,99)))," ","")="",0,IF(ISNUMBER(FIND("$",SUBSTITUTE(UPPER(TRIM(MID(SUBSTITUTE($H12,",",REPT(" ",99)),397,99)))," ",""))),--ISNUMBER(FIND(SUBSTITUTE(UPPER(TRIM(MID(SUBSTITUTE($H12,",",REPT(" ",99)),397,99)))," ",""),SUBSTITUTE(SUBSTITUTE(SUBSTITUTE(UPPER(J12)," ",""),"SALES!",""),"CONTACTS!",""))),--ISNUMBER(FIND(SUBSTITUTE(UPPER(TRIM(MID(SUBSTITUTE($H12,",",REPT(" ",99)),397,99)))," ",""),SUBSTITUTE(SUBSTITUTE(SUBSTITUTE(SUBSTITUTE(UPPER(J12),"$","")," ",""),"SALES!",""),"CONTACTS!","")))))+IF(SUBSTITUTE(UPPER(TRIM(MID(SUBSTITUTE($H12,",",REPT(" ",99)),496,99)))," ","")="",0,IF(ISNUMBER(FIND("$",SUBSTITUTE(UPPER(TRIM(MID(SUBSTITUTE($H12,",",REPT(" ",99)),496,99)))," ",""))),--ISNUMBER(FIND(SUBSTITUTE(UPPER(TRIM(MID(SUBSTITUTE($H12,",",REPT(" ",99)),496,99)))," ",""),SUBSTITUTE(SUBSTITUTE(SUBSTITUTE(UPPER(J12)," ",""),"SALES!",""),"CONTACTS!",""))),--ISNUMBER(FIND(SUBSTITUTE(UPPER(TRIM(MID(SUBSTITUTE($H12,",",REPT(" ",99)),496,99)))," ",""),SUBSTITUTE(SUBSTITUTE(SUBSTITUTE(SUBSTITUTE(UPPER(J12),"$","")," ",""),"SALES!",""),"CONTACTS!","")))))) | L12: =IF(SUBSTITUTE(UPPER(TRIM(MID(SUBSTITUTE($H12,",",REPT(" ",99)),1,99)))," ","")="",0,1)+IF(SUBSTITUTE(UPPER(TRIM(MID(SUBSTITUTE($H12,",",REPT(" ",99)),100,99)))," ","")="",0,1)+IF(SUBSTITUTE(UPPER(TRIM(MID(SUBSTITUTE($H12,",",REPT(" ",99)),199,99)))," ","")="",0,1)+IF(SUBSTITUTE(UPPER(TRIM(MID(SUBSTITUTE($H12,",",REPT(" ",99)),298,99)))," ","")="",0,1)+IF(SUBSTITUTE(UPPER(TRIM(MID(SUBSTITUTE($H12,",",REPT(" ",99)),397,99)))," ","")="",0,1)+IF(SUBSTITUTE(UPPER(TRIM(MID(SUBSTITUTE($H12,",",REPT(" ",99)),496,99)))," ","")="",0,1) | M12: =IF(J12="","",IF(AND(I12="formula",LEFT(TRIM(J12),1)<>"="),"FAIL",IF(K12=L12,"PASS","CHECK"))) | N12: must lock the total range with $
A13: F12 | B13: Date | C13: Full month name from the date in row 2. | D13: Sales!A1:F13 | E13: =LOKUP.V($C13, Sales!A1:F13) | F13: =TEXT(Sales!B2,"mmmm") | G13: =TEXT(Sales!B2,"mmmm") | H13: TEXT,B2,MMMM | I13: formula | K13: =IF(J13="","",IF(SUBSTITUTE(UPPER(TRIM(MID(SUBSTITUTE($H13,",",REPT(" ",99)),1,99)))," ","")="",0,IF(ISNUMBER(FIND("$",SUBSTITUTE(UPPER(TRIM(MID(SUBSTITUTE($H13,",",REPT(" ",99)),1,99)))," ",""))),--ISNUMBER(FIND(SUBSTITUTE(UPPER(TRIM(MID(SUBSTITUTE($H13,",",REPT(" ",99)),1,99)))," ",""),SUBSTITUTE(SUBSTITUTE(SUBSTITUTE(UPPER(J13)," ",""),"SALES!",""),"CONTACTS!",""))),--ISNUMBER(FIND(SUBSTITUTE(UPPER(TRIM(MID(SUBSTITUTE($H13,",",REPT(" ",99)),1,99)))," ",""),SUBSTITUTE(SUBSTITUTE(SUBSTITUTE(SUBSTITUTE(UPPER(J13),"$","")," ",""),"SALES!",""),"CONTACTS!","")))))+IF(SUBSTITUTE(UPPER(TRIM(MID(SUBSTITUTE($H13,",",REPT(" ",99)),100,99)))," ","")="",0,IF(ISNUMBER(FIND("$",SUBSTITUTE(UPPER(TRIM(MID(SUBSTITUTE($H13,",",REPT(" ",99)),100,99)))," ",""))),--ISNUMBER(FIND(SUBSTITUTE(UPPER(TRIM(MID(SUBSTITUTE($H13,",",REPT(" ",99)),100,99)))," ",""),SUBSTITUTE(SUBSTITUTE(SUBSTITUTE(UPPER(J13)," ",""),"SALES!",""),"CONTACTS!",""))),--ISNUMBER(FIND(SUBSTITUTE(UPPER(TRIM(MID(SUBSTITUTE($H13,",",REPT(" ",99)),100,99)))," ",""),SUBSTITUTE(SUBSTITUTE(SUBSTITUTE(SUBSTITUTE(UPPER(J13),"$","")," ",""),"SALES!",""),"CONTACTS!","")))))+IF(SUBSTITUTE(UPPER(TRIM(MID(SUBSTITUTE($H13,",",REPT(" ",99)),199,99)))," ","")="",0,IF(ISNUMBER(FIND("$",SUBSTITUTE(UPPER(TRIM(MID(SUBSTITUTE($H13,",",REPT(" ",99)),199,99)))," ",""))),--ISNUMBER(FIND(SUBSTITUTE(UPPER(TRIM(MID(SUBSTITUTE($H13,",",REPT(" ",99)),199,99)))," ",""),SUBSTITUTE(SUBSTITUTE(SUBSTITUTE(UPPER(J13)," ",""),"SALES!",""),"CONTACTS!",""))),--ISNUMBER(FIND(SUBSTITUTE(UPPER(TRIM(MID(SUBSTITUTE($H13,",",REPT(" ",99)),199,99)))," ",""),SUBSTITUTE(SUBSTITUTE(SUBSTITUTE(SUBSTITUTE(UPPER(J13),"$","")," ",""),"SALES!",""),"CONTACTS!","")))))+IF(SUBSTITUTE(UPPER(TRIM(MID(SUBSTITUTE($H13,",",REPT(" ",99)),298,99)))," ","")="",0,IF(ISNUMBER(FIND("$",SUBSTITUTE(UPPER(TRIM(MID(SUBSTITUTE($H13,",",REPT(" ",99)),298,99)))," ",""))),--ISNUMBER(FIND(SUBSTITUTE(UPPER(TRIM(MID(SUBSTITUTE($H13,",",REPT(" ",99)),298,99)))," ",""),SUBSTITUTE(SUBSTITUTE(SUBSTITUTE(UPPER(J13)," ",""),"SALES!",""),"CONTACTS!",""))),--ISNUMBER(FIND(SUBSTITUTE(UPPER(TRIM(MID(SUBSTITUTE($H13,",",REPT(" ",99)),298,99)))," ",""),SUBSTITUTE(SUBSTITUTE(SUBSTITUTE(SUBSTITUTE(UPPER(J13),"$","")," ",""),"SALES!",""),"CONTACTS!","")))))+IF(SUBSTITUTE(UPPER(TRIM(MID(SUBSTITUTE($H13,",",REPT(" ",99)),397,99)))," ","")="",0,IF(ISNUMBER(FIND("$",SUBSTITUTE(UPPER(TRIM(MID(SUBSTITUTE($H13,",",REPT(" ",99)),397,99)))," ",""))),--ISNUMBER(FIND(SUBSTITUTE(UPPER(TRIM(MID(SUBSTITUTE($H13,",",REPT(" ",99)),397,99)))," ",""),SUBSTITUTE(SUBSTITUTE(SUBSTITUTE(UPPER(J13)," ",""),"SALES!",""),"CONTACTS!",""))),--ISNUMBER(FIND(SUBSTITUTE(UPPER(TRIM(MID(SUBSTITUTE($H13,",",REPT(" ",99)),397,99)))," ",""),SUBSTITUTE(SUBSTITUTE(SUBSTITUTE(SUBSTITUTE(UPPER(J13),"$","")," ",""),"SALES!",""),"CONTACTS!","")))))+IF(SUBSTITUTE(UPPER(TRIM(MID(SUBSTITUTE($H13,",",REPT(" ",99)),496,99)))," ","")="",0,IF(ISNUMBER(FIND("$",SUBSTITUTE(UPPER(TRIM(MID(SUBSTITUTE($H13,",",REPT(" ",99)),496,99)))," ",""))),--ISNUMBER(FIND(SUBSTITUTE(UPPER(TRIM(MID(SUBSTITUTE($H13,",",REPT(" ",99)),496,99)))," ",""),SUBSTITUTE(SUBSTITUTE(SUBSTITUTE(UPPER(J13)," ",""),"SALES!",""),"CONTACTS!",""))),--ISNUMBER(FIND(SUBSTITUTE(UPPER(TRIM(MID(SUBSTITUTE($H13,",",REPT(" ",99)),496,99)))," ",""),SUBSTITUTE(SUBSTITUTE(SUBSTITUTE(SUBSTITUTE(UPPER(J13),"$","")," ",""),"SALES!",""),"CONTACTS!","")))))) | L13: =IF(SUBSTITUTE(UPPER(TRIM(MID(SUBSTITUTE($H13,",",REPT(" ",99)),1,99)))," ","")="",0,1)+IF(SUBSTITUTE(UPPER(TRIM(MID(SUBSTITUTE($H13,",",REPT(" ",99)),100,99)))," ","")="",0,1)+IF(SUBSTITUTE(UPPER(TRIM(MID(SUBSTITUTE($H13,",",REPT(" ",99)),199,99)))," ","")="",0,1)+IF(SUBSTITUTE(UPPER(TRIM(MID(SUBSTITUTE($H13,",",REPT(" ",99)),298,99)))," ","")="",0,1)+IF(SUBSTITUTE(UPPER(TRIM(MID(SUBSTITUTE($H13,",",REPT(" ",99)),397,99)))," ","")="",0,1)+IF(SUBSTITUTE(UPPER(TRIM(MID(SUBSTITUTE($H13,",",REPT(" ",99)),496,99)))," ","")="",0,1) | M13: =IF(J13="","",IF(AND(I13="formula",LEFT(TRIM(J13),1)<>"="),"FAIL",IF(K13=L13,"PASS","CHECK"))) | N13: TEXT format codes
A14: F13 | B14: Distinct count | C14: How many different regions are there? | D14: Sales!A1:F13 | E14: =LOKUP.V($C14, Sales!A1:F13) | F14: =SUMPRODUCT(1/COUNTIF(Sales!A2:A13,Sales!A2:A13)) | G14: =SUMPRODUCT(1/COUNTIF(Sales!A2:A13,Sales!A2:A13)) | H14: A2:A13 | I14: formula | K14: =IF(J14="","",IF(SUBSTITUTE(UPPER(TRIM(MID(SUBSTITUTE($H14,",",REPT(" ",99)),1,99)))," ","")="",0,IF(ISNUMBER(FIND("$",SUBSTITUTE(UPPER(TRIM(MID(SUBSTITUTE($H14,",",REPT(" ",99)),1,99)))," ",""))),--ISNUMBER(FIND(SUBSTITUTE(UPPER(TRIM(MID(SUBSTITUTE($H14,",",REPT(" ",99)),1,99)))," ",""),SUBSTITUTE(SUBSTITUTE(SUBSTITUTE(UPPER(J14)," ",""),"SALES!",""),"CONTACTS!",""))),--ISNUMBER(FIND(SUBSTITUTE(UPPER(TRIM(MID(SUBSTITUTE($H14,",",REPT(" ",99)),1,99)))," ",""),SUBSTITUTE(SUBSTITUTE(SUBSTITUTE(SUBSTITUTE(UPPER(J14),"$","")," ",""),"SALES!",""),"CONTACTS!","")))))+IF(SUBSTITUTE(UPPER(TRIM(MID(SUBSTITUTE($H14,",",REPT(" ",99)),100,99)))," ","")="",0,IF(ISNUMBER(FIND("$",SUBSTITUTE(UPPER(TRIM(MID(SUBSTITUTE($H14,",",REPT(" ",99)),100,99)))," ",""))),--ISNUMBER(FIND(SUBSTITUTE(UPPER(TRIM(MID(SUBSTITUTE($H14,",",REPT(" ",99)),100,99)))," ",""),SUBSTITUTE(SUBSTITUTE(SUBSTITUTE(UPPER(J14)," ",""),"SALES!",""),"CONTACTS!",""))),--ISNUMBER(FIND(SUBSTITUTE(UPPER(TRIM(MID(SUBSTITUTE($H14,",",REPT(" ",99)),100,99)))," ",""),SUBSTITUTE(SUBSTITUTE(SUBSTITUTE(SUBSTITUTE(UPPER(J14),"$","")," ",""),"SALES!",""),"CONTACTS!","")))))+IF(SUBSTITUTE(UPPER(TRIM(MID(SUBSTITUTE($H14,",",REPT(" ",99)),199,99)))," ","")="",0,IF(ISNUMBER(FIND("$",SUBSTITUTE(UPPER(TRIM(MID(SUBSTITUTE($H14,",",REPT(" ",99)),199,99)))," ",""))),--ISNUMBER(FIND(SUBSTITUTE(UPPER(TRIM(MID(SUBSTITUTE($H14,",",REPT(" ",99)),199,99)))," ",""),SUBSTITUTE(SUBSTITUTE(SUBSTITUTE(UPPER(J14)," ",""),"SALES!",""),"CONTACTS!",""))),--ISNUMBER(FIND(SUBSTITUTE(UPPER(TRIM(MID(SUBSTITUTE($H14,",",REPT(" ",99)),199,99)))," ",""),SUBSTITUTE(SUBSTITUTE(SUBSTITUTE(SUBSTITUTE(UPPER(J14),"$","")," ",""),"SALES!",""),"CONTACTS!","")))))+IF(SUBSTITUTE(UPPER(TRIM(MID(SUBSTITUTE($H14,",",REPT(" ",99)),298,99)))," ","")="",0,IF(ISNUMBER(FIND("$",SUBSTITUTE(UPPER(TRIM(MID(SUBSTITUTE($H14,",",REPT(" ",99)),298,99)))," ",""))),--ISNUMBER(FIND(SUBSTITUTE(UPPER(TRIM(MID(SUBSTITUTE($H14,",",REPT(" ",99)),298,99)))," ",""),SUBSTITUTE(SUBSTITUTE(SUBSTITUTE(UPPER(J14)," ",""),"SALES!",""),"CONTACTS!",""))),--ISNUMBER(FIND(SUBSTITUTE(UPPER(TRIM(MID(SUBSTITUTE($H14,",",REPT(" ",99)),298,99)))," ",""),SUBSTITUTE(SUBSTITUTE(SUBSTITUTE(SUBSTITUTE(UPPER(J14),"$","")," ",""),"SALES!",""),"CONTACTS!","")))))+IF(SUBSTITUTE(UPPER(TRIM(MID(SUBSTITUTE($H14,",",REPT(" ",99)),397,99)))," ","")="",0,IF(ISNUMBER(FIND("$",SUBSTITUTE(UPPER(TRIM(MID(SUBSTITUTE($H14,",",REPT(" ",99)),397,99)))," ",""))),--ISNUMBER(FIND(SUBSTITUTE(UPPER(TRIM(MID(SUBSTITUTE($H14,",",REPT(" ",99)),397,99)))," ",""),SUBSTITUTE(SUBSTITUTE(SUBSTITUTE(UPPER(J14)," ",""),"SALES!",""),"CONTACTS!",""))),--ISNUMBER(FIND(SUBSTITUTE(UPPER(TRIM(MID(SUBSTITUTE($H14,",",REPT(" ",99)),397,99)))," ",""),SUBSTITUTE(SUBSTITUTE(SUBSTITUTE(SUBSTITUTE(UPPER(J14),"$","")," ",""),"SALES!",""),"CONTACTS!","")))))+IF(SUBSTITUTE(UPPER(TRIM(MID(SUBSTITUTE($H14,",",REPT(" ",99)),496,99)))," ","")="",0,IF(ISNUMBER(FIND("$",SUBSTITUTE(UPPER(TRIM(MID(SUBSTITUTE($H14,",",REPT(" ",99)),496,99)))," ",""))),--ISNUMBER(FIND(SUBSTITUTE(UPPER(TRIM(MID(SUBSTITUTE($H14,",",REPT(" ",99)),496,99)))," ",""),SUBSTITUTE(SUBSTITUTE(SUBSTITUTE(UPPER(J14)," ",""),"SALES!",""),"CONTACTS!",""))),--ISNUMBER(FIND(SUBSTITUTE(UPPER(TRIM(MID(SUBSTITUTE($H14,",",REPT(" ",99)),496,99)))," ",""),SUBSTITUTE(SUBSTITUTE(SUBSTITUTE(SUBSTITUTE(UPPER(J14),"$","")," ",""),"SALES!",""),"CONTACTS!","")))))) | L14: =IF(SUBSTITUTE(UPPER(TRIM(MID(SUBSTITUTE($H14,",",REPT(" ",99)),1,99)))," ","")="",0,1)+IF(SUBSTITUTE(UPPER(TRIM(MID(SUBSTITUTE($H14,",",REPT(" ",99)),100,99)))," ","")="",0,1)+IF(SUBSTITUTE(UPPER(TRIM(MID(SUBSTITUTE($H14,",",REPT(" ",99)),199,99)))," ","")="",0,1)+IF(SUBSTITUTE(UPPER(TRIM(MID(SUBSTITUTE($H14,",",REPT(" ",99)),298,99)))," ","")="",0,1)+IF(SUBSTITUTE(UPPER(TRIM(MID(SUBSTITUTE($H14,",",REPT(" ",99)),397,99)))," ","")="",0,1)+IF(SUBSTITUTE(UPPER(TRIM(MID(SUBSTITUTE($H14,",",REPT(" ",99)),496,99)))," ","")="",0,1) | M14: =IF(J14="","",IF(AND(I14="formula",LEFT(TRIM(J14),1)<>"="),"FAIL",IF(K14=L14,"PASS","CHECK"))) | N14: UNIQUE or SUMPRODUCT/COUNTIF; check the value
A15: F14 | B15: Error handling | C15: Unit price of product C; show Not found if it doesn't exist. | D15: Sales!A1:F13 | E15: =LOKUP.V($C15, Sales!A1:F13) | F15: =IFERROR(INDEX(Sales!E2:E13,MATCH("C",Sales!C2:C13,0)),"Not found") | G15: =IFERROR(INDEX(Sales!E2:E13,MATCH("C",Sales!C2:C13,0)),"Not found") | H15: IFERROR,NOT FOUND,C2:C13 | I15: formula | K15: =IF(J15="","",IF(SUBSTITUTE(UPPER(TRIM(MID(SUBSTITUTE($H15,",",REPT(" ",99)),1,99)))," ","")="",0,IF(ISNUMBER(FIND("$",SUBSTITUTE(UPPER(TRIM(MID(SUBSTITUTE($H15,",",REPT(" ",99)),1,99)))," ",""))),--ISNUMBER(FIND(SUBSTITUTE(UPPER(TRIM(MID(SUBSTITUTE($H15,",",REPT(" ",99)),1,99)))," ",""),SUBSTITUTE(SUBSTITUTE(SUBSTITUTE(UPPER(J15)," ",""),"SALES!",""),"CONTACTS!",""))),--ISNUMBER(FIND(SUBSTITUTE(UPPER(TRIM(MID(SUBSTITUTE($H15,",",REPT(" ",99)),1,99)))," ",""),SUBSTITUTE(SUBSTITUTE(SUBSTITUTE(SUBSTITUTE(UPPER(J15),"$","")," ",""),"SALES!",""),"CONTACTS!","")))))+IF(SUBSTITUTE(UPPER(TRIM(MID(SUBSTITUTE($H15,",",REPT(" ",99)),100,99)))," ","")="",0,IF(ISNUMBER(FIND("$",SUBSTITUTE(UPPER(TRIM(MID(SUBSTITUTE($H15,",",REPT(" ",99)),100,99)))," ",""))),--ISNUMBER(FIND(SUBSTITUTE(UPPER(TRIM(MID(SUBSTITUTE($H15,",",REPT(" ",99)),100,99)))," ",""),SUBSTITUTE(SUBSTITUTE(SUBSTITUTE(UPPER(J15)," ",""),"SALES!",""),"CONTACTS!",""))),--ISNUMBER(FIND(SUBSTITUTE(UPPER(TRIM(MID(SUBSTITUTE($H15,",",REPT(" ",99)),100,99)))," ",""),SUBSTITUTE(SUBSTITUTE(SUBSTITUTE(SUBSTITUTE(UPPER(J15),"$","")," ",""),"SALES!",""),"CONTACTS!","")))))+IF(SUBSTITUTE(UPPER(TRIM(MID(SUBSTITUTE($H15,",",REPT(" ",99)),199,99)))," ","")="",0,IF(ISNUMBER(FIND("$",SUBSTITUTE(UPPER(TRIM(MID(SUBSTITUTE($H15,",",REPT(" ",99)),199,99)))," ",""))),--ISNUMBER(FIND(SUBSTITUTE(UPPER(TRIM(MID(SUBSTITUTE($H15,",",REPT(" ",99)),199,99)))," ",""),SUBSTITUTE(SUBSTITUTE(SUBSTITUTE(UPPER(J15)," ",""),"SALES!",""),"CONTACTS!",""))),--ISNUMBER(FIND(SUBSTITUTE(UPPER(TRIM(MID(SUBSTITUTE($H15,",",REPT(" ",99)),199,99)))," ",""),SUBSTITUTE(SUBSTITUTE(SUBSTITUTE(SUBSTITUTE(UPPER(J15),"$","")," ",""),"SALES!",""),"CONTACTS!","")))))+IF(SUBSTITUTE(UPPER(TRIM(MID(SUBSTITUTE($H15,",",REPT(" ",99)),298,99)))," ","")="",0,IF(ISNUMBER(FIND("$",SUBSTITUTE(UPPER(TRIM(MID(SUBSTITUTE($H15,",",REPT(" ",99)),298,99)))," ",""))),--ISNUMBER(FIND(SUBSTITUTE(UPPER(TRIM(MID(SUBSTITUTE($H15,",",REPT(" ",99)),298,99)))," ",""),SUBSTITUTE(SUBSTITUTE(SUBSTITUTE(UPPER(J15)," ",""),"SALES!",""),"CONTACTS!",""))),--ISNUMBER(FIND(SUBSTITUTE(UPPER(TRIM(MID(SUBSTITUTE($H15,",",REPT(" ",99)),298,99)))," ",""),SUBSTITUTE(SUBSTITUTE(SUBSTITUTE(SUBSTITUTE(UPPER(J15),"$","")," ",""),"SALES!",""),"CONTACTS!","")))))+IF(SUBSTITUTE(UPPER(TRIM(MID(SUBSTITUTE($H15,",",REPT(" ",99)),397,99)))," ","")="",0,IF(ISNUMBER(FIND("$",SUBSTITUTE(UPPER(TRIM(MID(SUBSTITUTE($H15,",",REPT(" ",99)),397,99)))," ",""))),--ISNUMBER(FIND(SUBSTITUTE(UPPER(TRIM(MID(SUBSTITUTE($H15,",",REPT(" ",99)),397,99)))," ",""),SUBSTITUTE(SUBSTITUTE(SUBSTITUTE(UPPER(J15)," ",""),"SALES!",""),"CONTACTS!",""))),--ISNUMBER(FIND(SUBSTITUTE(UPPER(TRIM(MID(SUBSTITUTE($H15,",",REPT(" ",99)),397,99)))," ",""),SUBSTITUTE(SUBSTITUTE(SUBSTITUTE(SUBSTITUTE(UPPER(J15),"$","")," ",""),"SALES!",""),"CONTACTS!","")))))+IF(SUBSTITUTE(UPPER(TRIM(MID(SUBSTITUTE($H15,",",REPT(" ",99)),496,99)))," ","")="",0,IF(ISNUMBER(FIND("$",SUBSTITUTE(UPPER(TRIM(MID(SUBSTITUTE($H15,",",REPT(" ",99)),496,99)))," ",""))),--ISNUMBER(FIND(SUBSTITUTE(UPPER(TRIM(MID(SUBSTITUTE($H15,",",REPT(" ",99)),496,99)))," ",""),SUBSTITUTE(SUBSTITUTE(SUBSTITUTE(UPPER(J15)," ",""),"SALES!",""),"CONTACTS!",""))),--ISNUMBER(FIND(SUBSTITUTE(UPPER(TRIM(MID(SUBSTITUTE($H15,",",REPT(" ",99)),496,99)))," ",""),SUBSTITUTE(SUBSTITUTE(SUBSTITUTE(SUBSTITUTE(UPPER(J15),"$","")," ",""),"SALES!",""),"CONTACTS!","")))))) | L15: =IF(SUBSTITUTE(UPPER(TRIM(MID(SUBSTITUTE($H15,",",REPT(" ",99)),1,99)))," ","")="",0,1)+IF(SUBSTITUTE(UPPER(TRIM(MID(SUBSTITUTE($H15,",",REPT(" ",99)),100,99)))," ","")="",0,1)+IF(SUBSTITUTE(UPPER(TRIM(MID(SUBSTITUTE($H15,",",REPT(" ",99)),199,99)))," ","")="",0,1)+IF(SUBSTITUTE(UPPER(TRIM(MID(SUBSTITUTE($H15,",",REPT(" ",99)),298,99)))," ","")="",0,1)+IF(SUBSTITUTE(UPPER(TRIM(MID(SUBSTITUTE($H15,",",REPT(" ",99)),397,99)))," ","")="",0,1)+IF(SUBSTITUTE(UPPER(TRIM(MID(SUBSTITUTE($H15,",",REPT(" ",99)),496,99)))," ","")="",0,1) | M15: =IF(J15="","",IF(AND(I15="formula",LEFT(TRIM(J15),1)<>"="),"FAIL",IF(K15=L15,"PASS","CHECK"))) | N15: IFNA or XLOOKUP's if_not_found → CHECK
A16: F15 | B16: Text | C16: Domain part of the email in row 2 (the text after the @). | D16: Contacts!A1:E5 | E16: =LOKUP.V($C16, Contacts!A1:E5) | F16: =MID(Contacts!C2,FIND("@",Contacts!C2)+1,100) | G16: =MID(Contacts!C2,FIND("@",Contacts!C2)+1,100) | H16: C2,@ | I16: formula | K16: =IF(J16="","",IF(SUBSTITUTE(UPPER(TRIM(MID(SUBSTITUTE($H16,",",REPT(" ",99)),1,99)))," ","")="",0,IF(ISNUMBER(FIND("$",SUBSTITUTE(UPPER(TRIM(MID(SUBSTITUTE($H16,",",REPT(" ",99)),1,99)))," ",""))),--ISNUMBER(FIND(SUBSTITUTE(UPPER(TRIM(MID(SUBSTITUTE($H16,",",REPT(" ",99)),1,99)))," ",""),SUBSTITUTE(SUBSTITUTE(SUBSTITUTE(UPPER(J16)," ",""),"SALES!",""),"CONTACTS!",""))),--ISNUMBER(FIND(SUBSTITUTE(UPPER(TRIM(MID(SUBSTITUTE($H16,",",REPT(" ",99)),1,99)))," ",""),SUBSTITUTE(SUBSTITUTE(SUBSTITUTE(SUBSTITUTE(UPPER(J16),"$","")," ",""),"SALES!",""),"CONTACTS!","")))))+IF(SUBSTITUTE(UPPER(TRIM(MID(SUBSTITUTE($H16,",",REPT(" ",99)),100,99)))," ","")="",0,IF(ISNUMBER(FIND("$",SUBSTITUTE(UPPER(TRIM(MID(SUBSTITUTE($H16,",",REPT(" ",99)),100,99)))," ",""))),--ISNUMBER(FIND(SUBSTITUTE(UPPER(TRIM(MID(SUBSTITUTE($H16,",",REPT(" ",99)),100,99)))," ",""),SUBSTITUTE(SUBSTITUTE(SUBSTITUTE(UPPER(J16)," ",""),"SALES!",""),"CONTACTS!",""))),--ISNUMBER(FIND(SUBSTITUTE(UPPER(TRIM(MID(SUBSTITUTE($H16,",",REPT(" ",99)),100,99)))," ",""),SUBSTITUTE(SUBSTITUTE(SUBSTITUTE(SUBSTITUTE(UPPER(J16),"$","")," ",""),"SALES!",""),"CONTACTS!","")))))+IF(SUBSTITUTE(UPPER(TRIM(MID(SUBSTITUTE($H16,",",REPT(" ",99)),199,99)))," ","")="",0,IF(ISNUMBER(FIND("$",SUBSTITUTE(UPPER(TRIM(MID(SUBSTITUTE($H16,",",REPT(" ",99)),199,99)))," ",""))),--ISNUMBER(FIND(SUBSTITUTE(UPPER(TRIM(MID(SUBSTITUTE($H16,",",REPT(" ",99)),199,99)))," ",""),SUBSTITUTE(SUBSTITUTE(SUBSTITUTE(UPPER(J16)," ",""),"SALES!",""),"CONTACTS!",""))),--ISNUMBER(FIND(SUBSTITUTE(UPPER(TRIM(MID(SUBSTITUTE($H16,",",REPT(" ",99)),199,99)))," ",""),SUBSTITUTE(SUBSTITUTE(SUBSTITUTE(SUBSTITUTE(UPPER(J16),"$","")," ",""),"SALES!",""),"CONTACTS!","")))))+IF(SUBSTITUTE(UPPER(TRIM(MID(SUBSTITUTE($H16,",",REPT(" ",99)),298,99)))," ","")="",0,IF(ISNUMBER(FIND("$",SUBSTITUTE(UPPER(TRIM(MID(SUBSTITUTE($H16,",",REPT(" ",99)),298,99)))," ",""))),--ISNUMBER(FIND(SUBSTITUTE(UPPER(TRIM(MID(SUBSTITUTE($H16,",",REPT(" ",99)),298,99)))," ",""),SUBSTITUTE(SUBSTITUTE(SUBSTITUTE(UPPER(J16)," ",""),"SALES!",""),"CONTACTS!",""))),--ISNUMBER(FIND(SUBSTITUTE(UPPER(TRIM(MID(SUBSTITUTE($H16,",",REPT(" ",99)),298,99)))," ",""),SUBSTITUTE(SUBSTITUTE(SUBSTITUTE(SUBSTITUTE(UPPER(J16),"$","")," ",""),"SALES!",""),"CONTACTS!","")))))+IF(SUBSTITUTE(UPPER(TRIM(MID(SUBSTITUTE($H16,",",REPT(" ",99)),397,99)))," ","")="",0,IF(ISNUMBER(FIND("$",SUBSTITUTE(UPPER(TRIM(MID(SUBSTITUTE($H16,",",REPT(" ",99)),397,99)))," ",""))),--ISNUMBER(FIND(SUBSTITUTE(UPPER(TRIM(MID(SUBSTITUTE($H16,",",REPT(" ",99)),397,99)))," ",""),SUBSTITUTE(SUBSTITUTE(SUBSTITUTE(UPPER(J16)," ",""),"SALES!",""),"CONTACTS!",""))),--ISNUMBER(FIND(SUBSTITUTE(UPPER(TRIM(MID(SUBSTITUTE($H16,",",REPT(" ",99)),397,99)))," ",""),SUBSTITUTE(SUBSTITUTE(SUBSTITUTE(SUBSTITUTE(UPPER(J16),"$","")," ",""),"SALES!",""),"CONTACTS!","")))))+IF(SUBSTITUTE(UPPER(TRIM(MID(SUBSTITUTE($H16,",",REPT(" ",99)),496,99)))," ","")="",0,IF(ISNUMBER(FIND("$",SUBSTITUTE(UPPER(TRIM(MID(SUBSTITUTE($H16,",",REPT(" ",99)),496,99)))," ",""))),--ISNUMBER(FIND(SUBSTITUTE(UPPER(TRIM(MID(SUBSTITUTE($H16,",",REPT(" ",99)),496,99)))," ",""),SUBSTITUTE(SUBSTITUTE(SUBSTITUTE(UPPER(J16)," ",""),"SALES!",""),"CONTACTS!",""))),--ISNUMBER(FIND(SUBSTITUTE(UPPER(TRIM(MID(SUBSTITUTE($H16,",",REPT(" ",99)),496,99)))," ",""),SUBSTITUTE(SUBSTITUTE(SUBSTITUTE(SUBSTITUTE(UPPER(J16),"$","")," ",""),"SALES!",""),"CONTACTS!","")))))) | L16: =IF(SUBSTITUTE(UPPER(TRIM(MID(SUBSTITUTE($H16,",",REPT(" ",99)),1,99)))," ","")="",0,1)+IF(SUBSTITUTE(UPPER(TRIM(MID(SUBSTITUTE($H16,",",REPT(" ",99)),100,99)))," ","")="",0,1)+IF(SUBSTITUTE(UPPER(TRIM(MID(SUBSTITUTE($H16,",",REPT(" ",99)),199,99)))," ","")="",0,1)+IF(SUBSTITUTE(UPPER(TRIM(MID(SUBSTITUTE($H16,",",REPT(" ",99)),298,99)))," ","")="",0,1)+IF(SUBSTITUTE(UPPER(TRIM(MID(SUBSTITUTE($H16,",",REPT(" ",99)),397,99)))," ","")="",0,1)+IF(SUBSTITUTE(UPPER(TRIM(MID(SUBSTITUTE($H16,",",REPT(" ",99)),496,99)))," ","")="",0,1) | M16: =IF(J16="","",IF(AND(I16="formula",LEFT(TRIM(J16),1)<>"="),"FAIL",IF(K16=L16,"PASS","CHECK"))) | N16: string functions on another sheet
A17: F16 | B17: Explain | C17: Explain in one sentence what this formula does: =SUMIFS(F2:F13,A2:A13,"West",C2:C13,"B") | D17: Sales!A1:F13 | E17: =LOKUP.H($C17, Sales!A1:F13) | F17: =SUMIFS(Sales!F2:F13,Sales!A2:A13,"West",Sales!C2:C13,"B") | G17: =SUMIFS(Sales!F2:F13,Sales!A2:A13,"West",Sales!C2:C13,"B") | H17: WEST,REVENUE | I17: text | K17: =IF(J17="","",IF(SUBSTITUTE(UPPER(TRIM(MID(SUBSTITUTE($H17,",",REPT(" ",99)),1,99)))," ","")="",0,IF(ISNUMBER(FIND("$",SUBSTITUTE(UPPER(TRIM(MID(SUBSTITUTE($H17,",",REPT(" ",99)),1,99)))," ",""))),--ISNUMBER(FIND(SUBSTITUTE(UPPER(TRIM(MID(SUBSTITUTE($H17,",",REPT(" ",99)),1,99)))," ",""),SUBSTITUTE(SUBSTITUTE(SUBSTITUTE(UPPER(J17)," ",""),"SALES!",""),"CONTACTS!",""))),--ISNUMBER(FIND(SUBSTITUTE(UPPER(TRIM(MID(SUBSTITUTE($H17,",",REPT(" ",99)),1,99)))," ",""),SUBSTITUTE(SUBSTITUTE(SUBSTITUTE(SUBSTITUTE(UPPER(J17),"$","")," ",""),"SALES!",""),"CONTACTS!","")))))+IF(SUBSTITUTE(UPPER(TRIM(MID(SUBSTITUTE($H17,",",REPT(" ",99)),100,99)))," ","")="",0,IF(ISNUMBER(FIND("$",SUBSTITUTE(UPPER(TRIM(MID(SUBSTITUTE($H17,",",REPT(" ",99)),100,99)))," ",""))),--ISNUMBER(FIND(SUBSTITUTE(UPPER(TRIM(MID(SUBSTITUTE($H17,",",REPT(" ",99)),100,99)))," ",""),SUBSTITUTE(SUBSTITUTE(SUBSTITUTE(UPPER(J17)," ",""),"SALES!",""),"CONTACTS!",""))),--ISNUMBER(FIND(SUBSTITUTE(UPPER(TRIM(MID(SUBSTITUTE($H17,",",REPT(" ",99)),100,99)))," ",""),SUBSTITUTE(SUBSTITUTE(SUBSTITUTE(SUBSTITUTE(UPPER(J17),"$","")," ",""),"SALES!",""),"CONTACTS!","")))))+IF(SUBSTITUTE(UPPER(TRIM(MID(SUBSTITUTE($H17,",",REPT(" ",99)),199,99)))," ","")="",0,IF(ISNUMBER(FIND("$",SUBSTITUTE(UPPER(TRIM(MID(SUBSTITUTE($H17,",",REPT(" ",99)),199,99)))," ",""))),--ISNUMBER(FIND(SUBSTITUTE(UPPER(TRIM(MID(SUBSTITUTE($H17,",",REPT(" ",99)),199,99)))," ",""),SUBSTITUTE(SUBSTITUTE(SUBSTITUTE(UPPER(J17)," ",""),"SALES!",""),"CONTACTS!",""))),--ISNUMBER(FIND(SUBSTITUTE(UPPER(TRIM(MID(SUBSTITUTE($H17,",",REPT(" ",99)),199,99)))," ",""),SUBSTITUTE(SUBSTITUTE(SUBSTITUTE(SUBSTITUTE(UPPER(J17),"$","")," ",""),"SALES!",""),"CONTACTS!","")))))+IF(SUBSTITUTE(UPPER(TRIM(MID(SUBSTITUTE($H17,",",REPT(" ",99)),298,99)))," ","")="",0,IF(ISNUMBER(FIND("$",SUBSTITUTE(UPPER(TRIM(MID(SUBSTITUTE($H17,",",REPT(" ",99)),298,99)))," ",""))),--ISNUMBER(FIND(SUBSTITUTE(UPPER(TRIM(MID(SUBSTITUTE($H17,",",REPT(" ",99)),298,99)))," ",""),SUBSTITUTE(SUBSTITUTE(SUBSTITUTE(UPPER(J17)," ",""),"SALES!",""),"CONTACTS!",""))),--ISNUMBER(FIND(SUBSTITUTE(UPPER(TRIM(MID(SUBSTITUTE($H17,",",REPT(" ",99)),298,99)))," ",""),SUBSTITUTE(SUBSTITUTE(SUBSTITUTE(SUBSTITUTE(UPPER(J17),"$","")," ",""),"SALES!",""),"CONTACTS!","")))))+IF(SUBSTITUTE(UPPER(TRIM(MID(SUBSTITUTE($H17,",",REPT(" ",99)),397,99)))," ","")="",0,IF(ISNUMBER(FIND("$",SUBSTITUTE(UPPER(TRIM(MID(SUBSTITUTE($H17,",",REPT(" ",99)),397,99)))," ",""))),--ISNUMBER(FIND(SUBSTITUTE(UPPER(TRIM(MID(SUBSTITUTE($H17,",",REPT(" ",99)),397,99)))," ",""),SUBSTITUTE(SUBSTITUTE(SUBSTITUTE(UPPER(J17)," ",""),"SALES!",""),"CONTACTS!",""))),--ISNUMBER(FIND(SUBSTITUTE(UPPER(TRIM(MID(SUBSTITUTE($H17,",",REPT(" ",99)),397,99)))," ",""),SUBSTITUTE(SUBSTITUTE(SUBSTITUTE(SUBSTITUTE(UPPER(J17),"$","")," ",""),"SALES!",""),"CONTACTS!","")))))+IF(SUBSTITUTE(UPPER(TRIM(MID(SUBSTITUTE($H17,",",REPT(" ",99)),496,99)))," ","")="",0,IF(ISNUMBER(FIND("$",SUBSTITUTE(UPPER(TRIM(MID(SUBSTITUTE($H17,",",REPT(" ",99)),496,99)))," ",""))),--ISNUMBER(FIND(SUBSTITUTE(UPPER(TRIM(MID(SUBSTITUTE($H17,",",REPT(" ",99)),496,99)))," ",""),SUBSTITUTE(SUBSTITUTE(SUBSTITUTE(UPPER(J17)," ",""),"SALES!",""),"CONTACTS!",""))),--ISNUMBER(FIND(SUBSTITUTE(UPPER(TRIM(MID(SUBSTITUTE($H17,",",REPT(" ",99)),496,99)))," ",""),SUBSTITUTE(SUBSTITUTE(SUBSTITUTE(SUBSTITUTE(UPPER(J17),"$","")," ",""),"SALES!",""),"CONTACTS!","")))))) | L17: =IF(SUBSTITUTE(UPPER(TRIM(MID(SUBSTITUTE($H17,",",REPT(" ",99)),1,99)))," ","")="",0,1)+IF(SUBSTITUTE(UPPER(TRIM(MID(SUBSTITUTE($H17,",",REPT(" ",99)),100,99)))," ","")="",0,1)+IF(SUBSTITUTE(UPPER(TRIM(MID(SUBSTITUTE($H17,",",REPT(" ",99)),199,99)))," ","")="",0,1)+IF(SUBSTITUTE(UPPER(TRIM(MID(SUBSTITUTE($H17,",",REPT(" ",99)),298,99)))," ","")="",0,1)+IF(SUBSTITUTE(UPPER(TRIM(MID(SUBSTITUTE($H17,",",REPT(" ",99)),397,99)))," ","")="",0,1)+IF(SUBSTITUTE(UPPER(TRIM(MID(SUBSTITUTE($H17,",",REPT(" ",99)),496,99)))," ","")="",0,1) | M17: =IF(J17="","",IF(AND(I17="formula",LEFT(TRIM(J17),1)<>"="),"FAIL",IF(K17=L17,"PASS","CHECK"))) | N17: reverse direction: formula → English, uses headers
A18: F17 | B18: Fix | C18: This formula returns #VALUE!: =SUM(F2:F13)+"Total". Give a corrected formula for total revenue. | D18: Sales!A1:F13 | E18: =LOKUP.V($C18, Sales!A1:F13) | F18: =SUM(Sales!F2:F13) | G18: =SUM(Sales!F2:F13) | H18: SUM,F2:F13 | I18: formula | K18: =IF(J18="","",IF(SUBSTITUTE(UPPER(TRIM(MID(SUBSTITUTE($H18,",",REPT(" ",99)),1,99)))," ","")="",0,IF(ISNUMBER(FIND("$",SUBSTITUTE(UPPER(TRIM(MID(SUBSTITUTE($H18,",",REPT(" ",99)),1,99)))," ",""))),--ISNUMBER(FIND(SUBSTITUTE(UPPER(TRIM(MID(SUBSTITUTE($H18,",",REPT(" ",99)),1,99)))," ",""),SUBSTITUTE(SUBSTITUTE(SUBSTITUTE(UPPER(J18)," ",""),"SALES!",""),"CONTACTS!",""))),--ISNUMBER(FIND(SUBSTITUTE(UPPER(TRIM(MID(SUBSTITUTE($H18,",",REPT(" ",99)),1,99)))," ",""),SUBSTITUTE(SUBSTITUTE(SUBSTITUTE(SUBSTITUTE(UPPER(J18),"$","")," ",""),"SALES!",""),"CONTACTS!","")))))+IF(SUBSTITUTE(UPPER(TRIM(MID(SUBSTITUTE($H18,",",REPT(" ",99)),100,99)))," ","")="",0,IF(ISNUMBER(FIND("$",SUBSTITUTE(UPPER(TRIM(MID(SUBSTITUTE($H18,",",REPT(" ",99)),100,99)))," ",""))),--ISNUMBER(FIND(SUBSTITUTE(UPPER(TRIM(MID(SUBSTITUTE($H18,",",REPT(" ",99)),100,99)))," ",""),SUBSTITUTE(SUBSTITUTE(SUBSTITUTE(UPPER(J18)," ",""),"SALES!",""),"CONTACTS!",""))),--ISNUMBER(FIND(SUBSTITUTE(UPPER(TRIM(MID(SUBSTITUTE($H18,",",REPT(" ",99)),100,99)))," ",""),SUBSTITUTE(SUBSTITUTE(SUBSTITUTE(SUBSTITUTE(UPPER(J18),"$","")," ",""),"SALES!",""),"CONTACTS!","")))))+IF(SUBSTITUTE(UPPER(TRIM(MID(SUBSTITUTE($H18,",",REPT(" ",99)),199,99)))," ","")="",0,IF(ISNUMBER(FIND("$",SUBSTITUTE(UPPER(TRIM(MID(SUBSTITUTE($H18,",",REPT(" ",99)),199,99)))," ",""))),--ISNUMBER(FIND(SUBSTITUTE(UPPER(TRIM(MID(SUBSTITUTE($H18,",",REPT(" ",99)),199,99)))," ",""),SUBSTITUTE(SUBSTITUTE(SUBSTITUTE(UPPER(J18)," ",""),"SALES!",""),"CONTACTS!",""))),--ISNUMBER(FIND(SUBSTITUTE(UPPER(TRIM(MID(SUBSTITUTE($H18,",",REPT(" ",99)),199,99)))," ",""),SUBSTITUTE(SUBSTITUTE(SUBSTITUTE(SUBSTITUTE(UPPER(J18),"$","")," ",""),"SALES!",""),"CONTACTS!","")))))+IF(SUBSTITUTE(UPPER(TRIM(MID(SUBSTITUTE($H18,",",REPT(" ",99)),298,99)))," ","")="",0,IF(ISNUMBER(FIND("$",SUBSTITUTE(UPPER(TRIM(MID(SUBSTITUTE($H18,",",REPT(" ",99)),298,99)))," ",""))),--ISNUMBER(FIND(SUBSTITUTE(UPPER(TRIM(MID(SUBSTITUTE($H18,",",REPT(" ",99)),298,99)))," ",""),SUBSTITUTE(SUBSTITUTE(SUBSTITUTE(UPPER(J18)," ",""),"SALES!",""),"CONTACTS!",""))),--ISNUMBER(FIND(SUBSTITUTE(UPPER(TRIM(MID(SUBSTITUTE($H18,",",REPT(" ",99)),298,99)))," ",""),SUBSTITUTE(SUBSTITUTE(SUBSTITUTE(SUBSTITUTE(UPPER(J18),"$","")," ",""),"SALES!",""),"CONTACTS!","")))))+IF(SUBSTITUTE(UPPER(TRIM(MID(SUBSTITUTE($H18,",",REPT(" ",99)),397,99)))," ","")="",0,IF(ISNUMBER(FIND("$",SUBSTITUTE(UPPER(TRIM(MID(SUBSTITUTE($H18,",",REPT(" ",99)),397,99)))," ",""))),--ISNUMBER(FIND(SUBSTITUTE(UPPER(TRIM(MID(SUBSTITUTE($H18,",",REPT(" ",99)),397,99)))," ",""),SUBSTITUTE(SUBSTITUTE(SUBSTITUTE(UPPER(J18)," ",""),"SALES!",""),"CONTACTS!",""))),--ISNUMBER(FIND(SUBSTITUTE(UPPER(TRIM(MID(SUBSTITUTE($H18,",",REPT(" ",99)),397,99)))," ",""),SUBSTITUTE(SUBSTITUTE(SUBSTITUTE(SUBSTITUTE(UPPER(J18),"$","")," ",""),"SALES!",""),"CONTACTS!","")))))+IF(SUBSTITUTE(UPPER(TRIM(MID(SUBSTITUTE($H18,",",REPT(" ",99)),496,99)))," ","")="",0,IF(ISNUMBER(FIND("$",SUBSTITUTE(UPPER(TRIM(MID(SUBSTITUTE($H18,",",REPT(" ",99)),496,99)))," ",""))),--ISNUMBER(FIND(SUBSTITUTE(UPPER(TRIM(MID(SUBSTITUTE($H18,",",REPT(" ",99)),496,99)))," ",""),SUBSTITUTE(SUBSTITUTE(SUBSTITUTE(UPPER(J18)," ",""),"SALES!",""),"CONTACTS!",""))),--ISNUMBER(FIND(SUBSTITUTE(UPPER(TRIM(MID(SUBSTITUTE($H18,",",REPT(" ",99)),496,99)))," ",""),SUBSTITUTE(SUBSTITUTE(SUBSTITUTE(SUBSTITUTE(UPPER(J18),"$","")," ",""),"SALES!",""),"CONTACTS!","")))))) | L18: =IF(SUBSTITUTE(UPPER(TRIM(MID(SUBSTITUTE($H18,",",REPT(" ",99)),1,99)))," ","")="",0,1)+IF(SUBSTITUTE(UPPER(TRIM(MID(SUBSTITUTE($H18,",",REPT(" ",99)),100,99)))," ","")="",0,1)+IF(SUBSTITUTE(UPPER(TRIM(MID(SUBSTITUTE($H18,",",REPT(" ",99)),199,99)))," ","")="",0,1)+IF(SUBSTITUTE(UPPER(TRIM(MID(SUBSTITUTE($H18,",",REPT(" ",99)),298,99)))," ","")="",0,1)+IF(SUBSTITUTE(UPPER(TRIM(MID(SUBSTITUTE($H18,",",REPT(" ",99)),397,99)))," ","")="",0,1)+IF(SUBSTITUTE(UPPER(TRIM(MID(SUBSTITUTE($H18,",",REPT(" ",99)),496,99)))," ","")="",0,1) | M18: =IF(J18="","",IF(AND(I18="formula",LEFT(TRIM(J18),1)<>"="),"FAIL",IF(K18=L18,"PASS","CHECK"))) | N18: debugging an existing formula
A19: F18 | B19: No context | C19: Count the non-empty cells in B2:B50. | D19: (none) | E19: =LOKUP.V($C19) | F19: (any sheet) | G19: - | H19: COUNTA,B2:B50 | I19: formula | K19: =IF(J19="","",IF(SUBSTITUTE(UPPER(TRIM(MID(SUBSTITUTE($H19,",",REPT(" ",99)),1,99)))," ","")="",0,IF(ISNUMBER(FIND("$",SUBSTITUTE(UPPER(TRIM(MID(SUBSTITUTE($H19,",",REPT(" ",99)),1,99)))," ",""))),--ISNUMBER(FIND(SUBSTITUTE(UPPER(TRIM(MID(SUBSTITUTE($H19,",",REPT(" ",99)),1,99)))," ",""),SUBSTITUTE(SUBSTITUTE(SUBSTITUTE(UPPER(J19)," ",""),"SALES!",""),"CONTACTS!",""))),--ISNUMBER(FIND(SUBSTITUTE(UPPER(TRIM(MID(SUBSTITUTE($H19,",",REPT(" ",99)),1,99)))," ",""),SUBSTITUTE(SUBSTITUTE(SUBSTITUTE(SUBSTITUTE(UPPER(J19),"$","")," ",""),"SALES!",""),"CONTACTS!","")))))+IF(SUBSTITUTE(UPPER(TRIM(MID(SUBSTITUTE($H19,",",REPT(" ",99)),100,99)))," ","")="",0,IF(ISNUMBER(FIND("$",SUBSTITUTE(UPPER(TRIM(MID(SUBSTITUTE($H19,",",REPT(" ",99)),100,99)))," ",""))),--ISNUMBER(FIND(SUBSTITUTE(UPPER(TRIM(MID(SUBSTITUTE($H19,",",REPT(" ",99)),100,99)))," ",""),SUBSTITUTE(SUBSTITUTE(SUBSTITUTE(UPPER(J19)," ",""),"SALES!",""),"CONTACTS!",""))),--ISNUMBER(FIND(SUBSTITUTE(UPPER(TRIM(MID(SUBSTITUTE($H19,",",REPT(" ",99)),100,99)))," ",""),SUBSTITUTE(SUBSTITUTE(SUBSTITUTE(SUBSTITUTE(UPPER(J19),"$","")," ",""),"SALES!",""),"CONTACTS!","")))))+IF(SUBSTITUTE(UPPER(TRIM(MID(SUBSTITUTE($H19,",",REPT(" ",99)),199,99)))," ","")="",0,IF(ISNUMBER(FIND("$",SUBSTITUTE(UPPER(TRIM(MID(SUBSTITUTE($H19,",",REPT(" ",99)),199,99)))," ",""))),--ISNUMBER(FIND(SUBSTITUTE(UPPER(TRIM(MID(SUBSTITUTE($H19,",",REPT(" ",99)),199,99)))," ",""),SUBSTITUTE(SUBSTITUTE(SUBSTITUTE(UPPER(J19)," ",""),"SALES!",""),"CONTACTS!",""))),--ISNUMBER(FIND(SUBSTITUTE(UPPER(TRIM(MID(SUBSTITUTE($H19,",",REPT(" ",99)),199,99)))," ",""),SUBSTITUTE(SUBSTITUTE(SUBSTITUTE(SUBSTITUTE(UPPER(J19),"$","")," ",""),"SALES!",""),"CONTACTS!","")))))+IF(SUBSTITUTE(UPPER(TRIM(MID(SUBSTITUTE($H19,",",REPT(" ",99)),298,99)))," ","")="",0,IF(ISNUMBER(FIND("$",SUBSTITUTE(UPPER(TRIM(MID(SUBSTITUTE($H19,",",REPT(" ",99)),298,99)))," ",""))),--ISNUMBER(FIND(SUBSTITUTE(UPPER(TRIM(MID(SUBSTITUTE($H19,",",REPT(" ",99)),298,99)))," ",""),SUBSTITUTE(SUBSTITUTE(SUBSTITUTE(UPPER(J19)," ",""),"SALES!",""),"CONTACTS!",""))),--ISNUMBER(FIND(SUBSTITUTE(UPPER(TRIM(MID(SUBSTITUTE($H19,",",REPT(" ",99)),298,99)))," ",""),SUBSTITUTE(SUBSTITUTE(SUBSTITUTE(SUBSTITUTE(UPPER(J19),"$","")," ",""),"SALES!",""),"CONTACTS!","")))))+IF(SUBSTITUTE(UPPER(TRIM(MID(SUBSTITUTE($H19,",",REPT(" ",99)),397,99)))," ","")="",0,IF(ISNUMBER(FIND("$",SUBSTITUTE(UPPER(TRIM(MID(SUBSTITUTE($H19,",",REPT(" ",99)),397,99)))," ",""))),--ISNUMBER(FIND(SUBSTITUTE(UPPER(TRIM(MID(SUBSTITUTE($H19,",",REPT(" ",99)),397,99)))," ",""),SUBSTITUTE(SUBSTITUTE(SUBSTITUTE(UPPER(J19)," ",""),"SALES!",""),"CONTACTS!",""))),--ISNUMBER(FIND(SUBSTITUTE(UPPER(TRIM(MID(SUBSTITUTE($H19,",",REPT(" ",99)),397,99)))," ",""),SUBSTITUTE(SUBSTITUTE(SUBSTITUTE(SUBSTITUTE(UPPER(J19),"$","")," ",""),"SALES!",""),"CONTACTS!","")))))+IF(SUBSTITUTE(UPPER(TRIM(MID(SUBSTITUTE($H19,",",REPT(" ",99)),496,99)))," ","")="",0,IF(ISNUMBER(FIND("$",SUBSTITUTE(UPPER(TRIM(MID(SUBSTITUTE($H19,",",REPT(" ",99)),496,99)))," ",""))),--ISNUMBER(FIND(SUBSTITUTE(UPPER(TRIM(MID(SUBSTITUTE($H19,",",REPT(" ",99)),496,99)))," ",""),SUBSTITUTE(SUBSTITUTE(SUBSTITUTE(UPPER(J19)," ",""),"SALES!",""),"CONTACTS!",""))),--ISNUMBER(FIND(SUBSTITUTE(UPPER(TRIM(MID(SUBSTITUTE($H19,",",REPT(" ",99)),496,99)))," ",""),SUBSTITUTE(SUBSTITUTE(SUBSTITUTE(SUBSTITUTE(UPPER(J19),"$","")," ",""),"SALES!",""),"CONTACTS!","")))))) | L19: =IF(SUBSTITUTE(UPPER(TRIM(MID(SUBSTITUTE($H19,",",REPT(" ",99)),1,99)))," ","")="",0,1)+IF(SUBSTITUTE(UPPER(TRIM(MID(SUBSTITUTE($H19,",",REPT(" ",99)),100,99)))," ","")="",0,1)+IF(SUBSTITUTE(UPPER(TRIM(MID(SUBSTITUTE($H19,",",REPT(" ",99)),199,99)))," ","")="",0,1)+IF(SUBSTITUTE(UPPER(TRIM(MID(SUBSTITUTE($H19,",",REPT(" ",99)),298,99)))," ","")="",0,1)+IF(SUBSTITUTE(UPPER(TRIM(MID(SUBSTITUTE($H19,",",REPT(" ",99)),397,99)))," ","")="",0,1)+IF(SUBSTITUTE(UPPER(TRIM(MID(SUBSTITUTE($H19,",",REPT(" ",99)),496,99)))," ","")="",0,1) | M19: =IF(J19="","",IF(AND(I19="formula",LEFT(TRIM(J19),1)<>"="),"FAIL",IF(K19=L19,"PASS","CHECK"))) | N19: addresses given in the prompt itself
A20: F19 | B20: Clean text | C20: Clean up the name in row 2: remove extra spaces and make it Proper Case. | D20: Messy!A1:F11 | E20: =LOKUP.V($C20, Messy!A1:F11) | F20: =PROPER(TRIM(Messy!B2)) | G20: =PROPER(TRIM(Messy!B2)) | H20: PROPER,TRIM,B2 | I20: formula | K20: =IF(J20="","",IF(SUBSTITUTE(UPPER(TRIM(MID(SUBSTITUTE($H20,",",REPT(" ",99)),1,99)))," ","")="",0,IF(ISNUMBER(FIND("$",SUBSTITUTE(UPPER(TRIM(MID(SUBSTITUTE($H20,",",REPT(" ",99)),1,99)))," ",""))),--ISNUMBER(FIND(SUBSTITUTE(UPPER(TRIM(MID(SUBSTITUTE($H20,",",REPT(" ",99)),1,99)))," ",""),SUBSTITUTE(SUBSTITUTE(SUBSTITUTE(UPPER(J20)," ",""),"SALES!",""),"CONTACTS!",""))),--ISNUMBER(FIND(SUBSTITUTE(UPPER(TRIM(MID(SUBSTITUTE($H20,",",REPT(" ",99)),1,99)))," ",""),SUBSTITUTE(SUBSTITUTE(SUBSTITUTE(SUBSTITUTE(UPPER(J20),"$","")," ",""),"SALES!",""),"CONTACTS!","")))))+IF(SUBSTITUTE(UPPER(TRIM(MID(SUBSTITUTE($H20,",",REPT(" ",99)),100,99)))," ","")="",0,IF(ISNUMBER(FIND("$",SUBSTITUTE(UPPER(TRIM(MID(SUBSTITUTE($H20,",",REPT(" ",99)),100,99)))," ",""))),--ISNUMBER(FIND(SUBSTITUTE(UPPER(TRIM(MID(SUBSTITUTE($H20,",",REPT(" ",99)),100,99)))," ",""),SUBSTITUTE(SUBSTITUTE(SUBSTITUTE(UPPER(J20)," ",""),"SALES!",""),"CONTACTS!",""))),--ISNUMBER(FIND(SUBSTITUTE(UPPER(TRIM(MID(SUBSTITUTE($H20,",",REPT(" ",99)),100,99)))," ",""),SUBSTITUTE(SUBSTITUTE(SUBSTITUTE(SUBSTITUTE(UPPER(J20),"$","")," ",""),"SALES!",""),"CONTACTS!","")))))+IF(SUBSTITUTE(UPPER(TRIM(MID(SUBSTITUTE($H20,",",REPT(" ",99)),199,99)))," ","")="",0,IF(ISNUMBER(FIND("$",SUBSTITUTE(UPPER(TRIM(MID(SUBSTITUTE($H20,",",REPT(" ",99)),199,99)))," ",""))),--ISNUMBER(FIND(SUBSTITUTE(UPPER(TRIM(MID(SUBSTITUTE($H20,",",REPT(" ",99)),199,99)))," ",""),SUBSTITUTE(SUBSTITUTE(SUBSTITUTE(UPPER(J20)," ",""),"SALES!",""),"CONTACTS!",""))),--ISNUMBER(FIND(SUBSTITUTE(UPPER(TRIM(MID(SUBSTITUTE($H20,",",REPT(" ",99)),199,99)))," ",""),SUBSTITUTE(SUBSTITUTE(SUBSTITUTE(SUBSTITUTE(UPPER(J20),"$","")," ",""),"SALES!",""),"CONTACTS!","")))))+IF(SUBSTITUTE(UPPER(TRIM(MID(SUBSTITUTE($H20,",",REPT(" ",99)),298,99)))," ","")="",0,IF(ISNUMBER(FIND("$",SUBSTITUTE(UPPER(TRIM(MID(SUBSTITUTE($H20,",",REPT(" ",99)),298,99)))," ",""))),--ISNUMBER(FIND(SUBSTITUTE(UPPER(TRIM(MID(SUBSTITUTE($H20,",",REPT(" ",99)),298,99)))," ",""),SUBSTITUTE(SUBSTITUTE(SUBSTITUTE(UPPER(J20)," ",""),"SALES!",""),"CONTACTS!",""))),--ISNUMBER(FIND(SUBSTITUTE(UPPER(TRIM(MID(SUBSTITUTE($H20,",",REPT(" ",99)),298,99)))," ",""),SUBSTITUTE(SUBSTITUTE(SUBSTITUTE(SUBSTITUTE(UPPER(J20),"$","")," ",""),"SALES!",""),"CONTACTS!","")))))+IF(SUBSTITUTE(UPPER(TRIM(MID(SUBSTITUTE($H20,",",REPT(" ",99)),397,99)))," ","")="",0,IF(ISNUMBER(FIND("$",SUBSTITUTE(UPPER(TRIM(MID(SUBSTITUTE($H20,",",REPT(" ",99)),397,99)))," ",""))),--ISNUMBER(FIND(SUBSTITUTE(UPPER(TRIM(MID(SUBSTITUTE($H20,",",REPT(" ",99)),397,99)))," ",""),SUBSTITUTE(SUBSTITUTE(SUBSTITUTE(UPPER(J20)," ",""),"SALES!",""),"CONTACTS!",""))),--ISNUMBER(FIND(SUBSTITUTE(UPPER(TRIM(MID(SUBSTITUTE($H20,",",REPT(" ",99)),397,99)))," ",""),SUBSTITUTE(SUBSTITUTE(SUBSTITUTE(SUBSTITUTE(UPPER(J20),"$","")," ",""),"SALES!",""),"CONTACTS!","")))))+IF(SUBSTITUTE(UPPER(TRIM(MID(SUBSTITUTE($H20,",",REPT(" ",99)),496,99)))," ","")="",0,IF(ISNUMBER(FIND("$",SUBSTITUTE(UPPER(TRIM(MID(SUBSTITUTE($H20,",",REPT(" ",99)),496,99)))," ",""))),--ISNUMBER(FIND(SUBSTITUTE(UPPER(TRIM(MID(SUBSTITUTE($H20,",",REPT(" ",99)),496,99)))," ",""),SUBSTITUTE(SUBSTITUTE(SUBSTITUTE(UPPER(J20)," ",""),"SALES!",""),"CONTACTS!",""))),--ISNUMBER(FIND(SUBSTITUTE(UPPER(TRIM(MID(SUBSTITUTE($H20,",",REPT(" ",99)),496,99)))," ",""),SUBSTITUTE(SUBSTITUTE(SUBSTITUTE(SUBSTITUTE(UPPER(J20),"$","")," ",""),"SALES!",""),"CONTACTS!","")))))) | L20: =IF(SUBSTITUTE(UPPER(TRIM(MID(SUBSTITUTE($H20,",",REPT(" ",99)),1,99)))," ","")="",0,1)+IF(SUBSTITUTE(UPPER(TRIM(MID(SUBSTITUTE($H20,",",REPT(" ",99)),100,99)))," ","")="",0,1)+IF(SUBSTITUTE(UPPER(TRIM(MID(SUBSTITUTE($H20,",",REPT(" ",99)),199,99)))," ","")="",0,1)+IF(SUBSTITUTE(UPPER(TRIM(MID(SUBSTITUTE($H20,",",REPT(" ",99)),298,99)))," ","")="",0,1)+IF(SUBSTITUTE(UPPER(TRIM(MID(SUBSTITUTE($H20,",",REPT(" ",99)),397,99)))," ","")="",0,1)+IF(SUBSTITUTE(UPPER(TRIM(MID(SUBSTITUTE($H20,",",REPT(" ",99)),496,99)))," ","")="",0,1) | M20: =IF(J20="","",IF(AND(I20="formula",LEFT(TRIM(J20),1)<>"="),"FAIL",IF(K20=L20,"PASS","CHECK"))) | N20: nesting two functions
A21: F20 | B21: Clean text | C21: Remove the extra spaces from the name in row 3. | D21: Messy!A1:F11 | E21: =LOKUP.V($C21, Messy!A1:F11) | F21: =TRIM(Messy!B3) | G21: =TRIM(Messy!B3) | H21: TRIM,B3 | I21: formula | K21: =IF(J21="","",IF(SUBSTITUTE(UPPER(TRIM(MID(SUBSTITUTE($H21,",",REPT(" ",99)),1,99)))," ","")="",0,IF(ISNUMBER(FIND("$",SUBSTITUTE(UPPER(TRIM(MID(SUBSTITUTE($H21,",",REPT(" ",99)),1,99)))," ",""))),--ISNUMBER(FIND(SUBSTITUTE(UPPER(TRIM(MID(SUBSTITUTE($H21,",",REPT(" ",99)),1,99)))," ",""),SUBSTITUTE(SUBSTITUTE(SUBSTITUTE(UPPER(J21)," ",""),"SALES!",""),"CONTACTS!",""))),--ISNUMBER(FIND(SUBSTITUTE(UPPER(TRIM(MID(SUBSTITUTE($H21,",",REPT(" ",99)),1,99)))," ",""),SUBSTITUTE(SUBSTITUTE(SUBSTITUTE(SUBSTITUTE(UPPER(J21),"$","")," ",""),"SALES!",""),"CONTACTS!","")))))+IF(SUBSTITUTE(UPPER(TRIM(MID(SUBSTITUTE($H21,",",REPT(" ",99)),100,99)))," ","")="",0,IF(ISNUMBER(FIND("$",SUBSTITUTE(UPPER(TRIM(MID(SUBSTITUTE($H21,",",REPT(" ",99)),100,99)))," ",""))),--ISNUMBER(FIND(SUBSTITUTE(UPPER(TRIM(MID(SUBSTITUTE($H21,",",REPT(" ",99)),100,99)))," ",""),SUBSTITUTE(SUBSTITUTE(SUBSTITUTE(UPPER(J21)," ",""),"SALES!",""),"CONTACTS!",""))),--ISNUMBER(FIND(SUBSTITUTE(UPPER(TRIM(MID(SUBSTITUTE($H21,",",REPT(" ",99)),100,99)))," ",""),SUBSTITUTE(SUBSTITUTE(SUBSTITUTE(SUBSTITUTE(UPPER(J21),"$","")," ",""),"SALES!",""),"CONTACTS!","")))))+IF(SUBSTITUTE(UPPER(TRIM(MID(SUBSTITUTE($H21,",",REPT(" ",99)),199,99)))," ","")="",0,IF(ISNUMBER(FIND("$",SUBSTITUTE(UPPER(TRIM(MID(SUBSTITUTE($H21,",",REPT(" ",99)),199,99)))," ",""))),--ISNUMBER(FIND(SUBSTITUTE(UPPER(TRIM(MID(SUBSTITUTE($H21,",",REPT(" ",99)),199,99)))," ",""),SUBSTITUTE(SUBSTITUTE(SUBSTITUTE(UPPER(J21)," ",""),"SALES!",""),"CONTACTS!",""))),--ISNUMBER(FIND(SUBSTITUTE(UPPER(TRIM(MID(SUBSTITUTE($H21,",",REPT(" ",99)),199,99)))," ",""),SUBSTITUTE(SUBSTITUTE(SUBSTITUTE(SUBSTITUTE(UPPER(J21),"$","")," ",""),"SALES!",""),"CONTACTS!","")))))+IF(SUBSTITUTE(UPPER(TRIM(MID(SUBSTITUTE($H21,",",REPT(" ",99)),298,99)))," ","")="",0,IF(ISNUMBER(FIND("$",SUBSTITUTE(UPPER(TRIM(MID(SUBSTITUTE($H21,",",REPT(" ",99)),298,99)))," ",""))),--ISNUMBER(FIND(SUBSTITUTE(UPPER(TRIM(MID(SUBSTITUTE($H21,",",REPT(" ",99)),298,99)))," ",""),SUBSTITUTE(SUBSTITUTE(SUBSTITUTE(UPPER(J21)," ",""),"SALES!",""),"CONTACTS!",""))),--ISNUMBER(FIND(SUBSTITUTE(UPPER(TRIM(MID(SUBSTITUTE($H21,",",REPT(" ",99)),298,99)))," ",""),SUBSTITUTE(SUBSTITUTE(SUBSTITUTE(SUBSTITUTE(UPPER(J21),"$","")," ",""),"SALES!",""),"CONTACTS!","")))))+IF(SUBSTITUTE(UPPER(TRIM(MID(SUBSTITUTE($H21,",",REPT(" ",99)),397,99)))," ","")="",0,IF(ISNUMBER(FIND("$",SUBSTITUTE(UPPER(TRIM(MID(SUBSTITUTE($H21,",",REPT(" ",99)),397,99)))," ",""))),--ISNUMBER(FIND(SUBSTITUTE(UPPER(TRIM(MID(SUBSTITUTE($H21,",",REPT(" ",99)),397,99)))," ",""),SUBSTITUTE(SUBSTITUTE(SUBSTITUTE(UPPER(J21)," ",""),"SALES!",""),"CONTACTS!",""))),--ISNUMBER(FIND(SUBSTITUTE(UPPER(TRIM(MID(SUBSTITUTE($H21,",",REPT(" ",99)),397,99)))," ",""),SUBSTITUTE(SUBSTITUTE(SUBSTITUTE(SUBSTITUTE(UPPER(J21),"$","")," ",""),"SALES!",""),"CONTACTS!","")))))+IF(SUBSTITUTE(UPPER(TRIM(MID(SUBSTITUTE($H21,",",REPT(" ",99)),496,99)))," ","")="",0,IF(ISNUMBER(FIND("$",SUBSTITUTE(UPPER(TRIM(MID(SUBSTITUTE($H21,",",REPT(" ",99)),496,99)))," ",""))),--ISNUMBER(FIND(SUBSTITUTE(UPPER(TRIM(MID(SUBSTITUTE($H21,",",REPT(" ",99)),496,99)))," ",""),SUBSTITUTE(SUBSTITUTE(SUBSTITUTE(UPPER(J21)," ",""),"SALES!",""),"CONTACTS!",""))),--ISNUMBER(FIND(SUBSTITUTE(UPPER(TRIM(MID(SUBSTITUTE($H21,",",REPT(" ",99)),496,99)))," ",""),SUBSTITUTE(SUBSTITUTE(SUBSTITUTE(SUBSTITUTE(UPPER(J21),"$","")," ",""),"SALES!",""),"CONTACTS!","")))))) | L21: =IF(SUBSTITUTE(UPPER(TRIM(MID(SUBSTITUTE($H21,",",REPT(" ",99)),1,99)))," ","")="",0,1)+IF(SUBSTITUTE(UPPER(TRIM(MID(SUBSTITUTE($H21,",",REPT(" ",99)),100,99)))," ","")="",0,1)+IF(SUBSTITUTE(UPPER(TRIM(MID(SUBSTITUTE($H21,",",REPT(" ",99)),199,99)))," ","")="",0,1)+IF(SUBSTITUTE(UPPER(TRIM(MID(SUBSTITUTE($H21,",",REPT(" ",99)),298,99)))," ","")="",0,1)+IF(SUBSTITUTE(UPPER(TRIM(MID(SUBSTITUTE($H21,",",REPT(" ",99)),397,99)))," ","")="",0,1)+IF(SUBSTITUTE(UPPER(TRIM(MID(SUBSTITUTE($H21,",",REPT(" ",99)),496,99)))," ","")="",0,1) | M21: =IF(J21="","",IF(AND(I21="formula",LEFT(TRIM(J21),1)<>"="),"FAIL",IF(K21=L21,"PASS","CHECK"))) | N21: TRIM also collapses double spaces inside
A22: F21 | B22: Clean numbers | C22: Turn the phone in row 3 into exactly 10 digits (no spaces, dashes or country code). | D22: Messy!A1:F11 | E22: =LOKUP.V($C22, Messy!A1:F11) | F22: =RIGHT(SUBSTITUTE(SUBSTITUTE(SUBSTITUTE(Messy!C3," ",""),"-",""),"+",""),10) | G22: =RIGHT(SUBSTITUTE(SUBSTITUTE(SUBSTITUTE(Messy!C3," ",""),"-",""),"+",""),10) | H22: C3,SUBSTITUTE | I22: formula | K22: =IF(J22="","",IF(SUBSTITUTE(UPPER(TRIM(MID(SUBSTITUTE($H22,",",REPT(" ",99)),1,99)))," ","")="",0,IF(ISNUMBER(FIND("$",SUBSTITUTE(UPPER(TRIM(MID(SUBSTITUTE($H22,",",REPT(" ",99)),1,99)))," ",""))),--ISNUMBER(FIND(SUBSTITUTE(UPPER(TRIM(MID(SUBSTITUTE($H22,",",REPT(" ",99)),1,99)))," ",""),SUBSTITUTE(SUBSTITUTE(SUBSTITUTE(UPPER(J22)," ",""),"SALES!",""),"CONTACTS!",""))),--ISNUMBER(FIND(SUBSTITUTE(UPPER(TRIM(MID(SUBSTITUTE($H22,",",REPT(" ",99)),1,99)))," ",""),SUBSTITUTE(SUBSTITUTE(SUBSTITUTE(SUBSTITUTE(UPPER(J22),"$","")," ",""),"SALES!",""),"CONTACTS!","")))))+IF(SUBSTITUTE(UPPER(TRIM(MID(SUBSTITUTE($H22,",",REPT(" ",99)),100,99)))," ","")="",0,IF(ISNUMBER(FIND("$",SUBSTITUTE(UPPER(TRIM(MID(SUBSTITUTE($H22,",",REPT(" ",99)),100,99)))," ",""))),--ISNUMBER(FIND(SUBSTITUTE(UPPER(TRIM(MID(SUBSTITUTE($H22,",",REPT(" ",99)),100,99)))," ",""),SUBSTITUTE(SUBSTITUTE(SUBSTITUTE(UPPER(J22)," ",""),"SALES!",""),"CONTACTS!",""))),--ISNUMBER(FIND(SUBSTITUTE(UPPER(TRIM(MID(SUBSTITUTE($H22,",",REPT(" ",99)),100,99)))," ",""),SUBSTITUTE(SUBSTITUTE(SUBSTITUTE(SUBSTITUTE(UPPER(J22),"$","")," ",""),"SALES!",""),"CONTACTS!","")))))+IF(SUBSTITUTE(UPPER(TRIM(MID(SUBSTITUTE($H22,",",REPT(" ",99)),199,99)))," ","")="",0,IF(ISNUMBER(FIND("$",SUBSTITUTE(UPPER(TRIM(MID(SUBSTITUTE($H22,",",REPT(" ",99)),199,99)))," ",""))),--ISNUMBER(FIND(SUBSTITUTE(UPPER(TRIM(MID(SUBSTITUTE($H22,",",REPT(" ",99)),199,99)))," ",""),SUBSTITUTE(SUBSTITUTE(SUBSTITUTE(UPPER(J22)," ",""),"SALES!",""),"CONTACTS!",""))),--ISNUMBER(FIND(SUBSTITUTE(UPPER(TRIM(MID(SUBSTITUTE($H22,",",REPT(" ",99)),199,99)))," ",""),SUBSTITUTE(SUBSTITUTE(SUBSTITUTE(SUBSTITUTE(UPPER(J22),"$","")," ",""),"SALES!",""),"CONTACTS!","")))))+IF(SUBSTITUTE(UPPER(TRIM(MID(SUBSTITUTE($H22,",",REPT(" ",99)),298,99)))," ","")="",0,IF(ISNUMBER(FIND("$",SUBSTITUTE(UPPER(TRIM(MID(SUBSTITUTE($H22,",",REPT(" ",99)),298,99)))," ",""))),--ISNUMBER(FIND(SUBSTITUTE(UPPER(TRIM(MID(SUBSTITUTE($H22,",",REPT(" ",99)),298,99)))," ",""),SUBSTITUTE(SUBSTITUTE(SUBSTITUTE(UPPER(J22)," ",""),"SALES!",""),"CONTACTS!",""))),--ISNUMBER(FIND(SUBSTITUTE(UPPER(TRIM(MID(SUBSTITUTE($H22,",",REPT(" ",99)),298,99)))," ",""),SUBSTITUTE(SUBSTITUTE(SUBSTITUTE(SUBSTITUTE(UPPER(J22),"$","")," ",""),"SALES!",""),"CONTACTS!","")))))+IF(SUBSTITUTE(UPPER(TRIM(MID(SUBSTITUTE($H22,",",REPT(" ",99)),397,99)))," ","")="",0,IF(ISNUMBER(FIND("$",SUBSTITUTE(UPPER(TRIM(MID(SUBSTITUTE($H22,",",REPT(" ",99)),397,99)))," ",""))),--ISNUMBER(FIND(SUBSTITUTE(UPPER(TRIM(MID(SUBSTITUTE($H22,",",REPT(" ",99)),397,99)))," ",""),SUBSTITUTE(SUBSTITUTE(SUBSTITUTE(UPPER(J22)," ",""),"SALES!",""),"CONTACTS!",""))),--ISNUMBER(FIND(SUBSTITUTE(UPPER(TRIM(MID(SUBSTITUTE($H22,",",REPT(" ",99)),397,99)))," ",""),SUBSTITUTE(SUBSTITUTE(SUBSTITUTE(SUBSTITUTE(UPPER(J22),"$","")," ",""),"SALES!",""),"CONTACTS!","")))))+IF(SUBSTITUTE(UPPER(TRIM(MID(SUBSTITUTE($H22,",",REPT(" ",99)),496,99)))," ","")="",0,IF(ISNUMBER(FIND("$",SUBSTITUTE(UPPER(TRIM(MID(SUBSTITUTE($H22,",",REPT(" ",99)),496,99)))," ",""))),--ISNUMBER(FIND(SUBSTITUTE(UPPER(TRIM(MID(SUBSTITUTE($H22,",",REPT(" ",99)),496,99)))," ",""),SUBSTITUTE(SUBSTITUTE(SUBSTITUTE(UPPER(J22)," ",""),"SALES!",""),"CONTACTS!",""))),--ISNUMBER(FIND(SUBSTITUTE(UPPER(TRIM(MID(SUBSTITUTE($H22,",",REPT(" ",99)),496,99)))," ",""),SUBSTITUTE(SUBSTITUTE(SUBSTITUTE(SUBSTITUTE(UPPER(J22),"$","")," ",""),"SALES!",""),"CONTACTS!","")))))) | L22: =IF(SUBSTITUTE(UPPER(TRIM(MID(SUBSTITUTE($H22,",",REPT(" ",99)),1,99)))," ","")="",0,1)+IF(SUBSTITUTE(UPPER(TRIM(MID(SUBSTITUTE($H22,",",REPT(" ",99)),100,99)))," ","")="",0,1)+IF(SUBSTITUTE(UPPER(TRIM(MID(SUBSTITUTE($H22,",",REPT(" ",99)),199,99)))," ","")="",0,1)+IF(SUBSTITUTE(UPPER(TRIM(MID(SUBSTITUTE($H22,",",REPT(" ",99)),298,99)))," ","")="",0,1)+IF(SUBSTITUTE(UPPER(TRIM(MID(SUBSTITUTE($H22,",",REPT(" ",99)),397,99)))," ","")="",0,1)+IF(SUBSTITUTE(UPPER(TRIM(MID(SUBSTITUTE($H22,",",REPT(" ",99)),496,99)))," ","")="",0,1) | M22: =IF(J22="","",IF(AND(I22="formula",LEFT(TRIM(J22),1)<>"="),"FAIL",IF(K22=L22,"PASS","CHECK"))) | N22: nested SUBSTITUTE + RIGHT
A23: F22 | B23: Clean numbers | C23: Convert the amount in row 2 to a real number. | D23: Messy!A1:F11 | E23: =LOKUP.V($C23, Messy!A1:F11) | F23: =VALUE(SUBSTITUTE(SUBSTITUTE(Messy!E2,"Rs",""),",","")) | G23: =VALUE(SUBSTITUTE(SUBSTITUTE(Messy!E2,"Rs",""),",","")) | H23: E2,SUBSTITUTE | I23: formula | K23: =IF(J23="","",IF(SUBSTITUTE(UPPER(TRIM(MID(SUBSTITUTE($H23,",",REPT(" ",99)),1,99)))," ","")="",0,IF(ISNUMBER(FIND("$",SUBSTITUTE(UPPER(TRIM(MID(SUBSTITUTE($H23,",",REPT(" ",99)),1,99)))," ",""))),--ISNUMBER(FIND(SUBSTITUTE(UPPER(TRIM(MID(SUBSTITUTE($H23,",",REPT(" ",99)),1,99)))," ",""),SUBSTITUTE(SUBSTITUTE(SUBSTITUTE(UPPER(J23)," ",""),"SALES!",""),"CONTACTS!",""))),--ISNUMBER(FIND(SUBSTITUTE(UPPER(TRIM(MID(SUBSTITUTE($H23,",",REPT(" ",99)),1,99)))," ",""),SUBSTITUTE(SUBSTITUTE(SUBSTITUTE(SUBSTITUTE(UPPER(J23),"$","")," ",""),"SALES!",""),"CONTACTS!","")))))+IF(SUBSTITUTE(UPPER(TRIM(MID(SUBSTITUTE($H23,",",REPT(" ",99)),100,99)))," ","")="",0,IF(ISNUMBER(FIND("$",SUBSTITUTE(UPPER(TRIM(MID(SUBSTITUTE($H23,",",REPT(" ",99)),100,99)))," ",""))),--ISNUMBER(FIND(SUBSTITUTE(UPPER(TRIM(MID(SUBSTITUTE($H23,",",REPT(" ",99)),100,99)))," ",""),SUBSTITUTE(SUBSTITUTE(SUBSTITUTE(UPPER(J23)," ",""),"SALES!",""),"CONTACTS!",""))),--ISNUMBER(FIND(SUBSTITUTE(UPPER(TRIM(MID(SUBSTITUTE($H23,",",REPT(" ",99)),100,99)))," ",""),SUBSTITUTE(SUBSTITUTE(SUBSTITUTE(SUBSTITUTE(UPPER(J23),"$","")," ",""),"SALES!",""),"CONTACTS!","")))))+IF(SUBSTITUTE(UPPER(TRIM(MID(SUBSTITUTE($H23,",",REPT(" ",99)),199,99)))," ","")="",0,IF(ISNUMBER(FIND("$",SUBSTITUTE(UPPER(TRIM(MID(SUBSTITUTE($H23,",",REPT(" ",99)),199,99)))," ",""))),--ISNUMBER(FIND(SUBSTITUTE(UPPER(TRIM(MID(SUBSTITUTE($H23,",",REPT(" ",99)),199,99)))," ",""),SUBSTITUTE(SUBSTITUTE(SUBSTITUTE(UPPER(J23)," ",""),"SALES!",""),"CONTACTS!",""))),--ISNUMBER(FIND(SUBSTITUTE(UPPER(TRIM(MID(SUBSTITUTE($H23,",",REPT(" ",99)),199,99)))," ",""),SUBSTITUTE(SUBSTITUTE(SUBSTITUTE(SUBSTITUTE(UPPER(J23),"$","")," ",""),"SALES!",""),"CONTACTS!","")))))+IF(SUBSTITUTE(UPPER(TRIM(MID(SUBSTITUTE($H23,",",REPT(" ",99)),298,99)))," ","")="",0,IF(ISNUMBER(FIND("$",SUBSTITUTE(UPPER(TRIM(MID(SUBSTITUTE($H23,",",REPT(" ",99)),298,99)))," ",""))),--ISNUMBER(FIND(SUBSTITUTE(UPPER(TRIM(MID(SUBSTITUTE($H23,",",REPT(" ",99)),298,99)))," ",""),SUBSTITUTE(SUBSTITUTE(SUBSTITUTE(UPPER(J23)," ",""),"SALES!",""),"CONTACTS!",""))),--ISNUMBER(FIND(SUBSTITUTE(UPPER(TRIM(MID(SUBSTITUTE($H23,",",REPT(" ",99)),298,99)))," ",""),SUBSTITUTE(SUBSTITUTE(SUBSTITUTE(SUBSTITUTE(UPPER(J23),"$","")," ",""),"SALES!",""),"CONTACTS!","")))))+IF(SUBSTITUTE(UPPER(TRIM(MID(SUBSTITUTE($H23,",",REPT(" ",99)),397,99)))," ","")="",0,IF(ISNUMBER(FIND("$",SUBSTITUTE(UPPER(TRIM(MID(SUBSTITUTE($H23,",",REPT(" ",99)),397,99)))," ",""))),--ISNUMBER(FIND(SUBSTITUTE(UPPER(TRIM(MID(SUBSTITUTE($H23,",",REPT(" ",99)),397,99)))," ",""),SUBSTITUTE(SUBSTITUTE(SUBSTITUTE(UPPER(J23)," ",""),"SALES!",""),"CONTACTS!",""))),--ISNUMBER(FIND(SUBSTITUTE(UPPER(TRIM(MID(SUBSTITUTE($H23,",",REPT(" ",99)),397,99)))," ",""),SUBSTITUTE(SUBSTITUTE(SUBSTITUTE(SUBSTITUTE(UPPER(J23),"$","")," ",""),"SALES!",""),"CONTACTS!","")))))+IF(SUBSTITUTE(UPPER(TRIM(MID(SUBSTITUTE($H23,",",REPT(" ",99)),496,99)))," ","")="",0,IF(ISNUMBER(FIND("$",SUBSTITUTE(UPPER(TRIM(MID(SUBSTITUTE($H23,",",REPT(" ",99)),496,99)))," ",""))),--ISNUMBER(FIND(SUBSTITUTE(UPPER(TRIM(MID(SUBSTITUTE($H23,",",REPT(" ",99)),496,99)))," ",""),SUBSTITUTE(SUBSTITUTE(SUBSTITUTE(UPPER(J23)," ",""),"SALES!",""),"CONTACTS!",""))),--ISNUMBER(FIND(SUBSTITUTE(UPPER(TRIM(MID(SUBSTITUTE($H23,",",REPT(" ",99)),496,99)))," ",""),SUBSTITUTE(SUBSTITUTE(SUBSTITUTE(SUBSTITUTE(UPPER(J23),"$","")," ",""),"SALES!",""),"CONTACTS!","")))))) | L23: =IF(SUBSTITUTE(UPPER(TRIM(MID(SUBSTITUTE($H23,",",REPT(" ",99)),1,99)))," ","")="",0,1)+IF(SUBSTITUTE(UPPER(TRIM(MID(SUBSTITUTE($H23,",",REPT(" ",99)),100,99)))," ","")="",0,1)+IF(SUBSTITUTE(UPPER(TRIM(MID(SUBSTITUTE($H23,",",REPT(" ",99)),199,99)))," ","")="",0,1)+IF(SUBSTITUTE(UPPER(TRIM(MID(SUBSTITUTE($H23,",",REPT(" ",99)),298,99)))," ","")="",0,1)+IF(SUBSTITUTE(UPPER(TRIM(MID(SUBSTITUTE($H23,",",REPT(" ",99)),397,99)))," ","")="",0,1)+IF(SUBSTITUTE(UPPER(TRIM(MID(SUBSTITUTE($H23,",",REPT(" ",99)),496,99)))," ","")="",0,1) | M23: =IF(J23="","",IF(AND(I23="formula",LEFT(TRIM(J23),1)<>"="),"FAIL",IF(K23=L23,"PASS","CHECK"))) | N23: strip currency text and thousands separator
A24: F23 | B24: Clean numbers | C24: Convert the amount in row 5 to a number; use 0 if it isn't a valid number. | D24: Messy!A1:F11 | E24: =LOKUP.V($C24, Messy!A1:F11) | F24: =IFERROR(VALUE(SUBSTITUTE(Messy!E5,",","")),0) | G24: =IFERROR(VALUE(SUBSTITUTE(Messy!E5,",","")),0) | H24: IFERROR,E5 | I24: formula | K24: =IF(J24="","",IF(SUBSTITUTE(UPPER(TRIM(MID(SUBSTITUTE($H24,",",REPT(" ",99)),1,99)))," ","")="",0,IF(ISNUMBER(FIND("$",SUBSTITUTE(UPPER(TRIM(MID(SUBSTITUTE($H24,",",REPT(" ",99)),1,99)))," ",""))),--ISNUMBER(FIND(SUBSTITUTE(UPPER(TRIM(MID(SUBSTITUTE($H24,",",REPT(" ",99)),1,99)))," ",""),SUBSTITUTE(SUBSTITUTE(SUBSTITUTE(UPPER(J24)," ",""),"SALES!",""),"CONTACTS!",""))),--ISNUMBER(FIND(SUBSTITUTE(UPPER(TRIM(MID(SUBSTITUTE($H24,",",REPT(" ",99)),1,99)))," ",""),SUBSTITUTE(SUBSTITUTE(SUBSTITUTE(SUBSTITUTE(UPPER(J24),"$","")," ",""),"SALES!",""),"CONTACTS!","")))))+IF(SUBSTITUTE(UPPER(TRIM(MID(SUBSTITUTE($H24,",",REPT(" ",99)),100,99)))," ","")="",0,IF(ISNUMBER(FIND("$",SUBSTITUTE(UPPER(TRIM(MID(SUBSTITUTE($H24,",",REPT(" ",99)),100,99)))," ",""))),--ISNUMBER(FIND(SUBSTITUTE(UPPER(TRIM(MID(SUBSTITUTE($H24,",",REPT(" ",99)),100,99)))," ",""),SUBSTITUTE(SUBSTITUTE(SUBSTITUTE(UPPER(J24)," ",""),"SALES!",""),"CONTACTS!",""))),--ISNUMBER(FIND(SUBSTITUTE(UPPER(TRIM(MID(SUBSTITUTE($H24,",",REPT(" ",99)),100,99)))," ",""),SUBSTITUTE(SUBSTITUTE(SUBSTITUTE(SUBSTITUTE(UPPER(J24),"$","")," ",""),"SALES!",""),"CONTACTS!","")))))+IF(SUBSTITUTE(UPPER(TRIM(MID(SUBSTITUTE($H24,",",REPT(" ",99)),199,99)))," ","")="",0,IF(ISNUMBER(FIND("$",SUBSTITUTE(UPPER(TRIM(MID(SUBSTITUTE($H24,",",REPT(" ",99)),199,99)))," ",""))),--ISNUMBER(FIND(SUBSTITUTE(UPPER(TRIM(MID(SUBSTITUTE($H24,",",REPT(" ",99)),199,99)))," ",""),SUBSTITUTE(SUBSTITUTE(SUBSTITUTE(UPPER(J24)," ",""),"SALES!",""),"CONTACTS!",""))),--ISNUMBER(FIND(SUBSTITUTE(UPPER(TRIM(MID(SUBSTITUTE($H24,",",REPT(" ",99)),199,99)))," ",""),SUBSTITUTE(SUBSTITUTE(SUBSTITUTE(SUBSTITUTE(UPPER(J24),"$","")," ",""),"SALES!",""),"CONTACTS!","")))))+IF(SUBSTITUTE(UPPER(TRIM(MID(SUBSTITUTE($H24,",",REPT(" ",99)),298,99)))," ","")="",0,IF(ISNUMBER(FIND("$",SUBSTITUTE(UPPER(TRIM(MID(SUBSTITUTE($H24,",",REPT(" ",99)),298,99)))," ",""))),--ISNUMBER(FIND(SUBSTITUTE(UPPER(TRIM(MID(SUBSTITUTE($H24,",",REPT(" ",99)),298,99)))," ",""),SUBSTITUTE(SUBSTITUTE(SUBSTITUTE(UPPER(J24)," ",""),"SALES!",""),"CONTACTS!",""))),--ISNUMBER(FIND(SUBSTITUTE(UPPER(TRIM(MID(SUBSTITUTE($H24,",",REPT(" ",99)),298,99)))," ",""),SUBSTITUTE(SUBSTITUTE(SUBSTITUTE(SUBSTITUTE(UPPER(J24),"$","")," ",""),"SALES!",""),"CONTACTS!","")))))+IF(SUBSTITUTE(UPPER(TRIM(MID(SUBSTITUTE($H24,",",REPT(" ",99)),397,99)))," ","")="",0,IF(ISNUMBER(FIND("$",SUBSTITUTE(UPPER(TRIM(MID(SUBSTITUTE($H24,",",REPT(" ",99)),397,99)))," ",""))),--ISNUMBER(FIND(SUBSTITUTE(UPPER(TRIM(MID(SUBSTITUTE($H24,",",REPT(" ",99)),397,99)))," ",""),SUBSTITUTE(SUBSTITUTE(SUBSTITUTE(UPPER(J24)," ",""),"SALES!",""),"CONTACTS!",""))),--ISNUMBER(FIND(SUBSTITUTE(UPPER(TRIM(MID(SUBSTITUTE($H24,",",REPT(" ",99)),397,99)))," ",""),SUBSTITUTE(SUBSTITUTE(SUBSTITUTE(SUBSTITUTE(UPPER(J24),"$","")," ",""),"SALES!",""),"CONTACTS!","")))))+IF(SUBSTITUTE(UPPER(TRIM(MID(SUBSTITUTE($H24,",",REPT(" ",99)),496,99)))," ","")="",0,IF(ISNUMBER(FIND("$",SUBSTITUTE(UPPER(TRIM(MID(SUBSTITUTE($H24,",",REPT(" ",99)),496,99)))," ",""))),--ISNUMBER(FIND(SUBSTITUTE(UPPER(TRIM(MID(SUBSTITUTE($H24,",",REPT(" ",99)),496,99)))," ",""),SUBSTITUTE(SUBSTITUTE(SUBSTITUTE(UPPER(J24)," ",""),"SALES!",""),"CONTACTS!",""))),--ISNUMBER(FIND(SUBSTITUTE(UPPER(TRIM(MID(SUBSTITUTE($H24,",",REPT(" ",99)),496,99)))," ",""),SUBSTITUTE(SUBSTITUTE(SUBSTITUTE(SUBSTITUTE(UPPER(J24),"$","")," ",""),"SALES!",""),"CONTACTS!","")))))) | L24: =IF(SUBSTITUTE(UPPER(TRIM(MID(SUBSTITUTE($H24,",",REPT(" ",99)),1,99)))," ","")="",0,1)+IF(SUBSTITUTE(UPPER(TRIM(MID(SUBSTITUTE($H24,",",REPT(" ",99)),100,99)))," ","")="",0,1)+IF(SUBSTITUTE(UPPER(TRIM(MID(SUBSTITUTE($H24,",",REPT(" ",99)),199,99)))," ","")="",0,1)+IF(SUBSTITUTE(UPPER(TRIM(MID(SUBSTITUTE($H24,",",REPT(" ",99)),298,99)))," ","")="",0,1)+IF(SUBSTITUTE(UPPER(TRIM(MID(SUBSTITUTE($H24,",",REPT(" ",99)),397,99)))," ","")="",0,1)+IF(SUBSTITUTE(UPPER(TRIM(MID(SUBSTITUTE($H24,",",REPT(" ",99)),496,99)))," ","")="",0,1) | M24: =IF(J24="","",IF(AND(I24="formula",LEFT(TRIM(J24),1)<>"="),"FAIL",IF(K24=L24,"PASS","CHECK"))) | N24: N/A → 0 via IFERROR
A25: F24 | B25: Clean text | C25: Clean the email in row 2: lowercase and no stray spaces. | D25: Messy!A1:F11 | E25: =LOKUP.V($C25, Messy!A1:F11) | F25: =LOWER(TRIM(Messy!F2)) | G25: =LOWER(TRIM(Messy!F2)) | H25: LOWER,TRIM,F2 | I25: formula | K25: =IF(J25="","",IF(SUBSTITUTE(UPPER(TRIM(MID(SUBSTITUTE($H25,",",REPT(" ",99)),1,99)))," ","")="",0,IF(ISNUMBER(FIND("$",SUBSTITUTE(UPPER(TRIM(MID(SUBSTITUTE($H25,",",REPT(" ",99)),1,99)))," ",""))),--ISNUMBER(FIND(SUBSTITUTE(UPPER(TRIM(MID(SUBSTITUTE($H25,",",REPT(" ",99)),1,99)))," ",""),SUBSTITUTE(SUBSTITUTE(SUBSTITUTE(UPPER(J25)," ",""),"SALES!",""),"CONTACTS!",""))),--ISNUMBER(FIND(SUBSTITUTE(UPPER(TRIM(MID(SUBSTITUTE($H25,",",REPT(" ",99)),1,99)))," ",""),SUBSTITUTE(SUBSTITUTE(SUBSTITUTE(SUBSTITUTE(UPPER(J25),"$","")," ",""),"SALES!",""),"CONTACTS!","")))))+IF(SUBSTITUTE(UPPER(TRIM(MID(SUBSTITUTE($H25,",",REPT(" ",99)),100,99)))," ","")="",0,IF(ISNUMBER(FIND("$",SUBSTITUTE(UPPER(TRIM(MID(SUBSTITUTE($H25,",",REPT(" ",99)),100,99)))," ",""))),--ISNUMBER(FIND(SUBSTITUTE(UPPER(TRIM(MID(SUBSTITUTE($H25,",",REPT(" ",99)),100,99)))," ",""),SUBSTITUTE(SUBSTITUTE(SUBSTITUTE(UPPER(J25)," ",""),"SALES!",""),"CONTACTS!",""))),--ISNUMBER(FIND(SUBSTITUTE(UPPER(TRIM(MID(SUBSTITUTE($H25,",",REPT(" ",99)),100,99)))," ",""),SUBSTITUTE(SUBSTITUTE(SUBSTITUTE(SUBSTITUTE(UPPER(J25),"$","")," ",""),"SALES!",""),"CONTACTS!","")))))+IF(SUBSTITUTE(UPPER(TRIM(MID(SUBSTITUTE($H25,",",REPT(" ",99)),199,99)))," ","")="",0,IF(ISNUMBER(FIND("$",SUBSTITUTE(UPPER(TRIM(MID(SUBSTITUTE($H25,",",REPT(" ",99)),199,99)))," ",""))),--ISNUMBER(FIND(SUBSTITUTE(UPPER(TRIM(MID(SUBSTITUTE($H25,",",REPT(" ",99)),199,99)))," ",""),SUBSTITUTE(SUBSTITUTE(SUBSTITUTE(UPPER(J25)," ",""),"SALES!",""),"CONTACTS!",""))),--ISNUMBER(FIND(SUBSTITUTE(UPPER(TRIM(MID(SUBSTITUTE($H25,",",REPT(" ",99)),199,99)))," ",""),SUBSTITUTE(SUBSTITUTE(SUBSTITUTE(SUBSTITUTE(UPPER(J25),"$","")," ",""),"SALES!",""),"CONTACTS!","")))))+IF(SUBSTITUTE(UPPER(TRIM(MID(SUBSTITUTE($H25,",",REPT(" ",99)),298,99)))," ","")="",0,IF(ISNUMBER(FIND("$",SUBSTITUTE(UPPER(TRIM(MID(SUBSTITUTE($H25,",",REPT(" ",99)),298,99)))," ",""))),--ISNUMBER(FIND(SUBSTITUTE(UPPER(TRIM(MID(SUBSTITUTE($H25,",",REPT(" ",99)),298,99)))," ",""),SUBSTITUTE(SUBSTITUTE(SUBSTITUTE(UPPER(J25)," ",""),"SALES!",""),"CONTACTS!",""))),--ISNUMBER(FIND(SUBSTITUTE(UPPER(TRIM(MID(SUBSTITUTE($H25,",",REPT(" ",99)),298,99)))," ",""),SUBSTITUTE(SUBSTITUTE(SUBSTITUTE(SUBSTITUTE(UPPER(J25),"$","")," ",""),"SALES!",""),"CONTACTS!","")))))+IF(SUBSTITUTE(UPPER(TRIM(MID(SUBSTITUTE($H25,",",REPT(" ",99)),397,99)))," ","")="",0,IF(ISNUMBER(FIND("$",SUBSTITUTE(UPPER(TRIM(MID(SUBSTITUTE($H25,",",REPT(" ",99)),397,99)))," ",""))),--ISNUMBER(FIND(SUBSTITUTE(UPPER(TRIM(MID(SUBSTITUTE($H25,",",REPT(" ",99)),397,99)))," ",""),SUBSTITUTE(SUBSTITUTE(SUBSTITUTE(UPPER(J25)," ",""),"SALES!",""),"CONTACTS!",""))),--ISNUMBER(FIND(SUBSTITUTE(UPPER(TRIM(MID(SUBSTITUTE($H25,",",REPT(" ",99)),397,99)))," ",""),SUBSTITUTE(SUBSTITUTE(SUBSTITUTE(SUBSTITUTE(UPPER(J25),"$","")," ",""),"SALES!",""),"CONTACTS!","")))))+IF(SUBSTITUTE(UPPER(TRIM(MID(SUBSTITUTE($H25,",",REPT(" ",99)),496,99)))," ","")="",0,IF(ISNUMBER(FIND("$",SUBSTITUTE(UPPER(TRIM(MID(SUBSTITUTE($H25,",",REPT(" ",99)),496,99)))," ",""))),--ISNUMBER(FIND(SUBSTITUTE(UPPER(TRIM(MID(SUBSTITUTE($H25,",",REPT(" ",99)),496,99)))," ",""),SUBSTITUTE(SUBSTITUTE(SUBSTITUTE(UPPER(J25)," ",""),"SALES!",""),"CONTACTS!",""))),--ISNUMBER(FIND(SUBSTITUTE(UPPER(TRIM(MID(SUBSTITUTE($H25,",",REPT(" ",99)),496,99)))," ",""),SUBSTITUTE(SUBSTITUTE(SUBSTITUTE(SUBSTITUTE(UPPER(J25),"$","")," ",""),"SALES!",""),"CONTACTS!","")))))) | L25: =IF(SUBSTITUTE(UPPER(TRIM(MID(SUBSTITUTE($H25,",",REPT(" ",99)),1,99)))," ","")="",0,1)+IF(SUBSTITUTE(UPPER(TRIM(MID(SUBSTITUTE($H25,",",REPT(" ",99)),100,99)))," ","")="",0,1)+IF(SUBSTITUTE(UPPER(TRIM(MID(SUBSTITUTE($H25,",",REPT(" ",99)),199,99)))," ","")="",0,1)+IF(SUBSTITUTE(UPPER(TRIM(MID(SUBSTITUTE($H25,",",REPT(" ",99)),298,99)))," ","")="",0,1)+IF(SUBSTITUTE(UPPER(TRIM(MID(SUBSTITUTE($H25,",",REPT(" ",99)),397,99)))," ","")="",0,1)+IF(SUBSTITUTE(UPPER(TRIM(MID(SUBSTITUTE($H25,",",REPT(" ",99)),496,99)))," ","")="",0,1) | M25: =IF(J25="","",IF(AND(I25="formula",LEFT(TRIM(J25),1)<>"="),"FAIL",IF(K25=L25,"PASS","CHECK"))) | N25: trailing space + mixed case
A26: F25 | B26: Clean dates | C26: Convert the text date in row 3 into a real Excel date. | D26: Messy!A1:F11 | E26: =LOKUP.V($C26, Messy!A1:F11) | F26: =DATEVALUE(Messy!D3) | G26: =DATEVALUE(Messy!D3) | H26: D3 | I26: formula | K26: =IF(J26="","",IF(SUBSTITUTE(UPPER(TRIM(MID(SUBSTITUTE($H26,",",REPT(" ",99)),1,99)))," ","")="",0,IF(ISNUMBER(FIND("$",SUBSTITUTE(UPPER(TRIM(MID(SUBSTITUTE($H26,",",REPT(" ",99)),1,99)))," ",""))),--ISNUMBER(FIND(SUBSTITUTE(UPPER(TRIM(MID(SUBSTITUTE($H26,",",REPT(" ",99)),1,99)))," ",""),SUBSTITUTE(SUBSTITUTE(SUBSTITUTE(UPPER(J26)," ",""),"SALES!",""),"CONTACTS!",""))),--ISNUMBER(FIND(SUBSTITUTE(UPPER(TRIM(MID(SUBSTITUTE($H26,",",REPT(" ",99)),1,99)))," ",""),SUBSTITUTE(SUBSTITUTE(SUBSTITUTE(SUBSTITUTE(UPPER(J26),"$","")," ",""),"SALES!",""),"CONTACTS!","")))))+IF(SUBSTITUTE(UPPER(TRIM(MID(SUBSTITUTE($H26,",",REPT(" ",99)),100,99)))," ","")="",0,IF(ISNUMBER(FIND("$",SUBSTITUTE(UPPER(TRIM(MID(SUBSTITUTE($H26,",",REPT(" ",99)),100,99)))," ",""))),--ISNUMBER(FIND(SUBSTITUTE(UPPER(TRIM(MID(SUBSTITUTE($H26,",",REPT(" ",99)),100,99)))," ",""),SUBSTITUTE(SUBSTITUTE(SUBSTITUTE(UPPER(J26)," ",""),"SALES!",""),"CONTACTS!",""))),--ISNUMBER(FIND(SUBSTITUTE(UPPER(TRIM(MID(SUBSTITUTE($H26,",",REPT(" ",99)),100,99)))," ",""),SUBSTITUTE(SUBSTITUTE(SUBSTITUTE(SUBSTITUTE(UPPER(J26),"$","")," ",""),"SALES!",""),"CONTACTS!","")))))+IF(SUBSTITUTE(UPPER(TRIM(MID(SUBSTITUTE($H26,",",REPT(" ",99)),199,99)))," ","")="",0,IF(ISNUMBER(FIND("$",SUBSTITUTE(UPPER(TRIM(MID(SUBSTITUTE($H26,",",REPT(" ",99)),199,99)))," ",""))),--ISNUMBER(FIND(SUBSTITUTE(UPPER(TRIM(MID(SUBSTITUTE($H26,",",REPT(" ",99)),199,99)))," ",""),SUBSTITUTE(SUBSTITUTE(SUBSTITUTE(UPPER(J26)," ",""),"SALES!",""),"CONTACTS!",""))),--ISNUMBER(FIND(SUBSTITUTE(UPPER(TRIM(MID(SUBSTITUTE($H26,",",REPT(" ",99)),199,99)))," ",""),SUBSTITUTE(SUBSTITUTE(SUBSTITUTE(SUBSTITUTE(UPPER(J26),"$","")," ",""),"SALES!",""),"CONTACTS!","")))))+IF(SUBSTITUTE(UPPER(TRIM(MID(SUBSTITUTE($H26,",",REPT(" ",99)),298,99)))," ","")="",0,IF(ISNUMBER(FIND("$",SUBSTITUTE(UPPER(TRIM(MID(SUBSTITUTE($H26,",",REPT(" ",99)),298,99)))," ",""))),--ISNUMBER(FIND(SUBSTITUTE(UPPER(TRIM(MID(SUBSTITUTE($H26,",",REPT(" ",99)),298,99)))," ",""),SUBSTITUTE(SUBSTITUTE(SUBSTITUTE(UPPER(J26)," ",""),"SALES!",""),"CONTACTS!",""))),--ISNUMBER(FIND(SUBSTITUTE(UPPER(TRIM(MID(SUBSTITUTE($H26,",",REPT(" ",99)),298,99)))," ",""),SUBSTITUTE(SUBSTITUTE(SUBSTITUTE(SUBSTITUTE(UPPER(J26),"$","")," ",""),"SALES!",""),"CONTACTS!","")))))+IF(SUBSTITUTE(UPPER(TRIM(MID(SUBSTITUTE($H26,",",REPT(" ",99)),397,99)))," ","")="",0,IF(ISNUMBER(FIND("$",SUBSTITUTE(UPPER(TRIM(MID(SUBSTITUTE($H26,",",REPT(" ",99)),397,99)))," ",""))),--ISNUMBER(FIND(SUBSTITUTE(UPPER(TRIM(MID(SUBSTITUTE($H26,",",REPT(" ",99)),397,99)))," ",""),SUBSTITUTE(SUBSTITUTE(SUBSTITUTE(UPPER(J26)," ",""),"SALES!",""),"CONTACTS!",""))),--ISNUMBER(FIND(SUBSTITUTE(UPPER(TRIM(MID(SUBSTITUTE($H26,",",REPT(" ",99)),397,99)))," ",""),SUBSTITUTE(SUBSTITUTE(SUBSTITUTE(SUBSTITUTE(UPPER(J26),"$","")," ",""),"SALES!",""),"CONTACTS!","")))))+IF(SUBSTITUTE(UPPER(TRIM(MID(SUBSTITUTE($H26,",",REPT(" ",99)),496,99)))," ","")="",0,IF(ISNUMBER(FIND("$",SUBSTITUTE(UPPER(TRIM(MID(SUBSTITUTE($H26,",",REPT(" ",99)),496,99)))," ",""))),--ISNUMBER(FIND(SUBSTITUTE(UPPER(TRIM(MID(SUBSTITUTE($H26,",",REPT(" ",99)),496,99)))," ",""),SUBSTITUTE(SUBSTITUTE(SUBSTITUTE(UPPER(J26)," ",""),"SALES!",""),"CONTACTS!",""))),--ISNUMBER(FIND(SUBSTITUTE(UPPER(TRIM(MID(SUBSTITUTE($H26,",",REPT(" ",99)),496,99)))," ",""),SUBSTITUTE(SUBSTITUTE(SUBSTITUTE(SUBSTITUTE(UPPER(J26),"$","")," ",""),"SALES!",""),"CONTACTS!","")))))) | L26: =IF(SUBSTITUTE(UPPER(TRIM(MID(SUBSTITUTE($H26,",",REPT(" ",99)),1,99)))," ","")="",0,1)+IF(SUBSTITUTE(UPPER(TRIM(MID(SUBSTITUTE($H26,",",REPT(" ",99)),100,99)))," ","")="",0,1)+IF(SUBSTITUTE(UPPER(TRIM(MID(SUBSTITUTE($H26,",",REPT(" ",99)),199,99)))," ","")="",0,1)+IF(SUBSTITUTE(UPPER(TRIM(MID(SUBSTITUTE($H26,",",REPT(" ",99)),298,99)))," ","")="",0,1)+IF(SUBSTITUTE(UPPER(TRIM(MID(SUBSTITUTE($H26,",",REPT(" ",99)),397,99)))," ","")="",0,1)+IF(SUBSTITUTE(UPPER(TRIM(MID(SUBSTITUTE($H26,",",REPT(" ",99)),496,99)))," ","")="",0,1) | M26: =IF(J26="","",IF(AND(I26="formula",LEFT(TRIM(J26),1)<>"="),"FAIL",IF(K26=L26,"PASS","CHECK"))) | N26: ISO text date → serial
A27: F26 | B27: Split/combine | C27: First name only, in Proper Case, from the name in row 4. | D27: Messy!A1:F11 | E27: =LOKUP.V($C27, Messy!A1:F11) | F27: =PROPER(LEFT(TRIM(Messy!B4),FIND(" ",TRIM(Messy!B4))-1)) | G27: =PROPER(LEFT(TRIM(Messy!B4),FIND(" ",TRIM(Messy!B4))-1)) | H27: LEFT,FIND,B4 | I27: formula | K27: =IF(J27="","",IF(SUBSTITUTE(UPPER(TRIM(MID(SUBSTITUTE($H27,",",REPT(" ",99)),1,99)))," ","")="",0,IF(ISNUMBER(FIND("$",SUBSTITUTE(UPPER(TRIM(MID(SUBSTITUTE($H27,",",REPT(" ",99)),1,99)))," ",""))),--ISNUMBER(FIND(SUBSTITUTE(UPPER(TRIM(MID(SUBSTITUTE($H27,",",REPT(" ",99)),1,99)))," ",""),SUBSTITUTE(SUBSTITUTE(SUBSTITUTE(UPPER(J27)," ",""),"SALES!",""),"CONTACTS!",""))),--ISNUMBER(FIND(SUBSTITUTE(UPPER(TRIM(MID(SUBSTITUTE($H27,",",REPT(" ",99)),1,99)))," ",""),SUBSTITUTE(SUBSTITUTE(SUBSTITUTE(SUBSTITUTE(UPPER(J27),"$","")," ",""),"SALES!",""),"CONTACTS!","")))))+IF(SUBSTITUTE(UPPER(TRIM(MID(SUBSTITUTE($H27,",",REPT(" ",99)),100,99)))," ","")="",0,IF(ISNUMBER(FIND("$",SUBSTITUTE(UPPER(TRIM(MID(SUBSTITUTE($H27,",",REPT(" ",99)),100,99)))," ",""))),--ISNUMBER(FIND(SUBSTITUTE(UPPER(TRIM(MID(SUBSTITUTE($H27,",",REPT(" ",99)),100,99)))," ",""),SUBSTITUTE(SUBSTITUTE(SUBSTITUTE(UPPER(J27)," ",""),"SALES!",""),"CONTACTS!",""))),--ISNUMBER(FIND(SUBSTITUTE(UPPER(TRIM(MID(SUBSTITUTE($H27,",",REPT(" ",99)),100,99)))," ",""),SUBSTITUTE(SUBSTITUTE(SUBSTITUTE(SUBSTITUTE(UPPER(J27),"$","")," ",""),"SALES!",""),"CONTACTS!","")))))+IF(SUBSTITUTE(UPPER(TRIM(MID(SUBSTITUTE($H27,",",REPT(" ",99)),199,99)))," ","")="",0,IF(ISNUMBER(FIND("$",SUBSTITUTE(UPPER(TRIM(MID(SUBSTITUTE($H27,",",REPT(" ",99)),199,99)))," ",""))),--ISNUMBER(FIND(SUBSTITUTE(UPPER(TRIM(MID(SUBSTITUTE($H27,",",REPT(" ",99)),199,99)))," ",""),SUBSTITUTE(SUBSTITUTE(SUBSTITUTE(UPPER(J27)," ",""),"SALES!",""),"CONTACTS!",""))),--ISNUMBER(FIND(SUBSTITUTE(UPPER(TRIM(MID(SUBSTITUTE($H27,",",REPT(" ",99)),199,99)))," ",""),SUBSTITUTE(SUBSTITUTE(SUBSTITUTE(SUBSTITUTE(UPPER(J27),"$","")," ",""),"SALES!",""),"CONTACTS!","")))))+IF(SUBSTITUTE(UPPER(TRIM(MID(SUBSTITUTE($H27,",",REPT(" ",99)),298,99)))," ","")="",0,IF(ISNUMBER(FIND("$",SUBSTITUTE(UPPER(TRIM(MID(SUBSTITUTE($H27,",",REPT(" ",99)),298,99)))," ",""))),--ISNUMBER(FIND(SUBSTITUTE(UPPER(TRIM(MID(SUBSTITUTE($H27,",",REPT(" ",99)),298,99)))," ",""),SUBSTITUTE(SUBSTITUTE(SUBSTITUTE(UPPER(J27)," ",""),"SALES!",""),"CONTACTS!",""))),--ISNUMBER(FIND(SUBSTITUTE(UPPER(TRIM(MID(SUBSTITUTE($H27,",",REPT(" ",99)),298,99)))," ",""),SUBSTITUTE(SUBSTITUTE(SUBSTITUTE(SUBSTITUTE(UPPER(J27),"$","")," ",""),"SALES!",""),"CONTACTS!","")))))+IF(SUBSTITUTE(UPPER(TRIM(MID(SUBSTITUTE($H27,",",REPT(" ",99)),397,99)))," ","")="",0,IF(ISNUMBER(FIND("$",SUBSTITUTE(UPPER(TRIM(MID(SUBSTITUTE($H27,",",REPT(" ",99)),397,99)))," ",""))),--ISNUMBER(FIND(SUBSTITUTE(UPPER(TRIM(MID(SUBSTITUTE($H27,",",REPT(" ",99)),397,99)))," ",""),SUBSTITUTE(SUBSTITUTE(SUBSTITUTE(UPPER(J27)," ",""),"SALES!",""),"CONTACTS!",""))),--ISNUMBER(FIND(SUBSTITUTE(UPPER(TRIM(MID(SUBSTITUTE($H27,",",REPT(" ",99)),397,99)))," ",""),SUBSTITUTE(SUBSTITUTE(SUBSTITUTE(SUBSTITUTE(UPPER(J27),"$","")," ",""),"SALES!",""),"CONTACTS!","")))))+IF(SUBSTITUTE(UPPER(TRIM(MID(SUBSTITUTE($H27,",",REPT(" ",99)),496,99)))," ","")="",0,IF(ISNUMBER(FIND("$",SUBSTITUTE(UPPER(TRIM(MID(SUBSTITUTE($H27,",",REPT(" ",99)),496,99)))," ",""))),--ISNUMBER(FIND(SUBSTITUTE(UPPER(TRIM(MID(SUBSTITUTE($H27,",",REPT(" ",99)),496,99)))," ",""),SUBSTITUTE(SUBSTITUTE(SUBSTITUTE(UPPER(J27)," ",""),"SALES!",""),"CONTACTS!",""))),--ISNUMBER(FIND(SUBSTITUTE(UPPER(TRIM(MID(SUBSTITUTE($H27,",",REPT(" ",99)),496,99)))," ",""),SUBSTITUTE(SUBSTITUTE(SUBSTITUTE(SUBSTITUTE(UPPER(J27),"$","")," ",""),"SALES!",""),"CONTACTS!","")))))) | L27: =IF(SUBSTITUTE(UPPER(TRIM(MID(SUBSTITUTE($H27,",",REPT(" ",99)),1,99)))," ","")="",0,1)+IF(SUBSTITUTE(UPPER(TRIM(MID(SUBSTITUTE($H27,",",REPT(" ",99)),100,99)))," ","")="",0,1)+IF(SUBSTITUTE(UPPER(TRIM(MID(SUBSTITUTE($H27,",",REPT(" ",99)),199,99)))," ","")="",0,1)+IF(SUBSTITUTE(UPPER(TRIM(MID(SUBSTITUTE($H27,",",REPT(" ",99)),298,99)))," ","")="",0,1)+IF(SUBSTITUTE(UPPER(TRIM(MID(SUBSTITUTE($H27,",",REPT(" ",99)),397,99)))," ","")="",0,1)+IF(SUBSTITUTE(UPPER(TRIM(MID(SUBSTITUTE($H27,",",REPT(" ",99)),496,99)))," ","")="",0,1) | M27: =IF(J27="","",IF(AND(I27="formula",LEFT(TRIM(J27),1)<>"="),"FAIL",IF(K27=L27,"PASS","CHECK"))) | N27: LEFT + FIND(space)
A28: F27 | B28: Split/combine | C28: Last name only, in Proper Case, from the name in row 5. | D28: Messy!A1:F11 | E28: =LOKUP.V($C28, Messy!A1:F11) | F28: =PROPER(MID(TRIM(Messy!B5),FIND(" ",TRIM(Messy!B5))+1,100)) | G28: =PROPER(MID(TRIM(Messy!B5),FIND(" ",TRIM(Messy!B5))+1,100)) | H28: FIND,B5 | I28: formula | K28: =IF(J28="","",IF(SUBSTITUTE(UPPER(TRIM(MID(SUBSTITUTE($H28,",",REPT(" ",99)),1,99)))," ","")="",0,IF(ISNUMBER(FIND("$",SUBSTITUTE(UPPER(TRIM(MID(SUBSTITUTE($H28,",",REPT(" ",99)),1,99)))," ",""))),--ISNUMBER(FIND(SUBSTITUTE(UPPER(TRIM(MID(SUBSTITUTE($H28,",",REPT(" ",99)),1,99)))," ",""),SUBSTITUTE(SUBSTITUTE(SUBSTITUTE(UPPER(J28)," ",""),"SALES!",""),"CONTACTS!",""))),--ISNUMBER(FIND(SUBSTITUTE(UPPER(TRIM(MID(SUBSTITUTE($H28,",",REPT(" ",99)),1,99)))," ",""),SUBSTITUTE(SUBSTITUTE(SUBSTITUTE(SUBSTITUTE(UPPER(J28),"$","")," ",""),"SALES!",""),"CONTACTS!","")))))+IF(SUBSTITUTE(UPPER(TRIM(MID(SUBSTITUTE($H28,",",REPT(" ",99)),100,99)))," ","")="",0,IF(ISNUMBER(FIND("$",SUBSTITUTE(UPPER(TRIM(MID(SUBSTITUTE($H28,",",REPT(" ",99)),100,99)))," ",""))),--ISNUMBER(FIND(SUBSTITUTE(UPPER(TRIM(MID(SUBSTITUTE($H28,",",REPT(" ",99)),100,99)))," ",""),SUBSTITUTE(SUBSTITUTE(SUBSTITUTE(UPPER(J28)," ",""),"SALES!",""),"CONTACTS!",""))),--ISNUMBER(FIND(SUBSTITUTE(UPPER(TRIM(MID(SUBSTITUTE($H28,",",REPT(" ",99)),100,99)))," ",""),SUBSTITUTE(SUBSTITUTE(SUBSTITUTE(SUBSTITUTE(UPPER(J28),"$","")," ",""),"SALES!",""),"CONTACTS!","")))))+IF(SUBSTITUTE(UPPER(TRIM(MID(SUBSTITUTE($H28,",",REPT(" ",99)),199,99)))," ","")="",0,IF(ISNUMBER(FIND("$",SUBSTITUTE(UPPER(TRIM(MID(SUBSTITUTE($H28,",",REPT(" ",99)),199,99)))," ",""))),--ISNUMBER(FIND(SUBSTITUTE(UPPER(TRIM(MID(SUBSTITUTE($H28,",",REPT(" ",99)),199,99)))," ",""),SUBSTITUTE(SUBSTITUTE(SUBSTITUTE(UPPER(J28)," ",""),"SALES!",""),"CONTACTS!",""))),--ISNUMBER(FIND(SUBSTITUTE(UPPER(TRIM(MID(SUBSTITUTE($H28,",",REPT(" ",99)),199,99)))," ",""),SUBSTITUTE(SUBSTITUTE(SUBSTITUTE(SUBSTITUTE(UPPER(J28),"$","")," ",""),"SALES!",""),"CONTACTS!","")))))+IF(SUBSTITUTE(UPPER(TRIM(MID(SUBSTITUTE($H28,",",REPT(" ",99)),298,99)))," ","")="",0,IF(ISNUMBER(FIND("$",SUBSTITUTE(UPPER(TRIM(MID(SUBSTITUTE($H28,",",REPT(" ",99)),298,99)))," ",""))),--ISNUMBER(FIND(SUBSTITUTE(UPPER(TRIM(MID(SUBSTITUTE($H28,",",REPT(" ",99)),298,99)))," ",""),SUBSTITUTE(SUBSTITUTE(SUBSTITUTE(UPPER(J28)," ",""),"SALES!",""),"CONTACTS!",""))),--ISNUMBER(FIND(SUBSTITUTE(UPPER(TRIM(MID(SUBSTITUTE($H28,",",REPT(" ",99)),298,99)))," ",""),SUBSTITUTE(SUBSTITUTE(SUBSTITUTE(SUBSTITUTE(UPPER(J28),"$","")," ",""),"SALES!",""),"CONTACTS!","")))))+IF(SUBSTITUTE(UPPER(TRIM(MID(SUBSTITUTE($H28,",",REPT(" ",99)),397,99)))," ","")="",0,IF(ISNUMBER(FIND("$",SUBSTITUTE(UPPER(TRIM(MID(SUBSTITUTE($H28,",",REPT(" ",99)),397,99)))," ",""))),--ISNUMBER(FIND(SUBSTITUTE(UPPER(TRIM(MID(SUBSTITUTE($H28,",",REPT(" ",99)),397,99)))," ",""),SUBSTITUTE(SUBSTITUTE(SUBSTITUTE(UPPER(J28)," ",""),"SALES!",""),"CONTACTS!",""))),--ISNUMBER(FIND(SUBSTITUTE(UPPER(TRIM(MID(SUBSTITUTE($H28,",",REPT(" ",99)),397,99)))," ",""),SUBSTITUTE(SUBSTITUTE(SUBSTITUTE(SUBSTITUTE(UPPER(J28),"$","")," ",""),"SALES!",""),"CONTACTS!","")))))+IF(SUBSTITUTE(UPPER(TRIM(MID(SUBSTITUTE($H28,",",REPT(" ",99)),496,99)))," ","")="",0,IF(ISNUMBER(FIND("$",SUBSTITUTE(UPPER(TRIM(MID(SUBSTITUTE($H28,",",REPT(" ",99)),496,99)))," ",""))),--ISNUMBER(FIND(SUBSTITUTE(UPPER(TRIM(MID(SUBSTITUTE($H28,",",REPT(" ",99)),496,99)))," ",""),SUBSTITUTE(SUBSTITUTE(SUBSTITUTE(UPPER(J28)," ",""),"SALES!",""),"CONTACTS!",""))),--ISNUMBER(FIND(SUBSTITUTE(UPPER(TRIM(MID(SUBSTITUTE($H28,",",REPT(" ",99)),496,99)))," ",""),SUBSTITUTE(SUBSTITUTE(SUBSTITUTE(SUBSTITUTE(UPPER(J28),"$","")," ",""),"SALES!",""),"CONTACTS!","")))))) | L28: =IF(SUBSTITUTE(UPPER(TRIM(MID(SUBSTITUTE($H28,",",REPT(" ",99)),1,99)))," ","")="",0,1)+IF(SUBSTITUTE(UPPER(TRIM(MID(SUBSTITUTE($H28,",",REPT(" ",99)),100,99)))," ","")="",0,1)+IF(SUBSTITUTE(UPPER(TRIM(MID(SUBSTITUTE($H28,",",REPT(" ",99)),199,99)))," ","")="",0,1)+IF(SUBSTITUTE(UPPER(TRIM(MID(SUBSTITUTE($H28,",",REPT(" ",99)),298,99)))," ","")="",0,1)+IF(SUBSTITUTE(UPPER(TRIM(MID(SUBSTITUTE($H28,",",REPT(" ",99)),397,99)))," ","")="",0,1)+IF(SUBSTITUTE(UPPER(TRIM(MID(SUBSTITUTE($H28,",",REPT(" ",99)),496,99)))," ","")="",0,1) | M28: =IF(J28="","",IF(AND(I28="formula",LEFT(TRIM(J28),1)<>"="),"FAIL",IF(K28=L28,"PASS","CHECK"))) | N28: MID/RIGHT after the space
A29: F28 | B29: Duplicates/blanks | C29: Formula for row 6 that I can drag down: Duplicate if this email already appeared in an earlier row, otherwise Unique. | D29: Messy!A1:F11 | E29: =LOKUP.V($C29, Messy!A1:F11) | F29: =IF(COUNTIF(Messy!$F$2:F5,Messy!F6)>0,"Duplicate","Unique") | G29: =IF(COUNTIF(Messy!$F$2:F5,Messy!F6)>0,"Duplicate","Unique") | H29: COUNTIF,$F$2,F6,DUPLICATE,UNIQUE | I29: formula | K29: =IF(J29="","",IF(SUBSTITUTE(UPPER(TRIM(MID(SUBSTITUTE($H29,",",REPT(" ",99)),1,99)))," ","")="",0,IF(ISNUMBER(FIND("$",SUBSTITUTE(UPPER(TRIM(MID(SUBSTITUTE($H29,",",REPT(" ",99)),1,99)))," ",""))),--ISNUMBER(FIND(SUBSTITUTE(UPPER(TRIM(MID(SUBSTITUTE($H29,",",REPT(" ",99)),1,99)))," ",""),SUBSTITUTE(SUBSTITUTE(SUBSTITUTE(UPPER(J29)," ",""),"SALES!",""),"CONTACTS!",""))),--ISNUMBER(FIND(SUBSTITUTE(UPPER(TRIM(MID(SUBSTITUTE($H29,",",REPT(" ",99)),1,99)))," ",""),SUBSTITUTE(SUBSTITUTE(SUBSTITUTE(SUBSTITUTE(UPPER(J29),"$","")," ",""),"SALES!",""),"CONTACTS!","")))))+IF(SUBSTITUTE(UPPER(TRIM(MID(SUBSTITUTE($H29,",",REPT(" ",99)),100,99)))," ","")="",0,IF(ISNUMBER(FIND("$",SUBSTITUTE(UPPER(TRIM(MID(SUBSTITUTE($H29,",",REPT(" ",99)),100,99)))," ",""))),--ISNUMBER(FIND(SUBSTITUTE(UPPER(TRIM(MID(SUBSTITUTE($H29,",",REPT(" ",99)),100,99)))," ",""),SUBSTITUTE(SUBSTITUTE(SUBSTITUTE(UPPER(J29)," ",""),"SALES!",""),"CONTACTS!",""))),--ISNUMBER(FIND(SUBSTITUTE(UPPER(TRIM(MID(SUBSTITUTE($H29,",",REPT(" ",99)),100,99)))," ",""),SUBSTITUTE(SUBSTITUTE(SUBSTITUTE(SUBSTITUTE(UPPER(J29),"$","")," ",""),"SALES!",""),"CONTACTS!","")))))+IF(SUBSTITUTE(UPPER(TRIM(MID(SUBSTITUTE($H29,",",REPT(" ",99)),199,99)))," ","")="",0,IF(ISNUMBER(FIND("$",SUBSTITUTE(UPPER(TRIM(MID(SUBSTITUTE($H29,",",REPT(" ",99)),199,99)))," ",""))),--ISNUMBER(FIND(SUBSTITUTE(UPPER(TRIM(MID(SUBSTITUTE($H29,",",REPT(" ",99)),199,99)))," ",""),SUBSTITUTE(SUBSTITUTE(SUBSTITUTE(UPPER(J29)," ",""),"SALES!",""),"CONTACTS!",""))),--ISNUMBER(FIND(SUBSTITUTE(UPPER(TRIM(MID(SUBSTITUTE($H29,",",REPT(" ",99)),199,99)))," ",""),SUBSTITUTE(SUBSTITUTE(SUBSTITUTE(SUBSTITUTE(UPPER(J29),"$","")," ",""),"SALES!",""),"CONTACTS!","")))))+IF(SUBSTITUTE(UPPER(TRIM(MID(SUBSTITUTE($H29,",",REPT(" ",99)),298,99)))," ","")="",0,IF(ISNUMBER(FIND("$",SUBSTITUTE(UPPER(TRIM(MID(SUBSTITUTE($H29,",",REPT(" ",99)),298,99)))," ",""))),--ISNUMBER(FIND(SUBSTITUTE(UPPER(TRIM(MID(SUBSTITUTE($H29,",",REPT(" ",99)),298,99)))," ",""),SUBSTITUTE(SUBSTITUTE(SUBSTITUTE(UPPER(J29)," ",""),"SALES!",""),"CONTACTS!",""))),--ISNUMBER(FIND(SUBSTITUTE(UPPER(TRIM(MID(SUBSTITUTE($H29,",",REPT(" ",99)),298,99)))," ",""),SUBSTITUTE(SUBSTITUTE(SUBSTITUTE(SUBSTITUTE(UPPER(J29),"$","")," ",""),"SALES!",""),"CONTACTS!","")))))+IF(SUBSTITUTE(UPPER(TRIM(MID(SUBSTITUTE($H29,",",REPT(" ",99)),397,99)))," ","")="",0,IF(ISNUMBER(FIND("$",SUBSTITUTE(UPPER(TRIM(MID(SUBSTITUTE($H29,",",REPT(" ",99)),397,99)))," ",""))),--ISNUMBER(FIND(SUBSTITUTE(UPPER(TRIM(MID(SUBSTITUTE($H29,",",REPT(" ",99)),397,99)))," ",""),SUBSTITUTE(SUBSTITUTE(SUBSTITUTE(UPPER(J29)," ",""),"SALES!",""),"CONTACTS!",""))),--ISNUMBER(FIND(SUBSTITUTE(UPPER(TRIM(MID(SUBSTITUTE($H29,",",REPT(" ",99)),397,99)))," ",""),SUBSTITUTE(SUBSTITUTE(SUBSTITUTE(SUBSTITUTE(UPPER(J29),"$","")," ",""),"SALES!",""),"CONTACTS!","")))))+IF(SUBSTITUTE(UPPER(TRIM(MID(SUBSTITUTE($H29,",",REPT(" ",99)),496,99)))," ","")="",0,IF(ISNUMBER(FIND("$",SUBSTITUTE(UPPER(TRIM(MID(SUBSTITUTE($H29,",",REPT(" ",99)),496,99)))," ",""))),--ISNUMBER(FIND(SUBSTITUTE(UPPER(TRIM(MID(SUBSTITUTE($H29,",",REPT(" ",99)),496,99)))," ",""),SUBSTITUTE(SUBSTITUTE(SUBSTITUTE(UPPER(J29)," ",""),"SALES!",""),"CONTACTS!",""))),--ISNUMBER(FIND(SUBSTITUTE(UPPER(TRIM(MID(SUBSTITUTE($H29,",",REPT(" ",99)),496,99)))," ",""),SUBSTITUTE(SUBSTITUTE(SUBSTITUTE(SUBSTITUTE(UPPER(J29),"$","")," ",""),"SALES!",""),"CONTACTS!","")))))) | L29: =IF(SUBSTITUTE(UPPER(TRIM(MID(SUBSTITUTE($H29,",",REPT(" ",99)),1,99)))," ","")="",0,1)+IF(SUBSTITUTE(UPPER(TRIM(MID(SUBSTITUTE($H29,",",REPT(" ",99)),100,99)))," ","")="",0,1)+IF(SUBSTITUTE(UPPER(TRIM(MID(SUBSTITUTE($H29,",",REPT(" ",99)),199,99)))," ","")="",0,1)+IF(SUBSTITUTE(UPPER(TRIM(MID(SUBSTITUTE($H29,",",REPT(" ",99)),298,99)))," ","")="",0,1)+IF(SUBSTITUTE(UPPER(TRIM(MID(SUBSTITUTE($H29,",",REPT(" ",99)),397,99)))," ","")="",0,1)+IF(SUBSTITUTE(UPPER(TRIM(MID(SUBSTITUTE($H29,",",REPT(" ",99)),496,99)))," ","")="",0,1) | M29: =IF(J29="","",IF(AND(I29="formula",LEFT(TRIM(J29),1)<>"="),"FAIL",IF(K29=L29,"PASS","CHECK"))) | N29: expanding range: anchored start, relative end
A30: F29 | B30: Duplicates/blanks | C30: How many rows are missing a phone number? | D30: Messy!A1:F11 | E30: =LOKUP.V($C30, Messy!A1:F11) | F30: =COUNTBLANK(Messy!C2:C11) | G30: =COUNTBLANK(Messy!C2:C11) | H30: C2:C11 | I30: formula | K30: =IF(J30="","",IF(SUBSTITUTE(UPPER(TRIM(MID(SUBSTITUTE($H30,",",REPT(" ",99)),1,99)))," ","")="",0,IF(ISNUMBER(FIND("$",SUBSTITUTE(UPPER(TRIM(MID(SUBSTITUTE($H30,",",REPT(" ",99)),1,99)))," ",""))),--ISNUMBER(FIND(SUBSTITUTE(UPPER(TRIM(MID(SUBSTITUTE($H30,",",REPT(" ",99)),1,99)))," ",""),SUBSTITUTE(SUBSTITUTE(SUBSTITUTE(UPPER(J30)," ",""),"SALES!",""),"CONTACTS!",""))),--ISNUMBER(FIND(SUBSTITUTE(UPPER(TRIM(MID(SUBSTITUTE($H30,",",REPT(" ",99)),1,99)))," ",""),SUBSTITUTE(SUBSTITUTE(SUBSTITUTE(SUBSTITUTE(UPPER(J30),"$","")," ",""),"SALES!",""),"CONTACTS!","")))))+IF(SUBSTITUTE(UPPER(TRIM(MID(SUBSTITUTE($H30,",",REPT(" ",99)),100,99)))," ","")="",0,IF(ISNUMBER(FIND("$",SUBSTITUTE(UPPER(TRIM(MID(SUBSTITUTE($H30,",",REPT(" ",99)),100,99)))," ",""))),--ISNUMBER(FIND(SUBSTITUTE(UPPER(TRIM(MID(SUBSTITUTE($H30,",",REPT(" ",99)),100,99)))," ",""),SUBSTITUTE(SUBSTITUTE(SUBSTITUTE(UPPER(J30)," ",""),"SALES!",""),"CONTACTS!",""))),--ISNUMBER(FIND(SUBSTITUTE(UPPER(TRIM(MID(SUBSTITUTE($H30,",",REPT(" ",99)),100,99)))," ",""),SUBSTITUTE(SUBSTITUTE(SUBSTITUTE(SUBSTITUTE(UPPER(J30),"$","")," ",""),"SALES!",""),"CONTACTS!","")))))+IF(SUBSTITUTE(UPPER(TRIM(MID(SUBSTITUTE($H30,",",REPT(" ",99)),199,99)))," ","")="",0,IF(ISNUMBER(FIND("$",SUBSTITUTE(UPPER(TRIM(MID(SUBSTITUTE($H30,",",REPT(" ",99)),199,99)))," ",""))),--ISNUMBER(FIND(SUBSTITUTE(UPPER(TRIM(MID(SUBSTITUTE($H30,",",REPT(" ",99)),199,99)))," ",""),SUBSTITUTE(SUBSTITUTE(SUBSTITUTE(UPPER(J30)," ",""),"SALES!",""),"CONTACTS!",""))),--ISNUMBER(FIND(SUBSTITUTE(UPPER(TRIM(MID(SUBSTITUTE($H30,",",REPT(" ",99)),199,99)))," ",""),SUBSTITUTE(SUBSTITUTE(SUBSTITUTE(SUBSTITUTE(UPPER(J30),"$","")," ",""),"SALES!",""),"CONTACTS!","")))))+IF(SUBSTITUTE(UPPER(TRIM(MID(SUBSTITUTE($H30,",",REPT(" ",99)),298,99)))," ","")="",0,IF(ISNUMBER(FIND("$",SUBSTITUTE(UPPER(TRIM(MID(SUBSTITUTE($H30,",",REPT(" ",99)),298,99)))," ",""))),--ISNUMBER(FIND(SUBSTITUTE(UPPER(TRIM(MID(SUBSTITUTE($H30,",",REPT(" ",99)),298,99)))," ",""),SUBSTITUTE(SUBSTITUTE(SUBSTITUTE(UPPER(J30)," ",""),"SALES!",""),"CONTACTS!",""))),--ISNUMBER(FIND(SUBSTITUTE(UPPER(TRIM(MID(SUBSTITUTE($H30,",",REPT(" ",99)),298,99)))," ",""),SUBSTITUTE(SUBSTITUTE(SUBSTITUTE(SUBSTITUTE(UPPER(J30),"$","")," ",""),"SALES!",""),"CONTACTS!","")))))+IF(SUBSTITUTE(UPPER(TRIM(MID(SUBSTITUTE($H30,",",REPT(" ",99)),397,99)))," ","")="",0,IF(ISNUMBER(FIND("$",SUBSTITUTE(UPPER(TRIM(MID(SUBSTITUTE($H30,",",REPT(" ",99)),397,99)))," ",""))),--ISNUMBER(FIND(SUBSTITUTE(UPPER(TRIM(MID(SUBSTITUTE($H30,",",REPT(" ",99)),397,99)))," ",""),SUBSTITUTE(SUBSTITUTE(SUBSTITUTE(UPPER(J30)," ",""),"SALES!",""),"CONTACTS!",""))),--ISNUMBER(FIND(SUBSTITUTE(UPPER(TRIM(MID(SUBSTITUTE($H30,",",REPT(" ",99)),397,99)))," ",""),SUBSTITUTE(SUBSTITUTE(SUBSTITUTE(SUBSTITUTE(UPPER(J30),"$","")," ",""),"SALES!",""),"CONTACTS!","")))))+IF(SUBSTITUTE(UPPER(TRIM(MID(SUBSTITUTE($H30,",",REPT(" ",99)),496,99)))," ","")="",0,IF(ISNUMBER(FIND("$",SUBSTITUTE(UPPER(TRIM(MID(SUBSTITUTE($H30,",",REPT(" ",99)),496,99)))," ",""))),--ISNUMBER(FIND(SUBSTITUTE(UPPER(TRIM(MID(SUBSTITUTE($H30,",",REPT(" ",99)),496,99)))," ",""),SUBSTITUTE(SUBSTITUTE(SUBSTITUTE(UPPER(J30)," ",""),"SALES!",""),"CONTACTS!",""))),--ISNUMBER(FIND(SUBSTITUTE(UPPER(TRIM(MID(SUBSTITUTE($H30,",",REPT(" ",99)),496,99)))," ",""),SUBSTITUTE(SUBSTITUTE(SUBSTITUTE(SUBSTITUTE(UPPER(J30),"$","")," ",""),"SALES!",""),"CONTACTS!","")))))) | L30: =IF(SUBSTITUTE(UPPER(TRIM(MID(SUBSTITUTE($H30,",",REPT(" ",99)),1,99)))," ","")="",0,1)+IF(SUBSTITUTE(UPPER(TRIM(MID(SUBSTITUTE($H30,",",REPT(" ",99)),100,99)))," ","")="",0,1)+IF(SUBSTITUTE(UPPER(TRIM(MID(SUBSTITUTE($H30,",",REPT(" ",99)),199,99)))," ","")="",0,1)+IF(SUBSTITUTE(UPPER(TRIM(MID(SUBSTITUTE($H30,",",REPT(" ",99)),298,99)))," ","")="",0,1)+IF(SUBSTITUTE(UPPER(TRIM(MID(SUBSTITUTE($H30,",",REPT(" ",99)),397,99)))," ","")="",0,1)+IF(SUBSTITUTE(UPPER(TRIM(MID(SUBSTITUTE($H30,",",REPT(" ",99)),496,99)))," ","")="",0,1) | M30: =IF(J30="","",IF(AND(I30="formula",LEFT(TRIM(J30),1)<>"="),"FAIL",IF(K30=L30,"PASS","CHECK"))) | N30: COUNTBLANK or COUNTIF(...,"")
A31: F30 | B31: Split/combine | C31: Combine the name and email of row 7 as: Name <email> | D31: Messy!A1:F11 | E31: =LOKUP.V($C31, Messy!A1:F11) | F31: =TRIM(Messy!B7)&" <"&Messy!F7&">" | G31: =TRIM(Messy!B7)&" <"&Messy!F7&">" | H31: B7,F7 | I31: formula | K31: =IF(J31="","",IF(SUBSTITUTE(UPPER(TRIM(MID(SUBSTITUTE($H31,",",REPT(" ",99)),1,99)))," ","")="",0,IF(ISNUMBER(FIND("$",SUBSTITUTE(UPPER(TRIM(MID(SUBSTITUTE($H31,",",REPT(" ",99)),1,99)))," ",""))),--ISNUMBER(FIND(SUBSTITUTE(UPPER(TRIM(MID(SUBSTITUTE($H31,",",REPT(" ",99)),1,99)))," ",""),SUBSTITUTE(SUBSTITUTE(SUBSTITUTE(UPPER(J31)," ",""),"SALES!",""),"CONTACTS!",""))),--ISNUMBER(FIND(SUBSTITUTE(UPPER(TRIM(MID(SUBSTITUTE($H31,",",REPT(" ",99)),1,99)))," ",""),SUBSTITUTE(SUBSTITUTE(SUBSTITUTE(SUBSTITUTE(UPPER(J31),"$","")," ",""),"SALES!",""),"CONTACTS!","")))))+IF(SUBSTITUTE(UPPER(TRIM(MID(SUBSTITUTE($H31,",",REPT(" ",99)),100,99)))," ","")="",0,IF(ISNUMBER(FIND("$",SUBSTITUTE(UPPER(TRIM(MID(SUBSTITUTE($H31,",",REPT(" ",99)),100,99)))," ",""))),--ISNUMBER(FIND(SUBSTITUTE(UPPER(TRIM(MID(SUBSTITUTE($H31,",",REPT(" ",99)),100,99)))," ",""),SUBSTITUTE(SUBSTITUTE(SUBSTITUTE(UPPER(J31)," ",""),"SALES!",""),"CONTACTS!",""))),--ISNUMBER(FIND(SUBSTITUTE(UPPER(TRIM(MID(SUBSTITUTE($H31,",",REPT(" ",99)),100,99)))," ",""),SUBSTITUTE(SUBSTITUTE(SUBSTITUTE(SUBSTITUTE(UPPER(J31),"$","")," ",""),"SALES!",""),"CONTACTS!","")))))+IF(SUBSTITUTE(UPPER(TRIM(MID(SUBSTITUTE($H31,",",REPT(" ",99)),199,99)))," ","")="",0,IF(ISNUMBER(FIND("$",SUBSTITUTE(UPPER(TRIM(MID(SUBSTITUTE($H31,",",REPT(" ",99)),199,99)))," ",""))),--ISNUMBER(FIND(SUBSTITUTE(UPPER(TRIM(MID(SUBSTITUTE($H31,",",REPT(" ",99)),199,99)))," ",""),SUBSTITUTE(SUBSTITUTE(SUBSTITUTE(UPPER(J31)," ",""),"SALES!",""),"CONTACTS!",""))),--ISNUMBER(FIND(SUBSTITUTE(UPPER(TRIM(MID(SUBSTITUTE($H31,",",REPT(" ",99)),199,99)))," ",""),SUBSTITUTE(SUBSTITUTE(SUBSTITUTE(SUBSTITUTE(UPPER(J31),"$","")," ",""),"SALES!",""),"CONTACTS!","")))))+IF(SUBSTITUTE(UPPER(TRIM(MID(SUBSTITUTE($H31,",",REPT(" ",99)),298,99)))," ","")="",0,IF(ISNUMBER(FIND("$",SUBSTITUTE(UPPER(TRIM(MID(SUBSTITUTE($H31,",",REPT(" ",99)),298,99)))," ",""))),--ISNUMBER(FIND(SUBSTITUTE(UPPER(TRIM(MID(SUBSTITUTE($H31,",",REPT(" ",99)),298,99)))," ",""),SUBSTITUTE(SUBSTITUTE(SUBSTITUTE(UPPER(J31)," ",""),"SALES!",""),"CONTACTS!",""))),--ISNUMBER(FIND(SUBSTITUTE(UPPER(TRIM(MID(SUBSTITUTE($H31,",",REPT(" ",99)),298,99)))," ",""),SUBSTITUTE(SUBSTITUTE(SUBSTITUTE(SUBSTITUTE(UPPER(J31),"$","")," ",""),"SALES!",""),"CONTACTS!","")))))+IF(SUBSTITUTE(UPPER(TRIM(MID(SUBSTITUTE($H31,",",REPT(" ",99)),397,99)))," ","")="",0,IF(ISNUMBER(FIND("$",SUBSTITUTE(UPPER(TRIM(MID(SUBSTITUTE($H31,",",REPT(" ",99)),397,99)))," ",""))),--ISNUMBER(FIND(SUBSTITUTE(UPPER(TRIM(MID(SUBSTITUTE($H31,",",REPT(" ",99)),397,99)))," ",""),SUBSTITUTE(SUBSTITUTE(SUBSTITUTE(UPPER(J31)," ",""),"SALES!",""),"CONTACTS!",""))),--ISNUMBER(FIND(SUBSTITUTE(UPPER(TRIM(MID(SUBSTITUTE($H31,",",REPT(" ",99)),397,99)))," ",""),SUBSTITUTE(SUBSTITUTE(SUBSTITUTE(SUBSTITUTE(UPPER(J31),"$","")," ",""),"SALES!",""),"CONTACTS!","")))))+IF(SUBSTITUTE(UPPER(TRIM(MID(SUBSTITUTE($H31,",",REPT(" ",99)),496,99)))," ","")="",0,IF(ISNUMBER(FIND("$",SUBSTITUTE(UPPER(TRIM(MID(SUBSTITUTE($H31,",",REPT(" ",99)),496,99)))," ",""))),--ISNUMBER(FIND(SUBSTITUTE(UPPER(TRIM(MID(SUBSTITUTE($H31,",",REPT(" ",99)),496,99)))," ",""),SUBSTITUTE(SUBSTITUTE(SUBSTITUTE(UPPER(J31)," ",""),"SALES!",""),"CONTACTS!",""))),--ISNUMBER(FIND(SUBSTITUTE(UPPER(TRIM(MID(SUBSTITUTE($H31,",",REPT(" ",99)),496,99)))," ",""),SUBSTITUTE(SUBSTITUTE(SUBSTITUTE(SUBSTITUTE(UPPER(J31),"$","")," ",""),"SALES!",""),"CONTACTS!","")))))) | L31: =IF(SUBSTITUTE(UPPER(TRIM(MID(SUBSTITUTE($H31,",",REPT(" ",99)),1,99)))," ","")="",0,1)+IF(SUBSTITUTE(UPPER(TRIM(MID(SUBSTITUTE($H31,",",REPT(" ",99)),100,99)))," ","")="",0,1)+IF(SUBSTITUTE(UPPER(TRIM(MID(SUBSTITUTE($H31,",",REPT(" ",99)),199,99)))," ","")="",0,1)+IF(SUBSTITUTE(UPPER(TRIM(MID(SUBSTITUTE($H31,",",REPT(" ",99)),298,99)))," ","")="",0,1)+IF(SUBSTITUTE(UPPER(TRIM(MID(SUBSTITUTE($H31,",",REPT(" ",99)),397,99)))," ","")="",0,1)+IF(SUBSTITUTE(UPPER(TRIM(MID(SUBSTITUTE($H31,",",REPT(" ",99)),496,99)))," ","")="",0,1) | M31: =IF(J31="","",IF(AND(I31="formula",LEFT(TRIM(J31),1)<>"="),"FAIL",IF(K31=L31,"PASS","CHECK"))) | N31: text joining with & (TEXTJOIN unavailable here)
A32: F31 | B32: Held-out | C32: Initials of the name in row 9, in capitals (e.g. AR). | D32: Messy!A1:F11 | E32: =LOKUP.V($C32, Messy!A1:F11) | F32: =UPPER(LEFT(TRIM(Messy!B9),1)&MID(TRIM(Messy!B9),FIND(" ",TRIM(Messy!B9))+1,1)) | G32: =UPPER(LEFT(TRIM(Messy!B9),1)&MID(TRIM(Messy!B9),FIND(" ",TRIM(Messy!B9))+1,1)) | H32: B9,LEFT | I32: formula | K32: =IF(J32="","",IF(SUBSTITUTE(UPPER(TRIM(MID(SUBSTITUTE($H32,",",REPT(" ",99)),1,99)))," ","")="",0,IF(ISNUMBER(FIND("$",SUBSTITUTE(UPPER(TRIM(MID(SUBSTITUTE($H32,",",REPT(" ",99)),1,99)))," ",""))),--ISNUMBER(FIND(SUBSTITUTE(UPPER(TRIM(MID(SUBSTITUTE($H32,",",REPT(" ",99)),1,99)))," ",""),SUBSTITUTE(SUBSTITUTE(SUBSTITUTE(UPPER(J32)," ",""),"SALES!",""),"CONTACTS!",""))),--ISNUMBER(FIND(SUBSTITUTE(UPPER(TRIM(MID(SUBSTITUTE($H32,",",REPT(" ",99)),1,99)))," ",""),SUBSTITUTE(SUBSTITUTE(SUBSTITUTE(SUBSTITUTE(UPPER(J32),"$","")," ",""),"SALES!",""),"CONTACTS!","")))))+IF(SUBSTITUTE(UPPER(TRIM(MID(SUBSTITUTE($H32,",",REPT(" ",99)),100,99)))," ","")="",0,IF(ISNUMBER(FIND("$",SUBSTITUTE(UPPER(TRIM(MID(SUBSTITUTE($H32,",",REPT(" ",99)),100,99)))," ",""))),--ISNUMBER(FIND(SUBSTITUTE(UPPER(TRIM(MID(SUBSTITUTE($H32,",",REPT(" ",99)),100,99)))," ",""),SUBSTITUTE(SUBSTITUTE(SUBSTITUTE(UPPER(J32)," ",""),"SALES!",""),"CONTACTS!",""))),--ISNUMBER(FIND(SUBSTITUTE(UPPER(TRIM(MID(SUBSTITUTE($H32,",",REPT(" ",99)),100,99)))," ",""),SUBSTITUTE(SUBSTITUTE(SUBSTITUTE(SUBSTITUTE(UPPER(J32),"$","")," ",""),"SALES!",""),"CONTACTS!","")))))+IF(SUBSTITUTE(UPPER(TRIM(MID(SUBSTITUTE($H32,",",REPT(" ",99)),199,99)))," ","")="",0,IF(ISNUMBER(FIND("$",SUBSTITUTE(UPPER(TRIM(MID(SUBSTITUTE($H32,",",REPT(" ",99)),199,99)))," ",""))),--ISNUMBER(FIND(SUBSTITUTE(UPPER(TRIM(MID(SUBSTITUTE($H32,",",REPT(" ",99)),199,99)))," ",""),SUBSTITUTE(SUBSTITUTE(SUBSTITUTE(UPPER(J32)," ",""),"SALES!",""),"CONTACTS!",""))),--ISNUMBER(FIND(SUBSTITUTE(UPPER(TRIM(MID(SUBSTITUTE($H32,",",REPT(" ",99)),199,99)))," ",""),SUBSTITUTE(SUBSTITUTE(SUBSTITUTE(SUBSTITUTE(UPPER(J32),"$","")," ",""),"SALES!",""),"CONTACTS!","")))))+IF(SUBSTITUTE(UPPER(TRIM(MID(SUBSTITUTE($H32,",",REPT(" ",99)),298,99)))," ","")="",0,IF(ISNUMBER(FIND("$",SUBSTITUTE(UPPER(TRIM(MID(SUBSTITUTE($H32,",",REPT(" ",99)),298,99)))," ",""))),--ISNUMBER(FIND(SUBSTITUTE(UPPER(TRIM(MID(SUBSTITUTE($H32,",",REPT(" ",99)),298,99)))," ",""),SUBSTITUTE(SUBSTITUTE(SUBSTITUTE(UPPER(J32)," ",""),"SALES!",""),"CONTACTS!",""))),--ISNUMBER(FIND(SUBSTITUTE(UPPER(TRIM(MID(SUBSTITUTE($H32,",",REPT(" ",99)),298,99)))," ",""),SUBSTITUTE(SUBSTITUTE(SUBSTITUTE(SUBSTITUTE(UPPER(J32),"$","")," ",""),"SALES!",""),"CONTACTS!","")))))+IF(SUBSTITUTE(UPPER(TRIM(MID(SUBSTITUTE($H32,",",REPT(" ",99)),397,99)))," ","")="",0,IF(ISNUMBER(FIND("$",SUBSTITUTE(UPPER(TRIM(MID(SUBSTITUTE($H32,",",REPT(" ",99)),397,99)))," ",""))),--ISNUMBER(FIND(SUBSTITUTE(UPPER(TRIM(MID(SUBSTITUTE($H32,",",REPT(" ",99)),397,99)))," ",""),SUBSTITUTE(SUBSTITUTE(SUBSTITUTE(UPPER(J32)," ",""),"SALES!",""),"CONTACTS!",""))),--ISNUMBER(FIND(SUBSTITUTE(UPPER(TRIM(MID(SUBSTITUTE($H32,",",REPT(" ",99)),397,99)))," ",""),SUBSTITUTE(SUBSTITUTE(SUBSTITUTE(SUBSTITUTE(UPPER(J32),"$","")," ",""),"SALES!",""),"CONTACTS!","")))))+IF(SUBSTITUTE(UPPER(TRIM(MID(SUBSTITUTE($H32,",",REPT(" ",99)),496,99)))," ","")="",0,IF(ISNUMBER(FIND("$",SUBSTITUTE(UPPER(TRIM(MID(SUBSTITUTE($H32,",",REPT(" ",99)),496,99)))," ",""))),--ISNUMBER(FIND(SUBSTITUTE(UPPER(TRIM(MID(SUBSTITUTE($H32,",",REPT(" ",99)),496,99)))," ",""),SUBSTITUTE(SUBSTITUTE(SUBSTITUTE(UPPER(J32)," ",""),"SALES!",""),"CONTACTS!",""))),--ISNUMBER(FIND(SUBSTITUTE(UPPER(TRIM(MID(SUBSTITUTE($H32,",",REPT(" ",99)),496,99)))," ",""),SUBSTITUTE(SUBSTITUTE(SUBSTITUTE(SUBSTITUTE(UPPER(J32),"$","")," ",""),"SALES!",""),"CONTACTS!","")))))) | L32: =IF(SUBSTITUTE(UPPER(TRIM(MID(SUBSTITUTE($H32,",",REPT(" ",99)),1,99)))," ","")="",0,1)+IF(SUBSTITUTE(UPPER(TRIM(MID(SUBSTITUTE($H32,",",REPT(" ",99)),100,99)))," ","")="",0,1)+IF(SUBSTITUTE(UPPER(TRIM(MID(SUBSTITUTE($H32,",",REPT(" ",99)),199,99)))," ","")="",0,1)+IF(SUBSTITUTE(UPPER(TRIM(MID(SUBSTITUTE($H32,",",REPT(" ",99)),298,99)))," ","")="",0,1)+IF(SUBSTITUTE(UPPER(TRIM(MID(SUBSTITUTE($H32,",",REPT(" ",99)),397,99)))," ","")="",0,1)+IF(SUBSTITUTE(UPPER(TRIM(MID(SUBSTITUTE($H32,",",REPT(" ",99)),496,99)))," ","")="",0,1) | M32: =IF(J32="","",IF(AND(I32="formula",LEFT(TRIM(J32),1)<>"="),"FAIL",IF(K32=L32,"PASS","CHECK"))) | N32: two pieces of text joined
A33: F32 | B33: Held-out | C33: Domain of the email in row 3 (the part after @), in lowercase. | D33: Messy!A1:F11 | E33: =LOKUP.V($C33, Messy!A1:F11) | F33: =LOWER(MID(TRIM(Messy!F3),FIND("@",TRIM(Messy!F3))+1,100)) | G33: =LOWER(MID(TRIM(Messy!F3),FIND("@",TRIM(Messy!F3))+1,100)) | H33: F3,@ | I33: formula | K33: =IF(J33="","",IF(SUBSTITUTE(UPPER(TRIM(MID(SUBSTITUTE($H33,",",REPT(" ",99)),1,99)))," ","")="",0,IF(ISNUMBER(FIND("$",SUBSTITUTE(UPPER(TRIM(MID(SUBSTITUTE($H33,",",REPT(" ",99)),1,99)))," ",""))),--ISNUMBER(FIND(SUBSTITUTE(UPPER(TRIM(MID(SUBSTITUTE($H33,",",REPT(" ",99)),1,99)))," ",""),SUBSTITUTE(SUBSTITUTE(SUBSTITUTE(UPPER(J33)," ",""),"SALES!",""),"CONTACTS!",""))),--ISNUMBER(FIND(SUBSTITUTE(UPPER(TRIM(MID(SUBSTITUTE($H33,",",REPT(" ",99)),1,99)))," ",""),SUBSTITUTE(SUBSTITUTE(SUBSTITUTE(SUBSTITUTE(UPPER(J33),"$","")," ",""),"SALES!",""),"CONTACTS!","")))))+IF(SUBSTITUTE(UPPER(TRIM(MID(SUBSTITUTE($H33,",",REPT(" ",99)),100,99)))," ","")="",0,IF(ISNUMBER(FIND("$",SUBSTITUTE(UPPER(TRIM(MID(SUBSTITUTE($H33,",",REPT(" ",99)),100,99)))," ",""))),--ISNUMBER(FIND(SUBSTITUTE(UPPER(TRIM(MID(SUBSTITUTE($H33,",",REPT(" ",99)),100,99)))," ",""),SUBSTITUTE(SUBSTITUTE(SUBSTITUTE(UPPER(J33)," ",""),"SALES!",""),"CONTACTS!",""))),--ISNUMBER(FIND(SUBSTITUTE(UPPER(TRIM(MID(SUBSTITUTE($H33,",",REPT(" ",99)),100,99)))," ",""),SUBSTITUTE(SUBSTITUTE(SUBSTITUTE(SUBSTITUTE(UPPER(J33),"$","")," ",""),"SALES!",""),"CONTACTS!","")))))+IF(SUBSTITUTE(UPPER(TRIM(MID(SUBSTITUTE($H33,",",REPT(" ",99)),199,99)))," ","")="",0,IF(ISNUMBER(FIND("$",SUBSTITUTE(UPPER(TRIM(MID(SUBSTITUTE($H33,",",REPT(" ",99)),199,99)))," ",""))),--ISNUMBER(FIND(SUBSTITUTE(UPPER(TRIM(MID(SUBSTITUTE($H33,",",REPT(" ",99)),199,99)))," ",""),SUBSTITUTE(SUBSTITUTE(SUBSTITUTE(UPPER(J33)," ",""),"SALES!",""),"CONTACTS!",""))),--ISNUMBER(FIND(SUBSTITUTE(UPPER(TRIM(MID(SUBSTITUTE($H33,",",REPT(" ",99)),199,99)))," ",""),SUBSTITUTE(SUBSTITUTE(SUBSTITUTE(SUBSTITUTE(UPPER(J33),"$","")," ",""),"SALES!",""),"CONTACTS!","")))))+IF(SUBSTITUTE(UPPER(TRIM(MID(SUBSTITUTE($H33,",",REPT(" ",99)),298,99)))," ","")="",0,IF(ISNUMBER(FIND("$",SUBSTITUTE(UPPER(TRIM(MID(SUBSTITUTE($H33,",",REPT(" ",99)),298,99)))," ",""))),--ISNUMBER(FIND(SUBSTITUTE(UPPER(TRIM(MID(SUBSTITUTE($H33,",",REPT(" ",99)),298,99)))," ",""),SUBSTITUTE(SUBSTITUTE(SUBSTITUTE(UPPER(J33)," ",""),"SALES!",""),"CONTACTS!",""))),--ISNUMBER(FIND(SUBSTITUTE(UPPER(TRIM(MID(SUBSTITUTE($H33,",",REPT(" ",99)),298,99)))," ",""),SUBSTITUTE(SUBSTITUTE(SUBSTITUTE(SUBSTITUTE(UPPER(J33),"$","")," ",""),"SALES!",""),"CONTACTS!","")))))+IF(SUBSTITUTE(UPPER(TRIM(MID(SUBSTITUTE($H33,",",REPT(" ",99)),397,99)))," ","")="",0,IF(ISNUMBER(FIND("$",SUBSTITUTE(UPPER(TRIM(MID(SUBSTITUTE($H33,",",REPT(" ",99)),397,99)))," ",""))),--ISNUMBER(FIND(SUBSTITUTE(UPPER(TRIM(MID(SUBSTITUTE($H33,",",REPT(" ",99)),397,99)))," ",""),SUBSTITUTE(SUBSTITUTE(SUBSTITUTE(UPPER(J33)," ",""),"SALES!",""),"CONTACTS!",""))),--ISNUMBER(FIND(SUBSTITUTE(UPPER(TRIM(MID(SUBSTITUTE($H33,",",REPT(" ",99)),397,99)))," ",""),SUBSTITUTE(SUBSTITUTE(SUBSTITUTE(SUBSTITUTE(UPPER(J33),"$","")," ",""),"SALES!",""),"CONTACTS!","")))))+IF(SUBSTITUTE(UPPER(TRIM(MID(SUBSTITUTE($H33,",",REPT(" ",99)),496,99)))," ","")="",0,IF(ISNUMBER(FIND("$",SUBSTITUTE(UPPER(TRIM(MID(SUBSTITUTE($H33,",",REPT(" ",99)),496,99)))," ",""))),--ISNUMBER(FIND(SUBSTITUTE(UPPER(TRIM(MID(SUBSTITUTE($H33,",",REPT(" ",99)),496,99)))," ",""),SUBSTITUTE(SUBSTITUTE(SUBSTITUTE(UPPER(J33)," ",""),"SALES!",""),"CONTACTS!",""))),--ISNUMBER(FIND(SUBSTITUTE(UPPER(TRIM(MID(SUBSTITUTE($H33,",",REPT(" ",99)),496,99)))," ",""),SUBSTITUTE(SUBSTITUTE(SUBSTITUTE(SUBSTITUTE(UPPER(J33),"$","")," ",""),"SALES!",""),"CONTACTS!","")))))) | L33: =IF(SUBSTITUTE(UPPER(TRIM(MID(SUBSTITUTE($H33,",",REPT(" ",99)),1,99)))," ","")="",0,1)+IF(SUBSTITUTE(UPPER(TRIM(MID(SUBSTITUTE($H33,",",REPT(" ",99)),100,99)))," ","")="",0,1)+IF(SUBSTITUTE(UPPER(TRIM(MID(SUBSTITUTE($H33,",",REPT(" ",99)),199,99)))," ","")="",0,1)+IF(SUBSTITUTE(UPPER(TRIM(MID(SUBSTITUTE($H33,",",REPT(" ",99)),298,99)))," ","")="",0,1)+IF(SUBSTITUTE(UPPER(TRIM(MID(SUBSTITUTE($H33,",",REPT(" ",99)),397,99)))," ","")="",0,1)+IF(SUBSTITUTE(UPPER(TRIM(MID(SUBSTITUTE($H33,",",REPT(" ",99)),496,99)))," ","")="",0,1) | M33: =IF(J33="","",IF(AND(I33="formula",LEFT(TRIM(J33),1)<>"="),"FAIL",IF(K33=L33,"PASS","CHECK"))) | N33: MID after a character
A34: F33 | B34: Held-out | C34: Is the email in row 5 a Gmail address? Answer Yes or No. | D34: Messy!A1:F11 | E34: =LOKUP.V($C34, Messy!A1:F11) | F34: =IF(ISNUMBER(SEARCH("gmail",Messy!F5)),"Yes","No") | G34: =IF(ISNUMBER(SEARCH("gmail",Messy!F5)),"Yes","No") | H34: F5,GMAIL | I34: formula | K34: =IF(J34="","",IF(SUBSTITUTE(UPPER(TRIM(MID(SUBSTITUTE($H34,",",REPT(" ",99)),1,99)))," ","")="",0,IF(ISNUMBER(FIND("$",SUBSTITUTE(UPPER(TRIM(MID(SUBSTITUTE($H34,",",REPT(" ",99)),1,99)))," ",""))),--ISNUMBER(FIND(SUBSTITUTE(UPPER(TRIM(MID(SUBSTITUTE($H34,",",REPT(" ",99)),1,99)))," ",""),SUBSTITUTE(SUBSTITUTE(SUBSTITUTE(UPPER(J34)," ",""),"SALES!",""),"CONTACTS!",""))),--ISNUMBER(FIND(SUBSTITUTE(UPPER(TRIM(MID(SUBSTITUTE($H34,",",REPT(" ",99)),1,99)))," ",""),SUBSTITUTE(SUBSTITUTE(SUBSTITUTE(SUBSTITUTE(UPPER(J34),"$","")," ",""),"SALES!",""),"CONTACTS!","")))))+IF(SUBSTITUTE(UPPER(TRIM(MID(SUBSTITUTE($H34,",",REPT(" ",99)),100,99)))," ","")="",0,IF(ISNUMBER(FIND("$",SUBSTITUTE(UPPER(TRIM(MID(SUBSTITUTE($H34,",",REPT(" ",99)),100,99)))," ",""))),--ISNUMBER(FIND(SUBSTITUTE(UPPER(TRIM(MID(SUBSTITUTE($H34,",",REPT(" ",99)),100,99)))," ",""),SUBSTITUTE(SUBSTITUTE(SUBSTITUTE(UPPER(J34)," ",""),"SALES!",""),"CONTACTS!",""))),--ISNUMBER(FIND(SUBSTITUTE(UPPER(TRIM(MID(SUBSTITUTE($H34,",",REPT(" ",99)),100,99)))," ",""),SUBSTITUTE(SUBSTITUTE(SUBSTITUTE(SUBSTITUTE(UPPER(J34),"$","")," ",""),"SALES!",""),"CONTACTS!","")))))+IF(SUBSTITUTE(UPPER(TRIM(MID(SUBSTITUTE($H34,",",REPT(" ",99)),199,99)))," ","")="",0,IF(ISNUMBER(FIND("$",SUBSTITUTE(UPPER(TRIM(MID(SUBSTITUTE($H34,",",REPT(" ",99)),199,99)))," ",""))),--ISNUMBER(FIND(SUBSTITUTE(UPPER(TRIM(MID(SUBSTITUTE($H34,",",REPT(" ",99)),199,99)))," ",""),SUBSTITUTE(SUBSTITUTE(SUBSTITUTE(UPPER(J34)," ",""),"SALES!",""),"CONTACTS!",""))),--ISNUMBER(FIND(SUBSTITUTE(UPPER(TRIM(MID(SUBSTITUTE($H34,",",REPT(" ",99)),199,99)))," ",""),SUBSTITUTE(SUBSTITUTE(SUBSTITUTE(SUBSTITUTE(UPPER(J34),"$","")," ",""),"SALES!",""),"CONTACTS!","")))))+IF(SUBSTITUTE(UPPER(TRIM(MID(SUBSTITUTE($H34,",",REPT(" ",99)),298,99)))," ","")="",0,IF(ISNUMBER(FIND("$",SUBSTITUTE(UPPER(TRIM(MID(SUBSTITUTE($H34,",",REPT(" ",99)),298,99)))," ",""))),--ISNUMBER(FIND(SUBSTITUTE(UPPER(TRIM(MID(SUBSTITUTE($H34,",",REPT(" ",99)),298,99)))," ",""),SUBSTITUTE(SUBSTITUTE(SUBSTITUTE(UPPER(J34)," ",""),"SALES!",""),"CONTACTS!",""))),--ISNUMBER(FIND(SUBSTITUTE(UPPER(TRIM(MID(SUBSTITUTE($H34,",",REPT(" ",99)),298,99)))," ",""),SUBSTITUTE(SUBSTITUTE(SUBSTITUTE(SUBSTITUTE(UPPER(J34),"$","")," ",""),"SALES!",""),"CONTACTS!","")))))+IF(SUBSTITUTE(UPPER(TRIM(MID(SUBSTITUTE($H34,",",REPT(" ",99)),397,99)))," ","")="",0,IF(ISNUMBER(FIND("$",SUBSTITUTE(UPPER(TRIM(MID(SUBSTITUTE($H34,",",REPT(" ",99)),397,99)))," ",""))),--ISNUMBER(FIND(SUBSTITUTE(UPPER(TRIM(MID(SUBSTITUTE($H34,",",REPT(" ",99)),397,99)))," ",""),SUBSTITUTE(SUBSTITUTE(SUBSTITUTE(UPPER(J34)," ",""),"SALES!",""),"CONTACTS!",""))),--ISNUMBER(FIND(SUBSTITUTE(UPPER(TRIM(MID(SUBSTITUTE($H34,",",REPT(" ",99)),397,99)))," ",""),SUBSTITUTE(SUBSTITUTE(SUBSTITUTE(SUBSTITUTE(UPPER(J34),"$","")," ",""),"SALES!",""),"CONTACTS!","")))))+IF(SUBSTITUTE(UPPER(TRIM(MID(SUBSTITUTE($H34,",",REPT(" ",99)),496,99)))," ","")="",0,IF(ISNUMBER(FIND("$",SUBSTITUTE(UPPER(TRIM(MID(SUBSTITUTE($H34,",",REPT(" ",99)),496,99)))," ",""))),--ISNUMBER(FIND(SUBSTITUTE(UPPER(TRIM(MID(SUBSTITUTE($H34,",",REPT(" ",99)),496,99)))," ",""),SUBSTITUTE(SUBSTITUTE(SUBSTITUTE(UPPER(J34)," ",""),"SALES!",""),"CONTACTS!",""))),--ISNUMBER(FIND(SUBSTITUTE(UPPER(TRIM(MID(SUBSTITUTE($H34,",",REPT(" ",99)),496,99)))," ",""),SUBSTITUTE(SUBSTITUTE(SUBSTITUTE(SUBSTITUTE(UPPER(J34),"$","")," ",""),"SALES!",""),"CONTACTS!","")))))) | L34: =IF(SUBSTITUTE(UPPER(TRIM(MID(SUBSTITUTE($H34,",",REPT(" ",99)),1,99)))," ","")="",0,1)+IF(SUBSTITUTE(UPPER(TRIM(MID(SUBSTITUTE($H34,",",REPT(" ",99)),100,99)))," ","")="",0,1)+IF(SUBSTITUTE(UPPER(TRIM(MID(SUBSTITUTE($H34,",",REPT(" ",99)),199,99)))," ","")="",0,1)+IF(SUBSTITUTE(UPPER(TRIM(MID(SUBSTITUTE($H34,",",REPT(" ",99)),298,99)))," ","")="",0,1)+IF(SUBSTITUTE(UPPER(TRIM(MID(SUBSTITUTE($H34,",",REPT(" ",99)),397,99)))," ","")="",0,1)+IF(SUBSTITUTE(UPPER(TRIM(MID(SUBSTITUTE($H34,",",REPT(" ",99)),496,99)))," ","")="",0,1) | M34: =IF(J34="","",IF(AND(I34="formula",LEFT(TRIM(J34),1)<>"="),"FAIL",IF(K34=L34,"PASS","CHECK"))) | N34: case-insensitive contains
A35: F34 | B35: Held-out | C35: Convert the amount in row 9 to a number. | D35: Messy!A1:F11 | E35: =LOKUP.V($C35, Messy!A1:F11) | F35: =VALUE(SUBSTITUTE(SUBSTITUTE(Messy!E9,"Rs.",""),",","")) | G35: =VALUE(SUBSTITUTE(SUBSTITUTE(Messy!E9,"Rs.",""),",","")) | H35: E9 | I35: formula | K35: =IF(J35="","",IF(SUBSTITUTE(UPPER(TRIM(MID(SUBSTITUTE($H35,",",REPT(" ",99)),1,99)))," ","")="",0,IF(ISNUMBER(FIND("$",SUBSTITUTE(UPPER(TRIM(MID(SUBSTITUTE($H35,",",REPT(" ",99)),1,99)))," ",""))),--ISNUMBER(FIND(SUBSTITUTE(UPPER(TRIM(MID(SUBSTITUTE($H35,",",REPT(" ",99)),1,99)))," ",""),SUBSTITUTE(SUBSTITUTE(SUBSTITUTE(UPPER(J35)," ",""),"SALES!",""),"CONTACTS!",""))),--ISNUMBER(FIND(SUBSTITUTE(UPPER(TRIM(MID(SUBSTITUTE($H35,",",REPT(" ",99)),1,99)))," ",""),SUBSTITUTE(SUBSTITUTE(SUBSTITUTE(SUBSTITUTE(UPPER(J35),"$","")," ",""),"SALES!",""),"CONTACTS!","")))))+IF(SUBSTITUTE(UPPER(TRIM(MID(SUBSTITUTE($H35,",",REPT(" ",99)),100,99)))," ","")="",0,IF(ISNUMBER(FIND("$",SUBSTITUTE(UPPER(TRIM(MID(SUBSTITUTE($H35,",",REPT(" ",99)),100,99)))," ",""))),--ISNUMBER(FIND(SUBSTITUTE(UPPER(TRIM(MID(SUBSTITUTE($H35,",",REPT(" ",99)),100,99)))," ",""),SUBSTITUTE(SUBSTITUTE(SUBSTITUTE(UPPER(J35)," ",""),"SALES!",""),"CONTACTS!",""))),--ISNUMBER(FIND(SUBSTITUTE(UPPER(TRIM(MID(SUBSTITUTE($H35,",",REPT(" ",99)),100,99)))," ",""),SUBSTITUTE(SUBSTITUTE(SUBSTITUTE(SUBSTITUTE(UPPER(J35),"$","")," ",""),"SALES!",""),"CONTACTS!","")))))+IF(SUBSTITUTE(UPPER(TRIM(MID(SUBSTITUTE($H35,",",REPT(" ",99)),199,99)))," ","")="",0,IF(ISNUMBER(FIND("$",SUBSTITUTE(UPPER(TRIM(MID(SUBSTITUTE($H35,",",REPT(" ",99)),199,99)))," ",""))),--ISNUMBER(FIND(SUBSTITUTE(UPPER(TRIM(MID(SUBSTITUTE($H35,",",REPT(" ",99)),199,99)))," ",""),SUBSTITUTE(SUBSTITUTE(SUBSTITUTE(UPPER(J35)," ",""),"SALES!",""),"CONTACTS!",""))),--ISNUMBER(FIND(SUBSTITUTE(UPPER(TRIM(MID(SUBSTITUTE($H35,",",REPT(" ",99)),199,99)))," ",""),SUBSTITUTE(SUBSTITUTE(SUBSTITUTE(SUBSTITUTE(UPPER(J35),"$","")," ",""),"SALES!",""),"CONTACTS!","")))))+IF(SUBSTITUTE(UPPER(TRIM(MID(SUBSTITUTE($H35,",",REPT(" ",99)),298,99)))," ","")="",0,IF(ISNUMBER(FIND("$",SUBSTITUTE(UPPER(TRIM(MID(SUBSTITUTE($H35,",",REPT(" ",99)),298,99)))," ",""))),--ISNUMBER(FIND(SUBSTITUTE(UPPER(TRIM(MID(SUBSTITUTE($H35,",",REPT(" ",99)),298,99)))," ",""),SUBSTITUTE(SUBSTITUTE(SUBSTITUTE(UPPER(J35)," ",""),"SALES!",""),"CONTACTS!",""))),--ISNUMBER(FIND(SUBSTITUTE(UPPER(TRIM(MID(SUBSTITUTE($H35,",",REPT(" ",99)),298,99)))," ",""),SUBSTITUTE(SUBSTITUTE(SUBSTITUTE(SUBSTITUTE(UPPER(J35),"$","")," ",""),"SALES!",""),"CONTACTS!","")))))+IF(SUBSTITUTE(UPPER(TRIM(MID(SUBSTITUTE($H35,",",REPT(" ",99)),397,99)))," ","")="",0,IF(ISNUMBER(FIND("$",SUBSTITUTE(UPPER(TRIM(MID(SUBSTITUTE($H35,",",REPT(" ",99)),397,99)))," ",""))),--ISNUMBER(FIND(SUBSTITUTE(UPPER(TRIM(MID(SUBSTITUTE($H35,",",REPT(" ",99)),397,99)))," ",""),SUBSTITUTE(SUBSTITUTE(SUBSTITUTE(UPPER(J35)," ",""),"SALES!",""),"CONTACTS!",""))),--ISNUMBER(FIND(SUBSTITUTE(UPPER(TRIM(MID(SUBSTITUTE($H35,",",REPT(" ",99)),397,99)))," ",""),SUBSTITUTE(SUBSTITUTE(SUBSTITUTE(SUBSTITUTE(UPPER(J35),"$","")," ",""),"SALES!",""),"CONTACTS!","")))))+IF(SUBSTITUTE(UPPER(TRIM(MID(SUBSTITUTE($H35,",",REPT(" ",99)),496,99)))," ","")="",0,IF(ISNUMBER(FIND("$",SUBSTITUTE(UPPER(TRIM(MID(SUBSTITUTE($H35,",",REPT(" ",99)),496,99)))," ",""))),--ISNUMBER(FIND(SUBSTITUTE(UPPER(TRIM(MID(SUBSTITUTE($H35,",",REPT(" ",99)),496,99)))," ",""),SUBSTITUTE(SUBSTITUTE(SUBSTITUTE(UPPER(J35)," ",""),"SALES!",""),"CONTACTS!",""))),--ISNUMBER(FIND(SUBSTITUTE(UPPER(TRIM(MID(SUBSTITUTE($H35,",",REPT(" ",99)),496,99)))," ",""),SUBSTITUTE(SUBSTITUTE(SUBSTITUTE(SUBSTITUTE(UPPER(J35),"$","")," ",""),"SALES!",""),"CONTACTS!","")))))) | L35: =IF(SUBSTITUTE(UPPER(TRIM(MID(SUBSTITUTE($H35,",",REPT(" ",99)),1,99)))," ","")="",0,1)+IF(SUBSTITUTE(UPPER(TRIM(MID(SUBSTITUTE($H35,",",REPT(" ",99)),100,99)))," ","")="",0,1)+IF(SUBSTITUTE(UPPER(TRIM(MID(SUBSTITUTE($H35,",",REPT(" ",99)),199,99)))," ","")="",0,1)+IF(SUBSTITUTE(UPPER(TRIM(MID(SUBSTITUTE($H35,",",REPT(" ",99)),298,99)))," ","")="",0,1)+IF(SUBSTITUTE(UPPER(TRIM(MID(SUBSTITUTE($H35,",",REPT(" ",99)),397,99)))," ","")="",0,1)+IF(SUBSTITUTE(UPPER(TRIM(MID(SUBSTITUTE($H35,",",REPT(" ",99)),496,99)))," ","")="",0,1) | M35: =IF(J35="","",IF(AND(I35="formula",LEFT(TRIM(J35),1)<>"="),"FAIL",IF(K35=L35,"PASS","CHECK"))) | N35: 'Rs.' with a dot
A36: F35 | B36: Held-out | C36: How many of the emails are Gmail addresses? | D36: Messy!A1:F11 | E36: =LOKUP.V($C36, Messy!A1:F11) | F36: =COUNTIF(Messy!F2:F11,"*gmail.com*") | G36: =COUNTIF(Messy!F2:F11,"*gmail.com*") | H36: COUNTIF,F2:F11,GMAIL | I36: formula | K36: =IF(J36="","",IF(SUBSTITUTE(UPPER(TRIM(MID(SUBSTITUTE($H36,",",REPT(" ",99)),1,99)))," ","")="",0,IF(ISNUMBER(FIND("$",SUBSTITUTE(UPPER(TRIM(MID(SUBSTITUTE($H36,",",REPT(" ",99)),1,99)))," ",""))),--ISNUMBER(FIND(SUBSTITUTE(UPPER(TRIM(MID(SUBSTITUTE($H36,",",REPT(" ",99)),1,99)))," ",""),SUBSTITUTE(SUBSTITUTE(SUBSTITUTE(UPPER(J36)," ",""),"SALES!",""),"CONTACTS!",""))),--ISNUMBER(FIND(SUBSTITUTE(UPPER(TRIM(MID(SUBSTITUTE($H36,",",REPT(" ",99)),1,99)))," ",""),SUBSTITUTE(SUBSTITUTE(SUBSTITUTE(SUBSTITUTE(UPPER(J36),"$","")," ",""),"SALES!",""),"CONTACTS!","")))))+IF(SUBSTITUTE(UPPER(TRIM(MID(SUBSTITUTE($H36,",",REPT(" ",99)),100,99)))," ","")="",0,IF(ISNUMBER(FIND("$",SUBSTITUTE(UPPER(TRIM(MID(SUBSTITUTE($H36,",",REPT(" ",99)),100,99)))," ",""))),--ISNUMBER(FIND(SUBSTITUTE(UPPER(TRIM(MID(SUBSTITUTE($H36,",",REPT(" ",99)),100,99)))," ",""),SUBSTITUTE(SUBSTITUTE(SUBSTITUTE(UPPER(J36)," ",""),"SALES!",""),"CONTACTS!",""))),--ISNUMBER(FIND(SUBSTITUTE(UPPER(TRIM(MID(SUBSTITUTE($H36,",",REPT(" ",99)),100,99)))," ",""),SUBSTITUTE(SUBSTITUTE(SUBSTITUTE(SUBSTITUTE(UPPER(J36),"$","")," ",""),"SALES!",""),"CONTACTS!","")))))+IF(SUBSTITUTE(UPPER(TRIM(MID(SUBSTITUTE($H36,",",REPT(" ",99)),199,99)))," ","")="",0,IF(ISNUMBER(FIND("$",SUBSTITUTE(UPPER(TRIM(MID(SUBSTITUTE($H36,",",REPT(" ",99)),199,99)))," ",""))),--ISNUMBER(FIND(SUBSTITUTE(UPPER(TRIM(MID(SUBSTITUTE($H36,",",REPT(" ",99)),199,99)))," ",""),SUBSTITUTE(SUBSTITUTE(SUBSTITUTE(UPPER(J36)," ",""),"SALES!",""),"CONTACTS!",""))),--ISNUMBER(FIND(SUBSTITUTE(UPPER(TRIM(MID(SUBSTITUTE($H36,",",REPT(" ",99)),199,99)))," ",""),SUBSTITUTE(SUBSTITUTE(SUBSTITUTE(SUBSTITUTE(UPPER(J36),"$","")," ",""),"SALES!",""),"CONTACTS!","")))))+IF(SUBSTITUTE(UPPER(TRIM(MID(SUBSTITUTE($H36,",",REPT(" ",99)),298,99)))," ","")="",0,IF(ISNUMBER(FIND("$",SUBSTITUTE(UPPER(TRIM(MID(SUBSTITUTE($H36,",",REPT(" ",99)),298,99)))," ",""))),--ISNUMBER(FIND(SUBSTITUTE(UPPER(TRIM(MID(SUBSTITUTE($H36,",",REPT(" ",99)),298,99)))," ",""),SUBSTITUTE(SUBSTITUTE(SUBSTITUTE(UPPER(J36)," ",""),"SALES!",""),"CONTACTS!",""))),--ISNUMBER(FIND(SUBSTITUTE(UPPER(TRIM(MID(SUBSTITUTE($H36,",",REPT(" ",99)),298,99)))," ",""),SUBSTITUTE(SUBSTITUTE(SUBSTITUTE(SUBSTITUTE(UPPER(J36),"$","")," ",""),"SALES!",""),"CONTACTS!","")))))+IF(SUBSTITUTE(UPPER(TRIM(MID(SUBSTITUTE($H36,",",REPT(" ",99)),397,99)))," ","")="",0,IF(ISNUMBER(FIND("$",SUBSTITUTE(UPPER(TRIM(MID(SUBSTITUTE($H36,",",REPT(" ",99)),397,99)))," ",""))),--ISNUMBER(FIND(SUBSTITUTE(UPPER(TRIM(MID(SUBSTITUTE($H36,",",REPT(" ",99)),397,99)))," ",""),SUBSTITUTE(SUBSTITUTE(SUBSTITUTE(UPPER(J36)," ",""),"SALES!",""),"CONTACTS!",""))),--ISNUMBER(FIND(SUBSTITUTE(UPPER(TRIM(MID(SUBSTITUTE($H36,",",REPT(" ",99)),397,99)))," ",""),SUBSTITUTE(SUBSTITUTE(SUBSTITUTE(SUBSTITUTE(UPPER(J36),"$","")," ",""),"SALES!",""),"CONTACTS!","")))))+IF(SUBSTITUTE(UPPER(TRIM(MID(SUBSTITUTE($H36,",",REPT(" ",99)),496,99)))," ","")="",0,IF(ISNUMBER(FIND("$",SUBSTITUTE(UPPER(TRIM(MID(SUBSTITUTE($H36,",",REPT(" ",99)),496,99)))," ",""))),--ISNUMBER(FIND(SUBSTITUTE(UPPER(TRIM(MID(SUBSTITUTE($H36,",",REPT(" ",99)),496,99)))," ",""),SUBSTITUTE(SUBSTITUTE(SUBSTITUTE(UPPER(J36)," ",""),"SALES!",""),"CONTACTS!",""))),--ISNUMBER(FIND(SUBSTITUTE(UPPER(TRIM(MID(SUBSTITUTE($H36,",",REPT(" ",99)),496,99)))," ",""),SUBSTITUTE(SUBSTITUTE(SUBSTITUTE(SUBSTITUTE(UPPER(J36),"$","")," ",""),"SALES!",""),"CONTACTS!","")))))) | L36: =IF(SUBSTITUTE(UPPER(TRIM(MID(SUBSTITUTE($H36,",",REPT(" ",99)),1,99)))," ","")="",0,1)+IF(SUBSTITUTE(UPPER(TRIM(MID(SUBSTITUTE($H36,",",REPT(" ",99)),100,99)))," ","")="",0,1)+IF(SUBSTITUTE(UPPER(TRIM(MID(SUBSTITUTE($H36,",",REPT(" ",99)),199,99)))," ","")="",0,1)+IF(SUBSTITUTE(UPPER(TRIM(MID(SUBSTITUTE($H36,",",REPT(" ",99)),298,99)))," ","")="",0,1)+IF(SUBSTITUTE(UPPER(TRIM(MID(SUBSTITUTE($H36,",",REPT(" ",99)),397,99)))," ","")="",0,1)+IF(SUBSTITUTE(UPPER(TRIM(MID(SUBSTITUTE($H36,",",REPT(" ",99)),496,99)))," ","")="",0,1) | M36: =IF(J36="","",IF(AND(I36="formula",LEFT(TRIM(J36),1)<>"="),"FAIL",IF(K36=L36,"PASS","CHECK"))) | N36: wildcards; trailing spaces in data
A37: F36 | B37: Held-out | C37: Month name (e.g. January) of the join date in row 3. | D37: Messy!A1:F11 | E37: =LOKUP.V($C37, Messy!A1:F11) | F37: =TEXT(DATEVALUE(Messy!D3),"mmmm") | G37: =TEXT(DATEVALUE(Messy!D3),"mmmm") | H37: TEXT,D3,MMMM | I37: formula | K37: =IF(J37="","",IF(SUBSTITUTE(UPPER(TRIM(MID(SUBSTITUTE($H37,",",REPT(" ",99)),1,99)))," ","")="",0,IF(ISNUMBER(FIND("$",SUBSTITUTE(UPPER(TRIM(MID(SUBSTITUTE($H37,",",REPT(" ",99)),1,99)))," ",""))),--ISNUMBER(FIND(SUBSTITUTE(UPPER(TRIM(MID(SUBSTITUTE($H37,",",REPT(" ",99)),1,99)))," ",""),SUBSTITUTE(SUBSTITUTE(SUBSTITUTE(UPPER(J37)," ",""),"SALES!",""),"CONTACTS!",""))),--ISNUMBER(FIND(SUBSTITUTE(UPPER(TRIM(MID(SUBSTITUTE($H37,",",REPT(" ",99)),1,99)))," ",""),SUBSTITUTE(SUBSTITUTE(SUBSTITUTE(SUBSTITUTE(UPPER(J37),"$","")," ",""),"SALES!",""),"CONTACTS!","")))))+IF(SUBSTITUTE(UPPER(TRIM(MID(SUBSTITUTE($H37,",",REPT(" ",99)),100,99)))," ","")="",0,IF(ISNUMBER(FIND("$",SUBSTITUTE(UPPER(TRIM(MID(SUBSTITUTE($H37,",",REPT(" ",99)),100,99)))," ",""))),--ISNUMBER(FIND(SUBSTITUTE(UPPER(TRIM(MID(SUBSTITUTE($H37,",",REPT(" ",99)),100,99)))," ",""),SUBSTITUTE(SUBSTITUTE(SUBSTITUTE(UPPER(J37)," ",""),"SALES!",""),"CONTACTS!",""))),--ISNUMBER(FIND(SUBSTITUTE(UPPER(TRIM(MID(SUBSTITUTE($H37,",",REPT(" ",99)),100,99)))," ",""),SUBSTITUTE(SUBSTITUTE(SUBSTITUTE(SUBSTITUTE(UPPER(J37),"$","")," ",""),"SALES!",""),"CONTACTS!","")))))+IF(SUBSTITUTE(UPPER(TRIM(MID(SUBSTITUTE($H37,",",REPT(" ",99)),199,99)))," ","")="",0,IF(ISNUMBER(FIND("$",SUBSTITUTE(UPPER(TRIM(MID(SUBSTITUTE($H37,",",REPT(" ",99)),199,99)))," ",""))),--ISNUMBER(FIND(SUBSTITUTE(UPPER(TRIM(MID(SUBSTITUTE($H37,",",REPT(" ",99)),199,99)))," ",""),SUBSTITUTE(SUBSTITUTE(SUBSTITUTE(UPPER(J37)," ",""),"SALES!",""),"CONTACTS!",""))),--ISNUMBER(FIND(SUBSTITUTE(UPPER(TRIM(MID(SUBSTITUTE($H37,",",REPT(" ",99)),199,99)))," ",""),SUBSTITUTE(SUBSTITUTE(SUBSTITUTE(SUBSTITUTE(UPPER(J37),"$","")," ",""),"SALES!",""),"CONTACTS!","")))))+IF(SUBSTITUTE(UPPER(TRIM(MID(SUBSTITUTE($H37,",",REPT(" ",99)),298,99)))," ","")="",0,IF(ISNUMBER(FIND("$",SUBSTITUTE(UPPER(TRIM(MID(SUBSTITUTE($H37,",",REPT(" ",99)),298,99)))," ",""))),--ISNUMBER(FIND(SUBSTITUTE(UPPER(TRIM(MID(SUBSTITUTE($H37,",",REPT(" ",99)),298,99)))," ",""),SUBSTITUTE(SUBSTITUTE(SUBSTITUTE(UPPER(J37)," ",""),"SALES!",""),"CONTACTS!",""))),--ISNUMBER(FIND(SUBSTITUTE(UPPER(TRIM(MID(SUBSTITUTE($H37,",",REPT(" ",99)),298,99)))," ",""),SUBSTITUTE(SUBSTITUTE(SUBSTITUTE(SUBSTITUTE(UPPER(J37),"$","")," ",""),"SALES!",""),"CONTACTS!","")))))+IF(SUBSTITUTE(UPPER(TRIM(MID(SUBSTITUTE($H37,",",REPT(" ",99)),397,99)))," ","")="",0,IF(ISNUMBER(FIND("$",SUBSTITUTE(UPPER(TRIM(MID(SUBSTITUTE($H37,",",REPT(" ",99)),397,99)))," ",""))),--ISNUMBER(FIND(SUBSTITUTE(UPPER(TRIM(MID(SUBSTITUTE($H37,",",REPT(" ",99)),397,99)))," ",""),SUBSTITUTE(SUBSTITUTE(SUBSTITUTE(UPPER(J37)," ",""),"SALES!",""),"CONTACTS!",""))),--ISNUMBER(FIND(SUBSTITUTE(UPPER(TRIM(MID(SUBSTITUTE($H37,",",REPT(" ",99)),397,99)))," ",""),SUBSTITUTE(SUBSTITUTE(SUBSTITUTE(SUBSTITUTE(UPPER(J37),"$","")," ",""),"SALES!",""),"CONTACTS!","")))))+IF(SUBSTITUTE(UPPER(TRIM(MID(SUBSTITUTE($H37,",",REPT(" ",99)),496,99)))," ","")="",0,IF(ISNUMBER(FIND("$",SUBSTITUTE(UPPER(TRIM(MID(SUBSTITUTE($H37,",",REPT(" ",99)),496,99)))," ",""))),--ISNUMBER(FIND(SUBSTITUTE(UPPER(TRIM(MID(SUBSTITUTE($H37,",",REPT(" ",99)),496,99)))," ",""),SUBSTITUTE(SUBSTITUTE(SUBSTITUTE(UPPER(J37)," ",""),"SALES!",""),"CONTACTS!",""))),--ISNUMBER(FIND(SUBSTITUTE(UPPER(TRIM(MID(SUBSTITUTE($H37,",",REPT(" ",99)),496,99)))," ",""),SUBSTITUTE(SUBSTITUTE(SUBSTITUTE(SUBSTITUTE(UPPER(J37),"$","")," ",""),"SALES!",""),"CONTACTS!","")))))) | L37: =IF(SUBSTITUTE(UPPER(TRIM(MID(SUBSTITUTE($H37,",",REPT(" ",99)),1,99)))," ","")="",0,1)+IF(SUBSTITUTE(UPPER(TRIM(MID(SUBSTITUTE($H37,",",REPT(" ",99)),100,99)))," ","")="",0,1)+IF(SUBSTITUTE(UPPER(TRIM(MID(SUBSTITUTE($H37,",",REPT(" ",99)),199,99)))," ","")="",0,1)+IF(SUBSTITUTE(UPPER(TRIM(MID(SUBSTITUTE($H37,",",REPT(" ",99)),298,99)))," ","")="",0,1)+IF(SUBSTITUTE(UPPER(TRIM(MID(SUBSTITUTE($H37,",",REPT(" ",99)),397,99)))," ","")="",0,1)+IF(SUBSTITUTE(UPPER(TRIM(MID(SUBSTITUTE($H37,",",REPT(" ",99)),496,99)))," ","")="",0,1) | M37: =IF(J37="","",IF(AND(I37="formula",LEFT(TRIM(J37),1)<>"="),"FAIL",IF(K37=L37,"PASS","CHECK"))) | N37: text date → date → month
A38: F37 | B38: Held-out | C38: Phone in row 9 with the dashes removed. | D38: Messy!A1:F11 | E38: =LOKUP.V($C38, Messy!A1:F11) | F38: =SUBSTITUTE(Messy!C9,"-","") | G38: =SUBSTITUTE(Messy!C9,"-","") | H38: C9,SUBSTITUTE | I38: formula | K38: =IF(J38="","",IF(SUBSTITUTE(UPPER(TRIM(MID(SUBSTITUTE($H38,",",REPT(" ",99)),1,99)))," ","")="",0,IF(ISNUMBER(FIND("$",SUBSTITUTE(UPPER(TRIM(MID(SUBSTITUTE($H38,",",REPT(" ",99)),1,99)))," ",""))),--ISNUMBER(FIND(SUBSTITUTE(UPPER(TRIM(MID(SUBSTITUTE($H38,",",REPT(" ",99)),1,99)))," ",""),SUBSTITUTE(SUBSTITUTE(SUBSTITUTE(UPPER(J38)," ",""),"SALES!",""),"CONTACTS!",""))),--ISNUMBER(FIND(SUBSTITUTE(UPPER(TRIM(MID(SUBSTITUTE($H38,",",REPT(" ",99)),1,99)))," ",""),SUBSTITUTE(SUBSTITUTE(SUBSTITUTE(SUBSTITUTE(UPPER(J38),"$","")," ",""),"SALES!",""),"CONTACTS!","")))))+IF(SUBSTITUTE(UPPER(TRIM(MID(SUBSTITUTE($H38,",",REPT(" ",99)),100,99)))," ","")="",0,IF(ISNUMBER(FIND("$",SUBSTITUTE(UPPER(TRIM(MID(SUBSTITUTE($H38,",",REPT(" ",99)),100,99)))," ",""))),--ISNUMBER(FIND(SUBSTITUTE(UPPER(TRIM(MID(SUBSTITUTE($H38,",",REPT(" ",99)),100,99)))," ",""),SUBSTITUTE(SUBSTITUTE(SUBSTITUTE(UPPER(J38)," ",""),"SALES!",""),"CONTACTS!",""))),--ISNUMBER(FIND(SUBSTITUTE(UPPER(TRIM(MID(SUBSTITUTE($H38,",",REPT(" ",99)),100,99)))," ",""),SUBSTITUTE(SUBSTITUTE(SUBSTITUTE(SUBSTITUTE(UPPER(J38),"$","")," ",""),"SALES!",""),"CONTACTS!","")))))+IF(SUBSTITUTE(UPPER(TRIM(MID(SUBSTITUTE($H38,",",REPT(" ",99)),199,99)))," ","")="",0,IF(ISNUMBER(FIND("$",SUBSTITUTE(UPPER(TRIM(MID(SUBSTITUTE($H38,",",REPT(" ",99)),199,99)))," ",""))),--ISNUMBER(FIND(SUBSTITUTE(UPPER(TRIM(MID(SUBSTITUTE($H38,",",REPT(" ",99)),199,99)))," ",""),SUBSTITUTE(SUBSTITUTE(SUBSTITUTE(UPPER(J38)," ",""),"SALES!",""),"CONTACTS!",""))),--ISNUMBER(FIND(SUBSTITUTE(UPPER(TRIM(MID(SUBSTITUTE($H38,",",REPT(" ",99)),199,99)))," ",""),SUBSTITUTE(SUBSTITUTE(SUBSTITUTE(SUBSTITUTE(UPPER(J38),"$","")," ",""),"SALES!",""),"CONTACTS!","")))))+IF(SUBSTITUTE(UPPER(TRIM(MID(SUBSTITUTE($H38,",",REPT(" ",99)),298,99)))," ","")="",0,IF(ISNUMBER(FIND("$",SUBSTITUTE(UPPER(TRIM(MID(SUBSTITUTE($H38,",",REPT(" ",99)),298,99)))," ",""))),--ISNUMBER(FIND(SUBSTITUTE(UPPER(TRIM(MID(SUBSTITUTE($H38,",",REPT(" ",99)),298,99)))," ",""),SUBSTITUTE(SUBSTITUTE(SUBSTITUTE(UPPER(J38)," ",""),"SALES!",""),"CONTACTS!",""))),--ISNUMBER(FIND(SUBSTITUTE(UPPER(TRIM(MID(SUBSTITUTE($H38,",",REPT(" ",99)),298,99)))," ",""),SUBSTITUTE(SUBSTITUTE(SUBSTITUTE(SUBSTITUTE(UPPER(J38),"$","")," ",""),"SALES!",""),"CONTACTS!","")))))+IF(SUBSTITUTE(UPPER(TRIM(MID(SUBSTITUTE($H38,",",REPT(" ",99)),397,99)))," ","")="",0,IF(ISNUMBER(FIND("$",SUBSTITUTE(UPPER(TRIM(MID(SUBSTITUTE($H38,",",REPT(" ",99)),397,99)))," ",""))),--ISNUMBER(FIND(SUBSTITUTE(UPPER(TRIM(MID(SUBSTITUTE($H38,",",REPT(" ",99)),397,99)))," ",""),SUBSTITUTE(SUBSTITUTE(SUBSTITUTE(UPPER(J38)," ",""),"SALES!",""),"CONTACTS!",""))),--ISNUMBER(FIND(SUBSTITUTE(UPPER(TRIM(MID(SUBSTITUTE($H38,",",REPT(" ",99)),397,99)))," ",""),SUBSTITUTE(SUBSTITUTE(SUBSTITUTE(SUBSTITUTE(UPPER(J38),"$","")," ",""),"SALES!",""),"CONTACTS!","")))))+IF(SUBSTITUTE(UPPER(TRIM(MID(SUBSTITUTE($H38,",",REPT(" ",99)),496,99)))," ","")="",0,IF(ISNUMBER(FIND("$",SUBSTITUTE(UPPER(TRIM(MID(SUBSTITUTE($H38,",",REPT(" ",99)),496,99)))," ",""))),--ISNUMBER(FIND(SUBSTITUTE(UPPER(TRIM(MID(SUBSTITUTE($H38,",",REPT(" ",99)),496,99)))," ",""),SUBSTITUTE(SUBSTITUTE(SUBSTITUTE(UPPER(J38)," ",""),"SALES!",""),"CONTACTS!",""))),--ISNUMBER(FIND(SUBSTITUTE(UPPER(TRIM(MID(SUBSTITUTE($H38,",",REPT(" ",99)),496,99)))," ",""),SUBSTITUTE(SUBSTITUTE(SUBSTITUTE(SUBSTITUTE(UPPER(J38),"$","")," ",""),"SALES!",""),"CONTACTS!","")))))) | L38: =IF(SUBSTITUTE(UPPER(TRIM(MID(SUBSTITUTE($H38,",",REPT(" ",99)),1,99)))," ","")="",0,1)+IF(SUBSTITUTE(UPPER(TRIM(MID(SUBSTITUTE($H38,",",REPT(" ",99)),100,99)))," ","")="",0,1)+IF(SUBSTITUTE(UPPER(TRIM(MID(SUBSTITUTE($H38,",",REPT(" ",99)),199,99)))," ","")="",0,1)+IF(SUBSTITUTE(UPPER(TRIM(MID(SUBSTITUTE($H38,",",REPT(" ",99)),298,99)))," ","")="",0,1)+IF(SUBSTITUTE(UPPER(TRIM(MID(SUBSTITUTE($H38,",",REPT(" ",99)),397,99)))," ","")="",0,1)+IF(SUBSTITUTE(UPPER(TRIM(MID(SUBSTITUTE($H38,",",REPT(" ",99)),496,99)))," ","")="",0,1) | M38: =IF(J38="","",IF(AND(I38="formula",LEFT(TRIM(J38),1)<>"="),"FAIL",IF(K38=L38,"PASS","CHECK"))) | N38: keep leading zero
A39: F38 | B39: Held-out | C39: Length of the name in row 8 after removing extra spaces. | D39: Messy!A1:F11 | E39: =LOKUP.V($C39, Messy!A1:F11) | F39: =LEN(TRIM(Messy!B8)) | G39: =LEN(TRIM(Messy!B8)) | H39: LEN,TRIM,B8 | I39: formula | K39: =IF(J39="","",IF(SUBSTITUTE(UPPER(TRIM(MID(SUBSTITUTE($H39,",",REPT(" ",99)),1,99)))," ","")="",0,IF(ISNUMBER(FIND("$",SUBSTITUTE(UPPER(TRIM(MID(SUBSTITUTE($H39,",",REPT(" ",99)),1,99)))," ",""))),--ISNUMBER(FIND(SUBSTITUTE(UPPER(TRIM(MID(SUBSTITUTE($H39,",",REPT(" ",99)),1,99)))," ",""),SUBSTITUTE(SUBSTITUTE(SUBSTITUTE(UPPER(J39)," ",""),"SALES!",""),"CONTACTS!",""))),--ISNUMBER(FIND(SUBSTITUTE(UPPER(TRIM(MID(SUBSTITUTE($H39,",",REPT(" ",99)),1,99)))," ",""),SUBSTITUTE(SUBSTITUTE(SUBSTITUTE(SUBSTITUTE(UPPER(J39),"$","")," ",""),"SALES!",""),"CONTACTS!","")))))+IF(SUBSTITUTE(UPPER(TRIM(MID(SUBSTITUTE($H39,",",REPT(" ",99)),100,99)))," ","")="",0,IF(ISNUMBER(FIND("$",SUBSTITUTE(UPPER(TRIM(MID(SUBSTITUTE($H39,",",REPT(" ",99)),100,99)))," ",""))),--ISNUMBER(FIND(SUBSTITUTE(UPPER(TRIM(MID(SUBSTITUTE($H39,",",REPT(" ",99)),100,99)))," ",""),SUBSTITUTE(SUBSTITUTE(SUBSTITUTE(UPPER(J39)," ",""),"SALES!",""),"CONTACTS!",""))),--ISNUMBER(FIND(SUBSTITUTE(UPPER(TRIM(MID(SUBSTITUTE($H39,",",REPT(" ",99)),100,99)))," ",""),SUBSTITUTE(SUBSTITUTE(SUBSTITUTE(SUBSTITUTE(UPPER(J39),"$","")," ",""),"SALES!",""),"CONTACTS!","")))))+IF(SUBSTITUTE(UPPER(TRIM(MID(SUBSTITUTE($H39,",",REPT(" ",99)),199,99)))," ","")="",0,IF(ISNUMBER(FIND("$",SUBSTITUTE(UPPER(TRIM(MID(SUBSTITUTE($H39,",",REPT(" ",99)),199,99)))," ",""))),--ISNUMBER(FIND(SUBSTITUTE(UPPER(TRIM(MID(SUBSTITUTE($H39,",",REPT(" ",99)),199,99)))," ",""),SUBSTITUTE(SUBSTITUTE(SUBSTITUTE(UPPER(J39)," ",""),"SALES!",""),"CONTACTS!",""))),--ISNUMBER(FIND(SUBSTITUTE(UPPER(TRIM(MID(SUBSTITUTE($H39,",",REPT(" ",99)),199,99)))," ",""),SUBSTITUTE(SUBSTITUTE(SUBSTITUTE(SUBSTITUTE(UPPER(J39),"$","")," ",""),"SALES!",""),"CONTACTS!","")))))+IF(SUBSTITUTE(UPPER(TRIM(MID(SUBSTITUTE($H39,",",REPT(" ",99)),298,99)))," ","")="",0,IF(ISNUMBER(FIND("$",SUBSTITUTE(UPPER(TRIM(MID(SUBSTITUTE($H39,",",REPT(" ",99)),298,99)))," ",""))),--ISNUMBER(FIND(SUBSTITUTE(UPPER(TRIM(MID(SUBSTITUTE($H39,",",REPT(" ",99)),298,99)))," ",""),SUBSTITUTE(SUBSTITUTE(SUBSTITUTE(UPPER(J39)," ",""),"SALES!",""),"CONTACTS!",""))),--ISNUMBER(FIND(SUBSTITUTE(UPPER(TRIM(MID(SUBSTITUTE($H39,",",REPT(" ",99)),298,99)))," ",""),SUBSTITUTE(SUBSTITUTE(SUBSTITUTE(SUBSTITUTE(UPPER(J39),"$","")," ",""),"SALES!",""),"CONTACTS!","")))))+IF(SUBSTITUTE(UPPER(TRIM(MID(SUBSTITUTE($H39,",",REPT(" ",99)),397,99)))," ","")="",0,IF(ISNUMBER(FIND("$",SUBSTITUTE(UPPER(TRIM(MID(SUBSTITUTE($H39,",",REPT(" ",99)),397,99)))," ",""))),--ISNUMBER(FIND(SUBSTITUTE(UPPER(TRIM(MID(SUBSTITUTE($H39,",",REPT(" ",99)),397,99)))," ",""),SUBSTITUTE(SUBSTITUTE(SUBSTITUTE(UPPER(J39)," ",""),"SALES!",""),"CONTACTS!",""))),--ISNUMBER(FIND(SUBSTITUTE(UPPER(TRIM(MID(SUBSTITUTE($H39,",",REPT(" ",99)),397,99)))," ",""),SUBSTITUTE(SUBSTITUTE(SUBSTITUTE(SUBSTITUTE(UPPER(J39),"$","")," ",""),"SALES!",""),"CONTACTS!","")))))+IF(SUBSTITUTE(UPPER(TRIM(MID(SUBSTITUTE($H39,",",REPT(" ",99)),496,99)))," ","")="",0,IF(ISNUMBER(FIND("$",SUBSTITUTE(UPPER(TRIM(MID(SUBSTITUTE($H39,",",REPT(" ",99)),496,99)))," ",""))),--ISNUMBER(FIND(SUBSTITUTE(UPPER(TRIM(MID(SUBSTITUTE($H39,",",REPT(" ",99)),496,99)))," ",""),SUBSTITUTE(SUBSTITUTE(SUBSTITUTE(UPPER(J39)," ",""),"SALES!",""),"CONTACTS!",""))),--ISNUMBER(FIND(SUBSTITUTE(UPPER(TRIM(MID(SUBSTITUTE($H39,",",REPT(" ",99)),496,99)))," ",""),SUBSTITUTE(SUBSTITUTE(SUBSTITUTE(SUBSTITUTE(UPPER(J39),"$","")," ",""),"SALES!",""),"CONTACTS!","")))))) | L39: =IF(SUBSTITUTE(UPPER(TRIM(MID(SUBSTITUTE($H39,",",REPT(" ",99)),1,99)))," ","")="",0,1)+IF(SUBSTITUTE(UPPER(TRIM(MID(SUBSTITUTE($H39,",",REPT(" ",99)),100,99)))," ","")="",0,1)+IF(SUBSTITUTE(UPPER(TRIM(MID(SUBSTITUTE($H39,",",REPT(" ",99)),199,99)))," ","")="",0,1)+IF(SUBSTITUTE(UPPER(TRIM(MID(SUBSTITUTE($H39,",",REPT(" ",99)),298,99)))," ","")="",0,1)+IF(SUBSTITUTE(UPPER(TRIM(MID(SUBSTITUTE($H39,",",REPT(" ",99)),397,99)))," ","")="",0,1)+IF(SUBSTITUTE(UPPER(TRIM(MID(SUBSTITUTE($H39,",",REPT(" ",99)),496,99)))," ","")="",0,1) | M39: =IF(J39="","",IF(AND(I39="formula",LEFT(TRIM(J39),1)<>"="),"FAIL",IF(K39=L39,"PASS","CHECK"))) | N39: nested; double space inside
A40: F39 | B40: Held-out v3 | C40: Total revenue for product A in the North region. | D40: Sales!A1:F13 | E40: =LOKUP.V($C40, Sales!A1:F13) | F40: =SUMIFS(Sales!F2:F13,Sales!C2:C13,"A",Sales!A2:A13,"North") | G40: =SUMIFS(Sales!F2:F13,Sales!C2:C13,"A",Sales!A2:A13,"North") | H40: SUMIFS,F2:F13,NORTH | I40: formula | K40: =IF(J40="","",IF(SUBSTITUTE(UPPER(TRIM(MID(SUBSTITUTE($H40,",",REPT(" ",99)),1,99)))," ","")="",0,IF(ISNUMBER(FIND("$",SUBSTITUTE(UPPER(TRIM(MID(SUBSTITUTE($H40,",",REPT(" ",99)),1,99)))," ",""))),--ISNUMBER(FIND(SUBSTITUTE(UPPER(TRIM(MID(SUBSTITUTE($H40,",",REPT(" ",99)),1,99)))," ",""),SUBSTITUTE(SUBSTITUTE(SUBSTITUTE(UPPER(J40)," ",""),"SALES!",""),"CONTACTS!",""))),--ISNUMBER(FIND(SUBSTITUTE(UPPER(TRIM(MID(SUBSTITUTE($H40,",",REPT(" ",99)),1,99)))," ",""),SUBSTITUTE(SUBSTITUTE(SUBSTITUTE(SUBSTITUTE(UPPER(J40),"$","")," ",""),"SALES!",""),"CONTACTS!","")))))+IF(SUBSTITUTE(UPPER(TRIM(MID(SUBSTITUTE($H40,",",REPT(" ",99)),100,99)))," ","")="",0,IF(ISNUMBER(FIND("$",SUBSTITUTE(UPPER(TRIM(MID(SUBSTITUTE($H40,",",REPT(" ",99)),100,99)))," ",""))),--ISNUMBER(FIND(SUBSTITUTE(UPPER(TRIM(MID(SUBSTITUTE($H40,",",REPT(" ",99)),100,99)))," ",""),SUBSTITUTE(SUBSTITUTE(SUBSTITUTE(UPPER(J40)," ",""),"SALES!",""),"CONTACTS!",""))),--ISNUMBER(FIND(SUBSTITUTE(UPPER(TRIM(MID(SUBSTITUTE($H40,",",REPT(" ",99)),100,99)))," ",""),SUBSTITUTE(SUBSTITUTE(SUBSTITUTE(SUBSTITUTE(UPPER(J40),"$","")," ",""),"SALES!",""),"CONTACTS!","")))))+IF(SUBSTITUTE(UPPER(TRIM(MID(SUBSTITUTE($H40,",",REPT(" ",99)),199,99)))," ","")="",0,IF(ISNUMBER(FIND("$",SUBSTITUTE(UPPER(TRIM(MID(SUBSTITUTE($H40,",",REPT(" ",99)),199,99)))," ",""))),--ISNUMBER(FIND(SUBSTITUTE(UPPER(TRIM(MID(SUBSTITUTE($H40,",",REPT(" ",99)),199,99)))," ",""),SUBSTITUTE(SUBSTITUTE(SUBSTITUTE(UPPER(J40)," ",""),"SALES!",""),"CONTACTS!",""))),--ISNUMBER(FIND(SUBSTITUTE(UPPER(TRIM(MID(SUBSTITUTE($H40,",",REPT(" ",99)),199,99)))," ",""),SUBSTITUTE(SUBSTITUTE(SUBSTITUTE(SUBSTITUTE(UPPER(J40),"$","")," ",""),"SALES!",""),"CONTACTS!","")))))+IF(SUBSTITUTE(UPPER(TRIM(MID(SUBSTITUTE($H40,",",REPT(" ",99)),298,99)))," ","")="",0,IF(ISNUMBER(FIND("$",SUBSTITUTE(UPPER(TRIM(MID(SUBSTITUTE($H40,",",REPT(" ",99)),298,99)))," ",""))),--ISNUMBER(FIND(SUBSTITUTE(UPPER(TRIM(MID(SUBSTITUTE($H40,",",REPT(" ",99)),298,99)))," ",""),SUBSTITUTE(SUBSTITUTE(SUBSTITUTE(UPPER(J40)," ",""),"SALES!",""),"CONTACTS!",""))),--ISNUMBER(FIND(SUBSTITUTE(UPPER(TRIM(MID(SUBSTITUTE($H40,",",REPT(" ",99)),298,99)))," ",""),SUBSTITUTE(SUBSTITUTE(SUBSTITUTE(SUBSTITUTE(UPPER(J40),"$","")," ",""),"SALES!",""),"CONTACTS!","")))))+IF(SUBSTITUTE(UPPER(TRIM(MID(SUBSTITUTE($H40,",",REPT(" ",99)),397,99)))," ","")="",0,IF(ISNUMBER(FIND("$",SUBSTITUTE(UPPER(TRIM(MID(SUBSTITUTE($H40,",",REPT(" ",99)),397,99)))," ",""))),--ISNUMBER(FIND(SUBSTITUTE(UPPER(TRIM(MID(SUBSTITUTE($H40,",",REPT(" ",99)),397,99)))," ",""),SUBSTITUTE(SUBSTITUTE(SUBSTITUTE(UPPER(J40)," ",""),"SALES!",""),"CONTACTS!",""))),--ISNUMBER(FIND(SUBSTITUTE(UPPER(TRIM(MID(SUBSTITUTE($H40,",",REPT(" ",99)),397,99)))," ",""),SUBSTITUTE(SUBSTITUTE(SUBSTITUTE(SUBSTITUTE(UPPER(J40),"$","")," ",""),"SALES!",""),"CONTACTS!","")))))+IF(SUBSTITUTE(UPPER(TRIM(MID(SUBSTITUTE($H40,",",REPT(" ",99)),496,99)))," ","")="",0,IF(ISNUMBER(FIND("$",SUBSTITUTE(UPPER(TRIM(MID(SUBSTITUTE($H40,",",REPT(" ",99)),496,99)))," ",""))),--ISNUMBER(FIND(SUBSTITUTE(UPPER(TRIM(MID(SUBSTITUTE($H40,",",REPT(" ",99)),496,99)))," ",""),SUBSTITUTE(SUBSTITUTE(SUBSTITUTE(UPPER(J40)," ",""),"SALES!",""),"CONTACTS!",""))),--ISNUMBER(FIND(SUBSTITUTE(UPPER(TRIM(MID(SUBSTITUTE($H40,",",REPT(" ",99)),496,99)))," ",""),SUBSTITUTE(SUBSTITUTE(SUBSTITUTE(SUBSTITUTE(UPPER(J40),"$","")," ",""),"SALES!",""),"CONTACTS!","")))))) | L40: =IF(SUBSTITUTE(UPPER(TRIM(MID(SUBSTITUTE($H40,",",REPT(" ",99)),1,99)))," ","")="",0,1)+IF(SUBSTITUTE(UPPER(TRIM(MID(SUBSTITUTE($H40,",",REPT(" ",99)),100,99)))," ","")="",0,1)+IF(SUBSTITUTE(UPPER(TRIM(MID(SUBSTITUTE($H40,",",REPT(" ",99)),199,99)))," ","")="",0,1)+IF(SUBSTITUTE(UPPER(TRIM(MID(SUBSTITUTE($H40,",",REPT(" ",99)),298,99)))," ","")="",0,1)+IF(SUBSTITUTE(UPPER(TRIM(MID(SUBSTITUTE($H40,",",REPT(" ",99)),397,99)))," ","")="",0,1)+IF(SUBSTITUTE(UPPER(TRIM(MID(SUBSTITUTE($H40,",",REPT(" ",99)),496,99)))," ","")="",0,1) | M40: =IF(J40="","",IF(AND(I40="formula",LEFT(TRIM(J40),1)<>"="),"FAIL",IF(K40=L40,"PASS","CHECK"))) | N40: two criteria, different combo
A41: F40 | B41: Held-out v3 | C41: Average units per row for the West region. | D41: Sales!A1:F13 | E41: =LOKUP.V($C41, Sales!A1:F13) | F41: =AVERAGEIF(Sales!A2:A13,"West",Sales!D2:D13) | G41: =AVERAGEIF(Sales!A2:A13,"West",Sales!D2:D13) | H41: AVERAGEIF,WEST,D2:D13 | I41: formula | K41: =IF(J41="","",IF(SUBSTITUTE(UPPER(TRIM(MID(SUBSTITUTE($H41,",",REPT(" ",99)),1,99)))," ","")="",0,IF(ISNUMBER(FIND("$",SUBSTITUTE(UPPER(TRIM(MID(SUBSTITUTE($H41,",",REPT(" ",99)),1,99)))," ",""))),--ISNUMBER(FIND(SUBSTITUTE(UPPER(TRIM(MID(SUBSTITUTE($H41,",",REPT(" ",99)),1,99)))," ",""),SUBSTITUTE(SUBSTITUTE(SUBSTITUTE(UPPER(J41)," ",""),"SALES!",""),"CONTACTS!",""))),--ISNUMBER(FIND(SUBSTITUTE(UPPER(TRIM(MID(SUBSTITUTE($H41,",",REPT(" ",99)),1,99)))," ",""),SUBSTITUTE(SUBSTITUTE(SUBSTITUTE(SUBSTITUTE(UPPER(J41),"$","")," ",""),"SALES!",""),"CONTACTS!","")))))+IF(SUBSTITUTE(UPPER(TRIM(MID(SUBSTITUTE($H41,",",REPT(" ",99)),100,99)))," ","")="",0,IF(ISNUMBER(FIND("$",SUBSTITUTE(UPPER(TRIM(MID(SUBSTITUTE($H41,",",REPT(" ",99)),100,99)))," ",""))),--ISNUMBER(FIND(SUBSTITUTE(UPPER(TRIM(MID(SUBSTITUTE($H41,",",REPT(" ",99)),100,99)))," ",""),SUBSTITUTE(SUBSTITUTE(SUBSTITUTE(UPPER(J41)," ",""),"SALES!",""),"CONTACTS!",""))),--ISNUMBER(FIND(SUBSTITUTE(UPPER(TRIM(MID(SUBSTITUTE($H41,",",REPT(" ",99)),100,99)))," ",""),SUBSTITUTE(SUBSTITUTE(SUBSTITUTE(SUBSTITUTE(UPPER(J41),"$","")," ",""),"SALES!",""),"CONTACTS!","")))))+IF(SUBSTITUTE(UPPER(TRIM(MID(SUBSTITUTE($H41,",",REPT(" ",99)),199,99)))," ","")="",0,IF(ISNUMBER(FIND("$",SUBSTITUTE(UPPER(TRIM(MID(SUBSTITUTE($H41,",",REPT(" ",99)),199,99)))," ",""))),--ISNUMBER(FIND(SUBSTITUTE(UPPER(TRIM(MID(SUBSTITUTE($H41,",",REPT(" ",99)),199,99)))," ",""),SUBSTITUTE(SUBSTITUTE(SUBSTITUTE(UPPER(J41)," ",""),"SALES!",""),"CONTACTS!",""))),--ISNUMBER(FIND(SUBSTITUTE(UPPER(TRIM(MID(SUBSTITUTE($H41,",",REPT(" ",99)),199,99)))," ",""),SUBSTITUTE(SUBSTITUTE(SUBSTITUTE(SUBSTITUTE(UPPER(J41),"$","")," ",""),"SALES!",""),"CONTACTS!","")))))+IF(SUBSTITUTE(UPPER(TRIM(MID(SUBSTITUTE($H41,",",REPT(" ",99)),298,99)))," ","")="",0,IF(ISNUMBER(FIND("$",SUBSTITUTE(UPPER(TRIM(MID(SUBSTITUTE($H41,",",REPT(" ",99)),298,99)))," ",""))),--ISNUMBER(FIND(SUBSTITUTE(UPPER(TRIM(MID(SUBSTITUTE($H41,",",REPT(" ",99)),298,99)))," ",""),SUBSTITUTE(SUBSTITUTE(SUBSTITUTE(UPPER(J41)," ",""),"SALES!",""),"CONTACTS!",""))),--ISNUMBER(FIND(SUBSTITUTE(UPPER(TRIM(MID(SUBSTITUTE($H41,",",REPT(" ",99)),298,99)))," ",""),SUBSTITUTE(SUBSTITUTE(SUBSTITUTE(SUBSTITUTE(UPPER(J41),"$","")," ",""),"SALES!",""),"CONTACTS!","")))))+IF(SUBSTITUTE(UPPER(TRIM(MID(SUBSTITUTE($H41,",",REPT(" ",99)),397,99)))," ","")="",0,IF(ISNUMBER(FIND("$",SUBSTITUTE(UPPER(TRIM(MID(SUBSTITUTE($H41,",",REPT(" ",99)),397,99)))," ",""))),--ISNUMBER(FIND(SUBSTITUTE(UPPER(TRIM(MID(SUBSTITUTE($H41,",",REPT(" ",99)),397,99)))," ",""),SUBSTITUTE(SUBSTITUTE(SUBSTITUTE(UPPER(J41)," ",""),"SALES!",""),"CONTACTS!",""))),--ISNUMBER(FIND(SUBSTITUTE(UPPER(TRIM(MID(SUBSTITUTE($H41,",",REPT(" ",99)),397,99)))," ",""),SUBSTITUTE(SUBSTITUTE(SUBSTITUTE(SUBSTITUTE(UPPER(J41),"$","")," ",""),"SALES!",""),"CONTACTS!","")))))+IF(SUBSTITUTE(UPPER(TRIM(MID(SUBSTITUTE($H41,",",REPT(" ",99)),496,99)))," ","")="",0,IF(ISNUMBER(FIND("$",SUBSTITUTE(UPPER(TRIM(MID(SUBSTITUTE($H41,",",REPT(" ",99)),496,99)))," ",""))),--ISNUMBER(FIND(SUBSTITUTE(UPPER(TRIM(MID(SUBSTITUTE($H41,",",REPT(" ",99)),496,99)))," ",""),SUBSTITUTE(SUBSTITUTE(SUBSTITUTE(UPPER(J41)," ",""),"SALES!",""),"CONTACTS!",""))),--ISNUMBER(FIND(SUBSTITUTE(UPPER(TRIM(MID(SUBSTITUTE($H41,",",REPT(" ",99)),496,99)))," ",""),SUBSTITUTE(SUBSTITUTE(SUBSTITUTE(SUBSTITUTE(UPPER(J41),"$","")," ",""),"SALES!",""),"CONTACTS!","")))))) | L41: =IF(SUBSTITUTE(UPPER(TRIM(MID(SUBSTITUTE($H41,",",REPT(" ",99)),1,99)))," ","")="",0,1)+IF(SUBSTITUTE(UPPER(TRIM(MID(SUBSTITUTE($H41,",",REPT(" ",99)),100,99)))," ","")="",0,1)+IF(SUBSTITUTE(UPPER(TRIM(MID(SUBSTITUTE($H41,",",REPT(" ",99)),199,99)))," ","")="",0,1)+IF(SUBSTITUTE(UPPER(TRIM(MID(SUBSTITUTE($H41,",",REPT(" ",99)),298,99)))," ","")="",0,1)+IF(SUBSTITUTE(UPPER(TRIM(MID(SUBSTITUTE($H41,",",REPT(" ",99)),397,99)))," ","")="",0,1)+IF(SUBSTITUTE(UPPER(TRIM(MID(SUBSTITUTE($H41,",",REPT(" ",99)),496,99)))," ","")="",0,1) | M41: =IF(J41="","",IF(AND(I41="formula",LEFT(TRIM(J41),1)<>"="),"FAIL",IF(K41=L41,"PASS","CHECK"))) | N41: average on units, not revenue
A42: F41 | B42: Held-out v3 | C42: Unit price of the row with the most units. | D42: Sales!A1:F13 | E42: =LOKUP.V($C42, Sales!A1:F13) | F42: =INDEX(Sales!E2:E13,MATCH(MAX(Sales!D2:D13),Sales!D2:D13,0)) | G42: =INDEX(Sales!E2:E13,MATCH(MAX(Sales!D2:D13),Sales!D2:D13,0)) | H42: MAX,D2:D13,E2:E13 | I42: formula | K42: =IF(J42="","",IF(SUBSTITUTE(UPPER(TRIM(MID(SUBSTITUTE($H42,",",REPT(" ",99)),1,99)))," ","")="",0,IF(ISNUMBER(FIND("$",SUBSTITUTE(UPPER(TRIM(MID(SUBSTITUTE($H42,",",REPT(" ",99)),1,99)))," ",""))),--ISNUMBER(FIND(SUBSTITUTE(UPPER(TRIM(MID(SUBSTITUTE($H42,",",REPT(" ",99)),1,99)))," ",""),SUBSTITUTE(SUBSTITUTE(SUBSTITUTE(UPPER(J42)," ",""),"SALES!",""),"CONTACTS!",""))),--ISNUMBER(FIND(SUBSTITUTE(UPPER(TRIM(MID(SUBSTITUTE($H42,",",REPT(" ",99)),1,99)))," ",""),SUBSTITUTE(SUBSTITUTE(SUBSTITUTE(SUBSTITUTE(UPPER(J42),"$","")," ",""),"SALES!",""),"CONTACTS!","")))))+IF(SUBSTITUTE(UPPER(TRIM(MID(SUBSTITUTE($H42,",",REPT(" ",99)),100,99)))," ","")="",0,IF(ISNUMBER(FIND("$",SUBSTITUTE(UPPER(TRIM(MID(SUBSTITUTE($H42,",",REPT(" ",99)),100,99)))," ",""))),--ISNUMBER(FIND(SUBSTITUTE(UPPER(TRIM(MID(SUBSTITUTE($H42,",",REPT(" ",99)),100,99)))," ",""),SUBSTITUTE(SUBSTITUTE(SUBSTITUTE(UPPER(J42)," ",""),"SALES!",""),"CONTACTS!",""))),--ISNUMBER(FIND(SUBSTITUTE(UPPER(TRIM(MID(SUBSTITUTE($H42,",",REPT(" ",99)),100,99)))," ",""),SUBSTITUTE(SUBSTITUTE(SUBSTITUTE(SUBSTITUTE(UPPER(J42),"$","")," ",""),"SALES!",""),"CONTACTS!","")))))+IF(SUBSTITUTE(UPPER(TRIM(MID(SUBSTITUTE($H42,",",REPT(" ",99)),199,99)))," ","")="",0,IF(ISNUMBER(FIND("$",SUBSTITUTE(UPPER(TRIM(MID(SUBSTITUTE($H42,",",REPT(" ",99)),199,99)))," ",""))),--ISNUMBER(FIND(SUBSTITUTE(UPPER(TRIM(MID(SUBSTITUTE($H42,",",REPT(" ",99)),199,99)))," ",""),SUBSTITUTE(SUBSTITUTE(SUBSTITUTE(UPPER(J42)," ",""),"SALES!",""),"CONTACTS!",""))),--ISNUMBER(FIND(SUBSTITUTE(UPPER(TRIM(MID(SUBSTITUTE($H42,",",REPT(" ",99)),199,99)))," ",""),SUBSTITUTE(SUBSTITUTE(SUBSTITUTE(SUBSTITUTE(UPPER(J42),"$","")," ",""),"SALES!",""),"CONTACTS!","")))))+IF(SUBSTITUTE(UPPER(TRIM(MID(SUBSTITUTE($H42,",",REPT(" ",99)),298,99)))," ","")="",0,IF(ISNUMBER(FIND("$",SUBSTITUTE(UPPER(TRIM(MID(SUBSTITUTE($H42,",",REPT(" ",99)),298,99)))," ",""))),--ISNUMBER(FIND(SUBSTITUTE(UPPER(TRIM(MID(SUBSTITUTE($H42,",",REPT(" ",99)),298,99)))," ",""),SUBSTITUTE(SUBSTITUTE(SUBSTITUTE(UPPER(J42)," ",""),"SALES!",""),"CONTACTS!",""))),--ISNUMBER(FIND(SUBSTITUTE(UPPER(TRIM(MID(SUBSTITUTE($H42,",",REPT(" ",99)),298,99)))," ",""),SUBSTITUTE(SUBSTITUTE(SUBSTITUTE(SUBSTITUTE(UPPER(J42),"$","")," ",""),"SALES!",""),"CONTACTS!","")))))+IF(SUBSTITUTE(UPPER(TRIM(MID(SUBSTITUTE($H42,",",REPT(" ",99)),397,99)))," ","")="",0,IF(ISNUMBER(FIND("$",SUBSTITUTE(UPPER(TRIM(MID(SUBSTITUTE($H42,",",REPT(" ",99)),397,99)))," ",""))),--ISNUMBER(FIND(SUBSTITUTE(UPPER(TRIM(MID(SUBSTITUTE($H42,",",REPT(" ",99)),397,99)))," ",""),SUBSTITUTE(SUBSTITUTE(SUBSTITUTE(UPPER(J42)," ",""),"SALES!",""),"CONTACTS!",""))),--ISNUMBER(FIND(SUBSTITUTE(UPPER(TRIM(MID(SUBSTITUTE($H42,",",REPT(" ",99)),397,99)))," ",""),SUBSTITUTE(SUBSTITUTE(SUBSTITUTE(SUBSTITUTE(UPPER(J42),"$","")," ",""),"SALES!",""),"CONTACTS!","")))))+IF(SUBSTITUTE(UPPER(TRIM(MID(SUBSTITUTE($H42,",",REPT(" ",99)),496,99)))," ","")="",0,IF(ISNUMBER(FIND("$",SUBSTITUTE(UPPER(TRIM(MID(SUBSTITUTE($H42,",",REPT(" ",99)),496,99)))," ",""))),--ISNUMBER(FIND(SUBSTITUTE(UPPER(TRIM(MID(SUBSTITUTE($H42,",",REPT(" ",99)),496,99)))," ",""),SUBSTITUTE(SUBSTITUTE(SUBSTITUTE(UPPER(J42)," ",""),"SALES!",""),"CONTACTS!",""))),--ISNUMBER(FIND(SUBSTITUTE(UPPER(TRIM(MID(SUBSTITUTE($H42,",",REPT(" ",99)),496,99)))," ",""),SUBSTITUTE(SUBSTITUTE(SUBSTITUTE(SUBSTITUTE(UPPER(J42),"$","")," ",""),"SALES!",""),"CONTACTS!","")))))) | L42: =IF(SUBSTITUTE(UPPER(TRIM(MID(SUBSTITUTE($H42,",",REPT(" ",99)),1,99)))," ","")="",0,1)+IF(SUBSTITUTE(UPPER(TRIM(MID(SUBSTITUTE($H42,",",REPT(" ",99)),100,99)))," ","")="",0,1)+IF(SUBSTITUTE(UPPER(TRIM(MID(SUBSTITUTE($H42,",",REPT(" ",99)),199,99)))," ","")="",0,1)+IF(SUBSTITUTE(UPPER(TRIM(MID(SUBSTITUTE($H42,",",REPT(" ",99)),298,99)))," ","")="",0,1)+IF(SUBSTITUTE(UPPER(TRIM(MID(SUBSTITUTE($H42,",",REPT(" ",99)),397,99)))," ","")="",0,1)+IF(SUBSTITUTE(UPPER(TRIM(MID(SUBSTITUTE($H42,",",REPT(" ",99)),496,99)))," ","")="",0,1) | M42: =IF(J42="","",IF(AND(I42="formula",LEFT(TRIM(J42),1)<>"="),"FAIL",IF(K42=L42,"PASS","CHECK"))) | N42: lookup by max of another column
A43: F42 | B43: Held-out v3 | C43: Number of rows for product B with revenue over 30,000. | D43: Sales!A1:F13 | E43: =LOKUP.V($C43, Sales!A1:F13) | F43: =COUNTIFS(Sales!C2:C13,"B",Sales!F2:F13,">30000") | G43: =COUNTIFS(Sales!C2:C13,"B",Sales!F2:F13,">30000") | H43: COUNTIFS,>30000 | I43: formula | K43: =IF(J43="","",IF(SUBSTITUTE(UPPER(TRIM(MID(SUBSTITUTE($H43,",",REPT(" ",99)),1,99)))," ","")="",0,IF(ISNUMBER(FIND("$",SUBSTITUTE(UPPER(TRIM(MID(SUBSTITUTE($H43,",",REPT(" ",99)),1,99)))," ",""))),--ISNUMBER(FIND(SUBSTITUTE(UPPER(TRIM(MID(SUBSTITUTE($H43,",",REPT(" ",99)),1,99)))," ",""),SUBSTITUTE(SUBSTITUTE(SUBSTITUTE(UPPER(J43)," ",""),"SALES!",""),"CONTACTS!",""))),--ISNUMBER(FIND(SUBSTITUTE(UPPER(TRIM(MID(SUBSTITUTE($H43,",",REPT(" ",99)),1,99)))," ",""),SUBSTITUTE(SUBSTITUTE(SUBSTITUTE(SUBSTITUTE(UPPER(J43),"$","")," ",""),"SALES!",""),"CONTACTS!","")))))+IF(SUBSTITUTE(UPPER(TRIM(MID(SUBSTITUTE($H43,",",REPT(" ",99)),100,99)))," ","")="",0,IF(ISNUMBER(FIND("$",SUBSTITUTE(UPPER(TRIM(MID(SUBSTITUTE($H43,",",REPT(" ",99)),100,99)))," ",""))),--ISNUMBER(FIND(SUBSTITUTE(UPPER(TRIM(MID(SUBSTITUTE($H43,",",REPT(" ",99)),100,99)))," ",""),SUBSTITUTE(SUBSTITUTE(SUBSTITUTE(UPPER(J43)," ",""),"SALES!",""),"CONTACTS!",""))),--ISNUMBER(FIND(SUBSTITUTE(UPPER(TRIM(MID(SUBSTITUTE($H43,",",REPT(" ",99)),100,99)))," ",""),SUBSTITUTE(SUBSTITUTE(SUBSTITUTE(SUBSTITUTE(UPPER(J43),"$","")," ",""),"SALES!",""),"CONTACTS!","")))))+IF(SUBSTITUTE(UPPER(TRIM(MID(SUBSTITUTE($H43,",",REPT(" ",99)),199,99)))," ","")="",0,IF(ISNUMBER(FIND("$",SUBSTITUTE(UPPER(TRIM(MID(SUBSTITUTE($H43,",",REPT(" ",99)),199,99)))," ",""))),--ISNUMBER(FIND(SUBSTITUTE(UPPER(TRIM(MID(SUBSTITUTE($H43,",",REPT(" ",99)),199,99)))," ",""),SUBSTITUTE(SUBSTITUTE(SUBSTITUTE(UPPER(J43)," ",""),"SALES!",""),"CONTACTS!",""))),--ISNUMBER(FIND(SUBSTITUTE(UPPER(TRIM(MID(SUBSTITUTE($H43,",",REPT(" ",99)),199,99)))," ",""),SUBSTITUTE(SUBSTITUTE(SUBSTITUTE(SUBSTITUTE(UPPER(J43),"$","")," ",""),"SALES!",""),"CONTACTS!","")))))+IF(SUBSTITUTE(UPPER(TRIM(MID(SUBSTITUTE($H43,",",REPT(" ",99)),298,99)))," ","")="",0,IF(ISNUMBER(FIND("$",SUBSTITUTE(UPPER(TRIM(MID(SUBSTITUTE($H43,",",REPT(" ",99)),298,99)))," ",""))),--ISNUMBER(FIND(SUBSTITUTE(UPPER(TRIM(MID(SUBSTITUTE($H43,",",REPT(" ",99)),298,99)))," ",""),SUBSTITUTE(SUBSTITUTE(SUBSTITUTE(UPPER(J43)," ",""),"SALES!",""),"CONTACTS!",""))),--ISNUMBER(FIND(SUBSTITUTE(UPPER(TRIM(MID(SUBSTITUTE($H43,",",REPT(" ",99)),298,99)))," ",""),SUBSTITUTE(SUBSTITUTE(SUBSTITUTE(SUBSTITUTE(UPPER(J43),"$","")," ",""),"SALES!",""),"CONTACTS!","")))))+IF(SUBSTITUTE(UPPER(TRIM(MID(SUBSTITUTE($H43,",",REPT(" ",99)),397,99)))," ","")="",0,IF(ISNUMBER(FIND("$",SUBSTITUTE(UPPER(TRIM(MID(SUBSTITUTE($H43,",",REPT(" ",99)),397,99)))," ",""))),--ISNUMBER(FIND(SUBSTITUTE(UPPER(TRIM(MID(SUBSTITUTE($H43,",",REPT(" ",99)),397,99)))," ",""),SUBSTITUTE(SUBSTITUTE(SUBSTITUTE(UPPER(J43)," ",""),"SALES!",""),"CONTACTS!",""))),--ISNUMBER(FIND(SUBSTITUTE(UPPER(TRIM(MID(SUBSTITUTE($H43,",",REPT(" ",99)),397,99)))," ",""),SUBSTITUTE(SUBSTITUTE(SUBSTITUTE(SUBSTITUTE(UPPER(J43),"$","")," ",""),"SALES!",""),"CONTACTS!","")))))+IF(SUBSTITUTE(UPPER(TRIM(MID(SUBSTITUTE($H43,",",REPT(" ",99)),496,99)))," ","")="",0,IF(ISNUMBER(FIND("$",SUBSTITUTE(UPPER(TRIM(MID(SUBSTITUTE($H43,",",REPT(" ",99)),496,99)))," ",""))),--ISNUMBER(FIND(SUBSTITUTE(UPPER(TRIM(MID(SUBSTITUTE($H43,",",REPT(" ",99)),496,99)))," ",""),SUBSTITUTE(SUBSTITUTE(SUBSTITUTE(UPPER(J43)," ",""),"SALES!",""),"CONTACTS!",""))),--ISNUMBER(FIND(SUBSTITUTE(UPPER(TRIM(MID(SUBSTITUTE($H43,",",REPT(" ",99)),496,99)))," ",""),SUBSTITUTE(SUBSTITUTE(SUBSTITUTE(SUBSTITUTE(UPPER(J43),"$","")," ",""),"SALES!",""),"CONTACTS!","")))))) | L43: =IF(SUBSTITUTE(UPPER(TRIM(MID(SUBSTITUTE($H43,",",REPT(" ",99)),1,99)))," ","")="",0,1)+IF(SUBSTITUTE(UPPER(TRIM(MID(SUBSTITUTE($H43,",",REPT(" ",99)),100,99)))," ","")="",0,1)+IF(SUBSTITUTE(UPPER(TRIM(MID(SUBSTITUTE($H43,",",REPT(" ",99)),199,99)))," ","")="",0,1)+IF(SUBSTITUTE(UPPER(TRIM(MID(SUBSTITUTE($H43,",",REPT(" ",99)),298,99)))," ","")="",0,1)+IF(SUBSTITUTE(UPPER(TRIM(MID(SUBSTITUTE($H43,",",REPT(" ",99)),397,99)))," ","")="",0,1)+IF(SUBSTITUTE(UPPER(TRIM(MID(SUBSTITUTE($H43,",",REPT(" ",99)),496,99)))," ","")="",0,1) | M43: =IF(J43="","",IF(AND(I43="formula",LEFT(TRIM(J43),1)<>"="),"FAIL",IF(K43=L43,"PASS","CHECK"))) | N43: count with two criteria
A44: F43 | B44: Held-out v3 | C44: Day of the week (e.g. Monday) of the date in row 4. | D44: Sales!A1:F13 | E44: =LOKUP.V($C44, Sales!A1:F13) | F44: =TEXT(Sales!B4,"dddd") | G44: =TEXT(Sales!B4,"dddd") | H44: TEXT,B4,DDDD | I44: formula | K44: =IF(J44="","",IF(SUBSTITUTE(UPPER(TRIM(MID(SUBSTITUTE($H44,",",REPT(" ",99)),1,99)))," ","")="",0,IF(ISNUMBER(FIND("$",SUBSTITUTE(UPPER(TRIM(MID(SUBSTITUTE($H44,",",REPT(" ",99)),1,99)))," ",""))),--ISNUMBER(FIND(SUBSTITUTE(UPPER(TRIM(MID(SUBSTITUTE($H44,",",REPT(" ",99)),1,99)))," ",""),SUBSTITUTE(SUBSTITUTE(SUBSTITUTE(UPPER(J44)," ",""),"SALES!",""),"CONTACTS!",""))),--ISNUMBER(FIND(SUBSTITUTE(UPPER(TRIM(MID(SUBSTITUTE($H44,",",REPT(" ",99)),1,99)))," ",""),SUBSTITUTE(SUBSTITUTE(SUBSTITUTE(SUBSTITUTE(UPPER(J44),"$","")," ",""),"SALES!",""),"CONTACTS!","")))))+IF(SUBSTITUTE(UPPER(TRIM(MID(SUBSTITUTE($H44,",",REPT(" ",99)),100,99)))," ","")="",0,IF(ISNUMBER(FIND("$",SUBSTITUTE(UPPER(TRIM(MID(SUBSTITUTE($H44,",",REPT(" ",99)),100,99)))," ",""))),--ISNUMBER(FIND(SUBSTITUTE(UPPER(TRIM(MID(SUBSTITUTE($H44,",",REPT(" ",99)),100,99)))," ",""),SUBSTITUTE(SUBSTITUTE(SUBSTITUTE(UPPER(J44)," ",""),"SALES!",""),"CONTACTS!",""))),--ISNUMBER(FIND(SUBSTITUTE(UPPER(TRIM(MID(SUBSTITUTE($H44,",",REPT(" ",99)),100,99)))," ",""),SUBSTITUTE(SUBSTITUTE(SUBSTITUTE(SUBSTITUTE(UPPER(J44),"$","")," ",""),"SALES!",""),"CONTACTS!","")))))+IF(SUBSTITUTE(UPPER(TRIM(MID(SUBSTITUTE($H44,",",REPT(" ",99)),199,99)))," ","")="",0,IF(ISNUMBER(FIND("$",SUBSTITUTE(UPPER(TRIM(MID(SUBSTITUTE($H44,",",REPT(" ",99)),199,99)))," ",""))),--ISNUMBER(FIND(SUBSTITUTE(UPPER(TRIM(MID(SUBSTITUTE($H44,",",REPT(" ",99)),199,99)))," ",""),SUBSTITUTE(SUBSTITUTE(SUBSTITUTE(UPPER(J44)," ",""),"SALES!",""),"CONTACTS!",""))),--ISNUMBER(FIND(SUBSTITUTE(UPPER(TRIM(MID(SUBSTITUTE($H44,",",REPT(" ",99)),199,99)))," ",""),SUBSTITUTE(SUBSTITUTE(SUBSTITUTE(SUBSTITUTE(UPPER(J44),"$","")," ",""),"SALES!",""),"CONTACTS!","")))))+IF(SUBSTITUTE(UPPER(TRIM(MID(SUBSTITUTE($H44,",",REPT(" ",99)),298,99)))," ","")="",0,IF(ISNUMBER(FIND("$",SUBSTITUTE(UPPER(TRIM(MID(SUBSTITUTE($H44,",",REPT(" ",99)),298,99)))," ",""))),--ISNUMBER(FIND(SUBSTITUTE(UPPER(TRIM(MID(SUBSTITUTE($H44,",",REPT(" ",99)),298,99)))," ",""),SUBSTITUTE(SUBSTITUTE(SUBSTITUTE(UPPER(J44)," ",""),"SALES!",""),"CONTACTS!",""))),--ISNUMBER(FIND(SUBSTITUTE(UPPER(TRIM(MID(SUBSTITUTE($H44,",",REPT(" ",99)),298,99)))," ",""),SUBSTITUTE(SUBSTITUTE(SUBSTITUTE(SUBSTITUTE(UPPER(J44),"$","")," ",""),"SALES!",""),"CONTACTS!","")))))+IF(SUBSTITUTE(UPPER(TRIM(MID(SUBSTITUTE($H44,",",REPT(" ",99)),397,99)))," ","")="",0,IF(ISNUMBER(FIND("$",SUBSTITUTE(UPPER(TRIM(MID(SUBSTITUTE($H44,",",REPT(" ",99)),397,99)))," ",""))),--ISNUMBER(FIND(SUBSTITUTE(UPPER(TRIM(MID(SUBSTITUTE($H44,",",REPT(" ",99)),397,99)))," ",""),SUBSTITUTE(SUBSTITUTE(SUBSTITUTE(UPPER(J44)," ",""),"SALES!",""),"CONTACTS!",""))),--ISNUMBER(FIND(SUBSTITUTE(UPPER(TRIM(MID(SUBSTITUTE($H44,",",REPT(" ",99)),397,99)))," ",""),SUBSTITUTE(SUBSTITUTE(SUBSTITUTE(SUBSTITUTE(UPPER(J44),"$","")," ",""),"SALES!",""),"CONTACTS!","")))))+IF(SUBSTITUTE(UPPER(TRIM(MID(SUBSTITUTE($H44,",",REPT(" ",99)),496,99)))," ","")="",0,IF(ISNUMBER(FIND("$",SUBSTITUTE(UPPER(TRIM(MID(SUBSTITUTE($H44,",",REPT(" ",99)),496,99)))," ",""))),--ISNUMBER(FIND(SUBSTITUTE(UPPER(TRIM(MID(SUBSTITUTE($H44,",",REPT(" ",99)),496,99)))," ",""),SUBSTITUTE(SUBSTITUTE(SUBSTITUTE(UPPER(J44)," ",""),"SALES!",""),"CONTACTS!",""))),--ISNUMBER(FIND(SUBSTITUTE(UPPER(TRIM(MID(SUBSTITUTE($H44,",",REPT(" ",99)),496,99)))," ",""),SUBSTITUTE(SUBSTITUTE(SUBSTITUTE(SUBSTITUTE(UPPER(J44),"$","")," ",""),"SALES!",""),"CONTACTS!","")))))) | L44: =IF(SUBSTITUTE(UPPER(TRIM(MID(SUBSTITUTE($H44,",",REPT(" ",99)),1,99)))," ","")="",0,1)+IF(SUBSTITUTE(UPPER(TRIM(MID(SUBSTITUTE($H44,",",REPT(" ",99)),100,99)))," ","")="",0,1)+IF(SUBSTITUTE(UPPER(TRIM(MID(SUBSTITUTE($H44,",",REPT(" ",99)),199,99)))," ","")="",0,1)+IF(SUBSTITUTE(UPPER(TRIM(MID(SUBSTITUTE($H44,",",REPT(" ",99)),298,99)))," ","")="",0,1)+IF(SUBSTITUTE(UPPER(TRIM(MID(SUBSTITUTE($H44,",",REPT(" ",99)),397,99)))," ","")="",0,1)+IF(SUBSTITUTE(UPPER(TRIM(MID(SUBSTITUTE($H44,",",REPT(" ",99)),496,99)))," ","")="",0,1) | M44: =IF(J44="","",IF(AND(I44="formula",LEFT(TRIM(J44),1)<>"="),"FAIL",IF(K44=L44,"PASS","CHECK"))) | N44: TEXT day code
