Workbook

Sheet Read Me
A1: DATA ANALYTICS | EXCEL ASSESSMENT
A2: Mock analyst recruitment exercise • E-commerce performance & data quality • 60 minutes
A4: Candidate brief
A5: Scenario | B5: You are a Data Analyst supporting an e-commerce business. The manager wants a reliable performance snapshot for July–September 2026 and a short list of actionable insights.
A6: Time limit | B6: 60 minutes. Work in Excel only. Do not use external sources. Use formulas, PivotTables, filters or other standard Excel features where appropriate.
A7: Data notes | B7: The 'Raw Data' tab contains synthetic order-level records. Some records include missing fields, a duplicate order ID, and orders with different statuses. Do not silently delete data without explaining your treatment.
A8: Task 1 — Data quality (10 min) | B8: On 'Analysis', identify duplicate Order IDs, missing Customer ID / Region / Discount values, and create a clean status or data-quality flag. State how you would treat each issue.
A9: Task 2 — Create metrics (15 min) | B9: Add formulas on 'Raw Data' for Gross Sales (Unit Price × Quantity), Net Sales after discount, Gross Profit (Net Sales − Cost), and a Delivered flag. Handle missing discount values sensibly and document your assumption.
A10: Task 3 — Business analysis (20 min) | B10: On 'Analysis', calculate total orders, delivered orders, cancellation rate, return rate, net sales, gross profit, gross margin, average order value (AOV), and net sales by region, channel and category. Define denominators clearly; avoid treating cancelled/returned orders as delivered sales.
A11: Task 4 — Insights (10 min) | B11: Identify the best-performing region, channel and category using a clearly stated metric. Provide two actionable insights and one caveat about data quality or interpretation.
A12: Task 5 — Presentation (5 min) | B12: Create a compact summary table and at least one chart or PivotTable. Keep formulas readable, apply appropriate number formats and make your assumptions explicit.
A13: Formatting | B13: Blue font for raw inputs, black font for formulas, currency in INR, percentages as 0.0%, counts as whole numbers. Avoid hardcoding derived metrics.
A14: Important | B14: This is a realistic practice simulation, not a claim that every employer uses this exact test. Data analytics Excel rounds may focus on cleaning, lookups, PivotTables, formulas, dashboards, or business interpretation.

Sheet Raw Data
A1: RAW ORDER DATA
A2: Synthetic e-commerce transactions. Derived columns at right are intentionally blank for the candidate to calculate.
A4: Order ID | B4: Order Date | C4: Customer ID | D4: Region | E4: Channel | F4: Category | G4: Product | H4: Quantity | I4: Unit Price (INR) | J4: Discount % | K4: Cost (INR) | L4: Reported Revenue (INR) | M4: Status | N4: Rating | O4: Gross Sales (INR) | P4: Net Sales (INR) | Q4: Gross Profit (INR) | R4: Delivered Flag
A5: ORD5001 | B5: 46204 | C5: C1026 | D5: East | E5: Website | F5: Home & Kitchen | G5: Bedsheet Set | H5: 1 | I5: 1528.98 | J5: 0.2 | K5: 743.71 | L5: 1223.18 | M5: Delivered | N5: 2 | O5: =I5*H5 | P5: =O5*(1-IF(J5="",0,J5)) | Q5: =P5-K5 | R5: =IF(M5="Delivered",1,0)
A6: ORD5002 | B6: 46205 | C6: C1030 | D6: East | E6: Website | F6: Sports | G6: Dumbbell Set | H6: 2 | I6: 2424.03 | J6: 0.1 | K6: 3097.17 | L6: 4363.25 | M6: Delivered | N6: 5 | O6: =I6*H6 | P6: =O6*(1-IF(J6="",0,J6)) | Q6: =P6-K6 | R6: =IF(M6="Delivered",1,0)
A7: ORD5003 | B7: 46206 | C7: C1022 | D7: West | E7: Website | F7: Electronics | G7: Smart Watch | H7: 1 | I7: 4078.98 | J7: 0.15 | K7: 2919.7 | L7: 3467.13 | M7: Delivered | N7: 1 | O7: =I7*H7 | P7: =O7*(1-IF(J7="",0,J7)) | Q7: =P7-K7 | R7: =IF(M7="Delivered",1,0)
A8: ORD5004 | B8: 46207 | C8: C1020 | D8: Central | E8: Website | F8: Fashion | G8: Backpack | H8: 3 | I8: 1899 | J8: 0.05 | K8: 3247.61 | L8: 5412.15 | M8: Delivered | N8: 3 | O8: =I8*H8 | P8: =O8*(1-IF(J8="",0,J8)) | Q8: =P8-K8 | R8: =IF(M8="Delivered",1,0)
A9: ORD5005 | B9: 46208 | C9: C1059 | D9: North | E9: Website | F9: Home & Kitchen | G9: Mixer Grinder | H9: 3 | I9: 3299 | J9: 0.05 | K9: 5018.03 | L9: 9402.15 | M9: Delivered | N9: 3 | O9: =I9*H9 | P9: =O9*(1-IF(J9="",0,J9)) | Q9: =P9-K9 | R9: =IF(M9="Delivered",1,0)
A10: ORD5006 | B10: 46209 | C10: C1044 | D10: Central | E10: Mobile App | F10: Home & Kitchen | G10: Bedsheet Set | H10: 3 | I10: 1499 | J10: 0 | K10: 2170.28 | L10: 4497 | M10: Delivered | N10: 1 | O10: =I10*H10 | P10: =O10*(1-IF(J10="",0,J10)) | Q10: =P10-K10 | R10: =IF(M10="Delivered",1,0)
A11: ORD5007 | B11: 46210 | C11: C1055 | D11: South | E11: Website | F11: Fashion | G11: Running Shoes | H11: 1 | I11: 2938.95 | J11: 0.15 | K11: 1831.63 | L11: 2498.11 | M11: Delivered | N11: 2 | O11: =I11*H11 | P11: =O11*(1-IF(J11="",0,J11)) | Q11: =P11-K11 | R11: =IF(M11="Delivered",1,0)
A12: ORD5008 | B12: 46211 | C12: C1008 | D12: East | E12: Website | F12: Beauty | G12: Hair Dryer | H12: 1 | I12: 2308.95 | J12: 0.2 | K12: 1121.78 | L12: 1847.16 | M12: Delivered | N12: 5 | O12: =I12*H12 | P12: =O12*(1-IF(J12="",0,J12)) | Q12: =P12-K12 | R12: =IF(M12="Delivered",1,0)
A13: ORD5009 | B13: 46212 | C13: C1060 | D13: West | E13: Mobile App | F13: Home & Kitchen | G13: Mixer Grinder | H13: 1 | I13: 3299 | J13: 0.2 | K13: 2181.8 | L13: 2639.2 | M13: Delivered | N13: 2 | O13: =I13*H13 | P13: =O13*(1-IF(J13="",0,J13)) | Q13: =P13-K13 | R13: =IF(M13="Delivered",1,0)
A14: ORD5010 | B14: 46213 | C14: C1051 | D14: East | E14: Mobile App | F14: Sports | G14: Cricket Kit | H14: 1 | I14: 3568.98 | J14: 0.05 | K14: 2161.02 | L14: 3390.53 | M14: Delivered | N14: 5 | O14: =I14*H14 | P14: =O14*(1-IF(J14="",0,J14)) | Q14: =P14-K14 | R14: =IF(M14="Delivered",1,0)
A15: ORD5011 | B15: 46214 | C15: C1050 | D15: North | E15: Website | F15: Electronics | G15: Wireless Earbuds | H15: 2 | I15: 2548.98 | J15: 0 | K15: 3719.79 | L15: 5097.96 | M15: Delivered | N15: 5 | O15: =I15*H15 | P15: =O15*(1-IF(J15="",0,J15)) | Q15: =P15-K15 | R15: =IF(M15="Delivered",1,0)
A16: ORD5012 | B16: 46215 | C16: C1020 | D16: North | E16: Mobile App | F16: Sports | G16: Yoga Mat | H16: 3 | I16: 943.95 | J16: 0 | K16: 1561.04 | L16: 2831.85 | M16: Delivered | N16: 3 | O16: =I16*H16 | P16: =O16*(1-IF(J16="",0,J16)) | Q16: =P16-K16 | R16: =IF(M16="Delivered",1,0)
... A20: ORD5016 | B20: 46219 | C20: C1027 | D20: Central | E20: Marketplace | F20: Fashion | G20: Casual Shirt | H20: 3 | I20: 1260.03 | J20: 0.1 | K20: 2506.73 | L20: 3402.08 | M20: Delivered | N20: 2 | O20: =I20*H20 | P20: =O20*(1-IF(J20="",0,J20)) | Q20: =P20-K20 | R20: =IF(M20="Delivered",1,0)
A21: ORD5017 | B21: 46220 | D21: North | E21: Marketplace | F21: Beauty | G21: Hair Dryer | H21: 1 | I21: 2133.03 | J21: 0.2 | K21: 1479.04 | L21: 1706.42 | M21: Cancelled | O21: =I21*H21 | P21: =O21*(1-IF(J21="",0,J21)) | Q21: =P21-K21 | R21: =IF(M21="Delivered",1,0)
A22: ORD5018 | B22: 46221 | C22: C1008 | D22: South | E22: Website | F22: Fashion | G22: Running Shoes | H22: 1 | I22: 2715.03 | J22: 0.1 | K22: 1659.41 | L22: 2443.53 | M22: Delivered | N22: 3 | O22: =I22*H22 | P22: =O22*(1-IF(J22="",0,J22)) | Q22: =P22-K22 | R22: =IF(M22="Delivered",1,0)
A23: ORD5019 | B23: 46222 | C23: C1025 | D23: Central | E23: Mobile App | F23: Fashion | G23: Backpack | H23: 1 | I23: 1842.03 | J23: 0.1 | K23: 915.08 | L23: 1657.83 | M23: Delivered | N23: 2 | O23: =I23*H23 | P23: =O23*(1-IF(J23="",0,J23)) | Q23: =P23-K23 | R23: =IF(M23="Delivered",1,0)
A24: ORD5020 | B24: 46223 | C24: C1045 | D24: Central | E24: Website | F24: Fashion | G24: Backpack | H24: 3 | I24: 1993.95 | J24: 0.1 | K24: 3034.94 | L24: 5383.67 | M24: Returned | O24: =I24*H24 | P24: =O24*(1-IF(J24="",0,J24)) | Q24: =P24-K24 | R24: =IF(M24="Delivered",1,0)
A25: ORD5021 | B25: 46224 | C25: C1026 | D25: West | E25: Website | F25: Electronics | G25: Bluetooth Speaker | H25: 2 | I25: 1745.03 | J25: 0.1 | K25: 1679.44 | L25: 3141.05 | M25: Delivered | N25: 5 | O25: =I25*H25 | P25: =O25*(1-IF(J25="",0,J25)) | Q25: =P25-K25 | R25: =IF(M25="Delivered",1,0)
A26: ORD5022 | B26: 46225 | C26: C1039 | D26: East | E26: Mobile App | F26: Home & Kitchen | G26: Bedsheet Set | H26: 1 | I26: 1528.98 | J26: 0.05 | K26: 1123.84 | L26: 1452.53 | M26: Delivered | N26: 5 | O26: =I26*H26 | P26: =O26*(1-IF(J26="",0,J26)) | Q26: =P26-K26 | R26: =IF(M26="Delivered",1,0)
A27: ORD5023 | B27: 46226 | C27: C1043 | D27: North | E27: Website | F27: Beauty | G27: Hair Dryer | H27: 2 | I27: 2133.03 | J27: 0.15 | K27: 3194.62 | L27: 3626.15 | M27: Delivered | N27: 5 | O27: =I27*H27 | P27: =O27*(1-IF(J27="",0,J27)) | Q27: =P27-K27 | R27: =IF(M27="Delivered",1,0)
A28: ORD5024 | B28: 46227 | C28: C1003 | D28: East | E28: Website | F28: Electronics | G28: Wireless Earbuds | H28: 1 | I28: 2623.95 | J28: 0.15 | K28: 1376.51 | L28: 2230.36 | M28: Delivered | N28: 2 | O28: =I28*H28 | P28: =O28*(1-IF(J28="",0,J28)) | Q28: =P28-K28 | R28: =IF(M28="Delivered",1,0)
A29: ORD5025 | B29: 46228 | C29: C1048 | D29: West | E29: Mobile App | F29: Beauty | G29: Perfume | H29: 2 | I29: 1678.95 | J29: 0 | K29: 2125.38 | L29: 3357.9 | M29: Delivered | N29: 2 | O29: =I29*H29 | P29: =O29*(1-IF(J29="",0,J29)) | Q29: =P29-K29 | R29: =IF(M29="Delivered",1,0)
A30: ORD5026 | B30: 46229 | C30: C1055 | D30: East | E30: Marketplace | F30: Fashion | G30: Running Shoes | H30: 1 | I30: 2715.03 | J30: 0.2 | K30: 1648.05 | L30: 2172.02 | M30: Delivered | N30: 2 | O30: =I30*H30 | P30: =O30*(1-IF(J30="",0,J30)) | Q30: =P30-K30 | R30: =IF(M30="Delivered",1,0)
A31: ORD5027 | B31: 46230 | C31: C1013 | D31: South | E31: Website | F31: Home & Kitchen | G31: Bedsheet Set | H31: 3 | I31: 1528.98 | J31: 0.2 | K31: 3331.99 | L31: 3669.55 | M31: Delivered | N31: 2 | O31: =I31*H31 | P31: =O31*(1-IF(J31="",0,J31)) | Q31: =P31-K31 | R31: =IF(M31="Delivered",1,0)
A32: ORD5028 | B32: 46231 | C32: C1050 | D32: West | E32: Marketplace | F32: Sports | G32: Cricket Kit | H32: 2 | I32: 3568.98 | J32: 0.15 | K32: 4880.89 | L32: 6067.27 | M32: Delivered | N32: 3 | O32: =I32*H32 | P32: =O32*(1-IF(J32="",0,J32)) | Q32: =P32-K32 | R32: =IF(M32="Delivered",1,0)
A33: ORD5029 | B33: 46204 | C33: C1002 | D33: South | E33: Marketplace | F33: Beauty | G33: Hair Dryer | H33: 1 | I33: 2199 | J33: 0.1 | K33: 1242.3 | L33: 1979.1 | M33: Delivered | N33: 1 | O33: =I33*H33 | P33: =O33*(1-IF(J33="",0,J33)) | Q33: =P33-K33 | R33: =IF(M33="Delivered",1,0)
A34: ORD5030 | B34: 46205 | C34: C1025 | D34: Central | E34: Website | F34: Beauty | G34: Skin Care Kit | H34: 1 | I34: 1018.98 | J34: 0.2 | K34: 499.65 | L34: 815.18 | M34: Delivered | N34: 3 | O34: =I34*H34 | P34: =O34*(1-IF(J34="",0,J34)) | Q34: =P34-K34 | R34: =IF(M34="Delivered",1,0)
A35: ORD5031 | B35: 46206 | C35: C1033 | D35: Central | E35: Marketplace | F35: Sports | G35: Yoga Mat | H35: 2 | I35: 943.95 | J35: 0.1 | K35: 1178.23 | L35: 1699.11 | M35: Delivered | N35: 1 | O35: =I35*H35 | P35: =O35*(1-IF(J35="",0,J35)) | Q35: =P35-K35 | R35: =IF(M35="Delivered",1,0)
A36: ORD5032 | B36: 46207 | C36: C1034 | D36: West | E36: Website | F36: Home & Kitchen | G36: Air Fryer | H36: 2 | I36: 5499 | J36: 0 | K36: 5695.91 | L36: 10998 | M36: Returned | O36: =I36*H36 | P36: =O36*(1-IF(J36="",0,J36)) | Q36: =P36-K36 | R36: =IF(M36="Delivered",1,0)
A37: ORD5033 | B37: 46208 | C37: C1008 | E37: Mobile App | F37: Fashion | G37: Casual Shirt | H37: 1 | I37: 1299 | J37: 0.2 | K37: 835.49 | L37: 1039.2 | M37: Delivered | N37: 2 | O37: =I37*H37 | P37: =O37*(1-IF(J37="",0,J37)) | Q37: =P37-K37 | R37: =IF(M37="Delivered",1,0)
A38: ORD5034 | B38: 46209 | C38: C1035 | D38: North | E38: Mobile App | F38: Fashion | G38: Backpack | H38: 2 | I38: 1936.98 | J38: 0 | K38: 2855.06 | L38: 3873.96 | M38: Returned | O38: =I38*H38 | P38: =O38*(1-IF(J38="",0,J38)) | Q38: =P38-K38 | R38: =IF(M38="Delivered",1,0)
A39: ORD5035 | B39: 46210 | C39: C1030 | D39: East | E39: Website | F39: Sports | G39: Yoga Mat | H39: 1 | I39: 899 | J39: 0.05 | K39: 488.85 | L39: 854.05 | M39: Delivered | N39: 3 | O39: =I39*H39 | P39: =O39*(1-IF(J39="",0,J39)) | Q39: =P39-K39 | R39: =IF(M39="Delivered",1,0)
A40: ORD5036 | B40: 46211 | C40: C1037 | D40: South | E40: Website | F40: Fashion | G40: Running Shoes | H40: 1 | I40: 2854.98 | J40: 0 | K40: 1784.64 | L40: 2854.98 | M40: Delivered | N40: 3 | O40: =I40*H40 | P40: =O40*(1-IF(J40="",0,J40)) | Q40: =P40-K40 | R40: =IF(M40="Delivered",1,0)
A41: ORD5037 | B41: 46212 | C41: C1009 | D41: North | E41: Website | F41: Home & Kitchen | G41: Air Fryer | H41: 1 | I41: 5773.95 | J41: 0.05 | K41: 3072.82 | L41: 5485.25 | M41: Delivered | N41: 4 | O41: =I41*H41 | P41: =O41*(1-IF(J41="",0,J41)) | Q41: =P41-K41 | R41: =IF(M41="Delivered",1,0)
A42: ORD5038 | B42: 46213 | C42: C1023 | D42: East | E42: Mobile App | F42: Electronics | G42: Bluetooth Speaker | H42: 4 | I42: 1888.95 | J42: 0.05 | K42: 5680.57 | L42: 7178.01 | M42: Delivered | N42: 4 | O42: =I42*H42 | P42: =O42*(1-IF(J42="",0,J42)) | Q42: =P42-K42 | R42: =IF(M42="Delivered",1,0)
A43: ORD5039 | B43: 46214 | C43: C1038 | D43: East | E43: Marketplace | F43: Sports | G43: Cricket Kit | H43: 2 | I43: 3394.03 | J43: 0 | K43: 3722.95 | L43: 6788.06 | M43: Delivered | N43: 5 | O43: =I43*H43 | P43: =O43*(1-IF(J43="",0,J43)) | Q43: =P43-K43 | R43: =IF(M43="Delivered",1,0)
A44: ORD5040 | B44: 46215 | C44: C1031 | D44: Central | E44: Mobile App | F44: Beauty | G44: Hair Dryer | H44: 2 | I44: 2133.03 | J44: 0.15 | K44: 2207.83 | L44: 3626.15 | M44: Delivered | N44: 1 | O44: =I44*H44 | P44: =O44*(1-IF(J44="",0,J44)) | Q44: =P44-K44 | R44: =IF(M44="Delivered",1,0)
A45: ORD5041 | B45: 46247 | C45: C1003 | D45: West | E45: Website | F45: Electronics | G45: Smart Watch | H45: 1 | I45: 3999 | J45: 0.05 | K45: 2006.56 | L45: 3799.05 | M45: Delivered | N45: 5 | O45: =I45*H45 | P45: =O45*(1-IF(J45="",0,J45)) | Q45: =P45-K45 | R45: =IF(M45="Delivered",1,0)
A46: ORD5042 | B46: 46248 | C46: C1038 | D46: South | E46: Website | F46: Electronics | G46: Wireless Earbuds | H46: 1 | I46: 2424.03 | J46: 0.1 | K46: 1680.33 | L46: 2181.63 | M46: Delivered | N46: 3 | O46: =I46*H46 | P46: =O46*(1-IF(J46="",0,J46)) | Q46: =P46-K46 | R46: =IF(M46="Delivered",1,0)
A47: ORD5043 | B47: 46249 | C47: C1057 | D47: South | E47: Website | F47: Beauty | G47: Perfume | H47: 1 | I47: 1678.95 | J47: 0.1 | K47: 894.38 | L47: 1511.06 | M47: Delivered | N47: 5 | O47: =I47*H47 | P47: =O47*(1-IF(J47="",0,J47)) | Q47: =P47-K47 | R47: =IF(M47="Delivered",1,0)
A48: ORD5044 | B48: 46250 | C48: C1010 | D48: North | E48: Mobile App | F48: Home & Kitchen | G48: Bedsheet Set | H48: 3 | I48: 1528.98 | K48: 3301.87 | L48: 4128.25 | M48: Delivered | N48: 4 | O48: =I48*H48 | P48: =O48*(1-IF(J48="",0,J48)) | Q48: =P48-K48 | R48: =IF(M48="Delivered",1,0)
A49: ORD5045 | B49: 46251 | C49: C1048 | D49: Central | E49: Mobile App | F49: Home & Kitchen | G49: Mixer Grinder | H49: 1 | I49: 3200.03 | J49: 0.05 | K49: 1876.76 | L49: 3040.03 | M49: Delivered | N49: 4 | O49: =I49*H49 | P49: =O49*(1-IF(J49="",0,J49)) | Q49: =P49-K49 | R49: =IF(M49="Delivered",1,0)
A50: ORD5046 | B50: 46252 | C50: C1042 | D50: East | E50: Mobile App | F50: Sports | G50: Dumbbell Set | H50: 2 | I50: 2548.98 | J50: 0.15 | K50: 3597.94 | L50: 4333.27 | M50: Delivered | N50: 5 | O50: =I50*H50 | P50: =O50*(1-IF(J50="",0,J50)) | Q50: =P50-K50 | R50: =IF(M50="Delivered",1,0)
A51: ORD5047 | B51: 46253 | C51: C1008 | D51: West | E51: Mobile App | F51: Fashion | G51: Backpack | H51: 1 | I51: 1936.98 | J51: 0.1 | K51: 1158.74 | L51: 1743.28 | M51: Delivered | N51: 5 | O51: =I51*H51 | P51: =O51*(1-IF(J51="",0,J51)) | Q51: =P51-K51 | R51: =IF(M51="Delivered",1,0)
A52: ORD5048 | B52: 46254 | D52: North | E52: Website | F52: Fashion | G52: Casual Shirt | H52: 1 | I52: 1299 | J52: 0.15 | K52: 769 | L52: 1104.15 | M52: Delivered | N52: 2 | O52: =I52*H52 | P52: =O52*(1-IF(J52="",0,J52)) | Q52: =P52-K52 | R52: =IF(M52="Delivered",1,0)
A53: ORD5049 | B53: 46255 | C53: C1031 | D53: West | E53: Marketplace | F53: Beauty | G53: Perfume | H53: 1 | I53: 1678.95 | J53: 0.05 | K53: 904.98 | L53: 1595 | M53: Delivered | N53: 1 | O53: =I53*H53 | P53: =O53*(1-IF(J53="",0,J53)) | Q53: =P53-K53 | R53: =IF(M53="Delivered",1,0)
A54: ORD5050 | B54: 46256 | C54: C1055 | D54: East | E54: Website | F54: Home & Kitchen | G54: Bedsheet Set | H54: 1 | I54: 1499 | J54: 0.05 | K54: 1007.21 | L54: 1424.05 | M54: Delivered | N54: 3 | O54: =I54*H54 | P54: =O54*(1-IF(J54="",0,J54)) | Q54: =P54-K54 | R54: =IF(M54="Delivered",1,0)
A55: ORD5051 | B55: 46257 | C55: C1012 | D55: East | E55: Marketplace | F55: Electronics | G55: Smart Watch | H55: 1 | I55: 4078.98 | J55: 0.05 | K55: 2433.23 | L55: 3875.03 | M55: Cancelled | O55: =I55*H55 | P55: =O55*(1-IF(J55="",0,J55)) | Q55: =P55-K55 | R55: =IF(M55="Delivered",1,0)
A56: ORD5052 | B56: 46258 | C56: C1015 | D56: North | E56: Marketplace | F56: Home & Kitchen | G56: Mixer Grinder | H56: 2 | I56: 3299 | J56: 0.2 | K56: 3746.12 | L56: 5278.4 | M56: Returned | O56: =I56*H56 | P56: =O56*(1-IF(J56="",0,J56)) | Q56: =P56-K56 | R56: =IF(M56="Delivered",1,0)
A57: ORD5053 | B57: 46259 | C57: C1016 | D57: South | E57: Website | F57: Electronics | G57: Bluetooth Speaker | H57: 1 | I57: 1799 | J57: 0.05 | K57: 1274.82 | L57: 1709.05 | M57: Delivered | N57: 2 | O57: =I57*H57 | P57: =O57*(1-IF(J57="",0,J57)) | Q57: =P57-K57 | R57: =IF(M57="Delivered",1,0)
A58: ORD5054 | B58: 46260 | C58: C1024 | D58: North | E58: Marketplace | F58: Home & Kitchen | G58: Air Fryer | H58: 4 | I58: 5499 | J58: 0.15 | K58: 12477.55 | L58: 18696.6 | M58: Delivered | N58: 5 | O58: =I58*H58 | P58: =O58*(1-IF(J58="",0,J58)) | Q58: =P58-K58 | R58: =IF(M58="Delivered",1,0)
A59: ORD5055 | B59: 46261 | C59: C1037 | D59: South | E59: Website | F59: Beauty | G59: Perfume | H59: 2 | I59: 1551.03 | J59: 0.05 | K59: 2014.91 | L59: 2946.96 | M59: Delivered | N59: 2 | O59: =I59*H59 | P59: =O59*(1-IF(J59="",0,J59)) | Q59: =P59-K59 | R59: =IF(M59="Delivered",1,0)
A60: ORD5056 | B60: 46262 | C60: C1055 | D60: South | E60: Mobile App | F60: Beauty | G60: Perfume | H60: 2 | I60: 1630.98 | J60: 0.2 | K60: 1677.63 | L60: 2609.57 | M60: Delivered | N60: 4 | O60: =I60*H60 | P60: =O60*(1-IF(J60="",0,J60)) | Q60: =P60-K60 | R60: =IF(M60="Delivered",1,0)
A61: ORD5057 | B61: 46235 | C61: C1054 | D61: East | E61: Website | F61: Beauty | G61: Perfume | H61: 2 | I61: 1599 | J61: 0.15 | K61: 2000.87 | L61: 2718.3 | M61: Delivered | N61: 2 | O61: =I61*H61 | P61: =O61*(1-IF(J61="",0,J61)) | Q61: =P61-K61 | R61: =IF(M61="Delivered",1,0)
A62: ORD5058 | B62: 46236 | C62: C1042 | D62: North | E62: Mobile App | F62: Sports | G62: Dumbbell Set | H62: 1 | I62: 2548.98 | J62: 0.1 | K62: 1333.72 | L62: 2294.08 | M62: Delivered | N62: 3 | O62: =I62*H62 | P62: =O62*(1-IF(J62="",0,J62)) | Q62: =P62-K62 | R62: =IF(M62="Delivered",1,0)
A63: ORD5059 | B63: 46237 | C63: C1022 | D63: East | E63: Website | F63: Electronics | G63: Wireless Earbuds | H63: 1 | I63: 2548.98 | J63: 0.05 | K63: 1377.55 | L63: 2421.53 | M63: Delivered | N63: 4 | O63: =I63*H63 | P63: =O63*(1-IF(J63="",0,J63)) | Q63: =P63-K63 | R63: =IF(M63="Delivered",1,0)
A64: ORD5060 | B64: 46238 | C64: C1032 | D64: West | E64: Mobile App | F64: Beauty | G64: Hair Dryer | H64: 1 | I64: 2133.03 | J64: 0 | K64: 1401.59 | L64: 2133.03 | M64: Delivered | N64: 1 | O64: =I64*H64 | P64: =O64*(1-IF(J64="",0,J64)) | Q64: =P64-K64 | R64: =IF(M64="Delivered",1,0)
A65: ORD5061 | B65: 46239 | C65: C1055 | D65: South | E65: Mobile App | F65: Fashion | G65: Running Shoes | H65: 2 | I65: 2715.03 | J65: 0.2 | K65: 2871.64 | L65: 4344.05 | M65: Delivered | N65: 4 | O65: =I65*H65 | P65: =O65*(1-IF(J65="",0,J65)) | Q65: =P65-K65 | R65: =IF(M65="Delivered",1,0)
A66: ORD5062 | B66: 46240 | C66: C1018 | D66: North | E66: Mobile App | F66: Sports | G66: Cricket Kit | H66: 1 | I66: 3568.98 | J66: 0.1 | K66: 1807.23 | L66: 3212.08 | M66: Delivered | N66: 5 | O66: =I66*H66 | P66: =O66*(1-IF(J66="",0,J66)) | Q66: =P66-K66 | R66: =IF(M66="Delivered",1,0)
A67: ORD5063 | B67: 46241 | C67: C1017 | D67: North | E67: Website | F67: Home & Kitchen | G67: Mixer Grinder | H67: 1 | I67: 3299 | J67: 0 | K67: 2091.16 | L67: 3299 | M67: Delivered | N67: 5 | O67: =I67*H67 | P67: =O67*(1-IF(J67="",0,J67)) | Q67: =P67-K67 | R67: =IF(M67="Delivered",1,0)
A68: ORD5064 | B68: 46242 | C68: C1047 | D68: Central | E68: Website | F68: Home & Kitchen | G68: Bedsheet Set | H68: 3 | I68: 1454.03 | J68: 0 | K68: 2616.03 | L68: 4362.09 | M68: Delivered | N68: 1 | O68: =I68*H68 | P68: =O68*(1-IF(J68="",0,J68)) | Q68: =P68-K68 | R68: =IF(M68="Delivered",1,0)
... A75: ORD5071 | B75: 46249 | C75: C1038 | D75: East | E75: Website | F75: Fashion | G75: Backpack | H75: 1 | I75: 1842.03 | J75: 0.1 | K75: 1113.47 | L75: 1657.83 | M75: Delivered | N75: 4 | O75: =I75*H75 | P75: =O75*(1-IF(J75="",0,J75)) | Q75: =P75-K75 | R75: =IF(M75="Delivered",1,0)
A76: ORD5072 | B76: 46250 | C76: C1025 | D76: West | E76: Website | F76: Electronics | G76: Bluetooth Speaker | H76: 1 | I76: 1834.98 | J76: 0 | K76: 1237.15 | L76: 1834.98 | M76: Returned | O76: =I76*H76 | P76: =O76*(1-IF(J76="",0,J76)) | Q76: =P76-K76 | R76: =IF(M76="Delivered",1,0)
A77: ORD5073 | B77: 46251 | C77: C1022 | D77: West | E77: Website | F77: Fashion | G77: Backpack | H77: 1 | I77: 1842.03 | J77: 0.1 | K77: 1012.67 | L77: 1657.83 | M77: Delivered | N77: 2 | O77: =I77*H77 | P77: =O77*(1-IF(J77="",0,J77)) | Q77: =P77-K77 | R77: =IF(M77="Delivered",1,0)
A78: ORD5074 | B78: 46252 | C78: C1032 | D78: West | E78: Website | F78: Sports | G78: Dumbbell Set | H78: 4 | I78: 2499 | J78: 0.05 | K78: 6181.57 | L78: 9496.2 | M78: Delivered | N78: 1 | O78: =I78*H78 | P78: =O78*(1-IF(J78="",0,J78)) | Q78: =P78-K78 | R78: =IF(M78="Delivered",1,0)
A79: ORD5075 | B79: 46253 | C79: C1029 | D79: North | E79: Website | F79: Home & Kitchen | G79: Mixer Grinder | H79: 2 | I79: 3200.03 | J79: 0.05 | K79: 4475.8 | L79: 6080.06 | M79: Delivered | N79: 2 | O79: =I79*H79 | P79: =O79*(1-IF(J79="",0,J79)) | Q79: =P79-K79 | R79: =IF(M79="Delivered",1,0)
A80: ORD5076 | B80: 46254 | C80: C1049 | D80: East | E80: Website | F80: Beauty | G80: Hair Dryer | H80: 2 | I80: 2308.95 | J80: 0.15 | K80: 2247.02 | L80: 3925.21 | M80: Returned | O80: =I80*H80 | P80: =O80*(1-IF(J80="",0,J80)) | Q80: =P80-K80 | R80: =IF(M80="Delivered",1,0)
A81: ORD5077 | B81: 46255 | C81: C1020 | D81: Central | E81: Mobile App | F81: Home & Kitchen | G81: Mixer Grinder | H81: 3 | I81: 3299 | J81: 0 | K81: 5263.42 | L81: 9897 | M81: Delivered | N81: 1 | O81: =I81*H81 | P81: =O81*(1-IF(J81="",0,J81)) | Q81: =P81-K81 | R81: =IF(M81="Delivered",1,0)
A82: ORD5078 | B82: 46256 | C82: C1049 | E82: Mobile App | F82: Electronics | G82: Wireless Earbuds | H82: 3 | I82: 2548.98 | J82: 0 | K82: 5428.17 | L82: 7646.94 | M82: Delivered | N82: 3 | O82: =I82*H82 | P82: =O82*(1-IF(J82="",0,J82)) | Q82: =P82-K82 | R82: =IF(M82="Delivered",1,0)
A83: ORD5079 | B83: 46257 | C83: C1056 | D83: North | E83: Website | F83: Electronics | G83: Wireless Earbuds | H83: 3 | I83: 2499 | J83: 0.2 | K83: 4769.34 | L83: 5997.6 | M83: Delivered | N83: 4 | O83: =I83*H83 | P83: =O83*(1-IF(J83="",0,J83)) | Q83: =P83-K83 | R83: =IF(M83="Delivered",1,0)
A84: ORD5080 | B84: 46258 | C84: C1037 | D84: West | E84: Website | F84: Home & Kitchen | G84: Bedsheet Set | H84: 3 | I84: 1499 | J84: 0.2 | K84: 2909.78 | L84: 3597.6 | M84: Delivered | N84: 5 | O84: =I84*H84 | P84: =O84*(1-IF(J84="",0,J84)) | Q84: =P84-K84 | R84: =IF(M84="Delivered",1,0)
A85: ORD5081 | B85: 46290 | C85: C1015 | D85: North | E85: Mobile App | F85: Sports | G85: Dumbbell Set | H85: 2 | I85: 2548.98 | J85: 0.15 | K85: 3853.15 | L85: 4333.27 | M85: Delivered | N85: 3 | O85: =I85*H85 | P85: =O85*(1-IF(J85="",0,J85)) | Q85: =P85-K85 | R85: =IF(M85="Delivered",1,0)
A86: ORD5082 | B86: 46291 | C86: C1043 | D86: South | E86: Website | F86: Beauty | G86: Skin Care Kit | H86: 1 | I86: 999 | J86: 0 | K86: 591.06 | L86: 999 | M86: Delivered | N86: 4 | O86: =I86*H86 | P86: =O86*(1-IF(J86="",0,J86)) | Q86: =P86-K86 | R86: =IF(M86="Delivered",1,0)
A87: ORD5083 | B87: 46292 | C87: C1040 | D87: East | E87: Website | F87: Electronics | G87: Smart Watch | H87: 2 | I87: 4078.98 | J87: 0.15 | K87: 5954.12 | L87: 6934.27 | M87: Delivered | N87: 3 | O87: =I87*H87 | P87: =O87*(1-IF(J87="",0,J87)) | Q87: =P87-K87 | R87: =IF(M87="Delivered",1,0)
A88: ORD5084 | B88: 46293 | C88: C1003 | D88: North | E88: Mobile App | F88: Sports | G88: Cricket Kit | H88: 1 | I88: 3568.98 | J88: 0.05 | K88: 1735.96 | L88: 3390.53 | M88: Delivered | N88: 4 | O88: =I88*H88 | P88: =O88*(1-IF(J88="",0,J88)) | Q88: =P88-K88 | R88: =IF(M88="Delivered",1,0)
A89: ORD5085 | B89: 46266 | C89: C1029 | D89: West | E89: Mobile App | F89: Sports | G89: Yoga Mat | H89: 1 | I89: 872.03 | J89: 0.2 | K89: 440.55 | L89: 697.62 | M89: Delivered | N89: 1 | O89: =I89*H89 | P89: =O89*(1-IF(J89="",0,J89)) | Q89: =P89-K89 | R89: =IF(M89="Delivered",1,0)
A90: ORD5086 | B90: 46267 | C90: C1010 | D90: East | E90: Marketplace | F90: Sports | G90: Yoga Mat | H90: 3 | I90: 899 | J90: 0.2 | K90: 1576.31 | L90: 2157.6 | M90: Returned | O90: =I90*H90 | P90: =O90*(1-IF(J90="",0,J90)) | Q90: =P90-K90 | R90: =IF(M90="Delivered",1,0)
A91: ORD5087 | B91: 46268 | C91: C1037 | D91: East | E91: Marketplace | F91: Home & Kitchen | G91: Bedsheet Set | H91: 3 | I91: 1573.95 | J91: 0.05 | K91: 2871.2 | L91: 4485.76 | M91: Delivered | N91: 3 | O91: =I91*H91 | P91: =O91*(1-IF(J91="",0,J91)) | Q91: =P91-K91 | R91: =IF(M91="Delivered",1,0)
A92: ORD5088 | B92: 46269 | C92: C1056 | D92: North | E92: Mobile App | F92: Sports | G92: Cricket Kit | H92: 1 | I92: 3394.03 | J92: 0.1 | K92: 2157.35 | L92: 3054.63 | M92: Delivered | N92: 2 | O92: =I92*H92 | P92: =O92*(1-IF(J92="",0,J92)) | Q92: =P92-K92 | R92: =IF(M92="Delivered",1,0)
A93: ORD5089 | B93: 46270 | C93: C1027 | D93: Central | E93: Mobile App | F93: Fashion | G93: Backpack | H93: 1 | I93: 1936.98 | J93: 0.15 | K93: 1231.58 | L93: 1646.43 | M93: Delivered | N93: 3 | O93: =I93*H93 | P93: =O93*(1-IF(J93="",0,J93)) | Q93: =P93-K93 | R93: =IF(M93="Delivered",1,0)
A94: ORD5090 | B94: 46271 | C94: C1041 | D94: South | E94: Mobile App | F94: Home & Kitchen | G94: Air Fryer | H94: 3 | I94: 5773.95 | J94: 0.15 | K94: 9696.7 | L94: 14723.57 | M94: Delivered | N94: 3 | O94: =I94*H94 | P94: =O94*(1-IF(J94="",0,J94)) | Q94: =P94-K94 | R94: =IF(M94="Delivered",1,0)
A95: ORD5091 | B95: 46272 | D95: North | E95: Mobile App | F95: Home & Kitchen | G95: Air Fryer | H95: 2 | I95: 5773.95 | J95: 0.2 | K95: 8747.73 | L95: 9238.32 | M95: Delivered | N95: 2 | O95: =I95*H95 | P95: =O95*(1-IF(J95="",0,J95)) | Q95: =P95-K95 | R95: =IF(M95="Delivered",1,0)
A96: ORD5092 | B96: 46273 | C96: C1014 | D96: West | E96: Mobile App | F96: Electronics | G96: Smart Watch | H96: 2 | I96: 4198.95 | J96: 0.05 | K96: 5737.58 | L96: 7978 | M96: Returned | O96: =I96*H96 | P96: =O96*(1-IF(J96="",0,J96)) | Q96: =P96-K96 | R96: =IF(M96="Delivered",1,0)
A97: ORD5093 | B97: 46274 | C97: C1019 | D97: South | E97: Mobile App | F97: Beauty | G97: Skin Care Kit | H97: 1 | I97: 969.03 | J97: 0 | K97: 606 | L97: 969.03 | M97: Delivered | N97: 1 | O97: =I97*H97 | P97: =O97*(1-IF(J97="",0,J97)) | Q97: =P97-K97 | R97: =IF(M97="Delivered",1,0)
A98: ORD5094 | B98: 46275 | C98: C1035 | D98: East | E98: Website | F98: Electronics | G98: Wireless Earbuds | H98: 1 | I98: 2548.98 | J98: 0.05 | K98: 1497.69 | L98: 2421.53 | M98: Returned | O98: =I98*H98 | P98: =O98*(1-IF(J98="",0,J98)) | Q98: =P98-K98 | R98: =IF(M98="Delivered",1,0)
A99: ORD5095 | B99: 46276 | C99: C1018 | D99: West | E99: Mobile App | F99: Fashion | G99: Running Shoes | H99: 2 | I99: 2715.03 | J99: 0.05 | K99: 3208.92 | L99: 5158.56 | M99: Delivered | N99: 2 | O99: =I99*H99 | P99: =O99*(1-IF(J99="",0,J99)) | Q99: =P99-K99 | R99: =IF(M99="Delivered",1,0)
A100: ORD5096 | B100: 46277 | C100: C1030 | D100: North | E100: Website | F100: Sports | G100: Yoga Mat | H100: 1 | I100: 943.95 | J100: 0.15 | K100: 597.33 | L100: 802.36 | M100: Delivered | N100: 2 | O100: =I100*H100 | P100: =O100*(1-IF(J100="",0,J100)) | Q100: =P100-K100 | R100: =IF(M100="Delivered",1,0)
A101: ORD5097 | B101: 46278 | C101: C1019 | D101: East | E101: Marketplace | F101: Electronics | G101: Bluetooth Speaker | H101: 1 | I101: 1888.95 | J101: 0.2 | K101: 1054.79 | L101: 1511.16 | M101: Delivered | N101: 4 | O101: =I101*H101 | P101: =O101*(1-IF(J101="",0,J101)) | Q101: =P101-K101 | R101: =IF(M101="Delivered",1,0)
A102: ORD5098 | B102: 46279 | C102: C1017 | D102: West | E102: Marketplace | F102: Electronics | G102: Wireless Earbuds | H102: 1 | I102: 2499 | J102: 0.05 | K102: 1461.63 | L102: 2374.05 | M102: Delivered | N102: 4 | O102: =I102*H102 | P102: =O102*(1-IF(J102="",0,J102)) | Q102: =P102-K102 | R102: =IF(M102="Delivered",1,0)
A103: ORD5099 | B103: 46280 | C103: C1033 | D103: West | E103: Website | F103: Fashion | G103: Running Shoes | H103: 1 | I103: 2799 | J103: 0 | K103: 1416.61 | L103: 2799 | M103: Delivered | N103: 4 | O103: =I103*H103 | P103: =O103*(1-IF(J103="",0,J103)) | Q103: =P103-K103 | R103: =IF(M103="Delivered",1,0)
A104: ORD5100 | B104: 46281 | C104: C1026 | D104: West | E104: Website | F104: Fashion | G104: Running Shoes | H104: 2 | I104: 2715.03 | J104: 0 | K104: 3518.91 | L104: 5430.06 | M104: Delivered | N104: 4 | O104: =I104*H104 | P104: =O104*(1-IF(J104="",0,J104)) | Q104: =P104-K104 | R104: =IF(M104="Delivered",1,0)
A105: ORD5101 | B105: 46282 | C105: C1038 | D105: North | E105: Mobile App | F105: Sports | G105: Cricket Kit | H105: 2 | I105: 3394.03 | J105: 0.05 | K105: 3901.63 | L105: 6448.66 | M105: Returned | O105: =I105*H105 | P105: =O105*(1-IF(J105="",0,J105)) | Q105: =P105-K105 | R105: =IF(M105="Delivered",1,0)
A106: ORD5102 | B106: 46283 | C106: C1039 | D106: West | E106: Mobile App | F106: Sports | G106: Yoga Mat | H106: 1 | I106: 899 | J106: 0.1 | K106: 666.4 | L106: 809.1 | M106: Delivered | N106: 2 | O106: =I106*H106 | P106: =O106*(1-IF(J106="",0,J106)) | Q106: =P106-K106 | R106: =IF(M106="Delivered",1,0)
A107: ORD5103 | B107: 46284 | C107: C1043 | D107: North | E107: Marketplace | F107: Sports | G107: Yoga Mat | H107: 2 | I107: 916.98 | K107: 1333.29 | L107: 1558.87 | M107: Delivered | N107: 5 | O107: =I107*H107 | P107: =O107*(1-IF(J107="",0,J107)) | Q107: =P107-K107 | R107: =IF(M107="Delivered",1,0)
A108: ORD5104 | B108: 46285 | C108: C1012 | D108: South | E108: Mobile App | F108: Electronics | G108: Bluetooth Speaker | H108: 4 | I108: 1888.95 | J108: 0.05 | K108: 3798.17 | L108: 7178.01 | M108: Delivered | N108: 3 | O108: =I108*H108 | P108: =O108*(1-IF(J108="",0,J108)) | Q108: =P108-K108 | R108: =IF(M108="Delivered",1,0)
A109: ORD5105 | B109: 46286 | C109: C1012 | D109: East | E109: Marketplace | F109: Fashion | G109: Running Shoes | H109: 1 | I109: 2715.03 | J109: 0.1 | K109: 1347.38 | L109: 2443.53 | M109: Delivered | N109: 3 | O109: =I109*H109 | P109: =O109*(1-IF(J109="",0,J109)) | Q109: =P109-K109 | R109: =IF(M109="Delivered",1,0)
A110: ORD5106 | B110: 46287 | C110: C1017 | D110: North | E110: Mobile App | F110: Home & Kitchen | G110: Mixer Grinder | H110: 3 | I110: 3299 | J110: 0 | K110: 6925.11 | L110: 9897 | M110: Delivered | N110: 1 | O110: =I110*H110 | P110: =O110*(1-IF(J110="",0,J110)) | Q110: =P110-K110 | R110: =IF(M110="Delivered",1,0)
...

Sheet Analysis
A1: ANALYSIS & KPI SUMMARY
A2: Use formulas, PivotTables or SUMIFS/COUNTIFS. Clearly define what is included in sales and rates.
A4: KPI | B4: Value | C4: Definition / notes | E4: Breakdown | F4: Net Sales (INR) | G4: Gross Profit (INR)
A5: Total records | B5: =COUNTA('Raw Data'!A5:A124) | C5: Count all rows, including cancelled and returned orders | E5: Region
A6: Unique Order IDs | B6: =SUMPRODUCT(('Raw Data'!A5:A124<>"")/COUNTIF('Raw Data'!A5:A124,'Raw Data'!A5:A124&"")) | C6: Count distinct IDs after identifying duplicate | E6: North | F6: =SUMIFS('Raw Data'!$P$5:$P$124,'Raw Data'!$D$5:$D$124,E6,'Raw Data'!$M$5:$M$124,"Delivered") | G6: =SUMIFS('Raw Data'!$Q$5:$Q$124,'Raw Data'!$D$5:$D$124,E6,'Raw Data'!$M$5:$M$124,"Delivered")
A7: Delivered orders | B7: =COUNTIF('Raw Data'!M5:M124,"Delivered") | C7: Status = Delivered | E7: South | F7: =SUMIFS('Raw Data'!$P$5:$P$124,'Raw Data'!$D$5:$D$124,E7,'Raw Data'!$M$5:$M$124,"Delivered") | G7: =SUMIFS('Raw Data'!$Q$5:$Q$124,'Raw Data'!$D$5:$D$124,E7,'Raw Data'!$M$5:$M$124,"Delivered")
A8: Return rate | B8: =COUNTIF('Raw Data'!M5:M124,"Returned")/COUNTA('Raw Data'!A5:A124) | C8: Returned orders ÷ total records; state if you use delivered-only denominator instead | E8: East | F8: =SUMIFS('Raw Data'!$P$5:$P$124,'Raw Data'!$D$5:$D$124,E8,'Raw Data'!$M$5:$M$124,"Delivered") | G8: =SUMIFS('Raw Data'!$Q$5:$Q$124,'Raw Data'!$D$5:$D$124,E8,'Raw Data'!$M$5:$M$124,"Delivered")
A9: Cancellation rate | B9: =COUNTIF('Raw Data'!M5:M124,"Cancelled")/COUNTA('Raw Data'!A5:A124) | C9: Cancelled orders ÷ total records | E9: West | F9: =SUMIFS('Raw Data'!$P$5:$P$124,'Raw Data'!$D$5:$D$124,E9,'Raw Data'!$M$5:$M$124,"Delivered") | G9: =SUMIFS('Raw Data'!$Q$5:$Q$124,'Raw Data'!$D$5:$D$124,E9,'Raw Data'!$M$5:$M$124,"Delivered")
A10: Net sales | B10: =SUMIFS('Raw Data'!P5:P124,'Raw Data'!M5:M124,"Delivered") | C10: Sum Net Sales for Delivered orders only | E10: Central | F10: =SUMIFS('Raw Data'!$P$5:$P$124,'Raw Data'!$D$5:$D$124,E10,'Raw Data'!$M$5:$M$124,"Delivered") | G10: =SUMIFS('Raw Data'!$Q$5:$Q$124,'Raw Data'!$D$5:$D$124,E10,'Raw Data'!$M$5:$M$124,"Delivered")
A11: Gross profit | B11: =SUMIFS('Raw Data'!Q5:Q124,'Raw Data'!M5:M124,"Delivered") | C11: Sum Gross Profit for Delivered orders only
A12: Gross margin | B12: =B11/B10 | C12: Gross profit ÷ delivered net sales | E12: Channel
A13: Average order value (AOV) | B13: =B10/B7 | C13: Delivered net sales ÷ delivered orders | E13: Website | F13: =SUMIFS('Raw Data'!$P$5:$P$124,'Raw Data'!$E$5:$E$124,E13,'Raw Data'!$M$5:$M$124,"Delivered") | G13: =SUMIFS('Raw Data'!$Q$5:$Q$124,'Raw Data'!$E$5:$E$124,E13,'Raw Data'!$M$5:$M$124,"Delivered")
A14: Missing Customer IDs | B14: =COUNTBLANK('Raw Data'!C5:C124) | C14: Count blank Customer ID | E14: Mobile App | F14: =SUMIFS('Raw Data'!$P$5:$P$124,'Raw Data'!$E$5:$E$124,E14,'Raw Data'!$M$5:$M$124,"Delivered") | G14: =SUMIFS('Raw Data'!$Q$5:$Q$124,'Raw Data'!$E$5:$E$124,E14,'Raw Data'!$M$5:$M$124,"Delivered")
A15: Missing Regions | B15: =COUNTBLANK('Raw Data'!D5:D124) | C15: Count blank Region | E15: Marketplace | F15: =SUMIFS('Raw Data'!$P$5:$P$124,'Raw Data'!$E$5:$E$124,E15,'Raw Data'!$M$5:$M$124,"Delivered") | G15: =SUMIFS('Raw Data'!$Q$5:$Q$124,'Raw Data'!$E$5:$E$124,E15,'Raw Data'!$M$5:$M$124,"Delivered")
A16: Missing Discounts | B16: =COUNTBLANK('Raw Data'!J5:J124) | C16: Count blank Discount %
A17: Duplicate Order IDs | B17: =COUNTA('Raw Data'!A5:A124)-SUMPRODUCT(1/COUNTIF('Raw Data'!A5:A124,'Raw Data'!A5:A124)) | C17: Count of rows beyond first occurrence for duplicate Order ID | E17: Category
E18: Electronics | F18: =SUMIFS('Raw Data'!$P$5:$P$124,'Raw Data'!$F$5:$F$124,E18,'Raw Data'!$M$5:$M$124,"Delivered") | G18: =SUMIFS('Raw Data'!$Q$5:$Q$124,'Raw Data'!$F$5:$F$124,E18,'Raw Data'!$M$5:$M$124,"Delivered")
E19: Home & Kitchen | F19: =SUMIFS('Raw Data'!$P$5:$P$124,'Raw Data'!$F$5:$F$124,E19,'Raw Data'!$M$5:$M$124,"Delivered") | G19: =SUMIFS('Raw Data'!$Q$5:$Q$124,'Raw Data'!$F$5:$F$124,E19,'Raw Data'!$M$5:$M$124,"Delivered")
F20: =SUMIFS('Raw Data'!$P$5:$P$124,'Raw Data'!$F$5:$F$124,E20,'Raw Data'!$M$5:$M$124,"Delivered") | G20: =SUMIFS('Raw Data'!$Q$5:$Q$124,'Raw Data'!$F$5:$F$124,E20,'Raw Data'!$M$5:$M$124,"Delivered")
F21: =SUMIFS('Raw Data'!$P$5:$P$124,'Raw Data'!$F$5:$F$124,E21,'Raw Data'!$M$5:$M$124,"Delivered") | G21: =SUMIFS('Raw Data'!$Q$5:$Q$124,'Raw Data'!$F$5:$F$124,E21,'Raw Data'!$M$5:$M$124,"Delivered")
F22: =SUMIFS('Raw Data'!$P$5:$P$124,'Raw Data'!$F$5:$F$124,E22,'Raw Data'!$M$5:$M$124,"Delivered") | G22: =SUMIFS('Raw Data'!$Q$5:$Q$124,'Raw Data'!$F$5:$F$124,E22,'Raw Data'!$M$5:$M$124,"Delivered")
A25: Business insights | B25: Write two actionable insights and one caveat. Mention the metric supporting each insight.
A29: Data-quality treatment | B29: Explain how you treated duplicate Order IDs and missing discount, region and customer values.

Sheet Answer Key
A1: ANSWER KEY — OPEN ONLY AFTER YOUR ATTEMPT
A3: Expected formulas / approach
A4: Gross Sales | B4: Unit Price × Quantity
A5: Net Sales | B5: Gross Sales × (1 − Discount); assume blank discount = 0% only if documented and flagged
A6: Gross Profit | B6: Net Sales − Cost. Report delivered-only sales/profit for this exercise.
A7: Delivered flag | B7: IF(Status="Delivered",1,0)
A8: Delivered net sales | B8: SUMIFS(Net Sales, Status, "Delivered")
A9: Return rate | B9: Returned rows ÷ all rows in this mock; alternative denominator acceptable if clearly defined.
A10: Cancellation rate | B10: Cancelled rows ÷ all rows in this mock.
A11: AOV | B11: Delivered net sales ÷ delivered order count.
A12: Duplicates | B12: Use COUNTIF to flag repeated Order IDs; investigate before removing. One duplicate ID occurs in two records.
A13: Missing fields | B13: Do not infer Customer ID or Region. Treat blank discount as 0 only as a stated assumption.
A14: Business interpretation | B14: Compare segments on delivered net sales and gross profit, with margin as a complementary metric. Avoid causal claims.
A16: Indicative results (under stated assumptions)
A17: Total records | B17: 120 | C17: rows
A18: Unique Order IDs | B18: 119 | C18: distinct IDs
A19: Delivered orders | B19: 104 | C19: orders
A20: Return rate | B20: 0.10833333 | C20: % of all records
A21: Cancellation rate | B21: 0.025 | C21: % of all records
A22: Delivered net sales | B22: 425867.85 | C22: INR
A23: Delivered gross profit | B23: 142709.11 | C23: INR
A24: Gross margin | B24: 0.33510187 | C24: %
A25: AOV | B25: 4094.8832 | C25: INR per delivered record
A26: Missing Customer IDs | B26: 3 | C26: rows
A27: Missing Regions | B27: 2 | C27: rows
A28: Missing Discounts | B28: 2 | C28: rows
A29: Duplicate rows beyond first | B29: 1 | C29: rows
A32: Delivered sales by segment
A33: Dimension | B33: Segment | C33: Net Sales (INR) | D33: Gross Profit (INR)
A34: Region | B34: North | C34: 128015.48 | D34: 41562.925
A35: Region | B35: South | C35: 69614.756 | D35: 24439.046
A36: Region | B36: East | C36: 79319.712 | D36: 24593.232
A37: Region | B37: West | C37: 98077.556 | D37: 32696.435
A38: Region | B38: Central | C38: 42154.215 | D38: 16994.995
A39: Channel | B39: Website | C39: 146886.04 | D39: 46822.188
A40: Channel | B40: Mobile App | C40: 204212.8 | D40: 71580.976
A41: Channel | B41: Marketplace | C41: 74769.019 | D41: 24305.949
A42: Category | B42: Electronics | C42: 78760.098 | D42: 25097.708
A43: Category | B43: Home & Kitchen | C43: 169467.81 | D43: 58965.511
A44: Category | B44: Fashion | C44: 65743.7 | D44: 21250.64
A45: Category | B45: Beauty | C45: 32331.988 | D45: 10609.388
A46: Category | B46: Sports | C46: 79564.257 | D46: 26785.867
