Workbook

Sheet Read Me
A1: INVESTMENT BANKING | EXCEL ASSESSMENT
A2: Mock recruitment exercise • Consumer products M&A • All figures fictional • 60 minutes
A4: Candidate brief
A5: Scenario | B5: You are an analyst supporting a potential acquisition of TargetCo by AcquirerCo. The VP needs a quick valuation and a first-pass view on whether the transaction is EPS-accretive or dilutive.
A6: Time limit | B6: 60 minutes. Work in Excel only. Do not use external sources. Use formulas rather than hardcoding derived outputs.
A7: Units | B7: INR millions, except per-share data, multiples and percentages. Share counts are in millions.
A8: Conventions | B8: Use FY2023A as the latest historical year. Treat FY2024E as the forecast year. Use net debt = debt less cash. Use EV = equity value + net debt.
A9: Task 1 — Data & operating metrics (10 min) | B9: On 'Operating Data', calculate FY2023A EBITDA margin for AcquirerCo and TargetCo, and FY2024E revenue growth and EBITDA margin for each. Use formulas.
A10: Task 2 — Trading comps (20 min) | B10: On 'Trading Comps', calculate EV, EV / FY2023A Revenue, EV / FY2023A EBITDA, and median EV / EBITDA for the peer set. Exclude companies with negative / zero EBITDA if any. Apply the median EV / EBITDA multiple to TargetCo FY2023A EBITDA to estimate implied enterprise value, then deduct TargetCo net debt to estimate equity value.
A11: Task 3 — Accretion / dilution (25 min) | B11: On 'Deal Model', calculate offer equity value using the premium to unaffected share price, transaction fees, new debt raised, interest expense on new debt, foregone interest on cash used, pro forma net income, new shares issued, pro forma EPS, standalone AcquirerCo EPS, and % accretion / dilution. Use the assumptions provided.
A12: Task 4 — Output & checks (5 min) | B12: On 'Summary', link the key outputs from your model and write a 2–3 sentence recommendation. Include at least two model checks (e.g., sources = uses; share count / EPS logic).
A13: Formatting | B13: Blue font for hardcodes; black font for formulas; currency in INR mm with comma separators; multiples as 0.0x; percentages as 0.0%; negatives in parentheses. Keep the workbook readable.
A14: Important | B14: This is a realistic practice simulation, not a claim that every bank uses this exact test. No single format is universal; some tests focus on speed, formulas, formatting, accounting, or a short model.

Sheet Operating Data
A1: OPERATING DATA
A2: Use formulas in the yellow cells. Figures in INR millions.
A4: Metric | B4: AcquirerCo FY2023A | C4: AcquirerCo FY2024E | D4: TargetCo FY2023A | E4: TargetCo FY2024E
A5: Revenue | B5: 12500 | C5: 13750 | D5: 4200 | E5: 4830
A6: EBITDA | B6: 1875 | C6: 2200 | D6: 630 | E6: 772.8
A7: D&A | B7: 375 | C7: 412.5 | D7: 126 | E7: 144.9
A8: EBIT | B8: 1500 | C8: 1787.5 | D8: 504 | E8: 627.9
A9: Interest expense | B9: 220 | C9: 230 | D9: 95 | E9: 110
A10: Tax rate | B10: 0.25 | C10: 0.25 | D10: 0.25 | E10: 0.25
A11: Net income | B11: 960 | C11: 1168.1 | D11: 306.75 | E11: 388.425
A12: Revenue growth | B12: =NA() | C12: =C5/B5-1 | D12: =NA() | E12: =E5/D5-1
A13: EBITDA margin | B13: =B6/B5 | C13: =C6/C5 | D13: =D6/D5 | E13: =E6/E5

Sheet Trading Comps
A1: TRADING COMPARABLES
A2: Populate yellow cells with formulas. Share counts in millions; INR figures in millions.
A4: Company | B4: Share Price (INR) | C4: Diluted Shares (mm) | D4: Debt | E4: Cash | F4: FY2023A Revenue | G4: FY2023A EBITDA | H4: Equity Value | I4: Enterprise Value | J4: EV / Revenue | K4: EV / EBITDA | L4: Notes
A5: Aster Consumer Ltd | B5: 420 | C5: 20 | D5: 1800 | E5: 450 | F5: 8400 | G5: 920 | H5: =B5*C5 | I5: =H5+D5-E5 | J5: =I5/F5 | K5: =I5/G5
A6: BluePeak Foods Ltd | B6: 285 | C6: 18 | D6: 950 | E6: 200 | F6: 6200 | G6: 620 | H6: =B6*C6 | I6: =H6+D6-E6 | J6: =I6/F6 | K6: =I6/G6
A7: Cedar Brands Ltd | B7: 610 | C7: 25 | D7: 2400 | E7: 700 | F7: 10500 | G7: 1365 | H7: =B7*C7 | I7: =H7+D7-E7 | J7: =I7/F7 | K7: =I7/G7
A8: Delta Household Ltd | B8: 165 | C8: 22 | D8: 1150 | E8: 250 | F8: 4900 | G8: 441 | H8: =B8*C8 | I8: =H8+D8-E8 | J8: =I8/F8 | K8: =I8/G8
A9: Evergreen Products Ltd | B9: 515 | C9: 16 | D9: 1300 | E9: 500 | F9: 7600 | G9: 988 | H9: =B9*C9 | I9: =H9+D9-E9 | J9: =I9/F9 | K9: =I9/G9
A10: Fable Retail Ltd | B10: 330 | C10: 30 | D10: 2200 | E10: 600 | F10: 9100 | G10: 728 | H10: =B10*C10 | I10: =H10+D10-E10 | J10: =I10/F10 | K10: =I10/G10
A11: Granite Consumer Ltd | B11: 390 | C11: 14 | D11: 900 | E11: 350 | F11: 5700 | G11: 684 | H11: =B11*C11 | I11: =H11+D11-E11 | J11: =I11/F11 | K11: =I11/G11
A12: Harbor Foods Ltd | B12: 720 | C12: 19 | D12: 2600 | E12: 850 | F12: 11800 | G12: 1534 | H12: =B12*C12 | I12: =H12+D12-E12 | J12: =I12/F12 | K12: =I12/G12
A13: Indigo Home Ltd | B13: 255 | C13: 24 | D13: 1400 | E13: 300 | F13: 6800 | G13: 748 | H13: =B13*C13 | I13: =H13+D13-E13 | J13: =I13/F13 | K13: =I13/G13
A14: Juniper Brands Ltd | B14: 140 | C14: 20 | D14: 800 | E14: 150 | F14: 4300 | G14: 387 | H14: =B14*C14 | I14: =H14+D14-E14 | J14: =I14/F14 | K14: =I14/G14
A17: Peer median EV / EBITDA | B17: =MEDIAN(K5:K14)
A19: TargetCo valuation
A20: TargetCo FY2023A EBITDA | B20: 630
A21: Implied Enterprise Value | B21: =MEDIAN(K5:K14)*B20
A22: TargetCo Debt | B22: 900
A23: TargetCo Cash | B23: 150
A24: Implied Equity Value | B24: =B21-B22+B23

Sheet Deal Model
A1: ACCRETION / DILUTION MODEL
A2: Complete yellow cells using linked assumptions and formulas. INR millions except per-share amounts.
A4: Assumption / Output | B4: Value | C4: Units | D4: Source / formula guidance | E4: Status
A5: AcquirerCo share price | B5: 480 | C5: INR/share | D5: Given | E5: Input
A6: AcquirerCo diluted shares | B6: 50 | C6: mm | D6: Given | E6: Input
A7: AcquirerCo net income | B7: ='Operating Data'!B11 | C7: INR mm | D7: Link Operating Data | E7: Input
A8: AcquirerCo cash available for deal | B8: 2500 | C8: INR mm | D8: Given | E8: Input
A9: TargetCo unaffected share price | B9: 210 | C9: INR/share | D9: Given | E9: Input
A10: TargetCo diluted shares | B10: 20 | C10: mm | D10: Given | E10: Input
A11: Offer premium | B11: 0.25 | C11: % | D11: Given | E11: Input
A12: Transaction fees | B12: 180 | C12: INR mm | D12: Given | E12: Input
A13: New debt raised | B13: 2500 | C13: INR mm | D13: Given | E13: Input
A14: Interest rate on new debt | B14: 0.09 | C14: % | D14: Given | E14: Input
A15: Interest rate foregone on cash | B15: 0.04 | C15: % | D15: Given | E15: Input
A16: Tax rate | B16: 0.25 | C16: % | D16: Given | E16: Input
A17: TargetCo net income | B17: ='Operating Data'!D11 | C17: INR mm | D17: Link Operating Data | E17: Input
A18: Offer price per TargetCo share | B18: =B9*(1+B11) | C18: INR/share | D18: Unaffected price × (1 + premium) | E18: Formula
A19: Offer equity value | B19: =B18*B10 | C19: INR mm | D19: Offer price × target diluted shares | E19: Formula
A20: Cash used | B20: =MIN(B8,MAX(0,B19+B12-B13)) | C20: INR mm | D20: MIN(cash available, offer equity value + fees − new debt) | E20: Formula
A21: Interest expense on new debt | B21: =B13*B14 | C21: INR mm | D21: New debt × interest rate | E21: Formula
A22: Foregone interest income | B22: =B20*B15 | C22: INR mm | D22: Cash used × foregone interest rate | E22: Formula
A23: Incremental after-tax financing cost | B23: =(B21+B22)*(1-B16) | C23: INR mm | D23: (new debt interest + foregone interest) × (1 − tax rate) | E23: Formula
A24: Pro forma net income | B24: =B7+B17-B23-B12*(1-B16) | C24: INR mm | D24: Acquirer NI + Target NI − after-tax financing cost − fees × (1 − tax rate) | E24: Formula
A25: New shares issued | B25: =MAX(0,(B19+B12-B13-B20)/B5) | C25: mm | D25: (offer equity value + fees − new debt − cash used) / acquirer share price; floor at zero | E25: Formula
A26: Pro forma shares outstanding | B26: =B6+B25 | C26: mm | D26: Acquirer shares + new shares issued | E26: Formula
A27: Standalone AcquirerCo EPS | B27: =B7/B6 | C27: INR/share | D27: Acquirer NI / Acquirer shares | E27: Formula
A28: Pro forma EPS | B28: =B24/B26 | C28: INR/share | D28: Pro forma NI / pro forma shares | E28: Formula
A29: Accretion / (dilution) | B29: =B28/B27-1 | C29: % | D29: Pro forma EPS / standalone EPS − 1 | E29: Formula

Sheet Summary
A1: TRANSACTION SNAPSHOT
A2: Complete the outputs by linking to your model. Recommendation should be concise and evidence-based.
A4: Output | B4: Value | C4: Units | D4: Comment
A5: Peer median EV / EBITDA | B5: ='Trading Comps'!B17 | C5: x | D5: Link Trading Comps
A6: TargetCo implied enterprise value | B6: ='Trading Comps'!B21 | C6: INR mm | D6: Link Trading Comps
A7: TargetCo implied equity value | B7: ='Trading Comps'!B24 | C7: INR mm | D7: Link Trading Comps
A8: Offer price per share | B8: ='Deal Model'!B18 | C8: INR/share | D8: Link Deal Model
A9: Offer equity value | B9: ='Deal Model'!B19 | C9: INR mm | D9: Link Deal Model
A10: Standalone AcquirerCo EPS | B10: ='Deal Model'!B27 | C10: INR/share | D10: Link Deal Model
A11: Pro forma EPS | B11: ='Deal Model'!B28 | C11: INR/share | D11: Link Deal Model
A12: Accretion / (dilution) | B12: ='Deal Model'!B29 | C12: % | D12: Link Deal Model
A13: Sources less uses | B13: =0 | C13: INR mm | D13: Check; should be zero or explain residual
A16: Recommendation | B16: Based on the peer median multiple, TargetCo's implied value is a useful benchmark but should be compared with the proposed offer. The model's EPS accretion/dilution result depends on the funding mix, financing costs, fees and assumptions. Key caveats include synergies being excluded and the use of a single forecast year.
A20: Model checks
A21: 1. Sources less uses | B21: =IF(ABS(B13)<0.1,"PASS","REVIEW")
A22: 2. Share count / EPS check | B22: =IF(ABS('Deal Model'!B28-'Deal Model'!B24/'Deal Model'!B26 )<0.0001,"PASS","REVIEW")

Sheet Answer Key
A1: ANSWER KEY — DO NOT OPEN UNTIL YOU FINISH
A3: Expected formulas / review points
A4: Trading comps Equity Value | B4: Share price × diluted shares
A5: Trading comps Enterprise Value | B5: Equity value + debt − cash
A6: EV / EBITDA | B6: Enterprise value ÷ FY2023A EBITDA
A7: Peer median multiple | B7: MEDIAN of peer EV / EBITDA multiples
A8: Target implied EV | B8: Peer median EV / EBITDA × TargetCo EBITDA
A9: Target implied equity value | B9: Implied EV − target debt + target cash
A10: Offer price | B10: Unaffected target price × (1 + premium)
A11: Offer equity value | B11: Offer price × target diluted shares
A12: Cash used | B12: MIN(cash available, MAX(0, offer equity value + fees − new debt))
A13: Pro forma NI | B13: Acquirer NI + Target NI − after-tax financing cost − after-tax fees
A14: New shares issued | B14: MAX(0, (offer equity value + fees − new debt − cash used) / acquirer share price)
A15: Pro forma EPS | B15: Pro forma NI ÷ pro forma shares
... A17: Key judgment | B17: State whether the deal is accretive/dilutive under assumptions; identify synergies, integration costs, financing and valuation as sensitivities.
A20: Indicative output values
A21: Peer median EV / EBITDA | B21: ='Trading Comps'!B17 | C21: x
A22: Target implied EV | B22: ='Trading Comps'!B21 | C22: INR mm
A23: Target implied equity value | B23: ='Trading Comps'!B24 | C23: INR mm
A24: Offer price/share | B24: ='Deal Model'!B18 | C24: INR/share
A25: Offer equity value | B25: ='Deal Model'!B19 | C25: INR mm
A26: Standalone EPS | B26: ='Deal Model'!B27 | C26: INR/share
A27: Pro forma EPS | B27: ='Deal Model'!B28 | C27: INR/share
A28: Accretion/(dilution) | B28: ='Deal Model'!B29 | C28: %
